Workbook
Name DEX: [1]主要情况!$G$10
Name STR: [1]主要情况!$G$8
Name 阿兰寇拉: 数据表!#REF!
Name 阿斯莫: 数据表!#REF!
Name 矮人: 数据表!#REF!
Name 斑猫人: 数据表!#REF!
Name 半精灵: 数据表!#REF!
Name 半人马: 数据表!#REF!
Name 半身人: 数据表!#REF!
Name 半兽人: 数据表!#REF!
Name 匕首: 装备!$O$5
Name 匕首伤害: 装备!#REF!
Name 鞭: 装备!$O$35
Name 鞭伤害: 装备!#REF!
Name 标枪: 装备!$O$8
Name 标枪伤害: 装备!#REF!
Name 捕网: 装备!$O$40
Name 捕网伤害: 装备!#REF!
Name 吹箭筒: 装备!$O$36
Name 吹箭筒伤害: 装备!#REF!
Name 纯种蛇人: 数据表!#REF!
Name 刺剑: 装备!$O$29
Name 刺剑伤害: 装备!#REF!
Name 地精: 数据表!#REF!
Name 钉头锤: 装备!$O$27
Name 钉头锤伤害: 装备!#REF!
Name 短棒: 装备!$O$4
Name 短棒伤害: 装备!#REF!
Name 短弓: 装备!$O$16
Name 短弓伤害: 装备!#REF!
Name 短剑: 装备!$O$31
Name 短剑伤害: 装备!#REF!
Name 飞镖: 装备!$O$15
Name 飞镖伤害: 装备!#REF!
Name 费尔伯格人: 数据表!#REF!
Name 歌利亚: 数据表!#REF!
Name 狗头人: 数据表!#REF!
Name 化兽者: 数据表!#REF!
Name 幻身灵: 数据表!#REF!
Name 吉斯人: 数据表!#REF!
Name 戟: 装备!$O$23
Name 戟伤害: 装备!#REF!
Name 精灵: 数据表!#REF!
Name 巨棒: 装备!$O$6
Name 巨棒伤害: 装备!#REF!
Name 巨锤: 装备!$O$26
Name 巨锤伤害: 装备!#REF!
Name 巨斧: 装备!$O$21
Name 巨斧伤害: 装备!#REF!
Name 巨剑: 装备!$O$22
Name 巨剑伤害: 装备!#REF!
Name 离梦人: 数据表!#REF!
Name 镰刀: 装备!$O$12
Name 镰刀伤害: 装备!#REF!
Name 链枷: 装备!$O$19
Name 链枷伤害: 装备!#REF!
Name 龙裔: 数据表!#REF!
Name 矛: 装备!$O$13
Name 矛伤害: 装备!#REF!
Name 牛头人: 数据表!#REF!

Sheet 背景
A1: 人物背景 Background
B3: 角色名 | E3: 诺菲雅 | Q3: 个性 | U3: 对事物的诞生与逝去，激烈的情感充满好奇
B4: 玩家 | E4: 霞秋羽 | U4: 每天都要尽可能的注视日升日落来见证时间的流逝
B5: 故乡 | E5: 星界 | Q5: 理念 | U5: 在这片陌生的土地上寻找对抗虚无的答案
B6: 背景 | E6: 远行者 | Q6: 羁绊 | U6: 我为这片美丽而神奇的新土地而着迷。
Q7: 缺陷 | U7: 我假装不懂这些人当地的语言以避免我不希望的交流。
B8: 年龄 | E8: 345 | I8: 发型 | L8: 高马尾
B9: 性别 | E9: 女 | I9: 发色 | L9: 淡灰色 | Q9: 人物衣装 外貌描述 | U9: 眼底闪烁着细碎的星光，情绪平静时像静谧的星空，激动时会流转起微光。平日里用发带束起高马尾，穿着一身方便行动的白色轻型皮甲，腰间挂着一把长剑和腰包。
B10: 身高 | E10: 176cm | I10: 肤色 | L10: 白
B11: 体重 | E11: 56kg | I11: 瞳色 | L11: 银蓝色
Q12: 背景特性 | U12: 众目焦点AllEyesonYou。你的口音，言谈举止，措辞风格甚至你的外表都表明你就是一个异乡人。无论你走到哪里，好奇的目光总会伴随着你。虽然这有些令人讨厌，但是也让你得以对那些感兴趣的学者们，和那些对远方好奇希望听你述说家乡故事之人的好感。与其他民众不同，你可以运用这种关注力为自己或旅伴们亲近想要接触之人。那些贵族领主、学者、商人望族等等可能会有兴趣听你那些有关远方故乡和人民的故事。
B13: 语言
B14: 通用语 | I14: 精灵语
B15: 天界语 | I15: 木族语
Q18: 背景故事 | U18: 我出生在星光位面那片银色的虚空里，那里没有日出日落，没有四季更迭，万物永恒不老，时间像一条静止的河 —— 我在那里生活了 345 年，看着同胞们在永恒的沉思里慢慢麻木，看着星界的光永远明亮却毫无温度。 我开始厌倦这种 “没有终点的存在”：没有成长，没有离别，没有 “完成一件事” 的喜悦，连生命本身都因为永恒而失去了重量。我想知道 “时间流逝” 是什么感觉，想看看会枯萎的花、会老去的人、会被黑夜吞噬的夕阳 —— 于是我背着竖琴，以 “远行者” 的身份，踏上了前往费伦大陆的旅途。 来到这片陌生的土地后，我找到了对抗虚无的方式：每天清晨追着日出，傍晚守着日落，用这个仪式来标记时间的流逝，证明 “我真的在活着”。 我着迷于费伦的一切：春日的樱花会在一夜之间绽放又凋零，凡人会为了一句誓言奔赴生死，篝火会在黎明前熄灭却留下温暖的余温 —— 这些都是星界永远不会有的 “真实”。我不想卷入琐碎的纷争，只想安静地做一个观察者，记录下所有短暂却炽热的瞬间。 但我也知道，我的旅途不止于此，我也不可能永远只是一个观察者，在这片陌生的土地上，或许我会找到属于我的友谊与羁绊。
B19: 熟练工具
B20: 竖琴
B25: 人物形象

Sheet 数据表
B1: 法术书 | C1: 专注 | D1: 仪式 | E1: 准备栏 | I1: 仪 | J1: 专 | M1: 1 | N1: 2 | O1: 3 | P1: 4 | Q1: 5 | R1: 6 | S1: 7 | T1: 8 | U1: 9 | V1: 10 | W1: 11 | X1: 12 | Y1: 13 | Z1: 14 | AA1: 15 | AB1: 16 | AC1: 17 | AD1: 18 | AE1: 19 | AF1: 20 | AK1: 戏法 | AL1: 0 | AO1: 物品效果 | AP1: 物品名称 | AQ1: 算盘 | AR1: - | AS1: 2gp | AT1: 2 | AU1: 物品重量 | AW1: 语言
A2: 1 | B2: =IF(#REF!="","",#REF!) -> #REF! | C2: =IFERROR(VLOOKUP(B2,#REF!,5,FALSE),"") | D2: =IFERROR(VLOOKUP(B2,#REF!,4,FALSE),"") | E2: 1 | F2: =B2 -> #REF! | H2: =IF(#REF!<>"",#REF!,"") -> #REF! | I2: =IF(VLOOKUP(H2,#REF!,4,0)="√",1,0) -> #REF! | J2: =IF(VLOOKUP(H2,#REF!,5,0)="√",1,0) -> #REF! | L2: 吟游诗人 | M2: 4 | N2: 5 | O2: 6 | P2: 7 | Q2: 8 | R2: 9 | S2: 10 | T2: 11 | U2: 12 | V2: 14 | W2: 15 | X2: 15 | Y2: 16 | Z2: 18 | AA2: 19 | AB2: 19 | AC2: 20 | AD2: 22 | AE2: 22 | AF2: 22 | AK2: 1环 | AL2: 1 | AO2: =IF(ISBLANK(#REF!),,INDEX(AR1:AT149,MATCH(#REF!&"*",AQ1:AQ149,0),1)) -> #REF! | AP2: =IF(ISBLANK(#REF!),,INDEX(AQ1:AT149,MATCH(#REF!&"*",AQ1:AQ149,0),1)) -> #REF! | AQ2: 强酸_小瓶 | AR2: 你可以用一个动作将这小瓶液体泼溅到你身边 5尺内的一个生物身上，或是将小瓶投到至多 20 尺远的地方，并利用冲击打破它。两种情况都可以视为对一个生物或物件发动一次远程攻击，并将强酸视为一件临时武器。命中时，目标受到 2d6点强酸伤害。 | AS2: 25gp | AT2: 1 | AU2: =VLOOKUP(AP2,AQ1:AT147,4,0) -> #REF! | AW2: 通用语
A3: 2 | B3: =IF(#REF!="","",#REF!) -> #REF! | C3: =IFERROR(VLOOKUP(B3,#REF!,5,FALSE),"") | D3: =IFERROR(VLOOKUP(B3,#REF!,4,FALSE),"") | E3: 2 | F3: =B3 -> #REF! | H3: =IF(#REF!<>"",#REF!,"") -> #REF! | I3: =IF(VLOOKUP(H3,#REF!,4,0)="√",1,0) -> #REF! | J3: =IF(VLOOKUP(H3,#REF!,5,0)="√",1,0) -> #REF! | L3: 牧师 | M3: =职业!$AI$4+#REF! -> #REF! | N3: =职业!$AI$4+#REF! -> #REF! | O3: =职业!$AI$4+#REF! -> #REF! | P3: =职业!$AI$4+#REF! -> #REF! | Q3: =职业!$AI$4+#REF! -> #REF! | R3: =职业!$AI$4+#REF! -> #REF! | S3: =职业!$AI$4+#REF! -> #REF! | T3: =职业!$AI$4+#REF! -> #REF! | ... AF3: =职业!$AI$4+#REF! -> #REF! | AK3: 2环 | AL3: 2 | AO3: =IF(ISBLANK(#REF!),,INDEX(AR1:AT149,MATCH(#REF!&"*",AQ1:AQ149,0),1)) -> #REF! | AP3: =IF(ISBLANK(#REF!),,INDEX(AQ1:AT149,MATCH(#REF!&"*",AQ1:AQ149,0),1)) -> #REF! | AQ3: 炽火胶_扁瓶 | AR3: 一种粘稠的流体，其一旦接触空气就会引起自燃。你可以用一个动作将这小瓶液体投到至多20尺远的地方，并利用冲击打破它。这个动作视为对一个生物或物件发动一次远程攻击，并将炽火胶视为一件临时武器。命中时，目标在它每回合开始时受到1d4点火焰伤害。被命中生物可以使用动作进行一次DC10的敏捷检定，以扑灭火焰来结束该伤害效应。 | AS3: 50gp | AT3: 1 | AU3: =VLOOKUP(AP3,AQ1:AT147,4,0) -> #REF! | AW3: 矮人语
A4: 3 | B4: =IF(#REF!="","",#REF!) -> #REF! | C4: =IFERROR(VLOOKUP(B4,#REF!,5,FALSE),"") | D4: =IFERROR(VLOOKUP(B4,#REF!,4,FALSE),"") | E4: 3 | F4: =B4 -> #REF! | H4: =IF(#REF!<>"",#REF!,"") -> #REF! | I4: =IF(VLOOKUP(H4,#REF!,4,0)="√",1,0) -> #REF! | J4: =IF(VLOOKUP(H4,#REF!,5,0)="√",1,0) -> #REF! | L4: 德鲁伊 | M4: =职业!$AI$5+#REF! -> #REF! | N4: =职业!$AI$5+#REF! -> #REF! | O4: =职业!$AI$5+#REF! -> #REF! | P4: =职业!$AI$5+#REF! -> #REF! | Q4: =职业!$AI$5+#REF! -> #REF! | R4: =职业!$AI$5+#REF! -> #REF! | S4: =职业!$AI$5+#REF! -> #REF! | T4: =职业!$AI$5+#REF! -> #REF! | ... AF4: =职业!$AI$5+#REF! -> #REF! | AK4: 3环 | AL4: 3 | AO4: =IF(ISBLANK(#REF!),,INDEX(AR1:AT149,MATCH(#REF!&"*",AQ1:AQ149,0),1)) -> #REF! | AP4: =IF(ISBLANK(#REF!),,INDEX(AQ1:AT149,MATCH(#REF!&"*",AQ1:AQ149,0),1)) -> #REF! | AQ4: 箭 | AR4: - | AS4: 1gp | AT4: 0.05 | AU4: =VLOOKUP(AP4,AQ1:AT147,4,0) -> #REF! | AW4: 精灵语
A5: 4 | B5: =IF(#REF!="","",#REF!) -> #REF! | C5: =IFERROR(VLOOKUP(B5,#REF!,5,FALSE),"") | D5: =IFERROR(VLOOKUP(B5,#REF!,4,FALSE),"") | E5: 4 | F5: =B5 -> #REF! | H5: =IF(#REF!<>"",#REF!,"") -> #REF! | I5: =IF(VLOOKUP(H5,#REF!,4,0)="√",1,0) -> #REF! | J5: =IF(VLOOKUP(H5,#REF!,5,0)="√",1,0) -> #REF! | L5: 圣武士 | M5: =ROUNDDOWN(职业!$AI$8/2,0)+#REF! -> #REF! | N5: =ROUNDDOWN(职业!$AI$8/2,0)+#REF! -> #REF! | O5: =ROUNDDOWN(职业!$AI$8/2,0)+#REF! -> #REF! | P5: =ROUNDDOWN(职业!$AI$8/2,0)+#REF! -> #REF! | Q5: =ROUNDDOWN(职业!$AI$8/2,0)+#REF! -> #REF! | R5: =ROUNDDOWN(职业!$AI$8/2,0)+#REF! -> #REF! | S5: =ROUNDDOWN(职业!$AI$8/2,0)+#REF! -> #REF! | T5: =ROUNDDOWN(职业!$AI$8/2,0)+#REF! -> #REF! | ... AF5: =ROUNDDOWN(职业!$AI$8/2,0)+#REF! -> #REF! | AI5: V 言语 | AK5: 4环 | AL5: 4 | AO5: =IF(ISBLANK(#REF!),,INDEX(AR1:AT149,MATCH(#REF!&"*",AQ1:AQ149,0),1)) -> #REF! | AP5: =IF(ISBLANK(#REF!),,INDEX(AQ1:AT149,MATCH(#REF!&"*",AQ1:AQ149,0),1)) -> #REF! | AQ5: 吹矢 | AR5: - | AS5: 1gp | AT5: 0.02 | AU5: =VLOOKUP(AP5,AQ1:AT147,4,0) -> #REF! | AW5: 巨人语
A6: 5 | B6: =IF(#REF!="","",#REF!) -> #REF! | C6: =IFERROR(VLOOKUP(B6,#REF!,5,FALSE),"") | D6: =IFERROR(VLOOKUP(B6,#REF!,4,FALSE),"") | E6: 5 | F6: =B6 -> #REF! | H6: =IF(#REF!<>"",#REF!,"") -> #REF! | I6: =IF(VLOOKUP(H6,#REF!,4,0)="√",1,0) -> #REF! | J6: =IF(VLOOKUP(H6,#REF!,5,0)="√",1,0) -> #REF! | L6: 游侠 | M6: 0 | N6: 2 | O6: 3 | P6: 3 | Q6: 4 | R6: 4 | S6: 5 | T6: 5 | U6: 6 | V6: 6 | W6: 7 | X6: 7 | Y6: 8 | Z6: 8 | AA6: 9 | AB6: 9 | AC6: 10 | AD6: 10 | AE6: 11 | AF6: 11 | AI6: S 姿势 | AK6: 5环 | AL6: 5 | AO6: =IF(ISBLANK(#REF!),,INDEX(AR1:AT149,MATCH(#REF!&"*",AQ1:AQ149,0),1)) -> #REF! | AP6: =IF(ISBLANK(#REF!),,INDEX(AQ1:AT149,MATCH(#REF!&"*",AQ1:AQ149,0),1)) -> #REF! | AQ6: 弩矢 | AR6: - | AS6: 1gp | AT6: 0.075 | AU6: =VLOOKUP(AP6,AQ1:AT147,4,0) -> #REF! | AW6: 侏儒语
A7: 6 | B7: =IF(#REF!="","",#REF!) -> #REF! | C7: =IFERROR(VLOOKUP(B7,#REF!,5,FALSE),"") | D7: =IFERROR(VLOOKUP(B7,#REF!,4,FALSE),"") | E7: 6 | F7: =B7 -> #REF! | H7: =IF(#REF!<>"",#REF!,"") -> #REF! | I7: =IF(VLOOKUP(H7,#REF!,4,0)="√",1,0) -> #REF! | J7: =IF(VLOOKUP(H7,#REF!,5,0)="√",1,0) -> #REF! | L7: 术士 | M7: 2 | N7: 3 | O7: 4 | P7: 5 | Q7: 6 | R7: 7 | S7: 8 | T7: 9 | U7: 10 | V7: 11 | W7: 12 | X7: 12 | Y7: 13 | Z7: 13 | AA7: 14 | AB7: 14 | AC7: 15 | AD7: 15 | AE7: 15 | AF7: 15 | AI7: M 材料 | AK7: 6环 | AL7: 6 | AO7: =IF(ISBLANK(#REF!),,INDEX(AR1:AT149,MATCH(#REF!&"*",AQ1:AQ149,0),1)) -> #REF! | AP7: =IF(ISBLANK(#REF!),,INDEX(AQ1:AT149,MATCH(#REF!&"*",AQ1:AQ149,0),1)) -> #REF! | AQ7: 投石索弹丸 | AR7: - | AS7: 0.04gp | AT7: 0.075 | AU7: =VLOOKUP(AP7,AQ1:AT147,4,0) -> #REF! | AW7: 地精语
A8: 7 | B8: =IF(#REF!="","",#REF!) -> #REF! | C8: =IFERROR(VLOOKUP(B8,#REF!,5,FALSE),"") | D8: =IFERROR(VLOOKUP(B8,#REF!,4,FALSE),"") | E8: 7 | F8: =B8 -> #REF! | H8: =IF(#REF!<>"",#REF!,"") -> #REF! | I8: =IF(VLOOKUP(H8,#REF!,4,0)="√",1,0) -> #REF! | J8: =IF(VLOOKUP(H8,#REF!,5,0)="√",1,0) -> #REF! | L8: 邪术师 | M8: 2 | N8: 3 | O8: 4 | P8: 5 | Q8: 6 | R8: 7 | S8: 8 | T8: 9 | U8: 10 | V8: 10 | W8: 11 | X8: 11 | Y8: 12 | Z8: 12 | AA8: 13 | AB8: 13 | AC8: 14 | AD8: 14 | AE8: 15 | AF8: 15 | AK8: 7环 | AL8: 7 | AO8: =IF(ISBLANK(#REF!),,INDEX(AR1:AT149,MATCH(#REF!&"*",AQ1:AQ149,0),1)) -> #REF! | AP8: =IF(ISBLANK(#REF!),,INDEX(AQ1:AT149,MATCH(#REF!&"*",AQ1:AQ149,0),1)) -> #REF! | AQ8: 子弹 | AR8: 采用复兴时期物品数据，如需使用现代弹药请自行填写。 | AS8: 3gp | AT8: 0.2 | AU8: =VLOOKUP(AP8,AQ1:AT147,4,0) -> #REF! | AW8: 半身人语
A9: 8 | B9: =IF(#REF!="","",#REF!) -> #REF! | C9: =IFERROR(VLOOKUP(B9,#REF!,5,FALSE),"") | D9: =IFERROR(VLOOKUP(B9,#REF!,4,FALSE),"") | E9: 8 | F9: =B9 -> #REF! | H9: =IF(#REF!<>"",#REF!,"") -> #REF! | I9: =IF(VLOOKUP(H9,#REF!,4,0)="√",1,0) -> #REF! | J9: =IF(VLOOKUP(H9,#REF!,5,0)="√",1,0) -> #REF! | L9: 法师 | M9: =职业!$AI$13+#REF! -> #REF! | N9: =职业!$AI$13+#REF! -> #REF! | O9: =职业!$AI$13+#REF! -> #REF! | P9: =职业!$AI$13+#REF! -> #REF! | Q9: =职业!$AI$13+#REF! -> #REF! | R9: =职业!$AI$13+#REF! -> #REF! | S9: =职业!$AI$13+#REF! -> #REF! | T9: =职业!$AI$13+#REF! -> #REF! | ... AF9: =职业!$AI$13+#REF! -> #REF! | AH9: 主职业 | AI9: 牧师 | AJ9: =#REF!+IF(#REF!="主职业",#REF!,IF(#REF!="兼职1",#REF!,IF(#REF!="兼职2",#REF!,))) -> #REF! | AK9: 8环 | AL9: 8 | AO9: =IF(ISBLANK(#REF!),,INDEX(AR1:AT149,MATCH(#REF!&"*",AQ1:AQ149,0),1)) -> #REF! | AP9: =IF(ISBLANK(#REF!),,INDEX(AQ1:AT149,MATCH(#REF!&"*",AQ1:AQ149,0),1)) -> #REF! | AQ9: 抗毒剂_小瓶 | AR9: 喝下瓶内液体的生物在1小时内进行对抗对毒素的豁免检定时具有优势。它无法为不死生物或构装生物提供任何增益。 | AS9: 50gp | AT9: 0 | AU9: =VLOOKUP(AP9,AQ1:AT147,4,0) -> #REF! | AW9: 兽人语
A10: 9 | B10: =IF(#REF!="","",#REF!) -> #REF! | C10: =IFERROR(VLOOKUP(B10,#REF!,5,FALSE),"") | D10: =IFERROR(VLOOKUP(B10,#REF!,4,FALSE),"") | E10: 9 | F10: =B10 -> #REF! | H10: =IF(#REF!<>"",#REF!,"") -> #REF! | I10: =IF(VLOOKUP(H10,#REF!,4,0)="√",1,0) -> #REF! | J10: =IF(VLOOKUP(H10,#REF!,5,0)="√",1,0) -> #REF! | AH10: 兼职1 | AI10: 圣武士 | AJ10: =#REF!+IF(#REF!="主职业",INT(#REF!/2),IF(#REF!="兼职1",INT(#REF!/2),IF(#REF!="兼职2",INT(#REF!/2),))) -> #REF! | AK10: 9环 | AL10: 9 | AO10: =IF(ISBLANK(#REF!),,INDEX(AR1:AT149,MATCH(#REF!&"*",AQ1:AQ149,0),1)) -> #REF! | AP10: =IF(ISBLANK(#REF!),,INDEX(AQ1:AT149,MATCH(#REF!&"*",AQ1:AQ149,0),1)) -> #REF! | AQ10: 水晶 | AR10: 奥术法器是一件用来引导奥术法术的特殊物品，它可以是一枚法球、一块水晶、一只权杖、一根特制法杖、一根魔杖般的长木条或是其它类似的物品。术士、邪术师或法师能将这样的物品用作施法法器。 | AS10: 10gp | AT10: 1 | AU10: =VLOOKUP(AP10,AQ1:AT147,4,0) -> #REF! | AW10: 深渊语
A11: 10 | B11: =IF(#REF!="","",#REF!) -> #REF! | C11: =IFERROR(VLOOKUP(B11,#REF!,5,FALSE),"") | D11: =IFERROR(VLOOKUP(B11,#REF!,4,FALSE),"") | E11: 10 | F11: =B11 -> #REF! | H11: =IF(#REF!<>"",#REF!,"") -> #REF! | I11: =IF(VLOOKUP(H11,#REF!,4,0)="√",1,0) -> #REF! | J11: =IF(VLOOKUP(H11,#REF!,5,0)="√",1,0) -> #REF! | L11: 主职业 | M11: =IF(#REF!="","",#REF!) -> #REF! | AH11: 兼职2 | AI11: 德鲁伊 | AJ11: =#REF!+IF(#REF!="主职业",#REF!,IF(#REF!="兼职1",#REF!,IF(#REF!="兼职2",#REF!,))) -> #REF! | AO11: =IF(ISBLANK(#REF!),,INDEX(AR1:AT149,MATCH(#REF!&"*",AQ1:AQ149,0),1)) -> #REF! | AP11: =IF(ISBLANK(#REF!),,INDEX(AQ1:AT149,MATCH(#REF!&"*",AQ1:AQ149,0),1)) -> #REF! | AQ11: 法球 | AR11: 奥术法器是一件用来引导奥术法术的特殊物品，它可以是一枚法球、一块水晶、一只权杖、一根特制法杖、一根魔杖般的长木条或是其它类似的物品。术士、邪术师或法师能将这样的物品用作施法法器。 | AS11: 20gp | AT11: 3 | AU11: =VLOOKUP(AP11,AQ1:AT147,4,0) -> #REF! | AW11: 天界语
A12: 11 | B12: =IF(#REF!="","",#REF!) -> #REF! | C12: =IFERROR(VLOOKUP(B12,#REF!,5,FALSE),"") | D12: =IFERROR(VLOOKUP(B12,#REF!,4,FALSE),"") | E12: 11 | F12: =B12 -> #REF! | H12: =IF(#REF!<>"",#REF!,"") -> #REF! | I12: =IF(VLOOKUP(H12,#REF!,4,0)="√",1,0) -> #REF! | J12: =IF(VLOOKUP(H12,#REF!,5,0)="√",1,0) -> #REF! | L12: 兼职1 | M12: =IF(#REF!="","",#REF!) -> #REF! | AI12: 法师 | AJ12: =#REF!+IF(#REF!="主职业",#REF!,IF(#REF!="兼职1",#REF!,IF(#REF!="兼职2",#REF!,))) -> #REF! | AQ12: 权杖 | AR12: 奥术法器是一件用来引导奥术法术的特殊物品，它可以是一枚法球、一块水晶、一只权杖、一根特制法杖、一根魔杖般的长木条或是其它类似的物品。术士、邪术师或法师能将这样的物品用作施法法器。 | AS12: 10gp | AT12: 2 | AW12: 龙语
A13: 12 | B13: =IF(#REF!="","",#REF!) -> #REF! | C13: =IFERROR(VLOOKUP(B13,#REF!,5,FALSE),"") | D13: =IFERROR(VLOOKUP(B13,#REF!,4,FALSE),"") | E13: 12 | F13: =B13 -> #REF! | H13: =IF(#REF!<>"",#REF!,"") -> #REF! | I13: =IF(VLOOKUP(H13,#REF!,4,0)="√",1,0) -> #REF! | J13: =IF(VLOOKUP(H13,#REF!,5,0)="√",1,0) -> #REF! | L13: 兼职2 | M13: =IF(#REF!="","",#REF!) -> #REF! | AI13: 奇械师 | AJ13: =#REF!+IF(#REF!="主职业",INT(#REF!/2),IF(#REF!="兼职1",INT(#REF!/2),IF(#REF!="兼职2",INT(#REF!/2),))) -> #REF! | AO13: =IF(ISBLANK(#REF!),,INDEX(AR1:AT149,MATCH(#REF!&"*",AQ1:AQ149,0),1)) -> #REF! | AP13: =IF(ISBLANK(#REF!),,INDEX(AQ1:AT149,MATCH(#REF!&"*",AQ1:AQ149,0),1)) -> #REF! | AQ13: 法杖 | AR13: 奥术法器是一件用来引导奥术法术的特殊物品，它可以是一枚法球、一块水晶、一只权杖、一根特制法杖、一根魔杖般的长木条或是其它类似的物品。术士、邪术师或法师能将这样的物品用作施法法器。 | AS13: 5gp | AT13: 4 | AU13: =VLOOKUP(AP13,AQ1:AT147,4,0) -> #REF! | AW13: 深潜语
A14: 13 | B14: =IF(#REF!="","",#REF!) -> #REF! | C14: =IFERROR(VLOOKUP(B14,#REF!,5,FALSE),"") | D14: =IFERROR(VLOOKUP(B14,#REF!,4,FALSE),"") | E14: 13 | F14: =B14 -> #REF! | H14: =IF(#REF!<>"",#REF!,"") -> #REF! | I14: =IF(VLOOKUP(H14,#REF!,4,0)="√",1,0) -> #REF! | J14: =IF(VLOOKUP(H14,#REF!,5,0)="√",1,0) -> #REF! | L14: =IFERROR(IF(#REF!="主职业",VLOOKUP(M11,L1:AF9,#REF!+1,IF(#REF!="兼职1",VLOOKUP(M12,L1:AF9,#REF!+1,IF(#REF!="兼职2",VLOOKUP(M13,L1:AF9,#REF!+1,0)))))),"") | AL14: 体型 | AO14: =IF(ISBLANK(#REF!),,INDEX(AR1:AT149,MATCH(#REF!&"*",AQ1:AQ149,0),1)) -> #REF! | AP14: =IF(ISBLANK(#REF!),,INDEX(AQ1:AT149,MATCH(#REF!&"*",AQ1:AQ149,0),1)) -> #REF! | AQ14: 魔杖 | AR14: 奥术法器是一件用来引导奥术法术的特殊物品，它可以是一枚法球、一块水晶、一只权杖、一根特制法杖、一根魔杖般的长木条或是其它类似的物品。术士、邪术师或法师能将这样的物品用作施法法器。 | AS14: 10gp | AT14: 1 | AU14: =VLOOKUP(AP14,AQ1:AT147,4,0) -> #REF! | AW14: 炼狱语
A15: 14 | B15: =IF(#REF!="","",#REF!) -> #REF! | C15: =IFERROR(VLOOKUP(B15,#REF!,5,FALSE),"") | D15: =IFERROR(VLOOKUP(B15,#REF!,4,FALSE),"") | E15: 14 | F15: =B15 -> #REF! | H15: =IF(#REF!<>"",#REF!,"") -> #REF! | I15: =IF(VLOOKUP(H15,#REF!,4,0)="√",1,0) -> #REF! | J15: =IF(VLOOKUP(H15,#REF!,5,0)="√",1,0) -> #REF! | AL15: 微型 | AO15: =IF(ISBLANK(#REF!),,INDEX(AR1:AT149,MATCH(#REF!&"*",AQ1:AQ149,0),1)) -> #REF! | AP15: =IF(ISBLANK(#REF!),,INDEX(AQ1:AT149,MATCH(#REF!&"*",AQ1:AQ149,0),1)) -> #REF! | AQ15: 背包 | AR15: 一个背包可以容纳1立方尺或30磅重的装备，你还可以将物品系在背包外面，例如一卷铺盖或是一捆绳索。 | AS15: 2gp | AT15: 5 | AU15: =VLOOKUP(AP15,AQ1:AT147,4,0) -> #REF! | AW15: 原初语
A16: 15 | B16: =IF(#REF!="","",#REF!) -> #REF! | C16: =IFERROR(VLOOKUP(B16,#REF!,5,FALSE),"") | D16: =IFERROR(VLOOKUP(B16,#REF!,4,FALSE),"") | E16: 15 | F16: =B16 -> #REF! | H16: =IF(#REF!<>"",#REF!,"") -> #REF! | I16: =IF(VLOOKUP(H16,#REF!,4,0)="√",1,0) -> #REF! | J16: =IF(VLOOKUP(H16,#REF!,5,0)="√",1,0) -> #REF! | AL16: 小型 | AO16: =IF(ISBLANK(#REF!),,INDEX(AR1:AT149,MATCH(#REF!&"*",AQ1:AQ149,0),1)) -> #REF! | AP16: =IF(ISBLANK(#REF!),,INDEX(AQ1:AT149,MATCH(#REF!&"*",AQ1:AQ149,0),1)) -> #REF! | AQ16: 滚珠_一包1000粒 | AR16: 你可以用一个动作将这些小金属珠从袋子中洒出，并覆盖一片边长10尺的方形区域。穿过这片区域的生物必须进行一次DC10的敏捷豁免，豁免失败则摔至倒地。以半速穿过该区域的生物不需要进行该豁免。 | AS16: 1gp | AT16: 2 | AU16: =VLOOKUP(AP16,AQ1:AT147,4,0) -> #REF! | AW16: 木族语
A17: 16 | B17: =IF(#REF!="","",#REF!) -> #REF! | C17: =IFERROR(VLOOKUP(B17,#REF!,5,FALSE),"") | D17: =IFERROR(VLOOKUP(B17,#REF!,4,FALSE),"") | E17: 16 | F17: =B17 -> #REF! | H17: =IF(#REF!<>"",#REF!,"") -> #REF! | I17: =IF(VLOOKUP(H17,#REF!,4,0)="√",1,0) -> #REF! | J17: =IF(VLOOKUP(H17,#REF!,5,0)="√",1,0) -> #REF! | AL17: 中型 | AO17: =IF(ISBLANK(#REF!),,INDEX(AR1:AT149,MATCH(#REF!&"*",AQ1:AQ149,0),1)) -> #REF! | AP17: =IF(ISBLANK(#REF!),,INDEX(AQ1:AT149,MATCH(#REF!&"*",AQ1:AQ149,0),1)) -> #REF! | AQ17: 粗腰桶 | AR17: 一个粗腰桶可以容纳40加仑的液体或4立方尺的固体。 | AS17: 2gp | AT17: 70 | AU17: =VLOOKUP(AP17,AQ1:AT147,4,0) -> #REF! | AW17: 地底通用语
A18: 17 | B18: =IF(#REF!="","",#REF!) -> #REF! | C18: =IFERROR(VLOOKUP(B18,#REF!,5,FALSE),"") | D18: =IFERROR(VLOOKUP(B18,#REF!,4,FALSE),"") | E18: 17 | F18: =B18 -> #REF! | H18: =IF(#REF!<>"",#REF!,"") -> #REF! | I18: =IF(VLOOKUP(H18,#REF!,4,0)="√",1,0) -> #REF! | J18: =IF(VLOOKUP(H18,#REF!,5,0)="√",1,0) -> #REF! | M18: 戏法 | N18: 变化 | O18: 动作 | P18: 触及 | Q18: 立即 | V18: 背包1 | W18: 背包2 | X18: 次元袋1 | Y18: 次元袋2 | AI18: 经验值 | AL18: 大型 | AO18: =IF(ISBLANK(#REF!),,INDEX(AR1:AT149,MATCH(#REF!&"*",AQ1:AQ149,0),1)) -> #REF! | AP18: =IF(ISBLANK(#REF!),,INDEX(AQ1:AT149,MATCH(#REF!&"*",AQ1:AQ149,0),1)) -> #REF! | AQ18: 篮子 | AR18: 篮子可以容纳2立方尺或40磅重的物品。 | AS18: 0.4gp | AT18: 2 | AU18: =VLOOKUP(AP18,AQ1:AT147,4,0) -> #REF! | AW18: 水族语
A19: 18 | B19: =IF(#REF!="","",#REF!) -> #REF! | C19: =IFERROR(VLOOKUP(B19,#REF!,5,FALSE),"") | D19: =IFERROR(VLOOKUP(B19,#REF!,4,FALSE),"") | E19: 18 | F19: =B19 -> #REF! | H19: =IF(#REF!<>"",#REF!,"") -> #REF! | I19: =IF(VLOOKUP(H19,#REF!,4,0)="√",1,0) -> #REF! | J19: =IF(VLOOKUP(H19,#REF!,5,0)="√",1,0) -> #REF! | M19: 1 | N19: 塑能 | O19: 附赠动作 | P19: 自身 | Q19: 1轮 | V19: =SUM(#REF!*#REF!) -> #REF! | W19: =SUM(#REF!*#REF!) -> #REF! | X19: =SUM(#REF!*#REF!) -> #REF! | Y19: =SUM(#REF!*#REF!) -> #REF! | AI19: Exp | AJ19: Lv | AL19: 巨型 | AO19: =IF(ISBLANK(#REF!),,INDEX(AR1:AT149,MATCH(#REF!&"*",AQ1:AQ149,0),1)) -> #REF! | AP19: =IF(ISBLANK(#REF!),,INDEX(AQ1:AT149,MATCH(#REF!&"*",AQ1:AQ149,0),1)) -> #REF! | AQ19: 铺盖 | AR19: - | AS19: 1gp | AT19: 7 | AU19: =VLOOKUP(AP19,AQ1:AT147,4,0) -> #REF! | AW19: 气族语
A20: 19 | B20: =IF(#REF!="","",#REF!) -> #REF! | C20: =IFERROR(VLOOKUP(B20,#REF!,5,FALSE),"") | D20: =IFERROR(VLOOKUP(B20,#REF!,4,FALSE),"") | E20: 19 | F20: =B20 -> #REF! | H20: =IF(#REF!<>"",#REF!,"") -> #REF! | I20: =IF(VLOOKUP(H20,#REF!,4,0)="√",1,0) -> #REF! | J20: =IF(VLOOKUP(H20,#REF!,5,0)="√",1,0) -> #REF! | M20: 2 | N20: 防护 | O20: 1分钟 | P20: 15尺 | Q20: 1分钟 | V20: =SUM(#REF!*#REF!) -> #REF! | W20: =SUM(#REF!*#REF!) -> #REF! | X20: =SUM(#REF!*#REF!) -> #REF! | Y20: =SUM(#REF!*#REF!) -> #REF! | AI20: 0 | AJ20: 1 | AL20: 超巨型 | AO20: =IF(ISBLANK(#REF!),,INDEX(AR1:AT149,MATCH(#REF!&"*",AQ1:AQ149,0),1)) -> #REF! | AP20: =IF(ISBLANK(#REF!),,INDEX(AQ1:AT149,MATCH(#REF!&"*",AQ1:AQ149,0),1)) -> #REF! | AQ20: 铃铛 | AR20: - | AS20: 1gp | AT20: 0 | AU20: =VLOOKUP(AP20,AQ1:AT147,4,0) -> #REF! | AW20: 刻洛语
A21: 20 | B21: =IF(#REF!="","",#REF!) -> #REF! | C21: =IFERROR(VLOOKUP(B21,#REF!,5,FALSE),"") | D21: =IFERROR(VLOOKUP(B21,#REF!,4,FALSE),"") | E21: 20 | F21: =B21 -> #REF! | H21: =IF(#REF!<>"",#REF!,"") -> #REF! | I21: =IF(VLOOKUP(H21,#REF!,4,0)="√",1,0) -> #REF! | J21: =IF(VLOOKUP(H21,#REF!,5,0)="√",1,0) -> #REF! | M21: 3 | N21: 死灵 | O21: 动作或仪式 | P21: 30尺 | Q21: 10分钟 | V21: =SUM(#REF!*#REF!) -> #REF! | W21: =SUM(#REF!*#REF!) -> #REF! | X21: =SUM(#REF!*#REF!) -> #REF! | Y21: =SUM(#REF!*#REF!) -> #REF! | AI21: 300 | AJ21: 2 | AO21: =IF(ISBLANK(#REF!),,INDEX(AR1:AT149,MATCH(#REF!&"*",AQ1:AQ149,0),1)) -> #REF! | AP21: =IF(ISBLANK(#REF!),,INDEX(AQ1:AT149,MATCH(#REF!&"*",AQ1:AQ149,0),1)) -> #REF! | AQ21: 毯子 | AR21: - | AS21: 0.5gp | AT21: 3 | AU21: =VLOOKUP(AP21,AQ1:AT147,4,0) -> #REF! | AW21: 人鱼语
A22: 21 | B22: =IF(#REF!="","",#REF!) -> #REF! | C22: =IFERROR(VLOOKUP(B22,#REF!,5,FALSE),"") | D22: =IFERROR(VLOOKUP(B22,#REF!,4,FALSE),"") | E22: 21 | F22: =B22 -> #REF! | H22: =IF(#REF!<>"",#REF!,"") -> #REF! | I22: =IF(VLOOKUP(H22,#REF!,4,0)="√",1,0) -> #REF! | J22: =IF(VLOOKUP(H22,#REF!,5,0)="√",1,0) -> #REF! | M22: 4 | N22: 预言 | O22: 1分钟或仪式 | P22: 60尺 | Q22: 1小时 | V22: =SUM(#REF!*#REF!) -> #REF! | W22: =SUM(#REF!*#REF!) -> #REF! | X22: =SUM(#REF!*#REF!) -> #REF! | Y22: =SUM(#REF!*#REF!) -> #REF! | AI22: 900 | AJ22: 3 | AL22: 装备同调数量 | AO22: =IF(ISBLANK(#REF!),,INDEX(AR1:AT149,MATCH(#REF!&"*",AQ1:AQ149,0),1)) -> #REF! | AP22: =IF(ISBLANK(#REF!),,INDEX(AQ1:AT149,MATCH(#REF!&"*",AQ1:AQ149,0),1)) -> #REF! | AQ22: 滑轮组 | AR22: 一组滑轮组，其中配有一根绳索绕过轮组中，其上还装着一个系物的钩子。滑轮组可以让你提起相当于你正常举重四倍重量的物件。 | AS22: 5gp | AT22: 5 | AU22: =VLOOKUP(AP22,AQ1:AT147,4,0) -> #REF! | AW22: 牛头人语
A23: 22 | B23: =IF(#REF!="","",#REF!) -> #REF! | C23: =IFERROR(VLOOKUP(B23,#REF!,5,FALSE),"") | D23: =IFERROR(VLOOKUP(B23,#REF!,4,FALSE),"") | E23: 22 | F23: =B23 -> #REF! | H23: =IF(#REF!<>"",#REF!,"") -> #REF! | I23: =IF(VLOOKUP(H23,#REF!,4,0)="√",1,0) -> #REF! | J23: =IF(VLOOKUP(H23,#REF!,5,0)="√",1,0) -> #REF! | M23: 5 | N23: 咒法 | O23: 10分钟 | P23: 90尺 | Q23: 8小时 | V23: =SUM(#REF!*#REF!) -> #REF! | W23: =SUM(#REF!*#REF!) -> #REF! | X23: =SUM(#REF!*#REF!) -> #REF! | Y23: =SUM(#REF!*#REF!) -> #REF! | AI23: =AI22*AJ22 -> 2700 | AJ23: 4 | AL23: =IF(#REF!="O",1,0) -> #REF! | AQ23: 书 | AR23: 一本书可能写着诗歌、故事或是其他的内容。里面可能有关于某个特定地区的学识信息，也可能有侏儒语记载的机械图和笔记，或者任何其它能够用文字或图形表达的内容。一本载有法术的书则是一本法术书（见后文详述）。 | AS23: 28gp | AT23: 5 | AW23: 斯芬克斯语
A24: 23 | B24: =IF(#REF!="","",#REF!) -> #REF! | C24: =IFERROR(VLOOKUP(B24,#REF!,5,FALSE),"") | D24: =IFERROR(VLOOKUP(B24,#REF!,4,FALSE),"") | E24: 23 | F24: =B24 -> #REF! | H24: =IF(#REF!<>"",#REF!,"") -> #REF! | I24: =IF(VLOOKUP(H24,#REF!,4,0)="√",1,0) -> #REF! | J24: =IF(VLOOKUP(H24,#REF!,5,0)="√",1,0) -> #REF! | M24: 6 | N24: 附魔 | O24: 1小时 | P24: 120尺 | Q24: 24小时 | V24: =SUM(#REF!*#REF!) -> #REF! | W24: =SUM(#REF!*#REF!) -> #REF! | X24: =SUM(#REF!*#REF!) -> #REF! | Y24: =SUM(#REF!*#REF!) -> #REF! | AI24: 6500 | AJ24: 5 | AL24: =IF(#REF!="O",1,0) -> #REF! | AQ24: 玻璃瓶 | AR24: - | AS24: 2gp | AT24: 2 | AW24: 吉斯语
A25: 24 | B25: =IF(#REF!="","",#REF!) -> #REF! | C25: =IFERROR(VLOOKUP(B25,#REF!,5,FALSE),"") | D25: =IFERROR(VLOOKUP(B25,#REF!,4,FALSE),"") | E25: 24 | F25: =B25 -> #REF! | H25: =IF(#REF!<>"",#REF!,"") -> #REF! | I25: =IF(VLOOKUP(H25,#REF!,4,0)="√",1,0) -> #REF! | J25: =IF(VLOOKUP(H25,#REF!,5,0)="√",1,0) -> #REF! | M25: 7 | N25: 幻术 | O25: 8小时 | P25: 150尺 | Q25: 专注，至多1轮 | V25: =SUM(#REF!*#REF!) -> #REF! | W25: =SUM(#REF!*#REF!) -> #REF! | X25: =SUM(#REF!*#REF!) -> #REF! | Y25: =SUM(#REF!*#REF!) -> #REF! | AI25: 14000 | AJ25: 6 | AL25: =IF(#REF!="O",1,0) -> #REF! | AQ25: 水桶 | AR25: 水桶可以容纳3加仑的液体或½立方尺的固体。 | AS25: 0.05gp | AT25: 2 | AW25: 象族语
A26: 25 | B26: =IF(#REF!="","",#REF!) -> #REF! | C26: =IFERROR(VLOOKUP(B26,#REF!,5,FALSE),"") | D26: =IFERROR(VLOOKUP(B26,#REF!,4,FALSE),"") | E26: 25 | F26: =B26 -> #REF! | H26: =IF(#REF!<>"",#REF!,"") -> #REF! | I26: =IF(VLOOKUP(H26,#REF!,4,0)="√",1,0) -> #REF! | J26: =IF(VLOOKUP(H26,#REF!,5,0)="√",1,0) -> #REF! | M26: 8 | P26: 300尺 | Q26: 专注，至多1分钟 | V26: =SUM(#REF!*#REF!) -> #REF! | W26: =SUM(#REF!*#REF!) -> #REF! | X26: =SUM(#REF!*#REF!) -> #REF! | Y26: =SUM(#REF!*#REF!) -> #REF! | AI26: 23000 | AJ26: 7 | AL26: =IF(#REF!="O",1,0) -> #REF! | AQ26: 铁蒺藜_一包20枚 | AR26: 你可以用一个动作将一包铁蒺藜撒出，并覆盖一块边长5尺的方形区域。任何进入该区域的生物必须进行一次DC15的敏捷豁免，豁免失败则该生物停止移动，并受到1点穿刺伤害。在该生物恢复至少1点生命值前，其步行速度将减少10尺。以半速穿过该区域的生物不需要进行该豁免。 | AS26: 1gp | AT26: 2 | AW26: 维多肯语
A27: 26 | B27: =IF(#REF!="","",#REF!) -> #REF! | C27: =IFERROR(VLOOKUP(B27,#REF!,5,FALSE),"") | D27: =IFERROR(VLOOKUP(B27,#REF!,4,FALSE),"") | E27: 26 | F27: =B27 -> #REF! | H27: =IF(#REF!<>"",#REF!,"") -> #REF! | I27: =IF(VLOOKUP(H27,#REF!,4,0)="√",1,0) -> #REF! | J27: =IF(VLOOKUP(H27,#REF!,5,0)="√",1,0) -> #REF! | M27: 9 | P27: 自身(5尺半径) | Q27: 专注，至多10分钟 | V27: =SUM(#REF!*#REF!) -> #REF! | W27: =SUM(#REF!*#REF!) -> #REF! | X27: =SUM(#REF!*#REF!) -> #REF! | Y27: =SUM(#REF!*#REF!) -> #REF! | AI27: 34000 | AJ27: 8 | AL27: =IF(#REF!="O",1,0) -> #REF! | AQ27: 蜡烛 | AR27: 一只蜡烛可以为其身边5尺半径范围提供明亮光照，以及该范围外5尺的微光光照。蜡烛的照明效果可以持续1小时。 | AS27: 0.01gp | AT27: 0 | AW27: 梦族语
A28: 27 | B28: =IF(#REF!="","",#REF!) -> #REF! | C28: =IFERROR(VLOOKUP(B28,#REF!,5,FALSE),"") | D28: =IFERROR(VLOOKUP(B28,#REF!,4,FALSE),"") | E28: 27 | F28: =B28 -> #REF! | H28: =IF(#REF!<>"",#REF!,"") -> #REF! | I28: =IF(VLOOKUP(H28,#REF!,4,0)="√",1,0) -> #REF! | J28: =IF(VLOOKUP(H28,#REF!,5,0)="√",1,0) -> #REF! | P28: 自身(30尺半径) | Q28: 专注，至多1小时 | V28: =SUM(#REF!*#REF!) -> #REF! | W28: =SUM(#REF!*#REF!) -> #REF! | X28: =SUM(#REF!*#REF!) -> #REF! | Y28: =SUM(#REF!*#REF!) -> #REF! | AI28: 48000 | AJ28: 9 | AL28: =IF(#REF!="O",1,0) -> #REF! | AQ28: 弩矢匣 | AR28: 一只木匣能装二十支弩矢。 | AS28: 1gp | AT28: 1 | AW28: 狮族语
A29: 28 | B29: =IF(#REF!="","",#REF!) -> #REF! | C29: =IFERROR(VLOOKUP(B29,#REF!,5,FALSE),"") | D29: =IFERROR(VLOOKUP(B29,#REF!,4,FALSE),"") | E29: 28 | F29: =B29 -> #REF! | H29: =IF(#REF!<>"",#REF!,"") -> #REF! | I29: =IF(VLOOKUP(H29,#REF!,4,0)="√",1,0) -> #REF! | J29: =IF(VLOOKUP(H29,#REF!,5,0)="√",1,0) -> #REF! | P29: 自身(15尺立方) | Q29: 10日 | AI29: 64000 | AJ29: 10 | AL29: =IF(#REF!="O",1,0) -> #REF! | AQ29: 地图或卷轴匣 | AR29: 一个圆柱形皮匣能够装上十张卷起的纸或是五张卷起的羊皮纸。 | AS29: 1gp | AT29: 1 | AW29: 阿兰寇拉语
A30: 29 | B30: =IF(#REF!="","",#REF!) -> #REF! | C30: =IFERROR(VLOOKUP(B30,#REF!,5,FALSE),"") | D30: =IFERROR(VLOOKUP(B30,#REF!,4,FALSE),"") | E30: 29 | F30: =B30 -> #REF! | H30: =IF(#REF!<>"",#REF!,"") -> #REF! | I30: =IF(VLOOKUP(H30,#REF!,4,0)="√",1,0) -> #REF! | J30: =IF(VLOOKUP(H30,#REF!,5,0)="√",1,0) -> #REF! | P30: 自身(30尺锥状) | Q30: 7日 | V30: =SUM(#REF!*#REF!) -> #REF! | W30: =SUM(#REF!*#REF!) -> #REF! | X30: =SUM(#REF!*#REF!) -> #REF! | Y30: =SUM(#REF!*#REF!) -> #REF! | AI30: 85000 | AJ30: 11 | AL30: =IF(#REF!="O",1,0) -> #REF! | AQ30: 链条_10尺 | AR30: 一根链条有10点生命值。它可以被一次成功的DC20力量检定挣断。 | AS30: 5gp | AT30: 10 | AW30: 哈多兹鼯猴人语
A31: 30 | B31: =IF(#REF!="","",#REF!) -> #REF! | C31: =IFERROR(VLOOKUP(B31,#REF!,5,FALSE),"") | D31: =IFERROR(VLOOKUP(B31,#REF!,4,FALSE),"") | E31: 30 | F31: =B31 -> #REF! | H31: =IF(#REF!<>"",#REF!,"") -> #REF! | I31: =IF(VLOOKUP(H31,#REF!,4,0)="√",1,0) -> #REF! | J31: =IF(VLOOKUP(H31,#REF!,5,0)="√",1,0) -> #REF! | P31: 自身(30尺线状) | Q31: 30日 | V31: =SUM(#REF!*#REF!) -> #REF! | W31: =SUM(#REF!*#REF!) -> #REF! | X31: =SUM(#REF!*#REF!) -> #REF! | Y31: =SUM(#REF!*#REF!) -> #REF! | AI31: 100000 | AJ31: 12 | AL31: =IF(#REF!="O",1,0) -> #REF! | AQ31: 粉笔_1块 | AR31: - | AS31: 0.01gp | AT31: 0 | AW31: 斯里克林语
A32: 31 | B32: =IF(#REF!="","",#REF!) -> #REF! | C32: =IFERROR(VLOOKUP(B32,#REF!,5,FALSE),"") | D32: =IFERROR(VLOOKUP(B32,#REF!,4,FALSE),"") | E32: 31 | F32: =B32 -> #REF! | H32: =IF(#REF!<>"",#REF!,"") -> #REF! | I32: =IF(VLOOKUP(H32,#REF!,4,0)="√",1,0) -> #REF! | J32: =IF(VLOOKUP(H32,#REF!,5,0)="√",1,0) -> #REF! | P32: 1里 | Q32: 特殊 | V32: =SUM(#REF!*#REF!) -> #REF! | W32: =SUM(#REF!*#REF!) -> #REF! | X32: =SUM(#REF!*#REF!) -> #REF! | Y32: =SUM(#REF!*#REF!) -> #REF! | AI32: 120000 | AJ32: 13 | AL32: =IF(#REF!="O",1,0) -> #REF! | AQ32: 箱子 | AR32: 一个箱子可以容纳12立方尺或300磅重的物品。 | AS32: 5gp | AT32: 25
A33: 32 | B33: =IF(#REF!="","",#REF!) -> #REF! | C33: =IFERROR(VLOOKUP(B33,#REF!,5,FALSE),"") | D33: =IFERROR(VLOOKUP(B33,#REF!,4,FALSE),"") | E33: 32 | F33: =B33 -> #REF! | H33: =IF(#REF!<>"",#REF!,"") -> #REF! | I33: =IF(VLOOKUP(H33,#REF!,4,0)="√",1,0) -> #REF! | J33: =IF(VLOOKUP(H33,#REF!,5,0)="√",1,0) -> #REF! | P33: 视野内 | Q33: 直到被解除 | V33: =SUM(#REF!*#REF!) -> #REF! | W33: =SUM(#REF!*#REF!) -> #REF! | X33: =SUM(#REF!*#REF!) -> #REF! | Y33: =SUM(#REF!*#REF!) -> #REF! | AI33: 140000 | AJ33: 14 | AL33: =IF(#REF!="O",1,0) -> #REF! | AQ33: 攀爬工具 | AR33: 一套攀爬工具包括特制的岩钉，靴子包头，手套和系带。你可以用一个动作来运用攀爬工具锚定自己；此时你不会从锚定处摔落超过25尺，且在解除锚定前无法从锚定处向外攀爬超过25尺。 | AS33: 25gp | AT33: 12
A34: 33 | B34: =IF(#REF!="","",#REF!) -> #REF! | C34: =IFERROR(VLOOKUP(B34,#REF!,5,FALSE),"") | D34: =IFERROR(VLOOKUP(B34,#REF!,4,FALSE),"") | E34: 33 | F34: =B34 -> #REF! | H34: =IF(#REF!<>"",#REF!,"") -> #REF! | I34: =IF(VLOOKUP(H34,#REF!,4,0)="√",1,0) -> #REF! | J34: =IF(VLOOKUP(H34,#REF!,5,0)="√",1,0) -> #REF! | P34: 特殊 | Q34: 直至被解除或被触发 | V34: =SUM(#REF!*#REF!) -> #REF! | W34: =SUM(#REF!*#REF!) -> #REF! | X34: =SUM(#REF!*#REF!) -> #REF! | Y34: =SUM(#REF!*#REF!) -> #REF! | AI34: 165000 | AJ34: 15 | AL34: =IF(#REF!="O",1,0) -> #REF! | AQ34: 普通服装 | AR34: - | AS34: 0.5gp | AT34: 3
A35: 34 | B35: =IF(#REF!="","",#REF!) -> #REF! | C35: =IFERROR(VLOOKUP(B35,#REF!,5,FALSE),"") | D35: =IFERROR(VLOOKUP(B35,#REF!,4,FALSE),"") | E35: 34 | F35: =B35 -> #REF! | H35: =IF(#REF!<>"",#REF!,"") -> #REF! | I35: =IF(VLOOKUP(H35,#REF!,4,0)="√",1,0) -> #REF! | J35: =IF(VLOOKUP(H35,#REF!,5,0)="√",1,0) -> #REF! | Q35: 直至被驱散 | V35: =SUM(#REF!*#REF!) -> #REF! | W35: =SUM(#REF!*#REF!) -> #REF! | X35: =SUM(#REF!*#REF!) -> #REF! | Y35: =SUM(#REF!*#REF!) -> #REF! | AI35: 195000 | AJ35: 16 | AL35: =IF(#REF!="O",1,0) -> #REF! | AQ35: 表演服装 | AR35: - | AS35: 5gp | AT35: 4
A36: 35 | B36: =IF(#REF!="","",#REF!) -> #REF! | C36: =IFERROR(VLOOKUP(B36,#REF!,5,FALSE),"") | D36: =IFERROR(VLOOKUP(B36,#REF!,4,FALSE),"") | E36: 35 | F36: =B36 -> #REF! | H36: =IF(#REF!<>"",#REF!,"") -> #REF! | I36: =IF(VLOOKUP(H36,#REF!,4,0)="√",1,0) -> #REF! | J36: =IF(VLOOKUP(H36,#REF!,5,0)="√",1,0) -> #REF! | V36: =SUM(#REF!*#REF!) -> #REF! | W36: =SUM(#REF!*#REF!) -> #REF! | X36: =SUM(#REF!*#REF!) -> #REF! | Y36: =SUM(#REF!*#REF!) -> #REF! | AI36: 225000 | AJ36: 17 | AL36: =IF(#REF!="O",1,0) -> #REF! | AQ36: 高档服装 | AR36: - | AS36: 15gp | AT36: 6
A37: 36 | B37: =IF(#REF!="","",#REF!) -> #REF! | C37: =IFERROR(VLOOKUP(B37,#REF!,5,FALSE),"") | D37: =IFERROR(VLOOKUP(B37,#REF!,4,FALSE),"") | E37: 36 | F37: =B37 -> #REF! | H37: =IF(#REF!<>"",#REF!,"") -> #REF! | I37: =IF(VLOOKUP(H37,#REF!,4,0)="√",1,0) -> #REF! | J37: =IF(VLOOKUP(H37,#REF!,5,0)="√",1,0) -> #REF! | V37: =SUM(#REF!*#REF!) -> #REF! | W37: =SUM(#REF!*#REF!) -> #REF! | X37: =SUM(#REF!*#REF!) -> #REF! | Y37: =SUM(#REF!*#REF!) -> #REF! | AI37: 265000 | AJ37: 18 | AL37: =IF(#REF!="O",1,0) -> #REF! | AQ37: 旅行者服装 | AR37: - | AS37: 2gp | AT37: 4
A38: 37 | B38: =IF(#REF!="","",#REF!) -> #REF! | C38: =IFERROR(VLOOKUP(B38,#REF!,5,FALSE),"") | D38: =IFERROR(VLOOKUP(B38,#REF!,4,FALSE),"") | E38: 37 | F38: =B38 -> #REF! | H38: =IF(#REF!<>"",#REF!,"") -> #REF! | I38: =IF(VLOOKUP(H38,#REF!,4,0)="√",1,0) -> #REF! | J38: =IF(VLOOKUP(H38,#REF!,5,0)="√",1,0) -> #REF! | V38: =SUM(#REF!*#REF!) -> #REF! | W38: =SUM(#REF!*#REF!) -> #REF! | X38: =SUM(#REF!*#REF!) -> #REF! | Y38: =SUM(#REF!*#REF!) -> #REF! | AI38: 305000 | AJ38: 19 | AL38: =IF(#REF!="O",1,0) -> #REF! | AQ38: 材料包 | AR38: 材料包是一个防水的皮质小小包，其内有间格用以放置各种材料成分以及其它你需要用以施展法术的特殊物品。某些有着特定价格的材料不包含在材料包中（详见相关法术的描述内容）。 | AS38: 25gp | AT38: 2
A39: 38 | B39: =IF(#REF!="","",#REF!) -> #REF! | C39: =IFERROR(VLOOKUP(B39,#REF!,5,FALSE),"") | D39: =IFERROR(VLOOKUP(B39,#REF!,4,FALSE),"") | E39: 38 | F39: =B39 -> #REF! | H39: =IF(#REF!<>"",#REF!,"") -> #REF! | I39: =IF(VLOOKUP(H39,#REF!,4,0)="√",1,0) -> #REF! | J39: =IF(VLOOKUP(H39,#REF!,5,0)="√",1,0) -> #REF! | V39: =SUM(#REF!*#REF!) -> #REF! | W39: =SUM(#REF!*#REF!) -> #REF! | X39: =SUM(#REF!*#REF!) -> #REF! | Y39: =SUM(#REF!*#REF!) -> #REF! | AI39: 355000 | AJ39: 20 | AQ39: 撬棍 | AR39: 在适当的地方使用撬棍时，可以让相应的力量检定具有优势。 | AS39: 2gp | AT39: 5
A40: 39 | B40: =IF(#REF!="","",#REF!) -> #REF! | C40: =IFERROR(VLOOKUP(B40,#REF!,5,FALSE),"") | D40: =IFERROR(VLOOKUP(B40,#REF!,4,FALSE),"") | E40: 39 | F40: =B40 -> #REF! | H40: =IF(#REF!<>"",#REF!,"") -> #REF! | I40: =IF(VLOOKUP(H40,#REF!,4,0)="√",1,0) -> #REF! | J40: =IF(VLOOKUP(H40,#REF!,5,0)="√",1,0) -> #REF! | AQ40: 槲寄生枝条 | AR40: 德鲁伊法器是一件用来引导德鲁伊法术的特殊物品。它可以是一枝槲寄生或冬青，一根用紫衫木或其它特殊木材制作的魔杖或节杖，一根从活树上折下的法杖或是一个包含神圣动物身上的羽毛、毛皮、骨头和牙齿组合成的图腾。德鲁伊能将这样的物品用作其施法的法器。 | AS40: 1gp | AT40: 0
A41: 40 | B41: =IF(#REF!="","",#REF!) -> #REF! | C41: =IFERROR(VLOOKUP(B41,#REF!,5,FALSE),"") | D41: =IFERROR(VLOOKUP(B41,#REF!,4,FALSE),"") | E41: 40 | F41: =B41 -> #REF! | H41: =IF(#REF!<>"",#REF!,"") -> #REF! | I41: =IF(VLOOKUP(H41,#REF!,4,0)="√",1,0) -> #REF! | J41: =IF(VLOOKUP(H41,#REF!,5,0)="√",1,0) -> #REF! | AI41: 阵营 | AQ41: 图腾 | AR41: 德鲁伊法器是一件用来引导德鲁伊法术的特殊物品。它可以是一枝槲寄生或冬青，一根用紫衫木或其它特殊木材制作的魔杖或节杖，一根从活树上折下的法杖或是一个包含神圣动物身上的羽毛、毛皮、骨头和牙齿组合成的图腾。德鲁伊能将这样的物品用作其施法的法器。 | AS41: 1gp | AT41: 0
A42: 41 | B42: =IF(#REF!="","",#REF!) -> #REF! | C42: =IFERROR(VLOOKUP(B42,#REF!,5,FALSE),"") | D42: =IFERROR(VLOOKUP(B42,#REF!,4,FALSE),"") | E42: 41 | F42: =B42 -> #REF! | H42: =IF(#REF!<>"",#REF!,"") -> #REF! | I42: =IF(VLOOKUP(H42,#REF!,4,0)="√",1,0) -> #REF! | J42: =IF(VLOOKUP(H42,#REF!,5,0)="√",1,0) -> #REF! | AI42: 守序善良 | AJ42: 中立善良 | AK42: 混乱善良 | AQ42: 木制法杖 | AR42: 德鲁伊法器是一件用来引导德鲁伊法术的特殊物品。它可以是一枝槲寄生或冬青，一根用紫衫木或其它特殊木材制作的魔杖或节杖，一根从活树上折下的法杖或是一个包含神圣动物身上的羽毛、毛皮、骨头和牙齿组合成的图腾。德鲁伊能将这样的物品用作其施法的法器。 | AS42: 5gp | AT42: 4
A43: 42 | B43: =IF(#REF!="","",#REF!) -> #REF! | C43: =IFERROR(VLOOKUP(B43,#REF!,5,FALSE),"") | D43: =IFERROR(VLOOKUP(B43,#REF!,4,FALSE),"") | E43: 42 | F43: =B43 -> #REF! | H43: =IF(#REF!<>"",#REF!,"") -> #REF! | I43: =IF(VLOOKUP(H43,#REF!,4,0)="√",1,0) -> #REF! | J43: =IF(VLOOKUP(H43,#REF!,5,0)="√",1,0) -> #REF! | AI43: 守序中立 | AJ43: 绝对中立 | AK43: 混乱中立 | AQ43: 紫衫魔杖 | AR43: 德鲁伊法器是一件用来引导德鲁伊法术的特殊物品。它可以是一枝槲寄生或冬青，一根用紫衫木或其它特殊木材制作的魔杖或节杖，一根从活树上折下的法杖或是一个包含神圣动物身上的羽毛、毛皮、骨头和牙齿组合成的图腾。德鲁伊能将这样的物品用作其施法的法器。 | AS43: 10gp | AT43: 1
A44: 43 | B44: =IF(#REF!="","",#REF!) -> #REF! | C44: =IFERROR(VLOOKUP(B44,#REF!,5,FALSE),"") | D44: =IFERROR(VLOOKUP(B44,#REF!,4,FALSE),"") | E44: 43 | F44: =B44 -> #REF! | H44: =IF(#REF!<>"",#REF!,"") -> #REF! | I44: =IF(VLOOKUP(H44,#REF!,4,0)="√",1,0) -> #REF! | J44: =IF(VLOOKUP(H44,#REF!,5,0)="√",1,0) -> #REF! | AI44: 守序邪恶 | AJ44: 中立邪恶 | AK44: 混乱邪恶 | AQ44: 渔具 | AR44: 一套渔具工具包中，装有一根木杆、丝线、软木转轴、铅坠、天鹅绒饵以及窄眼网。 | AS44: 1gp | AT44: 4
A45: 44 | B45: =IF(#REF!="","",#REF!) -> #REF! | C45: =IFERROR(VLOOKUP(B45,#REF!,5,FALSE),"") | D45: =IFERROR(VLOOKUP(B45,#REF!,4,FALSE),"") | E45: 44 | F45: =B45 -> #REF! | H45: =IF(#REF!<>"",#REF!,"") -> #REF! | I45: =IF(VLOOKUP(H45,#REF!,4,0)="√",1,0) -> #REF! | J45: =IF(VLOOKUP(H45,#REF!,5,0)="√",1,0) -> #REF! | AQ45: 扁瓶或大杯 | AR45: 一个扁瓶或大杯可以容纳1品脱的液体。 | AS45: 0.02gp | AT45: 1
A46: 45 | B46: =IF(#REF!="","",#REF!) -> #REF! | C46: =IFERROR(VLOOKUP(B46,#REF!,5,FALSE),"") | D46: =IFERROR(VLOOKUP(B46,#REF!,4,FALSE),"") | E46: 45 | F46: =B46 -> #REF! | H46: =IF(#REF!<>"",#REF!,"") -> #REF! | I46: =IF(VLOOKUP(H46,#REF!,4,0)="√",1,0) -> #REF! | J46: =IF(VLOOKUP(H46,#REF!,5,0)="√",1,0) -> #REF! | AL46: 等级 | AM46: 熟练加值 | AQ46: 爪钩 | AR46: - | AS46: 2gp | AT46: 4
A47: 46 | B47: =IF(#REF!="","",#REF!) -> #REF! | C47: =IFERROR(VLOOKUP(B47,#REF!,5,FALSE),"") | D47: =IFERROR(VLOOKUP(B47,#REF!,4,FALSE),"") | E47: 46 | F47: =B47 -> #REF! | H47: =IF(#REF!<>"",#REF!,"") -> #REF! | I47: =IF(VLOOKUP(H47,#REF!,4,0)="√",1,0) -> #REF! | J47: =IF(VLOOKUP(H47,#REF!,5,0)="√",1,0) -> #REF! | AL47: 1 | AM47: 2 | AQ47: 锤子 | AR47: - | AS47: 1gp | AT47: 3
A48: 47 | B48: =IF(#REF!="","",#REF!) -> #REF! | C48: =IFERROR(VLOOKUP(B48,#REF!,5,FALSE),"") | D48: =IFERROR(VLOOKUP(B48,#REF!,4,FALSE),"") | E48: 47 | F48: =B48 -> #REF! | H48: =IF(#REF!<>"",#REF!,"") -> #REF! | I48: =IF(VLOOKUP(H48,#REF!,4,0)="√",1,0) -> #REF! | J48: =IF(VLOOKUP(H48,#REF!,5,0)="√",1,0) -> #REF! | AL48: 2 | AM48: 2 | AQ48: 大锤 | AR48: - | AS48: 2gp | AT48: 10
A49: 48 | B49: =IF(#REF!="","",#REF!) -> #REF! | C49: =IFERROR(VLOOKUP(B49,#REF!,5,FALSE),"") | D49: =IFERROR(VLOOKUP(B49,#REF!,4,FALSE),"") | E49: 48 | F49: =B49 -> #REF! | H49: =IF(#REF!<>"",#REF!,"") -> #REF! | I49: =IF(VLOOKUP(H49,#REF!,4,0)="√",1,0) -> #REF! | J49: =IF(VLOOKUP(H49,#REF!,5,0)="√",1,0) -> #REF! | AL49: 3 | AM49: 2 | AQ49: 医疗包 | AR49: 一个医疗用小皮包中，装有绷带、药膏和夹板。医疗包可以使用十次。你可以使用一个动作，并花费一次使用次数来为一个生命值为0的生物稳定伤势，而无需进行相应的感知（医药）检定。 | AS49: 5gp | AT49: 3
A50: 49 | B50: =IF(#REF!="","",#REF!) -> #REF! | C50: =IFERROR(VLOOKUP(B50,#REF!,5,FALSE),"") | D50: =IFERROR(VLOOKUP(B50,#REF!,4,FALSE),"") | E50: 49 | F50: =B50 -> #REF! | H50: =IF(#REF!<>"",#REF!,"") -> #REF! | I50: =IF(VLOOKUP(H50,#REF!,4,0)="√",1,0) -> #REF! | J50: =IF(VLOOKUP(H50,#REF!,5,0)="√",1,0) -> #REF! | AL50: 4 | AM50: 2 | AQ50: 护符 | AR50: 枚圣徽是某个神袛或神系象征。它可能是一个描绘有代表一个神袛符号的护身符，相同的符号可能作为一个徽章被仔细地雕刻或镶嵌在一面盾牌上，也可能是一个盛有一块神圣遗物碎片的小盒。附录B中列举有多元宇宙众神的代表性徵记。牧师或圣武士能将圣徽用作其施法的法器。使用这些圣徽时，施法着必须将其握在手中，戴在身上可见处，或者将其装在盾上使用。 | AS50: 5gp | AT50: 1
A51: 50 | B51: =IF(#REF!="","",#REF!) -> #REF! | C51: =IFERROR(VLOOKUP(B51,#REF!,5,FALSE),"") | D51: =IFERROR(VLOOKUP(B51,#REF!,4,FALSE),"") | E51: 50 | F51: =B51 -> #REF! | H51: =IF(#REF!<>"",#REF!,"") -> #REF! | I51: =IF(VLOOKUP(H51,#REF!,4,0)="√",1,0) -> #REF! | J51: =IF(VLOOKUP(H51,#REF!,5,0)="√",1,0) -> #REF! | AL51: 5 | AM51: 3 | AQ51: 徽章 | AR51: 枚圣徽是某个神袛或神系象征。它可能是一个描绘有代表一个神袛符号的护身符，相同的符号可能作为一个徽章被仔细地雕刻或镶嵌在一面盾牌上，也可能是一个盛有一块神圣遗物碎片的小盒。附录B中列举有多元宇宙众神的代表性徵记。牧师或圣武士能将圣徽用作其施法的法器。使用这些圣徽时，施法着必须将其握在手中，戴在身上可见处，或者将其装在盾上使用。 | AS51: 5gp | AT51: 0
A52: 51 | B52: =IF(#REF!="","",#REF!) -> #REF! | C52: =IFERROR(VLOOKUP(B52,#REF!,5,FALSE),"") | D52: =IFERROR(VLOOKUP(B52,#REF!,4,FALSE),"") | E52: 51 | F52: =B52 -> #REF! | H52: =IF(#REF!<>"",#REF!,"") -> #REF! | I52: =IF(VLOOKUP(H52,#REF!,4,0)="√",1,0) -> #REF! | J52: =IF(VLOOKUP(H52,#REF!,5,0)="√",1,0) -> #REF! | AL52: 6 | AM52: 3 | AQ52: 圣物匣 | AR52: 枚圣徽是某个神袛或神系象征。它可能是一个描绘有代表一个神袛符号的护身符，相同的符号可能作为一个徽章被仔细地雕刻或镶嵌在一面盾牌上，也可能是一个盛有一块神圣遗物碎片的小盒。附录B中列举有多元宇宙众神的代表性徵记。牧师或圣武士能将圣徽用作其施法的法器。使用这些圣徽时，施法着必须将其握在手中，戴在身上可见处，或者将其装在盾上使用。 | AS52: 5gp | AT52: 2
A53: 52 | B53: =IF(#REF!="","",#REF!) -> #REF! | C53: =IFERROR(VLOOKUP(B53,#REF!,5,FALSE),"") | D53: =IFERROR(VLOOKUP(B53,#REF!,4,FALSE),"") | E53: 52 | F53: =B53 -> #REF! | H53: =IF(#REF!<>"",#REF!,"") -> #REF! | I53: =IF(VLOOKUP(H53,#REF!,4,0)="√",1,0) -> #REF! | J53: =IF(VLOOKUP(H53,#REF!,5,0)="√",1,0) -> #REF! | AL53: 7 | AM53: 3 | AQ53: 圣水_扁瓶 | AR53: 你可以用一个动作将这小瓶液体泼溅到你身边5尺范围内的一个生物身上，或是将小瓶投到至多20尺远的地方，并利用冲击打破它。两种情况都可以视为对一个生物或物件发动一次远程攻击，并将圣水视为一件临时武器。命中时，如果目标是一只邪魔或不死生物，则目标受到2d6点光耀伤害。 一名牧师或圣武士能通过主持一种特殊的仪式来创造圣水。该仪式花费1小时进行，且需要花费价值25gp的银粉，并消耗施法者一枚1环法术位。 | AS53: 25gp | AT53: 1
A54: 53 | B54: =IF(#REF!="","",#REF!) -> #REF! | C54: =IFERROR(VLOOKUP(B54,#REF!,5,FALSE),"") | D54: =IFERROR(VLOOKUP(B54,#REF!,4,FALSE),"") | E54: 53 | F54: =B54 -> #REF! | H54: =IF(#REF!<>"",#REF!,"") -> #REF! | I54: =IF(VLOOKUP(H54,#REF!,4,0)="√",1,0) -> #REF! | J54: =IF(VLOOKUP(H54,#REF!,5,0)="√",1,0) -> #REF! | AL54: 8 | AM54: 3 | AQ54: 沙漏 | AR54: - | AS54: 25gp | AT54: 1
A55: 54 | B55: =IF(#REF!="","",#REF!) -> #REF! | C55: =IFERROR(VLOOKUP(B55,#REF!,5,FALSE),"") | D55: =IFERROR(VLOOKUP(B55,#REF!,4,FALSE),"") | E55: 54 | F55: =B55 -> #REF! | H55: =IF(#REF!<>"",#REF!,"") -> #REF! | I55: =IF(VLOOKUP(H55,#REF!,4,0)="√",1,0) -> #REF! | J55: =IF(VLOOKUP(H55,#REF!,5,0)="√",1,0) -> #REF! | AI55: 运动 | AJ55: =VLOOKUP(AI55,#REF!,7,FALSE) -> #REF! | AL55: 9 | AM55: 4 | AQ55: 狩猎陷阱 | AR55: 使用动作设置好该陷阱后，其形成一个锯齿钢圈，并在生物踏上其中央压板时闭合。陷阱由一根沉重的链条固定在某处，例如一棵树或是一根钉在地上的钉子。任何踩上压板的生物都必须进行一次DC13的敏捷豁免，豁免失败则受到1d4点穿刺伤害，并停止移动。在该生物从陷阱中解脱前，其移动范围都被限制在链条的长度内（通常为3尺）。一个生物可以使用动作进行一次DC13的力量检定，以解脱自己或其触及范围内的另一生物。每次豁免失败时，被困生物都将受到1点穿刺伤害。 | AS55: 5gp | AT55: 25
A56: 55 | B56: =IF(#REF!="","",#REF!) -> #REF! | C56: =IFERROR(VLOOKUP(B56,#REF!,5,FALSE),"") | D56: =IFERROR(VLOOKUP(B56,#REF!,4,FALSE),"") | E56: 55 | F56: =B56 -> #REF! | H56: =IF(#REF!<>"",#REF!,"") -> #REF! | I56: =IF(VLOOKUP(H56,#REF!,4,0)="√",1,0) -> #REF! | J56: =IF(VLOOKUP(H56,#REF!,5,0)="√",1,0) -> #REF! | AI56: 特技 | AJ56: =VLOOKUP(AI56,#REF!,7,FALSE) -> #REF! | AL56: 10 | AM56: 4 | AQ56: 墨水_1盎司瓶 | AR56: - | AS56: 10gp | AT56: 0
A57: 56 | B57: =IF(#REF!="","",#REF!) -> #REF! | C57: =IFERROR(VLOOKUP(B57,#REF!,5,FALSE),"") | D57: =IFERROR(VLOOKUP(B57,#REF!,4,FALSE),"") | E57: 56 | F57: =B57 -> #REF! | H57: =IF(#REF!<>"",#REF!,"") -> #REF! | I57: =IF(VLOOKUP(H57,#REF!,4,0)="√",1,0) -> #REF! | J57: =IF(VLOOKUP(H57,#REF!,5,0)="√",1,0) -> #REF! | AI57: 巧手 | AJ57: =VLOOKUP(AI57,#REF!,7,FALSE) -> #REF! | AL57: 11 | AM57: 4 | AQ57: 墨水笔 | AR57: - | AS57: 0.02gp | AT57: 0
A58: 57 | B58: =IF(#REF!="","",#REF!) -> #REF! | C58: =IFERROR(VLOOKUP(B58,#REF!,5,FALSE),"") | D58: =IFERROR(VLOOKUP(B58,#REF!,4,FALSE),"") | E58: 57 | F58: =B58 -> #REF! | H58: =IF(#REF!<>"",#REF!,"") -> #REF! | I58: =IF(VLOOKUP(H58,#REF!,4,0)="√",1,0) -> #REF! | J58: =IF(VLOOKUP(H58,#REF!,5,0)="√",1,0) -> #REF! | AI58: 隐匿 | AJ58: =VLOOKUP(AI58,#REF!,7,FALSE) -> #REF! | AL58: 12 | AM58: 4 | AQ58: 壶或罐 | AR58: - | AS58: 0.02gp | AT58: 4
A59: 58 | B59: =IF(#REF!="","",#REF!) -> #REF! | C59: =IFERROR(VLOOKUP(B59,#REF!,5,FALSE),"") | D59: =IFERROR(VLOOKUP(B59,#REF!,4,FALSE),"") | E59: 58 | F59: =B59 -> #REF! | H59: =IF(#REF!<>"",#REF!,"") -> #REF! | I59: =IF(VLOOKUP(H59,#REF!,4,0)="√",1,0) -> #REF! | J59: =IF(VLOOKUP(H59,#REF!,5,0)="√",1,0) -> #REF! | AI59: 调查 | AJ59: =VLOOKUP(AI59,#REF!,7,FALSE) -> #REF! | AL59: 13 | AM59: 5 | AQ59: 爬梯_10尺 | AR59: - | AS59: 0.1gp | AT59: 25
A60: 59 | B60: =IF(#REF!="","",#REF!) -> #REF! | C60: =IFERROR(VLOOKUP(B60,#REF!,5,FALSE),"") | D60: =IFERROR(VLOOKUP(B60,#REF!,4,FALSE),"") | E60: 59 | F60: =B60 -> #REF! | H60: =IF(#REF!<>"",#REF!,"") -> #REF! | I60: =IF(VLOOKUP(H60,#REF!,4,0)="√",1,0) -> #REF! | J60: =IF(VLOOKUP(H60,#REF!,5,0)="√",1,0) -> #REF! | AI60: 奥秘 | AJ60: =VLOOKUP(AI60,#REF!,7,FALSE) -> #REF! | AL60: 14 | AM60: 5 | AQ60: 油灯 | AR60: 一只油灯可以为其身边15尺半径范围提供明亮光照，以及该范围外30尺的微光光照。点亮的油灯每6小时消耗一扁瓶灯油（1品脱）。 | AS60: 0.5gp | AT60: 1
A61: 60 | B61: =IF(#REF!="","",#REF!) -> #REF! | C61: =IFERROR(VLOOKUP(B61,#REF!,5,FALSE),"") | D61: =IFERROR(VLOOKUP(B61,#REF!,4,FALSE),"") | E61: 60 | F61: =B61 -> #REF! | H61: =IF(#REF!<>"",#REF!,"") -> #REF! | I61: =IF(VLOOKUP(H61,#REF!,4,0)="√",1,0) -> #REF! | J61: =IF(VLOOKUP(H61,#REF!,5,0)="√",1,0) -> #REF! | AI61: 历史 | AJ61: =VLOOKUP(AI61,#REF!,7,FALSE) -> #REF! | AL61: 15 | AM61: 5 | AQ61: 牛眼提灯 | AR61: 一盏牛眼提灯可以为前方60尺的锥状区域提供明亮光照，以及该范围外60尺的微光光照。点亮的牛眼提灯每6小时消耗一扁瓶的灯油（1品脱）。 | AS61: 10gp | AT61: 2
A62: 61 | B62: =IF(#REF!="","",#REF!) -> #REF! | C62: =IFERROR(VLOOKUP(B62,#REF!,5,FALSE),"") | D62: =IFERROR(VLOOKUP(B62,#REF!,4,FALSE),"") | E62: 61 | F62: =B62 -> #REF! | H62: =IF(#REF!<>"",#REF!,"") -> #REF! | I62: =IF(VLOOKUP(H62,#REF!,4,0)="√",1,0) -> #REF! | J62: =IF(VLOOKUP(H62,#REF!,5,0)="√",1,0) -> #REF! | AI62: 自然 | AJ62: =VLOOKUP(AI62,#REF!,7,FALSE) -> #REF! | AL62: 16 | AM62: 5 | AQ62: 附盖提灯 | AR62: 一盏附盖提灯可以为其身边30尺半径范围提供明亮光照，以及该范围外30尺的微光光照。点亮的提灯每6小时消耗一扁瓶的灯油（1品脱）。你可以使用一个动作放下盖子，使其光照减弱为5尺范围的微光照明。 | AS62: 5gp | AT62: 2
A63: 62 | B63: =IF(#REF!="","",#REF!) -> #REF! | C63: =IFERROR(VLOOKUP(B63,#REF!,5,FALSE),"") | D63: =IFERROR(VLOOKUP(B63,#REF!,4,FALSE),"") | E63: 62 | F63: =B63 -> #REF! | H63: =IF(#REF!<>"",#REF!,"") -> #REF! | I63: =IF(VLOOKUP(H63,#REF!,4,0)="√",1,0) -> #REF! | J63: =IF(VLOOKUP(H63,#REF!,5,0)="√",1,0) -> #REF! | AI63: 宗教 | AJ63: =VLOOKUP(AI63,#REF!,7,FALSE) -> #REF! | AL63: 17 | AM63: 6 | AQ63: 锁 | AR63: 每把锁与一把钥匙相配套。不使用钥匙时，一个具有盗贼工具熟练项的生物可以通过一次成功的DC15敏捷检定撬开这把锁。你的DM可以决定是否能够用更高的价格购买更好的锁。 | AS63: 10gp | AT63: 1
A64: 63 | B64: =IF(#REF!="","",#REF!) -> #REF! | C64: =IFERROR(VLOOKUP(B64,#REF!,5,FALSE),"") | D64: =IFERROR(VLOOKUP(B64,#REF!,4,FALSE),"") | E64: 63 | F64: =B64 -> #REF! | H64: =IF(#REF!<>"",#REF!,"") -> #REF! | I64: =IF(VLOOKUP(H64,#REF!,4,0)="√",1,0) -> #REF! | J64: =IF(VLOOKUP(H64,#REF!,5,0)="√",1,0) -> #REF! | AI64: 察觉 | AJ64: =VLOOKUP(AI64,#REF!,7,FALSE) -> #REF! | AL64: 18 | AM64: 6 | AQ64: 放大镜 | AR64: 一枚用以详细观察小物件的透镜。生火时，你也可以用它代替燧石与铁片。使用放大镜聚焦光来生火需要如同阳光般明亮的光照、可用的引火物质以及约5分钟的时间来完成点燃作业。进行估价或是检查某个细小或具有精细细节物件时所作的属性检定可以使用放大镜来获得优势。 | AS64: 100gp | AT64: 0
A65: 64 | B65: =IF(#REF!="","",#REF!) -> #REF! | C65: =IFERROR(VLOOKUP(B65,#REF!,5,FALSE),"") | D65: =IFERROR(VLOOKUP(B65,#REF!,4,FALSE),"") | E65: 64 | F65: =B65 -> #REF! | H65: =IF(#REF!<>"",#REF!,"") -> #REF! | I65: =IF(VLOOKUP(H65,#REF!,4,0)="√",1,0) -> #REF! | J65: =IF(VLOOKUP(H65,#REF!,5,0)="√",1,0) -> #REF! | AI65: 洞悉 | AJ65: =VLOOKUP(AI65,#REF!,7,FALSE) -> #REF! | AL65: 19 | AM65: 6 | AQ65: 镣铐 | AR65: 这些金属束具可以困住一只小型或中型体型的生物。解开镣铐必须成功通过一次DC20的敏捷检定。破坏镣铐则必须成功通过一次DC20的力量检定。每套镣铐配有一把对应的钥匙。不用钥匙时，一个具有盗贼工具熟练项的生物可以通过一次成功的DC15敏捷检定撬开镣铐的锁。镣铐具有15点生命值。 | AS65: 2gp | AT65: 6
A66: 65 | B66: =IF(#REF!="","",#REF!) -> #REF! | C66: =IFERROR(VLOOKUP(B66,#REF!,5,FALSE),"") | D66: =IFERROR(VLOOKUP(B66,#REF!,4,FALSE),"") | E66: 65 | F66: =B66 -> #REF! | H66: =IF(#REF!<>"",#REF!,"") -> #REF! | I66: =IF(VLOOKUP(H66,#REF!,4,0)="√",1,0) -> #REF! | J66: =IF(VLOOKUP(H66,#REF!,5,0)="√",1,0) -> #REF! | AI66: 驯养 | AJ66: =VLOOKUP(AI66,#REF!,7,FALSE) -> #REF! | AL66: 20 | AM66: 6 | AQ66: 野炊工具 | AR66: 一个野炊工具锡盒包括一只茶杯和一些简易餐具。盒子被夹在一起，并且其中一面能够被用作一只煎锅而另一面则可以作为一只碟子或是浅碗。 | AS66: 0.2gp | AT66: 1
A67: 66 | B67: =IF(#REF!="","",#REF!) -> #REF! | C67: =IFERROR(VLOOKUP(B67,#REF!,5,FALSE),"") | D67: =IFERROR(VLOOKUP(B67,#REF!,4,FALSE),"") | E67: 66 | F67: =B67 -> #REF! | H67: =IF(#REF!<>"",#REF!,"") -> #REF! | I67: =IF(VLOOKUP(H67,#REF!,4,0)="√",1,0) -> #REF! | J67: =IF(VLOOKUP(H67,#REF!,5,0)="√",1,0) -> #REF! | AI67: 医疗 | AJ67: =VLOOKUP(AI67,#REF!,7,FALSE) -> #REF! | AQ67: 钢面镜 | AR67: - | AS67: 5gp | AT67: 0.5
A68: 67 | B68: =IF(#REF!="","",#REF!) -> #REF! | C68: =IFERROR(VLOOKUP(B68,#REF!,5,FALSE),"") | D68: =IFERROR(VLOOKUP(B68,#REF!,4,FALSE),"") | E68: 67 | F68: =B68 -> #REF! | H68: =IF(#REF!<>"",#REF!,"") -> #REF! | I68: =IF(VLOOKUP(H68,#REF!,4,0)="√",1,0) -> #REF! | J68: =IF(VLOOKUP(H68,#REF!,5,0)="√",1,0) -> #REF! | AI68: 生存 | AJ68: =VLOOKUP(AI68,#REF!,7,FALSE) -> #REF! | AL68: CR | AM68: 熟练加值 | AQ68: 灯油_扁瓶 | AR68: 灯油通常装在一个1品脱大小的陶土扁瓶中。你可以用一个动作将扁瓶中的灯油泼溅到你身边5尺范围内的一个生物身上，或是将扁瓶投到至多20尺远的地方，并利用冲击打破它。两种情况都可以视为对一个生物或物件发动一次远程攻击，并将灯油视为一件临时武器。命中时，目标被灯油洒满全身。如果目标在灯油挥发前（1分钟后）受到任何火焰伤害，则目标因燃烧的灯油受到额外5点火焰伤害。你还可以将一扁瓶灯油泼在地面上，以覆盖一块边长5尺且保持水平的方形区域。点燃该区域后，灯油将持续燃烧2轮，并对任何进入该区域或在该区域结束其回合的生物造成5点火焰伤害。同一生物每回合只受该伤害作用一次。 | AS68: 0.1gp | AT68: 1
A69: 68 | B69: =IF(#REF!="","",#REF!) -> #REF! | C69: =IFERROR(VLOOKUP(B69,#REF!,5,FALSE),"") | D69: =IFERROR(VLOOKUP(B69,#REF!,4,FALSE),"") | E69: 68 | F69: =B69 -> #REF! | AI69: 说服 | AJ69: =VLOOKUP(AI69,#REF!,7,FALSE) -> #REF! | AL69: 0 | AM69: 2 | AQ69: 纸_每张 | AR69: - | AS69: 0.2gp | AT69: 0
A70: 69 | B70: =IF(#REF!="","",#REF!) -> #REF! | C70: =IFERROR(VLOOKUP(B70,#REF!,5,FALSE),"") | D70: =IFERROR(VLOOKUP(B70,#REF!,4,FALSE),"") | E70: 69 | F70: =B70 -> #REF! | AI70: 欺诈 | AJ70: =VLOOKUP(AI70,#REF!,7,FALSE) -> #REF! | AL70: 1/8 | AM70: 2 | AQ70: 羊皮纸_每张 | AR70: - | AS70: 0.1gp | AT70: 0
A71: 70 | B71: =IF(#REF!="","",#REF!) -> #REF! | C71: =IFERROR(VLOOKUP(B71,#REF!,5,FALSE),"") | D71: =IFERROR(VLOOKUP(B71,#REF!,4,FALSE),"") | E71: 70 | F71: =B71 -> #REF! | AI71: 威吓 | AJ71: =VLOOKUP(AI71,#REF!,7,FALSE) -> #REF! | AL71: 1/4 | AM71: 2 | AQ71: 香水_小瓶 | AR71: - | AS71: 5gp | AT71: 0
A72: 71 | B72: =IF(#REF!="","",#REF!) -> #REF! | C72: =IFERROR(VLOOKUP(B72,#REF!,5,FALSE),"") | D72: =IFERROR(VLOOKUP(B72,#REF!,4,FALSE),"") | E72: 71 | F72: =B72 -> #REF! | AI72: 表演 | AJ72: =VLOOKUP(AI72,#REF!,7,FALSE) -> #REF! | AL72: 1/2 | AM72: 2 | AQ72: 矿工镐 | AR72: - | AS72: 2gp | AT72: 10
A73: 72 | B73: =IF(#REF!="","",#REF!) -> #REF! | C73: =IFERROR(VLOOKUP(B73,#REF!,5,FALSE),"") | D73: =IFERROR(VLOOKUP(B73,#REF!,4,FALSE),"") | E73: 72 | F73: =B73 -> #REF! | AL73: 1 | AM73: 2 | AQ73: 岩钉 | AR73: - | AS73: 0.05gp | AT73: 0.25
A74: 73 | B74: =IF(#REF!="","",#REF!) -> #REF! | C74: =IFERROR(VLOOKUP(B74,#REF!,5,FALSE),"") | D74: =IFERROR(VLOOKUP(B74,#REF!,4,FALSE),"") | E74: 73 | F74: =B74 -> #REF! | AL74: 2 | AM74: 2 | AQ74: 基础毒药_小瓶 | AR74: 你可以用一个动作将小瓶中的毒药涂于一把挥砍或穿刺武器上，或者涂在至多三发弹药上。涂毒武器或弹药命中时，被命中生物必须进行一次DC10的体质豁免，豁免失败则受到1d4的毒素伤害。涂毒后，武器的毒性效果可以维持1分钟。 | AS74: 100gp | AT74: 0
A75: 74 | B75: =IF(#REF!="","",#REF!) -> #REF! | C75: =IFERROR(VLOOKUP(B75,#REF!,5,FALSE),"") | D75: =IFERROR(VLOOKUP(B75,#REF!,4,FALSE),"") | E75: 74 | F75: =B75 -> #REF! | AL75: 3 | AM75: 2 | AQ75: 长杆_10尺 | AR75: - | AS75: 0.05gp | AT75: 7
A76: 75 | B76: =IF(#REF!="","",#REF!) -> #REF! | C76: =IFERROR(VLOOKUP(B76,#REF!,5,FALSE),"") | D76: =IFERROR(VLOOKUP(B76,#REF!,4,FALSE),"") | E76: 75 | F76: =B76 -> #REF! | AL76: 4 | AM76: 2 | AQ76: 铁壶 | AR76: 一个铁壶可以容纳1加仑的液体。 | AS76: 2gp | AT76: 10
A77: 76 | B77: =IF(#REF!="","",#REF!) -> #REF! | C77: =IFERROR(VLOOKUP(B77,#REF!,5,FALSE),"") | D77: =IFERROR(VLOOKUP(B77,#REF!,4,FALSE),"") | E77: 76 | F77: =B77 -> #REF! | AL77: 5 | AM77: 3 | AQ77: 治疗药水 | AR77: 一种红色的魔力药剂，可以使饮用者恢复2d4+2的生命值。喝药或者喂人喝药需要使用一个动作。 | AS77: 50gp | AT77: 0.5
A78: 77 | B78: =IF(#REF!="","",#REF!) -> #REF! | C78: =IFERROR(VLOOKUP(B78,#REF!,5,FALSE),"") | D78: =IFERROR(VLOOKUP(B78,#REF!,4,FALSE),"") | E78: 77 | F78: =B78 -> #REF! | AL78: 6 | AM78: 3 | AQ78: 小包 | AR78: 一个布料或皮革制成的小包可以装20发弹丸或50发吹矢，或者其他东西。用来装施法材料成分的小包则成为材料包（详见前文）。一个小包最多可以容纳⅕立方尺或6磅重的物体。 | AS78: 0.5gp | AT78: 1
A79: 78 | B79: =IF(#REF!="","",#REF!) -> #REF! | C79: =IFERROR(VLOOKUP(B79,#REF!,5,FALSE),"") | D79: =IFERROR(VLOOKUP(B79,#REF!,4,FALSE),"") | E79: 78 | F79: =B79 -> #REF! | AL79: 7 | AM79: 3 | AQ79: 箭袋 | AR79: 一只箭袋可以盛装20支箭。 | AS79: 1gp | AT79: 1
A80: 79 | B80: =IF(#REF!="","",#REF!) -> #REF! | C80: =IFERROR(VLOOKUP(B80,#REF!,5,FALSE),"") | D80: =IFERROR(VLOOKUP(B80,#REF!,4,FALSE),"") | E80: 79 | F80: =B80 -> #REF! | AL80: 8 | AM80: 3 | AQ80: 便携式攻城锤 | AR80: 你可以使用一具便携式攻城锤破门。此时你破门的力量检定具有 +4加值。如果另一名角色从旁协助，则你破门的力量检定因此而具有优势。 | AS80: 4gp | AT80: 35
A81: 80 | B81: =IF(#REF!="","",#REF!) -> #REF! | C81: =IFERROR(VLOOKUP(B81,#REF!,5,FALSE),"") | D81: =IFERROR(VLOOKUP(B81,#REF!,4,FALSE),"") | E81: 80 | F81: =B81 -> #REF! | AL81: 9 | AM81: 4 | AQ81: 口粮_1日份 | AR81: 适合长途旅行携带的高能量干粮，包括牛肉干、干果、饼干和坚果等。 | AS81: 0.5gp | AT81: 2
A82: 81 | B82: =IF(#REF!="","",#REF!) -> #REF! | C82: =IFERROR(VLOOKUP(B82,#REF!,5,FALSE),"") | D82: =IFERROR(VLOOKUP(B82,#REF!,4,FALSE),"") | E82: 81 | F82: =B82 -> #REF! | AL82: 10 | AM82: 4 | AQ82: 长袍 | AR82: - | AS82: 1gp | AT82: 4
A83: 82 | B83: =IF(#REF!="","",#REF!) -> #REF! | C83: =IFERROR(VLOOKUP(B83,#REF!,5,FALSE),"") | D83: =IFERROR(VLOOKUP(B83,#REF!,4,FALSE),"") | E83: 82 | F83: =B83 -> #REF! | AL83: 11 | AM83: 4 | AQ83: 麻绳_50尺 | AR83: 麻质的绳索，拥有2点生命值，且可以通过一次成功的DC17力量检定扯断。 | AS83: 1gp | AT83: 10
A84: 83 | B84: =IF(#REF!="","",#REF!) -> #REF! | C84: =IFERROR(VLOOKUP(B84,#REF!,5,FALSE),"") | D84: =IFERROR(VLOOKUP(B84,#REF!,4,FALSE),"") | E84: 83 | F84: =B84 -> #REF! | AL84: 12 | AM84: 4 | AQ84: 丝绳_50尺 | AR84: 丝质的绳索，拥有2点生命值，且可以通过一次成功的DC17力量检定扯断。 | AS84: 10gp | AT84: 5
... A102: 101 | B102: =IF(#REF!="","",#REF!) -> #REF! | C102: =IFERROR(VLOOKUP(B102,#REF!,5,FALSE),"") | D102: =IFERROR(VLOOKUP(B102,#REF!,4,FALSE),"") | E102: 101 | F102: =B102 -> #REF! | AL102: 30 | AM102: 9 | AQ102: 酿酒工具 | AR102: 酿酒即是酿造酒精饮料。除了酿酒以外，这套程序还能用于蒸馏淡水。麦酒的发酵需要等待好几周时间，但酿造工作只需要几个小时。 组件Components。酿酒工具包括一个大玻璃罐、一些酵母、一根虹吸管，以及几尺长的管子。 历史History。酿酒工具熟练项能让你在进行与酒大有关联的事件的智力（历史）检定时有更多的了解。 医药Medicine。当你治疗酒精中毒的病人，或你能使用酒精来减轻疼痛时，酿酒工具熟练项会给你更多的启示。 游说Persuasion。酒逢知己千杯少。酿酒工具熟练项能让你向他人提供私酿的美酒，借此改善关系。 饮用水Potable Water。你的酿造知识允许你用非饮用水蒸馏纯净水。你在一次长休中可以蒸馏出6加仑的淡水，而一次短休则只有1加仑。 酿酒工具Brewer’s Supplies 用途 DC 检查饮品中的毒素或杂质 10 鉴定酒精饮料 15 抵抗酒精的影响 20 | AS102: 20gp | AT102: 9
A103: 102 | B103: =IF(#REF!="","",#REF!) -> #REF! | C103: =IFERROR(VLOOKUP(B103,#REF!,5,FALSE),"") | D103: =IFERROR(VLOOKUP(B103,#REF!,4,FALSE),"") | E103: 102 | F103: =B103 -> #REF! | AQ103: 书法工具 | AR103: 书法将写字升华为富有美感的艺术形式。 书法家用独特的风格创作出赏心悦目的文字。他们的工具也提供了验证文稿真伪的能力，前提是书法家要花费数个小时来不断临摹文稿，以掌握其书写风格和结构特征。 组件Components。书法工具包括墨水、一打羊皮纸，以及三支羽毛笔。 奥秘Arcana。虽然书法对于破解魔法密文来说没什么作用，但是书法工具熟练项至少能让你判断出这堆鬼画符的作者是谁。 历史History。该工具熟练项可以在进行分析或调查文本内容的成功检定中获得好处，例如古代文稿、卷轴，还有包括石头上的符文、壁画中的内容或者诸如此类的的其他文本。 解读藏宝图Decipher Treasure Map。该工具熟练项意味着你具有解读地图的专业知识。你可以进行一次智力检定以确定地图的年代，地图是否包含任何隐藏的信息，或类似的内容。 书法工具Calligrapher’s Supplies 用途 DC 判断非魔法手迹的作者 10 理解作者的心态 15 现场伪造文稿 15 伪造签名 20 | AS103: 10gp | AT103: 5
A104: 103 | B104: =IF(#REF!="","",#REF!) -> #REF! | C104: =IFERROR(VLOOKUP(B104,#REF!,5,FALSE),"") | D104: =IFERROR(VLOOKUP(B104,#REF!,4,FALSE),"") | E104: 103 | F104: =B104 -> #REF! | AQ104: 木匠工具 | AR104: 木工技能允许角色打造木结构的物品。木匠可以建造房屋、棚屋、木制橱柜或类似的物品。 组件Components。木匠工具包括一把锯子、一把锤子、一些钉子、一把短斧、一把角尺、一把直尺，一把扁斧，一具木工刨和一把凿子。 历史History。该工具熟练项有助于你分辨木结构建筑和其他大型木制品的用途和来历。 调查Investigation。当你调查木结构建筑时具有额外的洞察力，因为你深谙营造法则，可以发现隐藏的区域。 察觉Perception。你可以发现木墙或地板的不自然之处，从而更容易找到陷阱门和秘密通道。 隐匿Stealth。你可以很快地判断出木地板上的薄弱点，这样就可以更容易地避开，以免发出嘎吱声。 加固Fortify。消耗原材料并进行1分钟的加工，你可以使一扇门或窗更难强行打开。打开门窗的DC值增加5点。 临时住所Temporary Shelter。作为长休的一部分，你可以建造一个棚屋或类似的遮蔽物，使你的团队能在一个阴凉干燥的环境中休息。因为它只是草草搭建起来的临时住所，所以在1d3天后便会倒塌。 木匠工具Carpenter’s Tools 用途 DC 建造简单的木结构 10 设计复杂的木结构 15 在木墙上找到一个薄弱点 15 撬门 20 | AS104: 8gp | AT104: 6
A105: 104 | B105: =IF(#REF!="","",#REF!) -> #REF! | C105: =IFERROR(VLOOKUP(B105,#REF!,5,FALSE),"") | D105: =IFERROR(VLOOKUP(B105,#REF!,4,FALSE),"") | E105: 104 | F105: =B105 -> #REF! | AQ105: 制图工具 | AR105: 使用制图工具，您可以创建精确的地图做旅行为自己和那些来找你更容易。这些地图可以从山脉的大规模描述到显示地下城平面布局的图表。 组件Components。制图工具包括一支鹅毛笔、墨水、羊皮纸，一副圆规、卡尺，和一把直尺。 奥秘Arcana、历史History、宗教Religion。当你使用这些技能时，你可以利用有关于地图和定位的知识来挖掘更详细的信息。例如，你可以在发现一张地图中的隐藏信息，确定地图绘制的年代以判断地理特征从那时起是否发生了变化，等等。 自然Nature。你对自然地理的熟悉使你更容易回答或解释有关于你周遭地形的问题。 求生Survival。你拥有的地理知识能帮你找到走出荒野的道路，判断有可能找到村庄或城镇的方向，以避免迷路。你研究过大量具有共通模式的地图，以至于对贸易路线的演变和定居点的分布格局了然于心。 绘制地图Craft a map。旅行时，除了参加其他活动外，你还可以画一张地图。 制图工具Cartographer’s Tools 用途 DC 确定地图的年代和来历 10 估测地标的方向和距离 15 辨别地图的真伪 15 填补地图上缺漏的部分 20 | AS105: 15gp | AT105: 6
A106: 105 | B106: =IF(#REF!="","",#REF!) -> #REF! | C106: =IFERROR(VLOOKUP(B106,#REF!,5,FALSE),"") | D106: =IFERROR(VLOOKUP(B106,#REF!,4,FALSE),"") | E106: 105 | F106: =B106 -> #REF! | AQ106: 鞋匠工具 | AR106: 虽然鞋匠的生意对冒险者来说似乎太卑微了，但一双好鞋子却能在崎岖的荒野和致命的地牢帮上大忙。 组件Components。鞋匠的工具包括一把锤子、一支锥子、一柄小刀、一个鞋架、一把切刀、备用皮革和线。 奥秘Arcana、历史History。你对鞋子的知识有助于你识别魔法靴的魔法属性或这些物品的历史。 调查Investigation。鞋子能透露出的秘密远比你想象的多。你可以通过检查鞋子的磨损和污迹来推断出某人最近到过什么样的地方。你的修鞋经验能让你更好地判断出导致鞋子磨损的原因。 修鞋Maintain Shoes。作为长休的一部分，你可以保养同伴的鞋子。至多六个由你选定的穿着你修补过的鞋子的生物，接下来的24小时内，在需要进行对抗力竭Exhaustion状态的豁免检定前可以旅行至多10小时。 秘密夹层Craft Hidden Compartment。通过8小时的工作，你可以在一双鞋子内做出一个秘密夹层。这个夹层可以容纳一件至多长3寸、宽1寸的物品。你进行一次附带工具熟练加值的智力检定，以确定寻找夹层所需的智力（调查）检定DC值。 鞋匠工具Cobbler’s Tools 用途 DC 判断一双鞋子的年龄和来历 10 找出鞋后跟的秘密夹层 15 | AS106: 5gp | AT106: 5
A107: 106 | B107: =IF(#REF!="","",#REF!) -> #REF! | C107: =IFERROR(VLOOKUP(B107,#REF!,5,FALSE),"") | D107: =IFERROR(VLOOKUP(B107,#REF!,4,FALSE),"") | E107: 106 | F107: =B107 -> #REF! | AQ107: 厨师工具 | AR107: 冒险可是个辛苦活儿。如果能和一位厨师一起旅行，你的伙食可比整天啃饼干嚼果脯好多了。 组件Components。厨师工具包括一个金属锅、餐刀、餐叉、一柄搅拌勺，和一柄长柄勺。 历史History。你对厨艺的了解允许你品味从餐饮习惯中透露出来的社会模式。 医药Medicine。进行治疗时，你可以改善药物的口感，使其不那么难以下咽。 求生Survival。寻找食物时，你可以把他人认为不能吃的玩意儿处理成可食用的东西。 准备饭菜Prepare Meals。 作为短休的一部分，你可以准备一顿美味的饭菜，帮助同伴恢复体力。在短休时，你和至多五个你所选择的生物每消耗一枚生命骰就可以多恢复1点生命值，只要你有机会使用你的厨师工具并且食材充足。 厨师工具Cook's Utensils 用途 DC 稍微改善伙食 10 做一顿同样的饭 10 检验饭菜中的毒素或杂质 15 | AS107: 1gp | AT107: 8
A108: 107 | B108: =IF(#REF!="","",#REF!) -> #REF! | C108: =IFERROR(VLOOKUP(B108,#REF!,5,FALSE),"") | D108: =IFERROR(VLOOKUP(B108,#REF!,4,FALSE),"") | E108: 107 | F108: =B108 -> #REF! | AQ108: 玻璃匠工具 | AR108: 具有玻璃匠工具熟练项的人不仅知道如何将玻璃吹制成形，还懂得生产玻璃制品的专业知识。 组件Components。这些工具包括一支吹管、一个小搓板、一些模具，和几把工钳。此外你还需要一个热源才能吹制玻璃。 奥秘Arcana、历史History。你的玻璃制造技术有助于检查玻璃制品，例如在藏宝库中发现的药剂瓶或玻璃物品。例如，你可以研究玻璃药瓶受到内容物的影响，以判断药水的效果。（药水可能留有残液、使玻璃变形或造成色斑。） 调查Investigation。当你调查一个拥有碎玻璃或玻璃制品等线索的区域时，你的知识能够提供帮助。 发现弱点Identify Weakness。通过1分钟的研究，你能找出玻璃制品的薄弱点。击打该物件的薄弱点能够造成双倍的伤害。 玻璃匠工具Glassblower’s Tools 用途 DC 判断玻璃的产地 10 判断一件玻璃制品曾经装过什么 20 | AS108: 30gp | AT108: 5
A109: 108 | B109: =IF(#REF!="","",#REF!) -> #REF! | C109: =IFERROR(VLOOKUP(B109,#REF!,5,FALSE),"") | D109: =IFERROR(VLOOKUP(B109,#REF!,4,FALSE),"") | E109: 108 | F109: =B109 -> #REF! | AQ109: 珠宝匠工具 | AR109: 珠宝匠工具的培训包括加工珠宝的基本技术，以及鉴定宝石的专业知识。 组件Components。珠宝匠工具包括一把小锯、小锤、锉刀、钳子，和镊子。 奥秘Arcana。珠宝匠工具熟练项让你能够了解各种宝石的魔法用途。这一能力在你对宝石或镶嵌宝石的物品进行奥秘检定时很有用处。 调查Investigation。当你检查珠宝类物件时，珠宝匠工具熟练项有助于你发现可能存在的线索。 鉴定宝石Identify Gems。 你能很快鉴定出宝石的种类和价值。 珠宝匠工具Eweler’s Tools 用途 DC 宝石外观加工 15 鉴定宝石历史 20 | AS109: 25gp | AT109: 2
A110: 109 | B110: =IF(#REF!="","",#REF!) -> #REF! | C110: =IFERROR(VLOOKUP(B110,#REF!,5,FALSE),"") | D110: =IFERROR(VLOOKUP(B110,#REF!,4,FALSE),"") | E110: 109 | F110: =B110 -> #REF! | AQ110: 皮匠工具 | AR110: 皮匠工具 Leatherworker's Tools 皮革加工的知识还包括兽皮特性、皮革盔甲和类似物品的学识。 组件Components。皮匠工具包括一把小刀、一柄小木槌、一台磨边机、一个打孔器、一个纺锤，以及一些皮革碎料。 奥秘Arcana。皮匠工具熟练项在你检查皮制魔法物品，如鞋子和部分斗篷时提供额外的洞察力。 调查Investigation。当你研究皮制物品或与之相关的线索时，你具有额外的洞察力，因为你对于皮革的专业知识能够发现他人忽略的细节。 皮革鉴定Identify Hides。 当你检查皮革物品时，你能分辨出皮料的种类以及运用的特殊工艺。例如，你能分辨出矮人制革工艺与半身人制革工艺的不同。 皮匠工具Leatherworker’s Tools 用途 DC 皮革外观加工 10 检定皮革制品的历史 20 | AS110: 5gp | AT110: 5
A111: 110 | B111: =IF(#REF!="","",#REF!) -> #REF! | C111: =IFERROR(VLOOKUP(B111,#REF!,5,FALSE),"") | D111: =IFERROR(VLOOKUP(B111,#REF!,4,FALSE),"") | E111: 110 | F111: =B111 -> #REF! | AQ111: 泥瓦匠工具 | AR111: 泥瓦匠工具允许你制造石质或砖制建筑。 组件Components。泥瓦匠工具包括泥刀、锤子、凿子、刷子、和角尺。 历史History。你的专业知识有助于你确定一座石质建筑的建造日期和用途，以及可能是谁建造了它。 调查Investigation。当你检查石质建筑中的区域时，你具有额外的洞察力。 察觉Perception。你可以在石墙或地板上发现不规则的地方，从而更容易找到陷阱门和秘密通道。 拆迁Demolition。你对砖石结构的知识可以让你发现墙壁的薄弱点。你的武器攻击会对这种建筑造成双倍伤害。 泥瓦匠工具Mason’s Tools 用途 DC 在石墙上开个小洞 10 找出石墙的薄弱点 20 | AS111: 10gp | AT111: 8
A112: 111 | B112: =IF(#REF!="","",#REF!) -> #REF! | C112: =IFERROR(VLOOKUP(B112,#REF!,5,FALSE),"") | D112: =IFERROR(VLOOKUP(B112,#REF!,4,FALSE),"") | E112: 111 | F112: =B112 -> #REF! | AQ112: 画家工具 | AR112: 画家工具熟练项代表了你的素描和绘画能力。你也会对艺术史有所了解，这有助于你鉴赏艺术作品。 组件Components。画家工具包括画架、画布、颜料、画笔、炭笔，还有调色板。 奥秘Arcana、历史History、宗教Religion。你的专业知识有助于你了解任何与艺术有关的知识，比如一幅画作的魔法属性或在地下城中发现的奇怪壁画的来历。 调查Investigation、察觉Perception。当你检查一幅画作或类似的图画类艺术作品时，你的绘画功底可以给你额外的洞察力。 作画Painting and Drawing。作为短休或长休的一部分，你可以创作一件简单的艺术品。虽然你的画作可能不够精细，但你可以展现出一副图像或场景，或者快速还原出你所见过的一幅艺术品。 画家工具Painter’s Supplies 用途 DC 画一幅精确的肖像画 10 创作带有隐藏信息的画作 20 | AS112: 10gp | AT112: 5
A113: 112 | B113: =IF(#REF!="","",#REF!) -> #REF! | C113: =IFERROR(VLOOKUP(B113,#REF!,5,FALSE),"") | D113: =IFERROR(VLOOKUP(B113,#REF!,4,FALSE),"") | E113: 112 | F113: =B113 -> #REF! | AQ113: 陶匠工具 | AR113: 陶匠工具用于制造各种各样的陶器，最典型的是陶罐和类似的器皿。 组件Components。陶匠工具包括穿刺针、骨架刀、刮刀、小刀，以及卡尺。 历史History。你的专业知识有助于你鉴定陶器，包括生产时间，以及它们可能的产地或产地文化。 调查Investigation、察觉 Perception。你在检查陶器时具有额外的洞察力，通过一些小细节来发现他人忽略的线索。 复原Reconstruction。通过检查陶器碎片，你可以推断出该物件原本、完整的形状及其可能的用途。 陶匠工具Potter’s Tools 用途 DC 确认一件陶器装过什么 10 制作一个可用的陶罐 15 找出一件陶器的薄弱点 20 | AS113: 10gp | AT113: 3
A114: 113 | B114: =IF(#REF!="","",#REF!) -> #REF! | C114: =IFERROR(VLOOKUP(B114,#REF!,5,FALSE),"") | D114: =IFERROR(VLOOKUP(B114,#REF!,4,FALSE),"") | E114: 113 | F114: =B114 -> #REF! | AQ114: 铁匠工具 | AR114: 铁匠工具允许你加工金属，加热它来塑性变形、修复损坏，或者把钢锭加工成有用的物品。 组件Components。铁匠工具包括锤子、钳子、木炭、破布和磨刀石。 奥秘Arcana、历史History。当你检查金属物体，比如武器时，你的专业知识会给你额外的洞察力。 调查Investigation。在调查护甲、武器或其他金属制品时，你可以发现他人可能会忽略的线索并作出推论。 修复Repair。当你能够使用工具并且具备一处足以使金属热塑变形的明火时，你每花费1个小时的工作时间，就能为一件损坏的金属制品恢复10点生命值。 铁匠工具Smith’s Tools 用途 DC 磨刀 10 修复一套护甲 15 熔解非魔法金属物件 15 | AS114: 20gp | AT114: 8
... A118: 117 | B118: =IF(#REF!="","",#REF!) -> #REF! | C118: =IFERROR(VLOOKUP(B118,#REF!,5,FALSE),"") | D118: =IFERROR(VLOOKUP(B118,#REF!,4,FALSE),"") | E118: 117 | F118: =B118 -> #REF! | AQ118: 易容工具 | AR118: 对于伪装者来说，易容工具是必不可少的，它可以让使用者轻易地改头换面。 组件Components。易容工具包括化妆品、染发剂、小道具，以及几套衣服。 欺瞒Deception。在某些情况下，一副伪装可以提高你撒谎的能力。 恐吓Intimidation。合适的伪装会让你看起来更可怕，不管你是想假扮成瘟疫患者来吓跑路人或是装成暴徒以恐吓一帮恶棍。 表演Performance。巧妙的化妆可以提升观众的体验，前提是化妆要设计得当，能够唤起想要的反应。 说服Persuasion。人们往往会信任穿制服的人。如果你伪装成一个权威人物，你与他人的交涉会更有说服力。 易容Create Disguise。你可以在长休中制造一套伪装物品。完成后你可以花费1分钟时间来变装。为了避免过度的关注，你一次只能携带一套伪装，除非你有一个背包或类似的方法来隐藏它们。每套伪装重1磅。 在其他时候，需要10分钟来制作一套适当修改外观的的伪装，而大幅改变外观则需要30分钟。 易容工具Disguise Kit 用途 DC 遮盖伤疤或特征性标记 10 识破他人的伪装 15 易容成另一个类人生物 20 | AS118: 25gp | AT118: 3
A119: 118 | B119: =IF(#REF!="","",#REF!) -> #REF! | C119: =IFERROR(VLOOKUP(B119,#REF!,5,FALSE),"") | D119: =IFERROR(VLOOKUP(B119,#REF!,4,FALSE),"") | E119: 118 | F119: =B119 -> #REF! | AP119: 赌具描述 | AQ119: 文书伪造工具 | AR119: 文书伪造工具通常用于伪造一份信用文书和模仿某人的印章或签名。 组件Components。文书伪造工具包括几种不同类型的墨水、各种羊皮纸和普通纸、几支鹅毛笔、印章和封蜡、金银叶饰，以及伪造蜡封的小型雕刻工具。 奥秘Arcana。文书伪造工具与奥秘技能搭配可以鉴定一件魔法物品的真伪。 欺瞒Deception。一份精心伪造的文书，比如贵族血统证明或管制区通行证，可以让你的谎言更有可信度。 历史History。文书伪造工具与你的历史知识相结合，可以让你更轻易地伪造历史文献或鉴定文献的真伪。 调查Investigation。当你检查一个物件时，文书伪造工具熟练项有助于你判断该物件是如何制成的，以及它的真伪。 其他工具Other Tools。 掌握其他工具的用法可以提高你所制赝品的可信度。例如，同时具有文书伪造工具和制图工具熟练项可以制造一份假地图。 快速伪造Quick Fake。 你在一次短休中可以伪造篇幅不超过1页的假文书。而一次长休中，你至多可以制造4页的文书。你进行一次附带文书伪造工具熟练加值的智力检定，以决定他人识破赝品的智力（调查）检定DC值。 文书伪造工具Forgery Kit 用途 DC 伪造笔迹 15 伪造蜡封 20 | AS119: 15gp | AT119: 5
A120: 119 | B120: =IF(#REF!="","",#REF!) -> #REF! | C120: =IFERROR(VLOOKUP(B120,#REF!,5,FALSE),"") | D120: =IFERROR(VLOOKUP(B120,#REF!,4,FALSE),"") | E120: 119 | F120: =B120 -> #REF! | AP120: 赌具熟练项指的是精通单独的某种赌博类型，例如三龙牌Three-Dragon Ante或摇色子。 组件Components。一套赌具包含进行对应赌博游戏的全套赌具，例如一副完整的扑克牌或是棋盘与棋子。 历史History。你对赌博的掌握包括对它历史的了解，以及与它有关的重要事件或与之相关的历史名人的知识。 洞悉Insight。和某人赌上一把是了解他们个性的好方法，可以让你更好地分辨他们的谎言，了解他们的情绪。 巧手Sleight of Hand。想出老千的话，巧手是个很有用的技能，比如你可以棋子换位、掌中藏牌、控制骰点。亦或者，对沉浸于赌局的目标进行扒窃也是不错的选择。 赌具Gaming Set 用途 DC 抓住作弊的玩家 15 洞悉对手的个性 15 | AQ120: 骰子_整副 | AR120: =AP120 -> 赌具熟练项指的是精通单独的某种赌博类型，例如三龙牌Three-Dragon Ante或摇色子。 组件Components。一套赌具包含进行对应赌博游戏的全套赌具，例如一副完整的扑克牌或是棋盘与棋子。 历史History。你对赌博的掌握包括对它历史的了解，以及与它有关的重要事件或与之相关的历史名人的知识。 洞悉Insight。和某人赌上一把是了解他们个性的好方法，可以让你更好地分辨他们的谎言，了解他们的情绪。 巧手Sleight of Hand。想出老千的话，巧手是个很有用的技能，比如你可以棋子换位、掌中藏牌、控制骰点。亦或者，对沉浸于赌局的目标进行扒窃也是不错的选择。 赌具Gaming Set 用途 DC 抓住作弊的玩家 15 洞悉对手的个性 15 | AS120: 0.1gp | AT120: 0
...

Sheet 职业
B1: PHB | C1: XGE | D1: SCAG | E1: TCE | F1: EGtW | G1: BGG | H1: VGR | I1: FTD | T1: 主职业 | U1: 范型 | V1: 兼职1 | W1: 范型 | X1: 兼职2 | Y1: 范型 | Z1: 职业特性 | AA1: 范型 | AC1: 生命值成长 | AE1: 生命骰 | AF1: 期望值 | AH1: 职业 | AI1: 等级 | AJ1: 本职 | AK1: 子职 | AL1: 等级 | AN1: 等级 | AO1: 1环 | AP1: 2环 | AQ1: 3环 | AR1: 4环 | AS1: 5环 | AT1: 6环 | AU1: 7环 | AV1: 8环 | AW1: 9环 | AX1: 法术值 | AY1: 邪术师等级 | AZ1: 1环 | BA1: 2环 | BB1: 3环 | BC1: 4环 | BD1: 5环
B2: 0 | C2: 1 | D2: 2 | E2: 3 | F2: 4 | G2: 5 | H2: 6 | I2: 7 | J2: 8 | K2: 9 | L2: 10 | M2: 11 | N2: 12 | O2: 13 | P2: 14 | Q2: 15 | R2: 16 | T2: =#REF! -> #REF! | U2: =IFERROR(IF(VLOOKUP(T2,B3:R22,2,FALSE)=0,"",VLOOKUP(T2,B3:R22,2,FALSE)),"") | V2: =#REF! -> #REF! | W2: =IFERROR(IF(VLOOKUP(V2,B3:R22,2,FALSE)=0,"",VLOOKUP(V2,B3:R22,2,FALSE)),"") | X2: =#REF! -> #REF! | Y2: =IFERROR(IF(VLOOKUP(X2,B3:R22,2,FALSE)=0,"",VLOOKUP(X2,B3:R22,2,FALSE)),"") | Z2: =#REF! -> #REF! | AA2: =IFERROR(IF(VLOOKUP(Z2,B3:R22,2,FALSE)=0,"",VLOOKUP(Z2,B3:R22,2,FALSE)),"") | AC2: 法师 | AD2: 1d6 | AE2: =IFERROR(VLOOKUP(#REF!,AC2:AD14,2,FALSE),"") | AF2: =IFERROR(VLOOKUP(AE2,AC16:AD19,2,FALSE),0) -> 0 | AH2: 野蛮人 | AI2: =IFERROR(VLOOKUP(AH2,$AJ$2:$AL$4,3,0),0) -> 0 | AJ2: =IF(#REF!="",0,#REF!) -> #REF! | AK2: =IF(#REF!="",0,#REF!) -> #REF! | AL2: =IF(#REF!="",0,#REF!) -> #REF! | AN2: 0 | AY2: 0
A3: 1 | B3: 野蛮人 | C3: 狂战士 | D3: 图腾武者 | E3: 狂热者 | F3: 先祖守卫 | G3: 风暴先驱 | H3: 战狂 | I3: 狂野魔法道途 | J3: 野兽道途 | K3: 巨人道途 | U3: =IFERROR(IF(VLOOKUP(T2,B3:R22,3,FALSE)=0,"",VLOOKUP(T2,B3:R22,3,FALSE)),"") | W3: =IFERROR(IF(VLOOKUP(V2,B3:R22,3,FALSE)=0,"",VLOOKUP(V2,B3:R22,3,FALSE)),"") | Y3: =IFERROR(IF(VLOOKUP(X2,B3:R22,3,FALSE)=0,"",VLOOKUP(X2,B3:R22,3,FALSE)),"") | AA3: =IFERROR(IF(VLOOKUP(Z2,B3:R22,3,FALSE)=0,"",VLOOKUP(Z2,B3:R22,3,FALSE)),"") | AC3: 术士 | AD3: 1d6 | AE3: =IFERROR(VLOOKUP(#REF!,AC2:AD14,2,FALSE),"") | AF3: =IFERROR(VLOOKUP(AE3,AC16:AD19,2,FALSE),0) -> 0 | AH3: 吟游诗人 | AI3: =IFERROR(VLOOKUP(AH3,$AJ$2:$AL$4,3,0),0) -> 0 | AJ3: =IF(#REF!="",0,#REF!) -> #REF! | AK3: =IF(#REF!="",0,#REF!) -> #REF! | AL3: =IF(#REF!="",0,#REF!) -> #REF! | AN3: 1 | AO3: 2 | AX3: 4 | AY3: 1 | AZ3: 1
A4: 2 | B4: 吟游诗人 | C4: 逸闻学院 | D4: 勇气学院 | E4: 迷惑学院 | F4: 剑舞学院 | G4: 低语学院 | H4: 创造学院 | I4: 雄辩学院 | J4: 精魂学院 | U4: =IFERROR(IF(VLOOKUP(T2,B3:R22,4,FALSE)=0,"",VLOOKUP(T2,B3:R22,4,FALSE)),"") | W4: =IFERROR(IF(VLOOKUP(V2,B3:R22,4,FALSE)=0,"",VLOOKUP(V2,B3:R22,4,FALSE)),"") | Y4: =IFERROR(IF(VLOOKUP(X2,B3:R22,4,FALSE)=0,"",VLOOKUP(X2,B3:R22,4,FALSE)),"") | AA4: =IFERROR(IF(VLOOKUP(Z2,B3:R22,4,FALSE)=0,"",VLOOKUP(Z2,B3:R22,4,FALSE)),"") | AC4: 吟游诗人 | AD4: 1d8 | AE4: =IFERROR(VLOOKUP(#REF!,AC2:AD14,2,FALSE),"") | AF4: =IFERROR(VLOOKUP(AE4,AC16:AD19,2,FALSE),0) -> 0 | AH4: 牧师 | AI4: =IFERROR(VLOOKUP(AH4,$AJ$2:$AL$4,3,0),0) -> 0 | AJ4: =IF(#REF!="",0,#REF!) -> #REF! | AK4: =IF(#REF!="",0,#REF!) -> #REF! | AL4: =IF(#REF!="",0,#REF!) -> #REF! | AN4: 2 | AO4: 3 | AX4: 6 | AY4: 2 | AZ4: 2
A5: 3 | B5: 牧师 | C5: 知识领域 | D5: 生命领域 | E5: 光明领域 | F5: 自然领域 | G5: 风暴领域 | H5: 诡术领域 | I5: 战争领域 | J5: 锻造领域 | K5: 坟墓领域 | L5: 奥秘领域 | M5: 秩序领域 | N5: 和平领域 | O5: 暮光领域 | U5: =IFERROR(IF(VLOOKUP(T2,B3:R22,5,FALSE)=0,"",VLOOKUP(T2,B3:R22,5,FALSE)),"") | W5: =IFERROR(IF(VLOOKUP(V2,B3:R22,5,FALSE)=0,"",VLOOKUP(V2,B3:R22,5,FALSE)),"") | Y5: =IFERROR(IF(VLOOKUP(X2,B3:R22,5,FALSE)=0,"",VLOOKUP(X2,B3:R22,5,FALSE)),"") | AA5: =IFERROR(IF(VLOOKUP(Z2,B3:R22,5,FALSE)=0,"",VLOOKUP(Z2,B3:R22,5,FALSE)),"") | AC5: 牧师 | AD5: 1d8 | AH5: 德鲁伊 | AI5: =IFERROR(VLOOKUP(AH5,$AJ$2:$AL$4,3,0),0) -> 0 | AN5: 3 | AO5: 4 | AP5: 2 | AX5: 14 | AY5: 3 | BA5: 2
A6: 4 | B6: 德鲁伊 | C6: 大地结社 | D6: 月亮结社 | E6: 梦境结社 | F6: 牧人结社 | G6: 孢子结社 | H6: 星辰结社 | I6: 野火结社 | U6: =IFERROR(IF(VLOOKUP(T2,B3:R22,6,FALSE)=0,"",VLOOKUP(T2,B3:R22,6,FALSE)),"") | W6: =IFERROR(IF(VLOOKUP(V2,B3:R22,6,FALSE)=0,"",VLOOKUP(V2,B3:R22,6,FALSE)),"") | Y6: =IFERROR(IF(VLOOKUP(X2,B3:R22,6,FALSE)=0,"",VLOOKUP(X2,B3:R22,6,FALSE)),"") | AA6: =IFERROR(IF(VLOOKUP(Z2,B3:R22,6,FALSE)=0,"",VLOOKUP(Z2,B3:R22,6,FALSE)),"") | AC6: 德鲁伊 | AD6: 1d8 | AE6: 总等级 | AF6: =#REF!+#REF!+#REF! -> #REF! | AH6: 战士 | AI6: =IFERROR(VLOOKUP(AH6,$AJ$2:$AL$4,3,0),0) -> 0 | AK6: 奥法骑士 | AL6: =IF(AK2="奥法骑士",AL2,IF(AK3="奥法骑士",AL3,IF(AK4="奥法骑士",AL4,0))) -> #REF! | AN6: 4 | AO6: 4 | AP6: 3 | AX6: 17 | AY6: 4 | BA6: 2
A7: 5 | B7: 战士 | C7: 勇士 | D7: 战斗大师 | E7: 奥法骑士 | F7: 魔射手 | G7: 骑兵 | H7: 武士 | I7: 紫龙骑士 | J7: 回音骑士 | K7: 符文骑士 | L7: 灵能武士 | U7: =IFERROR(IF(VLOOKUP(T2,B3:R22,7,FALSE)=0,"",VLOOKUP(T2,B3:R22,7,FALSE)),"") | W7: =IFERROR(IF(VLOOKUP(V2,B3:R22,7,FALSE)=0,"",VLOOKUP(V2,B3:R22,7,FALSE)),"") | Y7: =IFERROR(IF(VLOOKUP(X2,B3:R22,7,FALSE)=0,"",VLOOKUP(X2,B3:R22,7,FALSE)),"") | AA7: =IFERROR(IF(VLOOKUP(Z2,B3:R22,7,FALSE)=0,"",VLOOKUP(Z2,B3:R22,7,FALSE)),"") | AC7: 武僧 | AD7: 1d8 | AE7: 首级 | AF7: =IFERROR(VLOOKUP(AE2,AC21:AD24,2,FALSE),0) -> 0 | AH7: 武僧 | AI7: =IFERROR(VLOOKUP(AH7,$AJ$2:$AL$4,3,0),0) -> 0 | AK7: 诡术师 | AL7: =IF(AK2="诡术师",AL2,IF(AK3="诡术师",AL3,IF(AK4="诡术师",AL4,0))) -> #REF! | AN7: 5 | AO7: 4 | AP7: 3 | AQ7: 2 | AX7: 27 | AY7: 5 | BB7: 2
A8: 6 | B8: 武僧 | C8: 散打宗 | D8: 暗影宗 | E8: 四象宗 | F8: 醉拳宗 | G8: 剑圣宗 | H8: 日魂宗 | I8: 永亡宗 | J8: 命流宗 | K8: 星我宗 | L8: 神龙宗 | U8: =IFERROR(IF(VLOOKUP(T2,B3:R22,8,FALSE)=0,"",VLOOKUP(T2,B3:R22,8,FALSE)),"") | W8: =IFERROR(IF(VLOOKUP(V2,B3:R22,8,FALSE)=0,"",VLOOKUP(V2,B3:R22,8,FALSE)),"") | Y8: =IFERROR(IF(VLOOKUP(X2,B3:R22,8,FALSE)=0,"",VLOOKUP(X2,B3:R22,8,FALSE)),"") | AA8: =IFERROR(IF(VLOOKUP(Z2,B3:R22,8,FALSE)=0,"",VLOOKUP(Z2,B3:R22,8,FALSE)),"") | AC8: 游荡者 | AD8: 1d8 | AH8: 圣武士 | AI8: =IFERROR(VLOOKUP(AH8,$AJ$2:$AL$4,3,0),0) -> 0 | AN8: 6 | AO8: 4 | AP8: 3 | AQ8: 3 | AX8: 32 | AY8: 6 | BB8: 2
A9: 7 | B9: 圣武士 | C9: 奉献之誓 | D9: 古贤之誓 | E9: 复仇之誓 | F9: 征服之誓 | G9: 救赎之誓 | H9: 王冠之誓 | I9: 荣耀之誓 | J9: 守望之誓 | U9: =IFERROR(IF(VLOOKUP(T2,B3:R22,9,FALSE)=0,"",VLOOKUP(T2,B3:R22,9,FALSE)),"") | W9: =IFERROR(IF(VLOOKUP(V2,B3:R22,9,FALSE)=0,"",VLOOKUP(V2,B3:R22,9,FALSE)),"") | Y9: =IFERROR(IF(VLOOKUP(X2,B3:R22,9,FALSE)=0,"",VLOOKUP(X2,B3:R22,9,FALSE)),"") | AA9: =IFERROR(IF(VLOOKUP(Z2,B3:R22,9,FALSE)=0,"",VLOOKUP(Z2,B3:R22,9,FALSE)),"") | AC9: 邪术师 | AD9: 1d8 | AE9: 全施法者 | AF9: =AI3+AI4+AI5+AI11+AI13 -> 0 | AH9: 游侠 | AI9: =IFERROR(VLOOKUP(AH9,$AJ$2:$AL$4,3,0),0) -> 0 | AN9: 7 | AO9: 4 | AP9: 3 | AQ9: 3 | AR9: 1 | AX9: 38 | AY9: 7 | BC9: 2
A10: 8 | B10: 游侠 | C10: 猎人 | D10: 驯兽师 | E10: 幽域追踪者 | F10: 边界行者 | G10: 怪物杀手 | H10: 集群牧者 | I10: 妖精漫游者 | J10: 龙兽守卫 | U10: =IFERROR(IF(VLOOKUP(T2,B3:R22,10,FALSE)=0,"",VLOOKUP(T2,B3:R22,10,FALSE)),"") | W10: =IFERROR(IF(VLOOKUP(V2,B3:R22,10,FALSE)=0,"",VLOOKUP(V2,B3:R22,10,FALSE)),"") | Y10: =IFERROR(IF(VLOOKUP(X2,B3:R22,10,FALSE)=0,"",VLOOKUP(X2,B3:R22,10,FALSE)),"") | AA10: =IFERROR(IF(VLOOKUP(Z2,B3:R22,10,FALSE)=0,"",VLOOKUP(Z2,B3:R22,10,FALSE)),"") | AC10: 奇械师 | AD10: 1d8 | AE10: 半施法者 | AF10: =ROUNDDOWN((AI8+AI9)/2,0) -> 0 | AH10: 游荡者 | AI10: =IFERROR(VLOOKUP(AH10,$AJ$2:$AL$4,3,0),0) -> 0 | AN10: 8 | AO10: 4 | AP10: 3 | AQ10: 3 | AR10: 2 | AX10: 44 | AY10: 8 | BC10: 2
A11: 9 | B11: 游荡者 | C11: 盗贼 | D11: 刺客 | E11: 诡术师 | F11: 调查员 | G11: 策士 | H11: 斥候 | I11: 游荡剑客 | J11: 鬼魅 | K11: 魂刃 | U11: =IFERROR(IF(VLOOKUP(T2,B3:R22,11,FALSE)=0,"",VLOOKUP(T2,B3:R22,11,FALSE)),"") | W11: =IFERROR(IF(VLOOKUP(V2,B3:R22,11,FALSE)=0,"",VLOOKUP(V2,B3:R22,11,FALSE)),"") | Y11: =IFERROR(IF(VLOOKUP(X2,B3:R22,11,FALSE)=0,"",VLOOKUP(X2,B3:R22,11,FALSE)),"") | AA11: =IFERROR(IF(VLOOKUP(Z2,B3:R22,11,FALSE)=0,"",VLOOKUP(Z2,B3:R22,11,FALSE)),"") | AC11: 战士 | AD11: 1d10 | AE11: 诡奥 | AF11: =IF(AF9=0,ROUNDUP((AL6+AL7)/3,0),ROUNDDOWN((AL6+AL7)/3,0)) -> #REF! | AH11: 术士 | AI11: =IFERROR(VLOOKUP(AH11,$AJ$2:$AL$4,3,0),0) -> 0 | AN11: 9 | AO11: 4 | AP11: 3 | AQ11: 3 | AR11: 3 | AS11: 1 | AX11: 57 | AY11: 9 | BD11: 3
A12: 10 | B12: 术士 | C12: 龙族血脉 | D12: 狂野魔法 | E12: 神圣之魂 | F12: 幽影魔法 | G12: 风暴术法 | H12: 畸变心智 | I12: 时械之魂 | J12: 月之术法 | U12: =IFERROR(IF(VLOOKUP(T2,B3:R22,12,FALSE)=0,"",VLOOKUP(T2,B3:R22,12,FALSE)),"") | W12: =IFERROR(IF(VLOOKUP(V2,B3:R22,12,FALSE)=0,"",VLOOKUP(V2,B3:R22,12,FALSE)),"") | Y12: =IFERROR(IF(VLOOKUP(X2,B3:R22,12,FALSE)=0,"",VLOOKUP(X2,B3:R22,12,FALSE)),"") | AA12: =IFERROR(IF(VLOOKUP(Z2,B3:R22,12,FALSE)=0,"",VLOOKUP(Z2,B3:R22,12,FALSE)),"") | AC12: 圣武士 | AD12: 1d10 | AH12: 邪术师 | AI12: =IFERROR(VLOOKUP(AH12,$AJ$2:$AL$4,3,0),0) -> 0 | AN12: 10 | AO12: 4 | AP12: 3 | AQ12: 3 | AR12: 3 | AS12: 2 | AX12: 64 | AY12: 10 | BD12: 3
A13: 11 | B13: 邪术师 | C13: 至高妖精 | D13: 邪魔宗主 | E13: 旧日支配者 | F13: 天界宗主 | G13: 咒剑士 | H13: 不朽者 | I13: 巨灵宗主 | J13: 深海意志 | K13: 死灵宗主 | U13: =IFERROR(IF(VLOOKUP(T2,B3:R22,13,FALSE)=0,"",VLOOKUP(T2,B3:R22,13,FALSE)),"") | W13: =IFERROR(IF(VLOOKUP(V2,B3:R22,13,FALSE)=0,"",VLOOKUP(V2,B3:R22,13,FALSE)),"") | Y13: =IFERROR(IF(VLOOKUP(X2,B3:R22,13,FALSE)=0,"",VLOOKUP(X2,B3:R22,13,FALSE)),"") | AA13: =IFERROR(IF(VLOOKUP(Z2,B3:R22,13,FALSE)=0,"",VLOOKUP(Z2,B3:R22,13,FALSE)),"") | AC13: 游侠 | AD13: 1d10 | AH13: 法师 | AI13: =IFERROR(VLOOKUP(AH13,$AJ$2:$AL$4,3,0),0) -> 0 | AN13: 11 | AO13: 4 | AP13: 3 | AQ13: 3 | AR13: 3 | AS13: 2 | AT13: 1 | AX13: 73 | AY13: 11 | BD13: 3
A14: 12 | B14: 法师 | C14: 防护学派 | D14: 咒法学派 | E14: 预言学派 | F14: 附魔学派 | G14: 塑能学派 | H14: 幻术学派 | I14: 死灵学派 | J14: 变化学派 | K14: 战争魔法 | L14: 剑咏者 | M14: 时间魔法 | N14: 重力魔法 | O14: 书士会 | U14: =IFERROR(IF(VLOOKUP(T2,B3:R22,14,FALSE)=0,"",VLOOKUP(T2,B3:R22,14,FALSE)),"") | W14: =IFERROR(IF(VLOOKUP(V2,B3:R22,14,FALSE)=0,"",VLOOKUP(V2,B3:R22,14,FALSE)),"") | Y14: =IFERROR(IF(VLOOKUP(X2,B3:R22,14,FALSE)=0,"",VLOOKUP(X2,B3:R22,14,FALSE)),"") | AA14: =IFERROR(IF(VLOOKUP(Z2,B3:R22,14,FALSE)=0,"",VLOOKUP(Z2,B3:R22,14,FALSE)),"") | AC14: 野蛮人 | AD14: 1d12 | AE14: 施法者等级 | AF14: =AF9+AF10+AF11 -> #REF! | AH14: 奇械师 | AI14: =IFERROR(VLOOKUP(AH14,$AJ$2:$AL$4,3,0),0) -> 0 | AN14: 12 | AO14: 4 | AP14: 3 | AQ14: 3 | AR14: 3 | AS14: 2 | AT14: 1 | AX14: 73 | AY14: 12 | BD14: 3
A15: 13 | B15: 奇械师 | C15: 炼金师 | D15: 魔炮师 | E15: 战地匠师 | F15: 装甲师 | U15: =IFERROR(IF(VLOOKUP(T2,B3:R22,15,FALSE)=0,"",VLOOKUP(T2,B3:R22,15,FALSE)),"") | W15: =IFERROR(IF(VLOOKUP(V2,B3:R22,15,FALSE)=0,"",VLOOKUP(V2,B3:R22,15,FALSE)),"") | Y15: =IFERROR(IF(VLOOKUP(X2,B3:R22,15,FALSE)=0,"",VLOOKUP(X2,B3:R22,15,FALSE)),"") | AA15: =IFERROR(IF(VLOOKUP(Z2,B3:R22,15,FALSE)=0,"",VLOOKUP(Z2,B3:R22,15,FALSE)),"") | AC15: 期望值 | AE15: 1环 | AF15: =IFERROR(VLOOKUP($AF$14,$AN$2:$AW$22,2,FALSE),"") | AN15: 13 | AO15: 4 | AP15: 3 | AQ15: 3 | AR15: 3 | AS15: 2 | AT15: 1 | AU15: 1 | AX15: 83 | AY15: 13 | BD15: 3
A16: 14 | U16: =IFERROR(IF(VLOOKUP(T2,B3:R22,16,FALSE)=0,"",VLOOKUP(T2,B3:R22,16,FALSE)),"") | W16: =IFERROR(IF(VLOOKUP(V2,B3:R22,16,FALSE)=0,"",VLOOKUP(V2,B3:R22,16,FALSE)),"") | Y16: =IFERROR(IF(VLOOKUP(X2,B3:R22,16,FALSE)=0,"",VLOOKUP(X2,B3:R22,16,FALSE)),"") | AA16: =IFERROR(IF(VLOOKUP(Z2,B3:R22,16,FALSE)=0,"",VLOOKUP(Z2,B3:R22,16,FALSE)),"") | AC16: 1d6 | AD16: 4 | AE16: 2环 | AF16: =IFERROR(VLOOKUP($AF$14,$AN$2:$AW$22,3,FALSE),"") | AI16: 1环 | AJ16: =IF(AF15+AH20=0,"",AF15+AH20) -> #VALUE! | AN16: 14 | AO16: 4 | AP16: 3 | AQ16: 3 | AR16: 3 | AS16: 2 | AT16: 1 | AU16: 1 | AX16: 83 | AY16: 14 | BD16: 3
A17: 15 | U17: =IFERROR(IF(VLOOKUP(T2,B3:R22,17,FALSE)=0,"",VLOOKUP(T2,B3:R22,17,FALSE)),"") | W17: =IFERROR(IF(VLOOKUP(V2,B3:R22,17,FALSE)=0,"",VLOOKUP(V2,B3:R22,17,FALSE)),"") | Y17: =IFERROR(IF(VLOOKUP(X2,B3:R22,17,FALSE)=0,"",VLOOKUP(X2,B3:R22,17,FALSE)),"") | AA17: =IFERROR(IF(VLOOKUP(Z2,B3:R22,17,FALSE)=0,"",VLOOKUP(Z2,B3:R22,17,FALSE)),"") | AC17: 1d8 | AD17: 5 | AE17: 3环 | AF17: =IFERROR(VLOOKUP($AF$14,$AN$2:$AW$22,4,FALSE),"") | AI17: 2环 | AJ17: =IF(AF16+AH21=0,"",AF16+AH21) -> #VALUE! | AN17: 15 | AO17: 4 | AP17: 3 | AQ17: 3 | AR17: 3 | AS17: 2 | AT17: 1 | AU17: 1 | AV17: 1 | AX17: 94 | AY17: 15 | BD17: 3
A18: 16 | AC18: 1d10 | AD18: 6 | AE18: 4环 | AF18: =IFERROR(VLOOKUP($AF$14,$AN$2:$AW$22,5,FALSE),"") | AI18: 3环 | AJ18: =IF(AF17+AH22=0,"",AF17+AH22) -> #VALUE! | AN18: 16 | AO18: 4 | AP18: 3 | AQ18: 3 | AR18: 3 | AS18: 2 | AT18: 1 | AU18: 1 | AV18: 1 | AX18: 94 | AY18: 16 | BD18: 3
A19: 17 | AC19: 1d12 | AD19: 7 | AE19: 5环 | AF19: =IFERROR(VLOOKUP($AF$14,$AN$2:$AW$22,6,FALSE),"") | AG19: 邪术师 | AI19: 4环 | AJ19: =IF(AF18+AH23=0,"",AF18+AH23) -> #VALUE! | AN19: 17 | AO19: 4 | AP19: 3 | AQ19: 3 | AR19: 3 | AS19: 2 | AT19: 1 | AU19: 1 | AV19: 1 | AW19: 1 | AX19: 107 | AY19: 17 | BD19: 4
A20: 18 | AC20: 首级 | AE20: 6环 | AF20: =IFERROR(VLOOKUP($AF$14,$AN$2:$AW$22,7,FALSE),"") | AG20: 1环 | AH20: =IFERROR(VLOOKUP($AI$12,$AY$2:$BD$22,2,FALSE),"") -> 0 | AI20: 5环 | AJ20: =IF(AF19+AH24=0,"",AF19+AH24) -> #VALUE! | AN20: 18 | AO20: 4 | AP20: 3 | AQ20: 3 | AR20: 3 | AS20: 3 | AT20: 1 | AU20: 1 | AV20: 1 | AW20: 1 | AX20: 114 | AY20: 18 | BD20: 4
A21: 19 | AC21: 1d6 | AD21: 2 | AE21: 7环 | AF21: =IFERROR(VLOOKUP($AF$14,$AN$2:$AW$22,8,FALSE),"") | AG21: 2环 | AH21: =IFERROR(VLOOKUP($AI$12,$AY$2:$BD$22,3,FALSE),"") -> 0 | AI21: 6环 | AJ21: =IF(AF20=0,"",AF20) | AN21: 19 | AO21: 4 | AP21: 3 | AQ21: 3 | AR21: 3 | AS21: 3 | AT21: 2 | AU21: 1 | AV21: 1 | AW21: 1 | AX21: 123 | AY21: 19 | BD21: 4
A22: 20 | AC22: 1d8 | AD22: 3 | AE22: 8环 | AF22: =IFERROR(VLOOKUP($AF$14,$AN$2:$AW$22,9,FALSE),"") | AG22: 3环 | AH22: =IFERROR(VLOOKUP($AI$12,$AY$2:$BD$22,4,FALSE),"") -> 0 | AI22: 7环 | AJ22: =IF(AF21=0,"",AF21) | AN22: 20 | AO22: 4 | AP22: 3 | AQ22: 3 | AR22: 3 | AS22: 3 | AT22: 2 | AU22: 2 | AV22: 1 | AW22: 1 | AX22: 133 | AY22: 20 | AZ22: ="" | BA22: ="" | BB22: ="" | BC22: ="" | BD22: 4
AC23: 1d10 | AD23: 4 | AE23: 9环 | AF23: =IFERROR(VLOOKUP($AF$14,$AN$2:$AW$22,10,FALSE),"") | AG23: 4环 | AH23: =IFERROR(VLOOKUP($AI$12,$AY$2:$BD$22,5,FALSE),"") -> 0 | AI23: 8环 | AJ23: =IF(AF22=0,"",AF22)
AC24: 1d12 | AD24: 5 | AE24: 法术值 | AF24: =IFERROR(VLOOKUP($AF$14,$AN$2:$AX$22,11,FALSE),"") | AG24: 5环 | AH24: =IFERROR(VLOOKUP($AI$12,$AY$2:$BD$22,6,FALSE),"") -> 0 | AI24: 9环 | AJ24: =IF(AF23=0,"",AF23)
AX25: 列1 | AY25: 列2 | AZ25: 最小数据行 | BA25: 最大数据行
AW26: =IF(#REF!<>"",#REF!,"") -> #REF! | AX26: =IFERROR(VLOOKUP(AW26,A29:E192,2,FALSE),"") | AY26: =IFERROR(VLOOKUP(AW26,A29:E192,3,FALSE),"") | AZ26: =IFERROR(VLOOKUP(AW26,A29:E192,4,FALSE),"") | BA26: =IFERROR(VLOOKUP(AW26,A29:E192,5,FALSE),"")
AW27: =IF(#REF!<>"",#REF!,"") -> #REF! | AX27: 0v0? | AY27: 0v0? | AZ27: =IFERROR(VLOOKUP(AW27,A29:E192,4,FALSE),"") | BA27: =IFERROR(VLOOKUP(AW27,A29:E192,5,FALSE),"")
B28: 名称列 | C28: 描述列 | D28: 最小数据行 | E28: 最大数据行
A29: 野蛮人 | B29: 1 | C29: 2 | D29: 1 | E29: 19 | H29: 1 | I29: 2 | J29: 3 | K29: 4 | L29: 5 | M29: 6 | N29: 7 | O29: 8 | P29: 9 | Q29: 10 | R29: 11 | S29: 12 | T29: 13 | U29: 14 | V29: 15 | W29: 16 | X29: 17 | Y29: 18 | Z29: 19 | AA29: 20 | AB29: 21 | AC29: 22 | AD29: 23 | AE29: 24 | AF29: 25 | AG29: 26 | AH29: 27 | AI29: 28 | AJ29: 29 | AK29: 30 | AL29: 31 | AM29: 32 | AN29: 33 | AO29: 34 | AP29: 35 | AQ29: 36 | AR29: 37 | AS29: 38 | AT29: 39 | AU29: 40 | AW29: 0 | AX29: 名称 | AY29: 描述 | AZ29: 增值
A30: 吟游诗人 | B30: 3 | C30: 4 | D30: 1 | E30: 22 | H30: 野蛮人 | J30: 吟游诗人 | L30: 牧师 | N30: 德鲁伊 | P30: 战士 | R30: 武僧 | T30: 圣武士 | V30: 游侠 | X30: 游荡者 | Z30: 术士 | AB30: 邪术师 | AD30: 法师 | AF30: 奇械师 | AH30: ？？？ | AJ30: ？？？ | AL30: ？？？ | AN30: ？？？ | AP30: ？？？ | AR30: ？？？ | AT30: ？？？ | AW30: =IFERROR(IF(AW29+1>BA26,IF(AW29+1>BA26,IF(AZ27+AZ29>BA27,"",AZ27+AZ29)),AW29+1),"") -> 1 | AX30: =IFERROR(INDEX(H31:AU181,AW30,AX26),"") | AY30: =IFERROR(INDEX(H31:AU181,AW30,AY26),"") | AZ30: =IFERROR(IF(AW29+1>BA26,AZ29+1,0),"") -> 0 | BB30: =IF(#REF!="","",#REF!) -> #REF! | BC30: =IFERROR(VLOOKUP(BB30,AX30:AY129,2,FALSE),"")
A31: 牧师 | B31: 5 | C31: 6 | D31: 1 | E31: 19 | G31: 1 | H31: 护甲熟练 | I31: 轻甲、中甲、盾牌 | J31: 护甲熟练 | K31: 轻甲 | L31: 护甲熟练 | M31: 轻甲、中甲、盾牌 | N31: 护甲熟练 | O31: 轻甲、中甲、盾牌（德鲁伊不能装备或使用金属质的护甲和盾） | P31: 护甲熟练 | Q31: 全部护甲、盾牌 | R31: 护甲熟练 | S31: 无 | T31: 护甲熟练 | U31: 所有护甲和盾牌 | V31: 护甲熟练 | W31: 轻甲、中甲、盾牌 | X31: 护甲熟练 | Y31: 轻甲 | Z31: 护甲熟练 | AA31: 无 | AB31: 护甲熟练 | AC31: 轻甲 | AD31: 护甲熟练 | AE31: 无 | AF31: 护甲熟练 | AG31: 轻甲、中甲、盾牌 | AW31: =IFERROR(IF(AW30+1>BA26,IF(AW30+1>BA26,IF(AZ27+AZ30>BA27,"",AZ27+AZ30)),AW30+1),"") -> 2 | AX31: =IFERROR(INDEX(H31:AU181,AW31,AX26),"") | AY31: =IFERROR(INDEX(H31:AU181,AW31,AY26),"") | AZ31: =IFERROR(IF(AW30+1>BA26,AZ30+1,0),"") -> 0 | BB31: =IF(#REF!="","",#REF!) -> #REF! | BC31: =IFERROR(VLOOKUP(BB31,AX30:AY129,2,FALSE),"")
A32: 德鲁伊 | B32: 7 | C32: 8 | D32: 1 | E32: 19 | G32: 2 | H32: 武器熟练 | I32: 简易武器、军用武器 | J32: 武器熟练 | K32: 简易武器、手弩、长剑、刺剑、短剑 | L32: 武器熟练 | M32: 简易武器 | N32: 武器熟练 | O32: 短棒、匕首、飞镖、标枪、硬头锤、长棍、弯刀、镰刀、投石索、矛 | P32: 武器熟练 | Q32: 简易武器、军用武器 | R32: 武器熟练 | S32: 简易武器、短剑 | T32: 武器熟练 | U32: 简易武器和军用武器 | V32: 武器熟练 | W32: 简易武器、军用武器 | X32: 武器熟练 | Y32: 简易武器、手弩、长剑、刺剑、短剑 | Z32: 武器熟练 | AA32: 匕首、飞镖、投石索、长棍、轻弩 | AB32: 武器熟练 | AC32: 简易武器 | AD32: 武器熟练 | AE32: 匕首、飞镖、投石索、长棍、轻弩 | AF32: 武器熟练 | AG32: 简易武器 | AW32: =IFERROR(IF(AW31+1>BA26,IF(AW31+1>BA26,IF(AZ27+AZ31>BA27,"",AZ27+AZ31)),AW31+1),"") -> 3 | AX32: =IFERROR(INDEX(H31:AU181,AW32,AX26),"") | AY32: =IFERROR(INDEX(H31:AU181,AW32,AY26),"") | AZ32: =IFERROR(IF(AW31+1>BA26,AZ31+1,0),"") -> 0 | BB32: =IF(#REF!="","",#REF!) -> #REF! | BC32: =IFERROR(VLOOKUP(BB32,AX30:AY129,2,FALSE),"")
A33: 战士 | B33: 9 | C33: 10 | D33: 1 | E33: 12 | G33: 3 | H33: 工具熟练 | I33: 无 | J33: 工具熟练 | K33: 自选三种乐器 | L33: 工具熟练 | M33: 无 | N33: 工具熟练 | O33: 草药工具 | P33: 工具熟练 | Q33: 无 | R33: 工具熟练 | S33: 选择一种工匠工具或一种乐器 | T33: 工具熟练 | U33: 无 | V33: 工具熟练 | W33: 无 | X33: 工具熟练 | Y33: 盗贼工具 | Z33: 工具熟练 | AA33: 无 | AB33: 工具熟练 | AC33: 无 | AD33: 工具熟练 | AE33: 无 | AF33: 工具熟练 | AG33: 盗贼工具、修补工具、其他一种你选择的工匠工具 | AW33: =IFERROR(IF(AW32+1>BA26,IF(AW32+1>BA26,IF(AZ27+AZ32>BA27,"",AZ27+AZ32)),AW32+1),"") -> 4 | AX33: =IFERROR(INDEX(H31:AU181,AW33,AX26),"") | AY33: =IFERROR(INDEX(H31:AU181,AW33,AY26),"") | AZ33: =IFERROR(IF(AW32+1>BA26,AZ32+1,0),"") -> 0 | BB33: =IF(#REF!="","",#REF!) -> #REF! | BC33: =IFERROR(VLOOKUP(BB33,AX30:AY129,2,FALSE),"")
A34: 武僧 | B34: 11 | C34: 12 | D34: 1 | E34: 29 | G34: 4 | H34: 狂暴 | I34: 你带着原初的狂怒作战。你可以在自己回合内以一个附赠动作进入狂暴。 狂暴持续期间，只要你未着装重甲就获得以下增益： • 你进行力量检定和力量豁免时具有优势。 • 你用力量值发动近战武器攻击时的伤害掷骰获得加值。此加值随你的野蛮人等级提升而增加，具体见“野蛮人职业表”中“狂暴伤害”一栏。 • 你拥有钝击，穿刺和挥砍伤害的抗性。 拥有施法能力的角色无法在狂暴持续期间施展法术或进行法术专注。 你的狂暴状态维持1分钟。如果你在狂暴其间陷入昏迷，或者，如果你从自己上回合结束开始到本回合结束时都未攻击任何敌对生物也未受到伤害，则狂暴提前结束。你也可以在自己回合里以一个附赠动作主动结束狂暴状态。 “野蛮人职业表”中根据你的野蛮人等级给出了相应的狂暴次数。如果你用光了这些次数，则必须完成一次长休才能再次使用狂暴。 | J34: 施法 | K34: 你习得以音乐为媒介随意解构、分解，再重新构造现实的方法。 你的法术是融入你纷繁奏乐中的音符，也是你以各种形式谱奏的魔法乐章。 | L34: 施法 | M34: 你作为神圣力量的导体得以施展牧师法术。 | N34: 德鲁伊语 | O34: 你习得德鲁伊语——即一种德鲁伊间的秘密语言。 你可以说这门语言并用它留下隐藏的信息。 懂得这门语言的人（包括你自己）会自动注意到此信息，而不懂此语言的人通过一次DC15的感知（察觉）检定后可以注意到其存在，不过不能用非魔法手段读懂。 | P34: 战斗风格 | Q34: 你专精于一种战斗风格，并从下列选项中选择。 另外，即使你有多次选择战斗风格的机会，也不能多次选择同一个战斗风格。 箭术：你使用远程武器进行攻击检定时具有+2加值。 防御：着装护甲时，你的AC获得+1加值。 对决：单手持用一把近战武器，且并未同时持用其他武器时，你用该武器攻击的伤害掷骰获得+2加值。 巨武器战斗：双手持用一把近战武器发动攻击时，如果你的伤害掷骰掷出1或2，则可以选择重掷。不过哪怕其仍是1或2，你都必须接受重掷的数值。此外，该武器必须具有双手或两用属性。 守护：当某个你能看见的生物攻击你身边5尺内除你之外的目标时，你可以用反应迫使该攻击的攻击检定具有劣势。此时你必须持用盾牌。 双武器战斗：使用两把武器战斗时，你可以将相应属性调整值加到第二次攻击的伤害上。 | R34: 无甲防御 | S34: 第1级起，未着装任何护甲也没持用盾牌时，你的AC值等于10＋你的敏捷调整值＋你的感知调整值。 | T34: 神圣感知 | U34: 强大的邪恶存在于你有如带毒的香气，而强大的善良光环于你则如仙乐般悠扬。 你可以使用一个动作扩展你的意识，以侦测此类势力。 直到你下回合结束前，你可以对身边60尺范围内进行感测，任何未对你处在全身掩护状态的天界生物、邪魔或不死生物都将被你定位。 你感应到范围内生物的种类（天界生物、邪魔、不死生物），不过并不能精确指明。 在同样的范围内，你也可以侦测任何受到圣居一类的法术祝福或亵渎的地点或物件。 该特性的可用次数等于1＋你的魅力调整值。 而已消耗的特性使用次数，则可以通过完成一次长休进行恢复。 | V34: 宿敌 | W34: 第1级起，你针对一种特定类型敌人的研究令你有着充足的经验用以追踪、狩猎乃至与之交流。 从下列种类中选择其一作为宿敌：异怪、野兽、天界生物、构装生物、龙、元素生物、精类生物、邪魔、巨人、怪兽、泥怪、植物、不死生物。 或者作为另一种方案，你也可以选择两个类人生物种族（例如豺狼人和兽人）作为宿敌。 追踪宿敌时，你的感知（求生）检定，以及回想关于宿敌信息时进行的智力检定具有优势。 获得该特性时，如果你选择的宿敌具有语言能力，则你还可以学会宿敌所知晓的一门语言。 第6和第14级时，你将分别获得一个额外的宿敌以及相关语言。 另外，随着等级的提升，你所选择的宿敌应该与你在冒险中所遭遇怪物的种类层次相符。 | X34: 专精 | Y34: 第1级起，你选择两个已有技能熟练项，或者一个技能熟练项和盗贼工具熟练项。 此后你进行该项目的检定时，可以使用双倍的熟练加值。 第6级时，你可以再选择另外两个已有的技能熟练项（或盗贼工具熟练项）从该特性中获益。 | Z34: 施法 | AA34: 过去的一个事件激发了你体内先辈的血脉，为你烙上了奥法力量的坚固印记。 这股起源于某种存在的魔力驱动着你的法术能力。 | AB34: 契约魔法 | AC34: 你的法术力量源于你的奥秘研究和宗主的魔法馈赠。 | AD34: 施法 | AE34: 作为一名奥术魔法的研习者，你拥有一本自己的法术书。 书中所包含的法术隐约透露着你真正的力量。 | AF34: 魔法工艺 | AG34: 在第1级，你将学习如何在平凡的物品中注入魔法的火花。 要使用这个能力，你必须手持盗贼工具，或工匠工具。 然后花费一个动作触摸一个微小的非魔法物体，从以下魔法属性中选择一个赋予它： 该物体提供5尺半径的明亮照明，以及该范围外5尺范围的微光照明。 无论何时，只要该物品被生物触碰，就会发出可在10英尺外听到的录音信息，录入的信息在你将此属性赋予对象时决定，且时长不可超过6秒。 物品不断地发出一种气味或一种非语言的声音（风声、浪声、鸟叫或类似的声音），这一现象最多能传播10英尺远。 一个静态的视觉效果出现在物体的表面上，这个效果可以是一幅图片，最多25个单词的文本，线条和形状，或者这些元素的混合，如你所愿。 所选的魔法属性持续时间无限。你能够以一个动作触摸对象来消除这一魔法属性。 你能够通过此特性将魔力赋予多个物品，每次使用该特性时都需要触摸一个物品，并且单个物品一次只能承载一种魔法属性。 你能够使用该特性影响的物品的最大数量等于你的智力调整值（最少一个物品）。 如果你试图超过最大值，最老的魔法属性将立即结束，然后新的魔法属性生效。 | AW34: =IFERROR(IF(AW33+1>BA26,IF(AW33+1>BA26,IF(AZ27+AZ33>BA27,"",AZ27+AZ33)),AW33+1),"") -> 5 | AX34: =IFERROR(INDEX(H31:AU181,AW34,AX26),"") | AY34: =IFERROR(INDEX(H31:AU181,AW34,AY26),"") | AZ34: =IFERROR(IF(AW33+1>BA26,AZ33+1,0),"") -> 0 | BB34: =IF(#REF!="","",#REF!) -> #REF! | BC34: =IFERROR(VLOOKUP(BB34,AX30:AY129,2,FALSE),"")
A35: 圣武士 | B35: 13 | C35: 14 | D35: 1 | E35: 24 | G35: 5 | H35: 无甲防御 | I35: 未着装任何护甲时，你的AC等于10＋你的敏捷调整值＋你的体质调整值。使用盾牌不会影响你从此特性获益。 | J35: 戏法 | K35: 第1级时，你从诗人法术列表中选择两个戏法作为已知法术。 在获得更高诗人等级后你还可以习得其它的戏法，具体数量见“吟游诗人职业表”中“已知戏法”一栏。 | L35: 戏法 | M35: 第1级时，你选择三个牧师法术列表中的戏法作为已知法术。 在获得更高的牧师等级后你还可以习得其它的戏法，具体数据参见“牧师职业表”中“已知戏法”一栏。 | N35: 施法 | O35: 你掌握自然世界的神圣本质，并依你的意志施展法术对其进行重塑。 | P35: 战斗风格选项 | Q35: 从1级起，当你在选择战斗风格时，下列选项加入你的可选战斗风格中。 盲斗：你获得10尺盲视，在10尺范围内，你可以看见除了处于全遮掩后的任何东西，哪怕你正在被目盲或是在黑暗之中，另外，你可以看见该范围内的未对你成功躲藏的隐形生物。 卓越技巧：你从战斗大师武术范型的战技列表中习得一项战技，如果该战技需要豁免，则豁免DC为8+你的熟练加值+你的力量或敏捷调整值（由你选择）。 你获得一个d6的卓越骰（此卓越骰与任何你能够其他方式获得的卓越骰累计），此卓越骰可用于启动你的战技，卓越骰一经使用即消耗，并在完成一次短休或长休后恢复。 投掷武器战斗：你可以在使用一件带有投掷属性武器进行进攻时，将那件武器作为攻击的一部分而拔出，另外，在你以一件投掷武器于远程攻击中命中对手时，你的伤害掷骰+2。 徒手战斗：你的徒手打击可以造成1d6+你力量调整值的钝击伤害，如果你没有手持任何武器或盾牌进行攻击，伤害骰从d6变成d8， 每个你的回合开始时，你可以对被你擒抱的生物造成1d4钝击伤害。 | R35: 武艺 | S35: 第1级时，你修行的武艺让你使用徒手打击和武僧武器时得心应手。 武僧武器包括短剑和所有不含双手与重型属性的简易近战武器。 未着装任何护甲也没持用盾牌时，如果你徒手或只持用武僧武器，则你发动的攻击拥有下列增益： 你使用徒手打击或武僧武器进行攻击时，可以用敏捷值代替力量值进行攻击检定和伤害掷骰。 你使用徒手打击或武僧武器进行攻击时，可以选择用d4骰代替原本的伤害掷骰。该骰子将随武僧职业等级的提升而增大，具体数据见“武僧职业表”中“武艺”一栏。 你使用徒手打击或武僧武器执行攻击动作时，可以在自己回合内以附赠动作发动一次徒手打击。 例如，你执行攻击动作并使用长棍发动攻击时，若你本轮没有执行任何附赠动作，则可以用附赠动作来发动一次徒手打击。 某些宗派的武僧会使用一些奇异的武僧武器，比如铁链连接的两根短棒（双截棍），或者带直刃的镰刀（单镰）。 无论你使用什么武器，其属性数据都参考与其相似的常规武器属性数据。 具体的武器数据见第5章。 | T35: 圣疗 | U35: 你的触碰溢满祝福，可以医治伤口。 你获得一个治疗能量池，其内的治疗能量在每次完成长休后自动补满。 治疗能量池储备的可恢复生命值总值等于你的圣武士职业等级×5。 你可以用一个动作触碰一个生物，并抽取治疗能量池中的能量恢复该生物的生命值，其恢复量最多等于你治疗能量池中剩余的治疗量。 此外，你也可以使用5点治疗量治愈目标生物身上的一种疾病，或者祛除一种中毒效应。 你可以在一次圣疗中治愈复数的疾病并祛除复数的毒素，但你需要为每一种疾病和毒素分别支付治疗量。 该职业特性对不死生物和构装生物无效。 | V35: 夙敌 | W35: 从1级起（替换宿敌并能够对屠灭众敌起效），当你以一次攻击掷骰命中一个生物时，你可以呼唤你与自然的神秘羁连以将目标标记为你的夙敌，持续一分钟或直到你失去专注(如同你在专注一道法术)。 你在你的回合内第一次命中你的夙敌并对其造成伤害，且你正在标记它时，你可以造成额外的1d4点伤害。 你可以使用同等于你的熟练加值次该特性来标记你的夙敌，你在完成一次长休后恢复所有已使用的次数。 这个特性的额外伤害在你达到特定等级时会增加：6级时1d6，14级时1d8。 | X35: 偷袭 | Y35: 第1级起，你就知道如何精确地攻击分心的敌人。 每当你的攻击命中一个生物时，如果该攻击的攻击检定带有优势，则可以造成额外1d6的伤害。 该伤害每回合可以产生一次，且造成伤害的攻击必须使用带灵巧属性的武器或远程武器。 如果目标生物身边5尺内还有其他与之对敌者，且该对敌者并未处于失能状态，则只要你的攻击检定没有劣势，就可以发动偷袭。 你的偷袭伤害也将会随游荡者职业等级的提升而提高，其具体数值见“游荡者职业表”。 | Z35: 戏法 | AA35: 第1级时，你从术士法术列表里选择四个戏法作为已知法术。 在获得更高的术士等级后你还可以习得其它的戏法，具体数量见“术士职业表”中“已知戏法”一栏。 | AB35: 戏法 | AC35: 你从邪术师法术列表中选择两个戏法作为已知法术。 在获得更高的邪术师等级后你还可以习得其它的戏法，具体数据见“邪术师职业表”中“已知戏法”一栏。 | AD35: 戏法 | AE35: 第1级时，你从法师法术列表中选择三个戏法作为已知法术。 在获得更高的法师等级后你还可以习得其它的戏法，具体数量参见“法师职业表”中“已知戏法”一栏。 | AF35: 技艺的魔法 | AG35: 身为一名奇械师，你在施法时使用工具，当描述你的施法时，请想想你是如何使用一个工具来执行这个法术效果的。 如果你使用炼金工具来施展疗伤术，你可以很快的制造出药膏。 如果你用修补工具来施展，你可能会拿出一个微型机械蜘蛛来缝合伤口。 当你施放毒液喷溅时，你可以喷射出有毒的化学物质，或者使用一根喷射毒液的魔杖。 法术的效果和其他的施法者职业是一样，但是你的施法方法是特殊的。 同样的原则也适用于你准备法术的时候，作为一名奇械师，你不需要学习魔法书，也不需要祈祷去准备你的魔法。 你需要使用工具来制造用于产生效果的特定物品，如果你用电爪替换疗伤术，你可能会破坏你用来治疗的设备，并用它的部件制造一个攻击性的物品——这可能是一只能够让你引导冲击性能量的长手套。 这些细节不会以任何方式限制你，也不会给你带来任何好处，你不需要证明你是如何使用工具来施展法术的，但是创造性地描述你的施法是一种能够让你从其他施法者中脱颖而出的有趣方法。 | AW35: =IFERROR(IF(AW34+1>BA26,IF(AW34+1>BA26,IF(AZ27+AZ34>BA27,"",AZ27+AZ34)),AW34+1),"") -> 6 | AX35: =IFERROR(INDEX(H31:AU181,AW35,AX26),"") | AY35: =IFERROR(INDEX(H31:AU181,AW35,AY26),"") | AZ35: =IFERROR(IF(AW34+1>BA26,AZ34+1,0),"") -> 0 | BB35: =IF(#REF!="","",#REF!) -> #REF! | BC35: =IFERROR(VLOOKUP(BB35,AX30:AY129,2,FALSE),"")
A36: 游侠 | B36: 15 | C36: 16 | D36: 1 | E36: 25 | G36: 6 | H36: 鲁莽攻击 | I36: 第2级起，你可以抛弃一切防御的执念进行狂乱的攻击。你在自己回合内发动第一次攻击时，可以选择发动鲁莽攻击。 使用此特性后，你本回合内所有使用力量值发动的近战武器攻击具有优势。此后，所有对你发动的攻击检定也将具有优势，且该优势持续存在至你的下个回合。 | J36: 法术位 | K36: “吟游诗人职业表”中记录了你可用以施展诗人法术的1环及更高环阶法术位数量。 施展诗人法术时，你必须同时消耗其对应环阶的法术位。 已消耗的法术位可在完成长休后恢复。 | L36: 法术的准备与施展 | M36: “牧师职业表”里记录了你用以施展牧师法术的1环及更高环阶法术位数量。 施展某个牧师法术时，你必须同时消耗其对应环阶的法术位。 已消耗的法术位可在完成长休后恢复。 你可以准备牧师法术列表中所有符合当前施展条件的法术。 准备法术时，你所准备法术的总数等于你的感知调整值＋你的牧师职业等级（最少可以准备一个）。 另外，你只能准备已经获得相应环阶法术位的法术。 例如，作为一名3级牧师时，你拥有四枚1环法术位和两枚2环法术位。假如你的感知为16，则你的准备法术列表可以囊括总共六个1环或2环法术的组合。如果你准备了1环法术疗伤术cure wounds，则你可以使用1环或者2环的法术位来施展它。另外，已施展的法术并不会从你的准备列表中移除。 你可以在完成长休后改变你的准备法术列表。 准备新的牧师法术列表时，你要再花时间进行祈祷和冥想。 准备时，你要为你列表上每个法术的每个环阶都花费至少1分钟时间。 | N36: 戏法 | O36: 第1级时，你选择两项德鲁伊法术列表中的戏法作为已知法术。 在获得更高的德鲁伊等级后你还可以习得其它的戏法，具体数据参见“德鲁伊职业表”中“已知戏法”一栏。 | P36: 回气 | Q36: 你拥有少量精力储备可用来保护自己免受伤害。 你可以在自己回合内用一个附赠动作恢复生命值，其总值为1d10＋你的战士职业等级。 你必须完成一次短休或长休才能再次使用该特性。 | R36: 气 | S36: 第2级起，你掌握一股名为气的神秘能量。 此后你将拥有一定数量的气作为储备。 而气的储备量由你的武僧等级决定，具体数值见“武僧职业表”中“气”一栏。 你可以消耗气以行使各种特性。 一开始你掌握三种特性：疾风连击，坚强防御，飞檐走壁。 此后，随着等级的提升你将习得更多的特性。 消耗掉的气必须在你短休或长休时完成至少30分钟的冥想，才能重获所有消耗掉的气值。 某些特性需要目标进行豁免检定来抵抗你特性造成的效应。 其豁免DC如下： 气豁免DC＝8＋你的熟练加值＋你的感知调整值 | T36: 战斗风格 | U36: 第2级起，你将精进于一种战斗风格，从下列选项中选择其一。 另外，即使你有多次选择战斗风格的机会，也不能重复选择同一个战斗风格。 防御：着装护甲时，你的AC获得+1加值。 对决：单手持用一把近战武器，且并未同时持用其他武器时，你使用该武器进行攻击的伤害掷骰获得+2加值。 巨武器战斗：双手持用一把近战武器发动攻击时，若你的伤害掷骰掷出1或2，则可以选择重掷。 不过哪怕其仍是1或2，你都必须接受重掷的数值。 此外，该武器必须具有双手或两用属性。 守护：当某个你能看见的生物攻击你身边5尺内除你之外的目标时，你可以用反应迫使该攻击的攻击检定具有劣势。 你必须持用盾牌以实现该效果。 | V36: 自然探索者 | W36: 你对某种自然环境特别熟悉，并适应了在其中行走及生存。 从下列类别中选择一种偏爱地形：极地、海岸、荒漠、丛林、草原、山地、沼泽或幽暗地。 当你进行与偏好地形相关的智力或感知检定时，如果你拥有该技能的熟练项，则在检定时加入双倍熟练加值。 当你在偏好地形上移动一小时或更长时间时，你获得以下增益： 你的队伍旅行时不会因困难地形而变慢 除非受魔法效应影响，否则你的队伍不会迷路 旅行时，即使你进行另一项活动（如觅食、导航或追踪），仍能对危险保持警觉 独自旅行时，你能够保持隐匿状态以正常步调移动 觅食时，你会发现两倍的食物 追踪其他生物时，你还能了解他们的确切数量、体型以及离开踪迹的时间 你在第6级和第10级时将分别获得一个额外的偏好地形。 | X36: 盗贼黑话 | Y36: 作为一名游荡者，你在平时的练习中学会了盗贼间的黑话。 盗贼黑话是一门混合了土话、术语和密语的秘密语言，掌握这门语言后，你可以在平时对话中不落痕迹的加入隐藏信息。 而只有另一个懂盗贼黑话的生物才能看懂这些隐藏信息。 不过这种交流方式需要花费四倍于直接交流所需要的时间。 另外，你还习得一套用以传达简单短小信息的秘密符文和标识。 它能发布的内容诸如某地区是否危险，是否受盗贼公会管辖，附近是否有战利品，附近的人是否好主顾或者路上是否有安全的房屋以供庇护。 | Z36: 法术位 | AA36: “术士职业表”中记录了你用以施展你术士法术的1环及更高环阶法术位数量。 施展某个术士法术时，你必须同时消耗其对应环阶的法术位。 已消耗的法术位可在完成长休后恢复。 例如，若你已知1环法术燃烧之手burning hands，并且拥有一枚可用的1环法术位和一枚可用的2环法术位，则这两枚法术位都可以用来施展该法术。 | AB36: 法术位 | AC36: “邪术师职业表”里记录了你可用以施展邪术师法术的1环至5环法术位数量。 表格中还记录了法术位对应的法术环阶，且你所有的法术位都属于同一环阶。 施展1环或更高环阶的邪术师法术时，都需要消耗一枚法术位。 已消耗的法术位可在完成长休或短休后恢复。 例如，达到第5级时，你总共具有两枚3环法术位。 你施展1环法术巫术箭时，必须消耗消耗这些法术位其中之一，并把它作为一个3环法术施放。 | AD36: 你的法术书 | AE36: 你在等级提升时加入法术书中的法师法术，体现了你的奥术研究成果，同时也代表你对多元宇宙本质的认知的新突破。 你也许会在冒险过程中发现其他的法术。 例如，你可能在一个邪恶法师的箱子里发现了一张记载有法术的卷轴，或者在一个上古图书馆中发现了灰尘覆盖的卷册。 将法术抄入法术书：当你发现一道1环或更高环阶的法师法术时，你可以将其抄入你的法术书中，前提是，你必须能够准备该法术，且也有时间去解读和复制它。 抄写法术时，你必须先重构该法术的基础式，然后解读抄写该法术的法师所使用的独特符号系统。 你必须反复练习这个法术，直至完全理解其所需的咒语和手势，最后用再用你自己的符号系统将之抄入法术书。 这个过程将消耗每法术环阶2小时的时间和每法术环阶50gp的资金。 这笔开销代表你在练习这个法术的过程中消耗的材料成分，还有抄录法术所需的上好的墨水。 当你花费了这一笔时间和金钱后，你就可以如同准备其他法术一般准备这个法术了。 替换法术书：你可以把法术从你的法术书抄到另一本书上——例如，你打算为你的法术书做一个备份时，就可以这么做。 这个进程和将新法术抄入法术书相似，但更快也更简单，因为你早已理解了你自己的符号系统，也知道如何施展这个法术。 这时，你只需要花费每环阶1小时和每环阶10gp的花费。 如果你弄丢了法术书，你也可以用相同的流程将你准备的法术抄入一本新法术书中。 而要填满法术书的其余部分就需要你自己去寻找新的法术了。 所以，很多法师都喜欢在安全的地方保存好备份的法术书。 法术书外观：你的法术书是一本独特的法术合集，其上有着独特的使用痕迹和空白页。 它可以是导师赠予的简洁实用的皮册；或是在远古图书馆中发现的华丽镶边书册；甚至可以是在你遭遇意外后，松散的订在一起的一堆手稿。 | AF36: 施法 | AG36: 你已经学习了魔法的工作原理，知道如何引导魔法进入物体，以及如何唤醒魔法。 因此，你获得了有限的施法能力，在旁观者看来，你不会用传统的方式施法——你看起来好像在通过各种物品创造奇迹。 | AW36: =IFERROR(IF(AW35+1>BA26,IF(AW35+1>BA26,IF(AZ27+AZ35>BA27,"",AZ27+AZ35)),AW35+1),"") -> 7 | AX36: =IFERROR(INDEX(H31:AU181,AW36,AX26),"") | AY36: =IFERROR(INDEX(H31:AU181,AW36,AY26),"") | AZ36: =IFERROR(IF(AW35+1>BA26,AZ35+1,0),"") -> 0 | BB36: =IF(#REF!="","",#REF!) -> #REF! | BC36: =IFERROR(VLOOKUP(BB36,AX30:AY129,2,FALSE),"")
A37: 游荡者 | B37: 17 | C37: 18 | D37: 1 | E37: 17 | G37: 7 | H37: 险境感知 | I37: 第2级时，你获得对周遭异常情况超乎寻常的感测力，让你能先一步脱离危险。 在受到你能看见的效应（诸如陷阱和法术）影响时，你对其进行的敏捷豁免具有优势。你无法在目盲、耳聋或是失能的状态下从此特性获益。 | J37: 已知法术 | K37: 第1级时，你从诗人法术列表中选择四个1环法术作为已知法术。 “吟游诗人职业表”中“已知法术”一栏记录了你获得更多已知法术时的相应等级。 但是，你只能获取已有相应环阶法术位的法术。 比如当达到第3级时，你将获得一个1环或2环法术。 另外，你每提升一个诗人等级，可以从诗人法术列表中选择一个新法术来代替一个已知法术列表中的旧法术，不过你必须已有新法术的相应环阶法术位。 | L37: 施法关键属性 | M37: 你的法术力量来源于你对神祇的信仰，因此感知是你施展牧师法术的关键属性。 每当你的牧师法术需要施法关键属性时均指向你的感知值。 而你牧师法术的豁免DC和攻击检定，则使用你的感知调整值。 法术豁免DC＝8＋你的熟练加值＋你的感知调整值 法术攻击调整值＝你的熟练加值＋你的感知调整值 | N37: 法术的准备和施展 | O37: “德鲁伊职业表”里记录了你用以施展德鲁伊法术的1环及更高环阶法术位数量。 施展某德鲁伊法术时，你必须同时消耗其对应环阶法术位。 已消耗的法术位可在完成长休后恢复。 你可以准备德鲁伊法术列表中所有符合当前施展条件的法术。 准备法术时，你所准备法术的总数等于你的感知调整值＋你的德鲁伊职业等级（最少可以准备一个）。 另外，你只能准备已经获得相应环阶法术位的法术。 | P37: 动作如潮 | Q37: 第2级起，你可以在短时间内突破极限，以使你在自己回合内执行一个额外的动作。 该特性在使用后必须完成一次短休或长休才能再使用。 第17级起，你可在休息前使用两次该特性，但每一回合只能使用一次。 | R37: 疾风连击 | S37: 你在自己回合内执行攻击动作后，可立即消耗1点气并以一个附赠动作发动两次徒手打击。 | T37: 战斗风格选项 | U37: 从2级起，当你选择战斗风格时，以下战斗风格加入可选战斗风格列表。 受祝福的勇士：你从牧师法术列表中选择两种戏法习得，这些戏法对你来说是圣武士法术，这些戏法的施法关键属性是魅力，当你提升此职业的等级时，你能够将一个已知戏法替换为牧师法术列表中的另一个戏法。 盲斗：你获得10尺盲视，在此范围内，你视为能看见任何未被完全遮蔽的事物，即便你目盲或在黑暗光照下，此外，你也可以看见范围内的隐形生物，除非其针对你进行隐匿并成功。 拦截：当一个你可见的生物攻击并击中了你5尺内一个你以外的生物时，你可以用反应减少该目标受到的伤害，减少数值为1d10+你的熟练加值（至少为0），你必须正在持用一面盾牌或一把简单武器或军用武器才能使用此能力。 | V37: 熟练探险家 | W37: 从1级起（替代自然探索者），你是一个无与伦比的探险家和求生专家。 你在1级时获得对应的特性，然后在第6级和第10级时再各获得对应的特性。 精明（1级）：你选择一项你拥有熟练的技能，你在使用该技能时的任何属性检定的使用两倍的熟练加值，此外，你可以额外说，读，写两门你选择的语言。 越野（6级）：你的步行速度增加5，同时你获得等于你步行速度的攀爬速度和游泳速度。 不知疲倦（10级）：以一个动作，你能够给予自己1d8+你的感知调整值的临时生命值，你能够使用此特性的次数等于你的熟练加值次（最少1次），已消费的次数可以通过完成一次长休进行恢复，此外，当你完成一次短休时，你的力竭等级减少1（若有）。 | X37: 灵巧动作 | Y37: 第2级起，你精妙的反应与身手使你的行动无比迅速。 你在战斗中每回合可执行一次附赠动作，该附赠动作可用以执行撤离、疾走或躲藏三种动作项其中之一。 | Z37: 已知法术 | AA37: 第1级时，你从术士法术列表里选择两个1环法术作为已知法术。 “术士职业表”中“已知法术”一栏记录了你获得更多已知法术时的相应等级。 但是你只能获取已有相应环阶法术位的法术。 比如，当你达到第3级时，你将获得一个1环或2环法术。 另外，你每提升一个术士等级，都可以从术士法术列表里选择一个新法术来代替一个已知法术列表中的旧法术。 但是，你必须拥有新法术的相应环阶法术位。 | AB37: 已知法术 | AC37: 第1级时，你从邪术师法术列表里选择两个1环法术作为已知法术。 “邪术师职业表”中“已知法术”一栏记录了你获得更多法术时的相应等级。 每个被选的法术都必须在当前等级拥有可用以施展该法术的法术位，具体见表。 比如，当你达到第6级时，你将获得一个1环、2环或3环的新邪术师法术。 另外，当你提升本职的职业等级时，你可以从邪术师法术列表里选择一个新法术来代替一个旧的邪术师已知法术，但是你的角色必须拥有用以施展新选法术的可用法术位。 | AD37: 法术书 | AE37: 第1级时，你让一本法术书纪录上六个你自选的1环法师法术。 你的法术书储存着你除戏法外的所有已知法术，而你的戏法则直接铭记在你脑海中。 | AF37: 必备工具 | AG37: 你通过你的工具产生你的奇械师法术效果，当你使用施法特性来施展法术时，必须手持一个法器——通常是盗贼工具或工匠工具。 你必须熟练这一工具才能将它作为法器使用，这些工具的描述请参见《玩家手册》第五章“装备”。 当你在第二级获得物品注法特性后，你也能使用任何你注入魔法的物品来作为法器使用，这意味着你施展的法术拥有“M（材料）”成分。 | AW37: =IFERROR(IF(AW36+1>BA26,IF(AW36+1>BA26,IF(AZ27+AZ36>BA27,"",AZ27+AZ36)),AW36+1),"") -> 8 | AX37: =IFERROR(INDEX(H31:AU181,AW37,AX26),"") | AY37: =IFERROR(INDEX(H31:AU181,AW37,AY26),"") | AZ37: =IFERROR(IF(AW36+1>BA26,AZ36+1,0),"") -> 0 | BB37: =IF(#REF!="","",#REF!) -> #REF! | BC37: =IFERROR(VLOOKUP(BB37,AX30:AY129,2,FALSE),"")
A38: 术士 | B38: 19 | C38: 20 | D38: 1 | E38: 30 | G38: 8 | H38: 原初道途 | I38: 第3级时，你选择一种道途来塑造你狂怒时的特质。 你可以从狂战士和图腾武者中选择其一。 随后，你将在第3、第6、第10、第14级时获得所选道途的相应特性。 | J38: 施法关键属性 | K38: 你的魔力源于你注入音乐或演说中的心灵力量，因此魅力是你施展吟游诗人法术的关键属性。 每当你的诗人法术需要施法关键属性时均指向你的魅力值。 而你诗人法术的豁免DC和攻击检定，则使用你的魅力调整值。 法术豁免DC＝8＋你的熟练加值＋你的魅力调整值 法术攻击调整值＝你的熟练加值＋你的魅力调整值 | L38: 仪式施法 | M38: 如果你所准备牧师法术中的某法术有带仪式标签，则你可以用这些法术进行仪式施法。 | N38: 圣树与圣木 | O38: 德鲁伊视特定种类的植物为圣物，典型的种类有：桤树、白蜡树、桦树、接骨木、榛树、冬青树、杜松、槲寄生、橡树、花楸树、柳树还有紫杉。 德鲁伊通常使用这些植物的一部分作为施法的法器，其中包括橡树或紫杉的长枝，或是槲寄生的枝条。 同样道理下，德鲁伊们也会使用这些木材制作其他物件，如武器和盾牌。 紫杉树代表了死亡与重生，因此常被用作弯刀和镰刀的手柄。 代表生命的白蜡树和代表力量的橡树，则非常适合制作手柄或整把武器（如短棒、长棍或盾牌）。 而代表大气的桤树则被用于制作投掷武器（如飞镖或标枪）。 某些地域的德鲁伊由于附近缺乏相应的植物，则会选择一些类似的品种作为代用。 比如荒漠地区的德鲁伊可能使用丝兰树甚至仙人掌作为代用。 例如，作为一名3级德鲁伊时，你拥有四枚1环法术位和两枚2环法术位。 假如你的感知为16，则你的准备法术列表可以囊括总共六个1环或2环法术的组合。 如果你准备了1环法术疗伤术，则你可以使用1环或者2环的法术位来施展它。 另外，已施展的法术并不会从你的准备列表中移除。 你可以在完成长休后改变你的准备法术列表。 准备新的德鲁伊法术列表时，你要再花时间进行祈祷和冥想。 准备时，你要为你列表上每个法术的每个环阶都花费至少1分钟时间。 | P38: 武术范型 | Q38: 第3级时，你选择一种范型以体现你的战斗风格和技巧。 你可以从诸如勇士、战斗大师、奥法骑士等范型中选择其一。 随后，你将在第3、第7、第10、第15、第18级获得所选范型的相应特性。 | R38: 坚强防御 | S38: 你在自己回合内，可以消耗1点气，并以一个附赠动作的形式来执行回避动作。 | T38: 施法 | U38: 第2级起，你学会通过冥想与祈祷引导神圣魔法，其原理与牧师相仿。 | V38: 战斗风格 | W38: 第2级起，你将精进于一种战斗风格，从下列选项中选择其一。 另外，即使你有多次选择战斗风格的机会，也不能重复选择同一个战斗风格。 箭术：使用远程武器进行攻击检定时具有+2加值。 防御：着装护甲时，你的AC获得+1加值。 对决：单手持用一把近战武器，且并未同时持用其他武器时，你用该武器攻击的伤害掷骰获得+2加值。 双武器战斗：使用两把武器战斗时，你可以将相应属性调整值加到第二次攻击的伤害上。 | X38: 游荡者范型 | Y38: 第3级时，你选择学习一种特定的战斗范型。 你可以从盗贼、刺客或者诡术师中选择其一。 随后，你将在第3，第9，第13、第17级时获得所选范型的相应特性。 | Z38: 施法关键属性 | AA38: 你的魔力来源于你意志的现实投影，因此魅力是你施展术士法术的关键属性。 每当你的法术需要施法关键属性时均指向你的魅力值。 而你术士法术的豁免DC和攻击检定，则使用你的魅力调整值。 法术豁免DC＝8＋你的熟练加值＋你的魅力调整值 法术攻击调整值＝你的熟练加值＋你的魅力调整值 | AB38: 施法关键属性 | AC38: 魅力是你施展邪术师法术的关键属性。 每当你的法术需要施法关键属性时均指向你的魅力值。 而你邪术师法术的豁免DC和攻击检定，则使用你的魅力调整值。 法术豁免DC＝8＋你的熟练加值＋你的魅力调整值 法术攻击调整值＝你的熟练加值＋你的魅力调整值 | AD38: 法术的准备和施展 | AE38: “法师职业表”里记录了你用以施展你法师法术的1环及更高环阶法术位数量。 施展某个法师法术时，你必须同时消耗其对应环阶的法术位。 已消耗的法术位可在完成长休后恢复。 你可以准备一系列符合当前施法条件的法师法术。 准备法术时，你从法术书中选择的准备法术总数等于你的智力调整值＋你的法师职业等级（最少为1）。 另外，你只能准备已经获得相应环阶法术位的法术。 例如，作为一名3级法师时，你拥有四枚1环法术位和两枚2环法术位。 假如你的智力为16，则你的准备法术列表可以囊括总共六个1环或2环法术的组合。 如果你准备了1环法术魔法飞弹，则你可以使用1环或者2环的法术位来施展它。 另外，已施展的法术并不会从你的准备列表中移除。 你可以在完成长休后改变你的准备法术列表。 准备新的法师法术列表时，你要再花时间研读你的法术书，并重新记忆所准备法术的咒语和施展动作。 准备时，你要为你列表上每个法术的每个环阶都花费至少1分钟时间。 | AF38: 戏法 | AG38: 在第1级，你从奇械师法术列表中习得两个戏法。 在更高的等级，你能够根据“奇械师职业表”习得更多戏法。 当你提升一个奇械师等级时，你能够从奇械师法术列表中习得一个新的戏法来替换一个原有的已知戏法。 | AW38: =IFERROR(IF(AW37+1>BA26,IF(AW37+1>BA26,IF(AZ27+AZ37>BA27,"",AZ27+AZ37)),AW37+1),"") -> 9 | AX38: =IFERROR(INDEX(H31:AU181,AW38,AX26),"") | AY38: =IFERROR(INDEX(H31:AU181,AW38,AY26),"") | AZ38: =IFERROR(IF(AW37+1>BA26,AZ37+1,0),"") -> 0 | BB38: =IF(#REF!="","",#REF!) -> #REF! | BC38: =IFERROR(VLOOKUP(BB38,AX30:AY129,2,FALSE),"")
A39: 邪术师 | B39: 21 | C39: 22 | D39: 1 | E39: 72 | G39: 9 | H39: 原初学识 | I39: 从3级起，当你的野蛮人职业等级达到3级和10级时，你可以从野蛮人1级所提供的技能熟练项列表中选择一个技能，获得该技能的熟练。 | J39: 仪式施法 | K39: 如果你已知法术列表中的某法术带有仪式标签，则你可以用这些法术进行仪式施法。 | L39: 法器 | M39: 你可以使用圣徽作为施展牧师法术的法器。 | N39: 施法关键属性 | O39: 你的法术力量源于你对自然的信仰与同调，因此感知是你施展德鲁伊法术的关键属性。 每当你的德鲁伊法术需要施法关键属性时均指向你的感知值。 而你德鲁伊法术的豁免DC和攻击检定，则使用你的感知调整值。 法术豁免DC＝8＋你的熟练加值＋你的感知调整值 法术攻击调整值＝你的熟练加值＋你的感知调整值 | P39: 替换武术 | Q39: 从4级起，当你的战士职业等级抵达能让你获得属性值提示职业特性时，你能进行以下一项改变。 这种变化代表着你改变了武术训练和练习的重点 用一个战士可用的战斗风格替换原有的一个战斗风格。 如果你通过战技大师范型掌握了战技，你可以将你的一个已知战技替换为一个不同的战技。 | R39: 飞檐走壁 | S39: 你在自己回合内，可以消耗1点气，并以一个附赠动作的形式来执行撤离动作或疾走动作，同时使你该回合内的跳跃距离翻倍。 | T39: 法术的准备与施展 | U39: “圣武士职业表”里记录了你用以施展圣武士法术的1环及更高环阶法术位数量。 施展某个圣武士法术时，你必须同时消耗其对应环阶的法术位。 而已消耗的法术位则可以通过完成一次长休进行恢复。 你可以准备圣武士法术列表中所有符合当前施展条件的法术。 准备法术时，你所准备法术的总数等于你的魅力调整值＋你圣武士职业等级的一半（最少可准备一个）。 另外，你只能准备已获得相应环阶法术位的法术。 例如，作为一名5级圣武士时，你拥有四枚1环法术位和两枚2环法术位。 假如你的魅力为14，则你的准备法术列表可以囊括四个1环或者2环法术的组合。 如果你已经准备了1环法术疗伤术，则你可以使用1环或2环的法术位来施展它。另外，已施展的法术并不会从你的准备列表中移除。 你可以在完成长休后改变你的准备法术列表。 准备新的圣武士法术列表时，你要再花时间进行祈祷和冥想。 准备时，你要为你列表上每个法术的每个环阶都花费至少1分钟时间。 | V39: 战斗风格选项 | W39: 从2级起，当你在选择战斗风格时，下列选项加入你的可选战斗风格中。 盲斗：你获得10尺盲视，在10尺范围内，你可以看见除了处于全遮掩后的任何东西，哪怕你正在被目盲或是在黑暗之中，另外，你可以看见该范围内的隐形生物，除非该生物成功地对你躲藏。 德鲁伊教战士：你学会两个来自德鲁伊法术列表的你自选的戏法，它们对你视作游侠法术，感知是你施展他们的施法关键属性。 当你升级时，你可以将其中一个戏法替换为德鲁伊法术列表中的另一个戏法。 投掷武器战斗：你可以在使用一件带有投掷属性武器进行进攻时，将那件武器作为攻击的一部分而拔出。 另外，在你以一件投掷武器于远程攻击中命中对手时，你的伤害掷骰+2。 | X39: 手稳就准 | Y39: 从3级起，作为一个附赠动作，你在当前回合为你的下一次攻击提供优势。 你只能在你本回合还没有移动的时候使用这个附赠动作，而且在你使用这个附赠动作后，你的速度在当前回合里归0。 | Z39: 法器 | AA39: 你可以使用奥术法器，作为你施展术士法术时的法器。 | AB39: 法器 | AC39: 你可以使用奥术法器作为你施展邪术师法术的法器。 | AD39: 施法关键属性 | AE39: 你的法术来自你专注的研习和记忆，因此智力是你施展法师法术的关键属性。 每当你的法术需要施法关键属性时均指向你的智力值。 而你法师法术的豁免DC和攻击检定，则使用你的智力调整值。 法术豁免DC＝8＋你的熟练加值＋你的智力调整值 法术攻击调整值＝你的熟练加值＋你的智力调整值 | AF39: 法术的准备和施展 | AG39: “奇械师职业表”显示出你有多少能用于施法的法术位。 施展某个奇械师法术时，你必须同时消耗其对应环阶的法术位。 而已消耗的法术位则可以通过完成一次长休进行恢复。 你需要从奇械师法术列表中选择想要准备的法术，你能选择的准备法术总数等于你的智力调整值＋你奇械师职业等级的一半（向下取整）（最少为1）。 你只能准备已经获得相应环阶法术位的法术。 例如，作为一名5级奇械师时，你拥有四枚1环法术位和两枚2环法术位。 假如你的智力为14，则你的准备法术列表可以囊括总共四个1环或2环法术的组合。 如果你准备了1环法术疗伤术，则你可以使用1环或者2环的法术位来施展它。 另外，已施展的法术并不会从你的准备列表中移除。 你可以在完成长休后改变你的准备法术列表，如需准备新的奇械师法术，你需要花时间来调整你的法器：每个法术要花费至少1分钟的时间。 | AW39: =IFERROR(IF(AW38+1>BA26,IF(AW38+1>BA26,IF(AZ27+AZ38>BA27,"",AZ27+AZ38)),AW38+1),"") -> 10 | AX39: =IFERROR(INDEX(H31:AU181,AW39,AX26),"") | AY39: =IFERROR(INDEX(H31:AU181,AW39,AY26),"") | AZ39: =IFERROR(IF(AW38+1>BA26,AZ38+1,0),"") -> 0 | BB39: =IF(#REF!="","",#REF!) -> #REF! | BC39: =IFERROR(VLOOKUP(BB39,AX30:AY129,2,FALSE),"")
A40: 法师 | B40: 23 | C40: 24 | D40: 1 | E40: 18 | G40: 10 | H40: 属性值提升 | I40: 当达到第4、8、12、16、19级时，你可以选择一项属性值提升2点，或是选择两项属性各提升1点。 不过你不能通过此特性让属性值超过20。 | J40: 法器 | K40: 你可以使用乐器作为施展诗人法术的法器。 | L40: 神圣领域 | M40: 你将选择一个与你所信仰神祇的神职相关的神圣领域。 你可以从知识、生命、光明、自然、风暴、诡术或者战争中选择其一。 某些领域其领域法术可能并不在牧师法术列表中，此时如果你选择了该领域，则你视该领域的领域法术为你的牧师法术。 | N40: 仪式施法 | O40: 如果你所准备德鲁伊法术中的某法术有带仪式标签，则你可以用这些法术进行仪式施法。 | P40: 属性值提升 | Q40: 当你达到第4、第6、第8、第12、第14、第16、第19级时，你可以选择一项属性值提升2点，或是选择两项属性各提升1点。 不过，你无法通过该特性让属性值超过20。 | R40: 无甲移动 | S40: 第2级起，当未穿着任何护甲也没持用盾牌时，你的移动速度增加10尺。 该加值将随着武僧职业等级的提升而增加，具体数值见“武僧职业表”中“无甲移动”一栏。 第9级起，你在自己的回合内，可以在垂直平面或水面等地形移动，但移动结束时你必须处在不会坠落的地方。 | T40: 施法关键属性 | U40: 你的法术源自你坚定信念产生的力量，因此魅力是你施展圣武士法术的关键属性。 每当你的圣武士法术需要施法关键属性是均指向你的魅力值。 而你圣武士法术的豁免DC和攻击检定，则使用你的魅力调整值。 法术豁免DC＝8＋你的熟练加值＋你的魅力调整值 法术攻击调整值＝你的熟练加值＋你的魅力调整值 | V40: 施法 | W40: 第2级起，你学会运用自然世界的魔法本源进行施法，你的施法方式与德鲁伊类似。 | X40: 属性值提升 | Y40: 当你达到第4、第8、第10、第12、第16、第19级时，你可以选择一项属性值提升2点，或是选择两项属性各提升1点。 不过你不能通过该特性让属性值超过20。 | Z40: 术法起源 | AA40: 选择一个术法起源作为你天赋魔力的源泉。 你可在龙族血脉或狂野魔法中选择其一。 随后，你将在第1、第6、第14、第18级获得相应起源的职业特性。 | AB40: 魔能祈唤 | AC40: 你在神秘学识的研习过程中发掘出魔能祈唤的方式，这些禁忌的知识残章让你获得了持久的魔法能力。 第2级时，你获得两种自选的魔能祈唤。 在获得更高的邪术师等级后你还可以习得其它的魔能祈唤，具体数据见“邪术师职业表”中“已知祈唤”一栏。 另外，你提升本职的等级时，可以用新的祈唤替换一个已学会的祈唤，但你的角色必须满足学习新祈唤的先决条件。 | AD40: 仪式施法 | AE40: 如果你法术书记录了带有仪式标签的法术，则你可以用这些法术进行仪式施法。 进行仪式施法时，你不需要准备相应的法术。 | AF40: 施法关键属性 | AG40: 你对魔法理论的理解使你能够以更高超的技法来使用这些法术，因此智力是你的施法关键属性。 每当你的法术需要施法关键属性时均指向你的智力值。 而你奇械师法术的豁免DC和攻击检定，也使用你的智力调整值。 法术豁免DC＝8＋你的熟练加值＋你的智力调整值 法术攻击调整值＝你的熟练加值＋你的智力调整值 | AW40: =IFERROR(IF(AW39+1>BA26,IF(AW39+1>BA26,IF(AZ27+AZ39>BA27,"",AZ27+AZ39)),AW39+1),"") -> 11 | AX40: =IFERROR(INDEX(H31:AU181,AW40,AX26),"") | AY40: =IFERROR(INDEX(H31:AU181,AW40,AY26),"") | AZ40: =IFERROR(IF(AW39+1>BA26,AZ39+1,0),"") -> 0 | BB40: =IF(#REF!="","",#REF!) -> #REF! | BC40: =IFERROR(VLOOKUP(BB40,AX30:AY129,2,FALSE),"")
A41: 奇械师 | B41: 25 | C41: 26 | D41: 1 | E41: 41 | G41: 11 | H41: 额外攻击 | I41: 第5级起，你在自己回合内执行攻击动作时可以发动两次攻击而非一次。 | J41: 诗人激励 | K41: 从第1级起，你可以用热血的话语和音乐激励他人。 此时，你可以在自己回合内用一个附赠动作指定身边60尺内一个能听到你声音的生物（不能指定你自身），并使该生物获得一个诗人激励，即一个d6的激励骰。 在接下来的10分钟内，该生物在进行单次属性检定、攻击检定、豁免检定时可以使用该激励骰，以将其结果加到掷骰结果中。该生物可以在d20结果掷出后，DM宣布结果前决定是否使用诗人激励。而诗人激励一旦使用即被消耗掉。一个生物同一时间里只能保有一个诗人激励。 你能够使用该特性的次数等于你的魅力调整值（最低一次）。完成一次长休后，你将重获所有消耗掉的诗人激励次数。 你产生的激励骰大小可以在达到本职业的特定等级时增大。第5级时为d8，第10级时为d10，而第15级时为d12。 | L41: 领域法术 | M41: 每个领域都有其相应的领域法术列表。 当你获得表中所对应的牧师等级时，你将同时习得这些法术。 领域法术一旦习得，将会一直在你的准备法术列表中，且不计入你的每日准备法术上限。 任何领域法术对你而言都是牧师法术，而不论其是否在牧师法术列表之上。 | N41: 法器 | O41: 你可以用德鲁伊法器作为你施展德鲁伊法术的法器。 | P41: 额外攻击 | Q41: 第5级起，你在自己回合内执行攻击动作时可以发动两次攻击而非一次。 第11级后，你可以攻击三次。 第20级后可以攻击四次。 | R41: 专用武器 | S41: 从2级起，你训练自己使用各种武器作为武僧武器，而不仅仅是简易近战武器和短剑。 每当你完成短休或长休时，可以碰触一件武器，将气集中在它之中，然后该武器就视为武僧武器，直到你再次使用这个能力。 所选武器必须符合以下标准： 武器必须是简易武器或军用武器 你必须拥有其熟练项 不能拥有重型或特殊属性 | T41: 法器 | U41: 你可用圣徽作为施展你圣武士法术的法器。 | V41: 法器 | W41: 从2级起，你可以使用一件德鲁伊法器作为你的游侠法术的法器。 一件德鲁伊法器可能会是一枝槲寄生或者冬青木的枝条，用紫衫木或者其他特殊木材制作而成的魔杖或权杖，一柄从活化树木上取来的法杖，或是一件混合了神圣动物的羽毛、毛发、骨头与牙齿的物件。 | X41: 直觉闪避 | Y41: 第5级起，当一个你能看见的敌人攻击命中你时，你可以用反应让此次攻击的伤害减半。 | Z41: 魔力泉涌 | AA41: 第2级时，你解除了体内魔力之源的封印，从中涌现的魔力体现为你的可用术法点。 你可以使用术法点创造各种魔法效应。 | AB41: 魔契恩泽 | AC41: 第3级时，你的宗主赋予你一份馈赠作为你忠诚服务的回馈。 你可以从下列特性中自选其一。 每种魔契恩泽都呈现为一种独特的生物或物品，并反应出你的宗主的本质。 链之魔契:你的魔宠比普通的魔宠更加机敏。 其默认形态是你的宗主的侧面体现，如至高妖精宗主的是小妖精和伪龙，邪魔宗主则是小魔鬼和夸赛魔。 因为旧日支配者不可名状的本质，任何形态的魔宠都适合它。 刃之魔契:如果你的宗主是至高妖精，那么你的武器可能是一把被藤蔓所缠绕的细长剑刃。 如果你的宗主是邪魔，你的武器则可能是一柄由黑金属铸成并雕以火焰纹饰的斧头。 如果你的宗主是旧日支配者，那么你的武器可能是一把样式古朴的长矛，一颗精心雕琢过的宝石镶嵌在矛头上，如同一只可怖的不瞑之目。 书之魔契:你那由高贵的至高妖精宗主所赐予的影之书可能是一本记载着附魔系和幻术系法术的精装镀金边书册。 你的邪魔宗主可能赐予你一本革质封皮附铁扣的沉重书册，其中记载着咒法系法术和大量的禁忌知识、以及宇宙之中的秽邪之地。 你的旧日支配者宗主可能会赐予你一本因接触它而疯狂者的破旧日记，其中记载着几个只有你自己癫狂的思维才能理解并施展的法术。 | AD41: 法器 | AE41: 你可以使用奥术法器来作为施展法师法术的法器。 | AF41: 仪式施法 | AG41: 如果你准备了带有仪式标签的法术，则你可以用这些法术进行仪式施法。 | AW41: =IFERROR(IF(AW40+1>BA26,IF(AW40+1>BA26,IF(AZ27+AZ40>BA27,"",AZ27+AZ40)),AW40+1),"") -> 12 | AX41: =IFERROR(INDEX(H31:AU181,AW41,AX26),"") | AY41: =IFERROR(INDEX(H31:AU181,AW41,AY26),"") | AZ41: =IFERROR(IF(AW40+1>BA26,AZ40+1,0),"") -> 0 | BB41: =IF(#REF!="","",#REF!) -> #REF! | BC41: =IFERROR(VLOOKUP(BB41,AX30:AY129,2,FALSE),"")
G42: 12 | H42: 快速移动 | I42: 第5级起，你在未着装重甲时速度提升10尺。 | J42: 万事通 | K42: 第2级起，在你进行属性检定时，如果检定结果不包含你的熟练加值，则你可以将自身熟练加值的一半（向下取整）加入到检定结果中。 | L42: 引导神力 | M42: 第2级时，你获得引导神祇所授予神圣能量的能力，所引导的能量将用以实现各种魔法效应。 你最初将获得两种效应：驱散不死生物和另一个与你所选领域相关的效应。 随着你在冒险中提升等级，某些领域会赋予更多额外的效应，具体信息可以参考相应领域的描述内容。 引导神力最终产生的效应由你自行选择。 引导神力后，你必须完成一次短休或长休才能重新使用该特性。 某些引导神力的效应需要豁免，其豁免DC等于你的牧师法术豁免DC。 第6级起，你可以在两次休息之间使用两次引导神力，第18级后可以使用三次。 完成一次短休或长休后，你将重新获得所有消耗掉的引导神力次数。 | N42: 荒野形态 | O42: 第2级起，你可以用动作以魔力变化为曾见识过的野兽形态。 该特性可以使用两次，且在完成一次短休或长休后，你将重新获得所有消耗掉的荒野形态次数。 你的德鲁伊职业等级决定了你可以变化的野兽种类，你可以变化成任意没有飞行或游泳速度且挑战等级为1/4或更低的野兽形态。 你可以在数个小时里保持着野兽形态，其持续时间具体数值等于你的德鲁伊职业等级的一半（向下取整）。你可以在持续时间过后恢复原形，或者你也可以再次使用此特性来维持变形。另外，你也可以在你的回合内用一个附赠动作来恢复原形。在你陷入昏迷、生命值为0或者死亡的时候，变形将自动解除。 你变形时必须遵从以下规则： 你的属性数据替换为新形态的数值，但你仍保持你的阵营、个性，以及智力值、感知值、魅力值。你保留技能与豁免的熟练项，并且获得新形态的技能和豁免熟练项。如果新形态的熟练项与你相同且熟练加值较高，则使用新形态的熟练加值。你不能使用新形态可能拥有的传奇动作或巢穴动作。 变形后，你使用新形态的生命值和生命骰。变回原形时，你的生命值恢复变形之前的数值。而任何让你的生命值降至0的伤害，都可以使你变回原形并承受该伤害的溢出伤害量。例如，你在动物形态下受到了10点伤害而你只剩1点生命值，则你变回原形并受到9点伤害。只要超过的伤害没有将你原形的生命值降至0，你就不会因此陷入昏迷。 你不能施法，并且任何说话或者需要用手的动作，在你处于野兽形态时都将受到限制。变形不会打断你正在专注的法术，也不会妨碍你执行作为已施展法术（例如召雷术call lightning）一部分的某些动作。 你保持从职业、种族或其它来源特性的收益，并且可以在新形态身体能力允许下使用这些特性。不过，你无法使用任何原有的特殊感官（例如黑暗视觉），除非你的新形态也具有这种感官。 变形时，你可以选择将你的装备丢在所处空间，或者将其融入新形态，又或者直接着装在身上。新形态直接着装的装备可以如常起作用，但DM有权基于新形态的体型和身姿作出判断，并最终决定新形态使用该装备是否合理。装备不会改变大小来适应新形态，新形态无法着装某装备时，该装备会掉落你所处空间或融入新形态中。融入新形态的装备失去其效应，且在你变回原形时才能恢复。 | P42: 不屈 | Q42: 第9级起，你可以重掷失败的豁免检定。 不过你必须采用重掷的结果。你必须完成一次长休才能再次使用该特性。 第13级起，你可以在两次长休之间使用两次该特性。 第17级起，你可以在两次长休之间使用三次该特性。 | R42: 宗派 | S42: 第3级时，你选择投入一个宗派精进你的技艺。 你可以从散打宗、暗影宗、四象宗中选择其一。 随后，你的将在第3、第6、第11、第17级时获得相应宗派的特性传承。 | T42: 至圣斩 | U42: 第2级起，你使用近战武器攻击命中一个生物时，可以消耗一枚法术位，并对目标造成除武器伤害外附加的光耀伤害。 额外伤害的数值为1环法术位时的2d8，以及更高法术位时每比1环高一环就外加1d8，其最高值为5d8。 如果目标是不死生物或邪魔，则该伤害将再额外增加1d8，至高提升至6d8。 | V42: 法术位 | W42: “游侠职业表”中记录了你可用以施展你游侠法术的1环及更高环阶法术位数量。 施展某个游侠法术时，你必须同时消耗其对应环阶的法术位。 而已消耗的法术位则可以通过完成一次长休进行恢复。 例如，若你已知1环法术化兽为友且有一枚可用的1环法术位和一枚可用的2环法术位，则两法术位都可用来施展该法术。 | X42: 反射闪避 | Y42: 第7级起，你可以灵巧躲过某些特定的区域效应，比如红龙的火焰吐息或是法术冰风暴。 你在成为某一范围效应影响对象时，若该效应允许你通过成功的敏捷豁免来使伤害减半，则你在该豁免成功时不受伤害，而豁免失败时只受一半伤害。 | Z42: 术法点 | AA42: 开始时，你拥有2个术法点。 此后你每提升一个术士等级，都会获得更多的术法点，详见“术士职业表”中“术法点”一栏。 你的术法点永远不能超过表中所列对应你当前等级的数值。 而已消耗的术法点则可以通过完成一次长休进行恢复。 | AB42: 链之魔契 | AC42: 你习得法术获得魔宠，并可以把它作为一个仪式施展。 此法术不计入你的已知法术数量。 施展该法术时，你可以选择召唤一个普通的生物，或是下列特殊生物之一：小魔鬼、伪龙、夸赛魔、或小妖精。 此外，当你执行攻击动作时可以放弃所有攻击中的一次攻击，转而让你的魔宠使用其反应发动一次攻击。 | AD42: 学习法术 | AE42: 你每提升一个法师等级，可以将两项自选的法师法术加入你的法术书中。 但是，你只能加入已经获得相应环阶法术位的法术。 你在冒险过程中所发现的法术也可以加入到法术书中。 | AF42: 物品注法 | AG42: 在第2级，你获得为普通物品注入魔法的能力。 使用此特性创造的魔法物品是永久性魔法物品的原型。 | AW42: =IFERROR(IF(AW41+1>BA26,IF(AW41+1>BA26,IF(AZ27+AZ41>BA27,"",AZ27+AZ41)),AW41+1),"") -> 13 | AX42: =IFERROR(INDEX(H31:AU181,AW42,AX26),"") | AY42: =IFERROR(INDEX(H31:AU181,AW42,AY26),"") | AZ42: =IFERROR(IF(AW41+1>BA26,AZ41+1,0),"") -> 0 | BB42: =IF(#REF!="","",#REF!) -> #REF! | BC42: =IFERROR(VLOOKUP(BB42,AX30:AY129,2,FALSE),"")
A43: 狂战士 | B43: 1 | C43: 2 | D43: =G50 -> 20 | E43: =D44-1 -> 23 | G43: 13 | H43: 野性直觉 | I43: 第7级时，你的直觉变的异常敏锐，从而使你骰先攻时具有优势。 此外，如果你在战斗开始时被突袭但并未陷入失能，则你仍可以在你的第一回合正常行动。不过你必须在进行任何其它行动前进入狂暴。 | J43: 休憩曲 | K43: 第2级起，你可以在短休时用轻柔的音乐或话语帮助伙伴们恢复伤势。 如果你或任何友方生物可以在其短休时听到你的演奏声，且决定在此时使用生命骰恢复生命值，则其恢复量可以额外增加1d6。 该额外恢复的数值在达到特定职业等级时可以再增加。第9级时增为1d8，第13级时增为1d10，第17级时增为1d12。 | L43: 引导神力：驱散不死生物 | M43: 你以一个动作展示你的圣徽，并说出一段谴责不死生物的祷言。 你身边30尺范围内能够看到圣徽或听到你祷言的不死生物必须进行一次感知豁免，豁免失败则受到驱散，其效应持续1分钟或直到其受到任何伤害。 一个被驱散的生物必须花费其回合内的所有速度尽力远离你，而且无法主动靠近你30尺内。 被驱散的生物无法使用反应，只能使用既有的疾走Dash动作或从任何妨碍他们移动的效应中挣脱。 该生物无路可走时会使用“回避”动作。 | N43: 德鲁伊结社 | O43: 第2级时，你将选择参与一个德鲁伊结社。 你可以从大地结社或月亮结社中选择其一。 随后，你将在第2、第6、第10、第14级时获得所选结社相应的特性。 | P43: 精通重击 | Q43: 从你第3级选择此范型起，你的武器攻击在掷出19或20时即可造成重击。 | R43: 拨挡飞弹 | S43: 第3级起，你可以用你的反应拨挡或抓取一个击中你的远程武器攻击。 使用本特性后，该次攻击的伤害将被削弱，其减数值等于1d10＋你的敏捷调整值＋你的武僧职业等级。 当被拨挡攻击的伤害减少至0，且实施伤害的飞弹可以被你单手抓住时，你可以用此时空闲的手去抓取该飞弹。 此时你可以消耗1点气以该“飞弹”进行一次远程攻击，而该攻击将视为本次反应的一部分。 无论你是否具有被拨挡武器的熟练项，本次攻击中你都视为进行具有熟练项的攻击，所使用的飞弹也视为武僧武器，其射程为20/60尺。 | T43: 神佑 | U43: 第3级起，你体内涌动的神圣魔法使你免疫疾病。 | V43: 已知法术 | W43: 你从游侠法术列表里选两个1环法术作为自己的已知法术。 “游侠职业表”中“已知法术”一栏记录了你获得更多已知法术时的相应等级。 你只能获取已有相应环阶法术位的法术。 比如，当你达到第5级时，你将获得一个1环或2环法术。 另外，你每提升一个游侠等级，还可以从游侠法术列表里选择一个新法术来代替一个已知法术列表中的旧法术。 但是，你必须拥有新法术的相应环阶法术位。 | X43: 可靠才能 | Y43: 第11级起，你自身技能经过精炼而更趋于完美。 每当你进行的属性检定可以使用熟练加值时，你可以将d20骰中9或以下的结果都视为10。 | Z43: 灵活施法 | AA43: 你可以使用术法点来获得额外的法术位，或是消耗法术位来换取额外的术法点。 随着术士等级的提升，你还可以学会其他术法点的使用方法。 | AB43: 刃之魔契 | AC43: 你可以用一个动作从空着的手中创造一把契约武器。 你每次创造契约武器时都可以从近战武器列表中选择它的形态。 当你使用该武器时，将视为拥有该武器的熟练项。 在攻击对非魔法攻击或伤害具有抗性或免疫的目标时，该武器将视为魔法武器。 你的契约武器在离你5尺外的区域停留超过1分钟或更长时间，其将自然消失。 当你再次创造契约武器、解散契约武器（无需动作）或是死亡的情况下，契约武器也会消失不见。 你可以通过一个特殊的仪式把持有的魔法武器变为你的契约武器。 该仪式花费1小时，并且可以在短休时进行。 仪式完成后，你随时可以解散该武器，以将其转移到一个异次元空间之中。 而每当你再次创造契约武器时再将它召唤出来。 该仪式无法对神器或智能武器起作用。 如果你死亡；或是花费1小时对另外一把武器举行了仪式；或是你通过1小时的仪式打破该契约，则该武器便不再是你的契约武器。 如果在它处于异次元空间时你打破契约，那么该武器将会出现在你的脚边。 | AD43: 奥术回想 | AE43: 你学会了通过研读法术书来恢复魔法能量的办法。 你可以每日使用一次奥术回想，以在你完成一次短休后恢复若干已消耗的法术位，所恢复的法术位环阶总和不得大于你法师等级的一半（向上取整），且任何一枚法术位的环阶都必须小于6环。 例如，作为一名4级法师时，你可恢复环阶总数最多为2的法术位。 你可以选择恢复一枚2环法术位或两枚1环法术位。 | AF43: 已知注法 | AG43: 当你获得这个特性时，从职业描述末尾的“奇械师注法”列表中选择选择四个奇械师注法习得。 当你提升奇械师等级时，还能够根据“奇械师职业表”习得更多注法。 当你提升一个奇械师等级时，你能够习得一个新的奇械师注法来来替换一个原有的已知注法。 | AW43: =IFERROR(IF(AW42+1>BA26,IF(AW42+1>BA26,IF(AZ27+AZ42>BA27,"",AZ27+AZ42)),AW42+1),"") -> 14 | AX43: =IFERROR(INDEX(H31:AU181,AW43,AX26),"") | AY43: =IFERROR(INDEX(H31:AU181,AW43,AY26),"") | AZ43: =IFERROR(IF(AW42+1>BA26,AZ42+1,0),"") -> 0 | BB43: =IF(#REF!="","",#REF!) -> #REF! | BC43: =IFERROR(VLOOKUP(BB43,AX30:AY129,2,FALSE),"")
A44: 图腾武者 | B44: 1 | C44: 2 | D44: =G54 -> 24 | E44: =D45-1 -> 28 | G44: 14 | H44: 直觉猛扑 | I44: 作为你进入狂暴状态的附赠动作的一部分，你可以移动一段等同于你速度的一半的距离。 | J44: 吟游诗人学院 | K44: 第3级时，你将选择加入一个吟游诗人的学院协会，以探寻更精深的技艺。 你可以从逸闻学院或勇气学院中选择其一。 随后，你将在第3、第6和第14级时获得相应的职业特性。 | L44: 神力掌控 | M44: 从2级起，你可以花费一次你的引导神力次数来充能你的法术。 你可以用一个附赠动作触碰你的圣徽并祈祷，你恢复一个环阶不超过你熟练加值的一半（向上取整）的法术位。 你能使用此特性的次数取决于你此职业的等级：2级一次；6级两次；18级三次。完成一次长休后，你将恢复所有已消耗的次数。 | N44: 荒野伙伴 | O44: 从2级起，你获得召唤呈现动物形态的精魂的能力，以一个动作，你能够消耗一次荒野变形使用次数来施放一次无需材料的获得魔宠法术。 当你以此方法施放该法术时，魔宠的类型是精类而不是野兽，魔宠会在等同于你德鲁伊等级一半的小时数后消失。 | P44: 运动健将 | Q44: 第7级起，你可以将一半的熟练加值（向上取整）加在你不包含熟练加值的任何力量、敏捷或体质检定上。 另外，当你助跑跳远时，你能跳出的距离增加等同于你力量调整值的尺数。 | R44: 驭气以击 | S44: 从3级起，如果你在你的回合中执行动作时花费了1点或更多的气，则你可以在回合结束前用1附赠动作以徒手打击或武僧武器进行一次攻击。 | T44: 神圣誓言 | U44: 第3级起，你将立下神圣誓言，并永远与你的圣武士身份同在。 你在此之前的圣武士修行被认为仅仅是接受了一条道路而尚未立誓遵从，你之前所躬行的行为都是为此刻作准备。 神圣誓言包括奉献之誓、古贤之誓、复仇之誓等，你可从中选择其一。 随后，你将在第3，第7，第15和第20级获得所选圣誓的相应特性。 | V44: 游侠范型 | W44: 第3级时，你选择学习一种特定的战斗范型。 你可以从猎人或驯兽师中进行选择。 随后，你将在第3，第7，第11、第15级时获得所选范型的相应特性。 | X44: 听声辨位 | Y44: 第14级起，只要能听到声音，你就可以定位身边10尺内躲藏或隐形的生物。 | Z44: 生成法术位 | AA44: 你可以在自己回合内以附赠动作将未使用的术法点转换为法术位。 表格“生成法术位”中列出了生成各法术位所需的术法点数。 另外，你无法生成高于5环的法术位。 以此方式生成的法术位将在完成一次长休后消散。 法术位环阶——术法点消耗 1环——————2 2环——————3 3环——————5 4环——————6 5环——————7 | AB44: 书之魔契 | AC44: 你的宗主给予你一本名为“影之书”的魔法书。 获得该特性后，从任意职业法术列表中选择三个戏法（这三个戏法不必来自同一个列表）。 该魔法书在你身上时，你可以随意施展那些法术。 它们不算入你的已知戏法数量中。 这些法术就算本来不属于邪术师法术列表，你也将其视为邪术师法术。 如果你丢失了自己的影之书，你可以举行一个1小时的仪式，并从你的宗主处获得一个替代品。 仪式可以在短休或长休期间完成，而它会摧毁之前的魔法书。 当你死亡时，该书也将化为灰烬。 | AD44: 奥术传承 | AE44: 第2级时，你选择一种奥术传承以使你的训练专注于八个学派之一。 从防护、咒法、预言、附魔、塑能、幻术、死灵、变化各学派中选择其一。 随后，你将在第2、第6、第10、第14级时获得所选学派相应的特性。 | AF44: 为物品进行注法 | AG44: 每当你完成一个长休后，你可以触摸一个非魔法的物体，使用奇械师注法来把它变成一个魔法物品。 注法只能作用于注法描述中写明的指定类型物品。 如果该物品需要调谐，你可以在为物品进行注法的那一刻调谐到它，或者你可以放弃调谐，以便其他人能够调谐到该物品。 如果你决定以后与这个物品进行调谐，你必须进行通常的调谐程序（参见《地下城主指南》第136页中的“调谐”）。 你的注法持续时间无限，但当你死亡时，注法会在你智力调整值的天数后消失（至少1天）。 如果你将某个注法从已知中替换掉，该注法的效果也将消失。 你能在一次长休后为复数物品进行注法；注法物品的最大数量请参见“奇械师职业表”。 你必须触摸每一个物体，且一种注法在同一时间内只能存在于一个物品上，而一个物品也无法进行复数次注法。 如果你试图超过你的最大注法量，则最旧的注法立即结束，然后新的注法适用。 如果注法结束时，该物品中包含有其他物品，例如是一个次元袋，其中的物品将无害地出现在它周围的空间中。 | AW44: =IFERROR(IF(AW43+1>BA26,IF(AW43+1>BA26,IF(AZ27+AZ43>BA27,"",AZ27+AZ43)),AW43+1),"") -> 15 | AX44: =IFERROR(INDEX(H31:AU181,AW44,AX26),"") | AY44: =IFERROR(INDEX(H31:AU181,AW44,AY26),"") | AZ44: =IFERROR(IF(AW43+1>BA26,AZ43+1,0),"") -> 0 | BB44: =IF(#REF!="","",#REF!) -> #REF! | BC44: =IFERROR(VLOOKUP(BB44,AX30:AY129,2,FALSE),"")
A45: 狂热者 | B45: 1 | C45: 2 | D45: =G59 -> 29 | E45: =D46-1 -> 33 | G45: 15 | H45: 凶蛮重击 | I45: 第9级起，计算近战攻击的重击伤害时，你可以额外骰一个所用武器的伤害骰。 第13级时，你可以额外骰两个；第17级时，你可以额外骰三个。 | J45: 专精 | K45: 第3级起，你选择两个已有的技能熟练项。此后你进行所选技能的属性检定时，可以使用双倍的熟练加值。 第10级后，你可以再选择另外两个已有的技能熟练项从该特性中获益。 | L45: 替换戏法 | M45: 从4级起，当你在此职业获得了属性值提升，你可以将一个你通过此职业的施法特性学会的牧师戏法替换为牧师法术列表中的另一个戏法。 | N45: 替换戏法 | O45: 从4级起，每当你达到该职业提升属性值的等级时，你就可以用德鲁伊法术列表中的另一个戏法来替换你从该职业的施法特性中学到的一个戏法。 | P45: 额外战斗风格 | Q45: 第10级时，你可以额外选择一个战斗风格。 | R45: 属性值提升 | S45: 当你达到第4，第8，第12，第16、第19级时，你可以选择一项属性值提升2点，或是选择两项属性各提升1点。 不过你不能通过该特性让属性值超过20。 | T45: 圣誓法术 | U45: 每种誓言都有其相应的圣誓法术列表。 当你达到表中所示的圣武士等级时，你将同时获得其对应的圣誓法术。 圣誓法术一旦获得，将会一直在你的准备法术列表中，且不计入你的每日准备法术上限。 任何圣誓法术对你而言都是圣武士法术，而不论其是否在圣武士法术列表之上。 | V45: 原初意识 | W45: 第3级起，你可以消耗一枚游侠法术位，并用动作将你的意识集中在身处的区域，感测1里内是否存在以下类型生物（在偏爱地形中时，扩展至6里）：异怪、天界生物、龙、精类生物、邪魔、元素生物和不死生物。 所消耗法术位每提高一环阶感测效果持续时间就多加1分钟。 另外，该特性并不会知晓生物的位置或数量。 | X45: 圆滑心智 | Y45: 第15级起，你的心理素质获得了大大的加强，并因此获得感知豁免的熟练项。 | Z45: 法术位转换术法点 | AA45: 你可以在自己回合内使用附赠动作将未使用的法术位转化为术法点。 你消耗一枚法术位并获得等于该法术位环阶的术法点。 所有你以该特性生成的法术位，在你完成一次长休后也将随之消失。 | AB45: 魔契恩泽·符之魔契 | AC45: 第3级时，你的宗主赐予你一个护身符，一个当需要的时候可以帮助佩戴者的护身符。 当佩戴者在一次能力检定中失败，他们可以在骰掷结果上增加一个d4骰，这可能将结果变为成功。 这一能力可使用的次数等于你的熟练加值，且所有已消耗的次数将会在你完成一次长休之后全部恢复。 如果你弄丢了护身符，你可以进行一个1小时的仪式从你的宗主那里得到一个替代品。 这一仪式可以在一个短休或一个长休过程中完成，且它将会破坏之前的护身符。 护身符将会在你死亡时消散为灰尘。 | AD45: 戏法公式 | AE45: 从3级起，你在法术书中写下了一套奥法公式，并能借此在心中推演出一个戏法。 每当你完成一次长休，你可以查阅法术书中所记的公式，以将你的一个已知法师戏法替换为另一个来自法师法术列表的戏法。 | AF45: 奇械师专业 | AG45: 在第3级，你选择自己将成为哪方面的专家：炼金师、魔炮师或战地匠师，这三个专业会在职业描述的最后进行说明。 你的选择将决定你在3级、5级、9级和15级获得的特性。 | AW45: =IFERROR(IF(AW44+1>BA26,IF(AW44+1>BA26,IF(AZ27+AZ44>BA27,"",AZ27+AZ44)),AW44+1),"") -> 16 | AX45: =IFERROR(INDEX(H31:AU181,AW45,AX26),"") | AY45: =IFERROR(INDEX(H31:AU181,AW45,AY26),"") | AZ45: =IFERROR(IF(AW44+1>BA26,AZ44+1,0),"") -> 0 | BB45: =IF(#REF!="","",#REF!) -> #REF! | BC45: =IFERROR(VLOOKUP(BB45,AX30:AY129,2,FALSE),"")
A46: 先祖守卫 | B46: 1 | C46: 2 | D46: =G64 -> 34 | E46: =D47-1 -> 37 | G46: 16 | H46: 坚韧狂暴 | I46: 第11级起，狂暴的力量让你即使身受重伤也能持续战斗。 狂暴期间，若你的生命值被降至0但未立即死亡，你可以进行一次DC10的体质豁免。豁免成功则你的生命值改为降至1。 第一次使用此特性后，每当你再次使用此特性时其体质豁免DC提高5。在你完成一次短休或长休后其DC重置为10。 | J46: 魔法激励 | K46: 第3级起，如果一个生物拥有来自你的吟游诗人激励骰子，在他释放一个恢复生命值或者造成伤害的法术时，他可以掷出激励骰子并选择法术的其中一个被法术影响的目标，在对该目标的恢复或者伤害数值上加上吟游诗人激励骰的掷骰结果，这个吟游诗人激励骰子随即被消耗。 | L46: 属性值提升 | M46: 当你达到第4、8、12、16、19级时，你可以选择一项属性值提升2点，或选择两项属性各提升1点。 不过你不能通过该特性让属性超过20。 | N46: 属性值提升 | O46: 当你达到第4、8、12、16、19级时，你可以选择一项属性值提升2点，或选择两项属性各提升1点。 不过你不能通过该特性让属性超过20。 | P46: 高效重击 | Q46: 第15级起，你的武器攻击掷出18~20时即可造成重击。 | R46: 轻身坠 | S46: 第4级起，当你要承受坠地伤害时，你可以使用反应将伤害减少等同于五倍武僧职业等级的数值。 | T46: 引导神力 | U46: 你的誓言使你获得引导神祇所授神圣能量的能力，引导的能量将用以实现各种魔法效应。 誓言赋予的相应效应，可以参考相关誓言的描述内容。 引导神力时，神力最终产生的效应由你自行选择。 引导神力后，你必须完成一次短休或长休才能再次使用该特性。 某些引导神力的效应需要豁免，其豁免DC等于你的圣武士法术豁免DC。 | V46: 原始意识 | W46: 从3级起（替换原初意识），你可以通过与自然的共鸣而集中你的意识:若你尚未习得下方表格种的法术，那么你在抵达对应等级时学会下方原始意识法术表格中的法术，这些法术不占用你的游侠已知法术。 始意识法术 三级 动物会话 五级 野兽知觉 九级 植物交谈 十三级 生物定位术 十七级 问道自然 你每天可以施展这些对应的法术每个一次而不需要消耗法术位，一旦你用这种方式施法，你在完成一次长休前不能再这么做。 | X46: 飘忽不定 | Y46: 第18级起，你飘忽不定的身形让敌人攻击时无从下手。 除非你处于失能状态，否则以你为目标的攻击检定无法取得优势。 | Z46: 超魔法 | AA46: 第3级起，你可以扭曲所施展的法术使其符合你的需求。 从下述超魔法选项中选择其二。随后你将在第10和第17级分别再获得其一。 除非特别说明，否则对一个法术只能应用一种超魔法项。 | AB46: 魔能选项 | AC46: 从4级起，每当你的邪术师达到了可以获得属性值提升的等级，你可以做以下的一件事来代表你在奥秘研究当中重点的转变。 可以将你从该职业契约法术中学到的戏法替换为另一个邪术师法术列表中的戏法。 可以将你从魔契恩泽中选择的一个选项替换为此魔契的另一选项。 如果你的角色已经12级或者更高，你可以将一个玄奥秘法的法术替换为另一个同环邪术师法术。 如果这些改变让你不再符合某些魔能祈唤的条件，你必须现在选择那些符合你条件的祈唤来替换它们。 | AD46: 属性值提升 | AE46: 当你达到第4、第8、第12、第16、第19级时，你可以选择一项属性值提升2点，或是选择两项属性各提升1点。 不过你不能通过该特性让属性值超过20。 | AF46: 称手工具 | AG46: 在第3级，你将学习如何精确地制作你所需要的工具：使用盗贼工具或工匠工具，你可以在离你5英尺内的未占据空间中魔法性地制作出一套工匠工具。 这一制造需要1小时不间断的工作，可以在短休或长休的过程中进行。 这套工具是魔法的产物，但其本身是非魔法的，当你再次使用此特性时，之前制造的工具就会消失。 | AW46: =IFERROR(IF(AW45+1>BA26,IF(AW45+1>BA26,IF(AZ27+AZ45>BA27,"",AZ27+AZ45)),AW45+1),"") -> 17 | AX46: =IFERROR(INDEX(H31:AU181,AW46,AX26),"") | AY46: =IFERROR(INDEX(H31:AU181,AW46,AY26),"") | AZ46: =IFERROR(IF(AW45+1>BA26,AZ45+1,0),"") -> 0 | BB46: =IF(#REF!="","",#REF!) -> #REF! | BC46: =IFERROR(VLOOKUP(BB46,AX30:AY129,2,FALSE),"")
A47: 风暴先驱 | B47: 1 | C47: 2 | D47: =G68 -> 38 | E47: =D48-1 -> 41 | G47: 17 | H47: 持久狂暴 | I47: 第15级起，你狂暴时的情绪高涨得难以抑制，以至于只有当你昏迷或是主动终止狂暴时才能使之提前结束。 | J47: 替换诗歌 | K47: 当你的吟游诗人职业等级抵达能让你获得属性值提示职业特性时，你能进行以下一项改变。 这种变化代表着你改变了使用法术和技能的重点。 替换一个你已经选择专精的技能，你可以选择专精于另一个你已经有熟练但还没有专精的技能，之后，你原先专精于的技能变回熟练而非专精。 从诗人戏法列表表中选择一个你未习得的戏法，替换一个你已经习得的戏法。 | L47: 摧毁不死生物 | M47: 第5级起，当不死生物进行对抗你驱散特性的豁免失败时，如果其挑战等级等于或低于一个既定的下限，则该不死生物将被即时摧毁。 相应的数值列举在表格“摧毁不死生物”中。 牧师等级——摧毁不死生物的挑战等级 5th——1/2或更低 8th——1或更低 11th——2或更低 14th——3或更低 17th——4或更低 | N47: 不朽身 | O47: 第18级起，你行使的原初荒野魔力让你的衰老速度减缓。 每经过10年的岁月，你的身体就仿佛只过了1年。 | P47: 生还者 | Q47: 第18级时，你持续战斗的能力达到巅峰。 你每回合开始时如果生命值不到上限的一半，则你恢复一部分生命值，其数值等于5＋你的体质调整值。 你生命值为0时不能以此获益。 | R47: 加速愈合 | S47: 从4级起，以一个动作，你能消耗2点气并且投掷一粒武艺骰，你恢复等同于掷骰结果加上你的熟练加值的生命值。 | T47: 驾驭神力 | U47: 从3级起，你能够消耗一次引导神力的使用次数来驱动法术。 以一个附赠动作，你能够通过接触圣徽，并献上祈祷，来恢复一个已消耗的法术位，其环数不能超过你的一半熟练加值（向上取整）。 你能使用此能力的次数取决于你的圣武士等级：3级1次，7级2次，15级3次。 当你完成一次长休息时，你重新获得已消耗的使用次数。 | V47: 替换武术 | W47: 从4级起，当你的游侠职业等级抵达能让你获得属性值提示职业特性时，你能用一个游侠可用的战斗风格替换原有的一个战斗风格，这种变化代表着你改变了武术训练和练习的重点。 | X47: 幸运一击 | Y47: 第20级时，你掌握了一手非凡技巧，让你可以随时把握自己的成功之时。 当你的攻击未命中时，可以直接更改判定为命中。 或者，当你的属性检定失败时，可以直接将d20骰的结果视为20。 你必须完成一次短休或长休后才能再次使用该特性。 | Z47: 谨慎法术 | AA47: 施展一个让其他生物进行豁免的法术时，你可以让其中一些生物免受法术的全额威力。 实现该效应需要你使用1术法点，并指定一定数量的目标生物，其最大数量等于你的魅力调整值（至少为1）。 而被指定的生物将直接成功通过法术的豁免检定。 | AB47: 属性值提升 | AC47: 当你达到第4，第8，第12，第16、第19级时，你可以选择一项属性值提升2点，或是选择两项属性各提升1点。 不过你不能通过该特性让属性值超过20。 | AD47: 法术精通 | AE47: 第18级时，你对特定的法术精熟于心，甚至可以随意施展这些法术。 选择你法术书中的一项1环法师法术和一项2环法师法术，此后只要你准备了它们，就可以随意施展其最低环阶版本，且无需消耗法术位。 你也可以消耗法术位来施展其更高环阶版本。 通过8小时的研习，你可以将这两项法术中的任一项替换为同环阶的其他法术。 | AF47: 属性值提升 | AG47: 当你达到第4、第8、第12、第16、第19级时，你可以选择一项属性值提升2点，或是选择两项属性各提升1点。 不过你不能通过该特性让属性值超过20。 | AW47: =IFERROR(IF(AW46+1>BA26,IF(AW46+1>BA26,IF(AZ27+AZ46>BA27,"",AZ27+AZ46)),AW46+1),"") -> 18 | AX47: =IFERROR(INDEX(H31:AU181,AW47,AX26),"") | AY47: =IFERROR(INDEX(H31:AU181,AW47,AY26),"") | AZ47: =IFERROR(IF(AW46+1>BA26,AZ46+1,0),"") -> 0 | BB47: =IF(#REF!="","",#REF!) -> #REF! | BC47: =IFERROR(VLOOKUP(BB47,AX30:AY129,2,FALSE),"")
A48: 战狂 | B48: 1 | C48: 2 | D48: =G72 -> 42 | E48: =D49-1 -> 46 | G48: 18 | H48: 不屈勇武 | I48: 第18级起，你进行力量检定的总值低于你的力量值时，可以直接使用力量值作为检定结果。 | J48: 属性值提升 | K48: 当你达到第4、8、12、16、19级时，你可以选择一项属性值提升2点，或选择两项属性各提升1点。 不过你不能通过此特性让属性超过20。 | L48: 受祝击 | M48: 从8级起（替代神圣打击或强力施法），在战斗中，你受到神力的祝福，当你通过戏法或武器攻击来伤害一个生物时，你能够对该生物造成额外1d8光耀伤害。 当你造成一次此伤害后，你直到自己的下一个回合开始前无法再次使用此特性。 | N48: 野兽施法 | O48: 第18级起，你在荒野变形状态下可以施展大部分的德鲁伊法术。 在野兽形态时，你可以完成德鲁伊法术的姿势与语言成分，但无法完成其材料成分的使用。 | P48: 卓越战技 | Q48: 在你选择此范型的第3级时，你习得战技并获得驱动战技的卓越骰。 战技：你习得三种自选战技，详见后文。 战技强化了你的攻击。而你在每次攻击时只能应用一种战技。 你在第7，第10和第15级时均习得两种新战技。 习得新战技时，你还可以额外替换一个已经习得的战技。 卓越骰：你拥有四个d8卓越骰。 卓越骰一经使用即消耗，完成短休或长休后恢复。 你的卓越骰在第7和第15级时各增加一粒。 豁免：某些战技需要目标进行豁免检定作抵抗。 战技的豁免DC为： 豁免DC＝8＋你的熟练加值＋你的力量或敏捷调整值（自选） | R48: 额外攻击 | S48: 第5级起，你在自己回合内执行攻击动作时可以发动两次攻击而非一次。 | T48: 战斗变通 | U48: 每当你通过提升圣武士等级获得属性值提升时，你可以用另一个圣武士能够选择的战斗风格替换你当前的战斗风格，这一变化代表着你在战斗训练上重心的转移。 | V48: 属性值提升 | W48: 当你达到第4、第8、第12、第16、第19级时，你可以选择一项属性值提升2点，或是选择两项属性各提升1点。 不过你不能通过该特性让属性值超过20。 | X48: 快手 | Y48: 第3级起，你可以使用从“灵巧动作”特性中得到的附赠动作来进行一次敏捷（巧手）检定，或是以该附赠动作使用盗贼工具来解除陷阱、撬锁，或执行“使用物件”动作。 | Z48: 远程法术 | AA48: 施展一个施法距离不小于5尺的法术时，你可以使用1术法点使该法术的施法距离翻倍。 施展一个施法距离为触及的法术时，你可以使用1术法点将法术的施法距离改为30尺。 | AB48: 玄奥秘法 | AC48: 第11级时，你的宗主赋予你一种称为秘法的魔法奥秘。 你可以选择一个6环的邪术师法术作为你的玄奥秘法。 你施展秘法时无需消耗法术位，而消耗掉的秘法可以通过完成一次长休进行恢复。 在获得更高的邪术师等级后，你将可以选择更多的邪术师法术以该方式施展：第13级时可选一个7环法术，15级时可选一个8环法术，17级时可选一个9环法术。 完成一次长休后，所有消耗掉的秘法都会恢复。 | AD48: 招牌法术 | AE48: 第20级时，你精通两个强大的法术，甚至可以用更低的成本施展这些法术。 选择你的法术书中的两个3环法师法术，作为你的招牌法术。 此后这两个法术将永远视为已准备法术，且不计入你的准备法术数量之中。 你可以施展这两个法术的3环版本各一次，且无需消耗法术位。 招牌法术使用后，需要完成一次短休或长休才能再次使用。 你也可以消耗法术位施展这两个法术的更高环阶版本。 | AF48: 工具专精 | AG48: 从第6级起，你在使用你熟练的工具时，能够使用双倍的熟练加值。 | AW48: =IFERROR(IF(AW47+1>BA26,IF(AW47+1>BA26,IF(AZ27+AZ47>BA27,"",AZ27+AZ47)),AW47+1),"") -> 19 | AX48: =IFERROR(INDEX(H31:AU181,AW48,AX26),"") | AY48: =IFERROR(INDEX(H31:AU181,AW48,AY26),"") | AZ48: =IFERROR(IF(AW47+1>BA26,AZ47+1,0),"") -> 0 | BB48: =IF(#REF!="","",#REF!) -> #REF! | BC48: =IFERROR(VLOOKUP(BB48,AX30:AY129,2,FALSE),"")
A49: 狂野魔法道途 | B49: 1 | C49: 2 | D49: 47 | E49: =D50-1 -> 51 | G49: 19 | H49: 原初斗士 | I49: 第20级时，你的存在即是野性之力的具现。你的力量和体质各提升4。并且你这两项属性的上限变为24。 | J49: 激励之源 | K49: 第5级起，你可以在完成短休或长休后恢复你已消耗的诗人激励次数。 | L49: 神圣干预 | M49: 第10级起，你可以在迫切需要帮助时，召唤神祇的协助。 你需要用一个动作来请求所信仰神祇的帮助。描述你所需要的帮助，然后掷d100。如果你的结果等于或者小于你的牧师等级，你将得到神祇的回应。 回应的结果由DM作出选择；此时通常请求任何牧师法术或者领域法术的效应都在可接受范围内。 如果你的神祇回应了请求，你在此后的7日内无法再次使用该特性；否则你可以在完成长休后再次使用该特性。 到达20级后，你的呼唤将自动得到神祇的回应，无需再掷d100。 | N49: 大德鲁伊 | O49: 第20级时，你可以无限次的使用荒野变形。 另外，你还可以将德鲁伊法术中的姿势和语言成分，以及非无价值且不被法术消耗的材料成分忽略。 你在原形态和荒野形态下都可以从此特性获益。 | P49: 战争学徒 | Q49: 第3级时，你选择一种工匠工具并获得其熟练项。 | R49: 震慑拳 | S49: 第5级起，你能够阻碍敌人体内的气的流动。 你的近战武器攻击命中时，可以消耗1点气尝试发动震慑拳。 被命中目标必须进行一次体质豁免，豁免失败则受到震慑，并持续至你的下一回合结束。 | T49: 属性值提升 | U49: 当你达到第4、8、12、16、19级时，你可以选择一项属性值提升2点，或选择两项属性各提升1点。 不过你不能通过该特性让属性超过20。 | V49: 额外攻击 | W49: 第5级起，你在自己回合内执行攻击动作时可以发动两次攻击而非一次。 | X49: 梁上君子 | Y49: 第3级选择此范型起，你获得比通常情况更快的攀爬速度，从而使攀爬不再消耗额外的移动力。 此外，当你做一个有助跑的跳远时，跳远距离增加一定的尺数，其数值等于你的敏捷调整值。 | Z49: 强效法术 | AA49: 为法术进行伤害掷骰时，你可以使用1术法点重掷其中一定数量的骰子。 重掷骰子的最大数等于你的魅力调整值（至少为1），且你必须接受新的结果。 强效法术超魔可以与其他超魔法选项合用。 | AB49: 魔能掌控 | AC49: 第20级时，你可以利用储备的魔力祈求你的宗主为你恢复已消耗的法术位。 你可以花1分钟祈求宗主的帮助，恢复所有你已消耗的契约魔法法术位。 使用该特性恢复法术位后，你必须完成一次长休才能再次使用该特性。 | AD49: 防护学者 | AE49: 从第2级你选择该学派起，你向法术书中抄写防护系法术的时间和金钱花费减半。 | AF49: 灵光一闪 | AG49: 从第7级起，你获得了在压力下想出解决方案的能力。 当你或距离你30英尺内的可见生物进行属性检定或豁免检定时，你能以一个反应将你的智力调整值添加到此次检定中。 你能使用此能力的次数等于你的智力调整值（最少1次）。 在你完成一次长休后，将恢复所有可用次数。 | AW49: =IFERROR(IF(AW48+1>BA26,IF(AW48+1>BA26,IF(AZ27+AZ48>BA27,"",AZ27+AZ48)),AW48+1),"") -> 20 | AX49: =IFERROR(INDEX(H31:AU181,AW49,AX26),"") | AY49: =IFERROR(INDEX(H31:AU181,AW49,AY26),"") | AZ49: =IFERROR(IF(AW48+1>BA26,AZ48+1,0),"") -> 0 | BB49: =IF(#REF!="","",#REF!) -> #REF! | BC49: =IFERROR(VLOOKUP(BB49,AX30:AY129,2,FALSE),"")
A50: 野兽道途 | B50: 1 | C50: 2 | D50: 52 | E50: 56 | G50: 20 | H50: 狂怒 | I50: 从你第3级选择此道途起，你可以在进入狂暴的同时进入狂怒。 使用此特性时，你可以在本回合之后狂暴持续时间内的每个回合里，以一个附赠动作发动一次近战武器攻击。而当本次狂暴终止时，你将提升一级力竭。 | J50: 反迷惑 | K50: 第6级起，你获得用音乐或话语来打断心控效应的能力。你可以使用一个动作开始一场持续至你的下一回合结束的演出。在这段时间内，你与你身边30尺内的友方生物进行对抗恐慌或魅惑效应的豁免检定具有优势。该生物必须能听到你的声音才能获得此增益。这场表演在你陷入失能状态、被沉默、或主动终止（无需动作）时会提前结束。 | L50: 知识领域法术 | M50: 牧师等级——法术 1st——命令术、鉴定术 3rd——卜筮术、暗示术 5th——回避侦测、死者交谈 7th——秘法眼、困惑术 9th——通晓传奇、探知 | N50: 附赠戏法 | O50: 在第2级选择该结社时，你学会一个额外的德鲁伊戏法。 | P50: 知己知彼 | Q50: 第7级起，你在战斗外观察某生物或与之交互至少1分钟后，可以获知有关其能力的一些情报。 从下列选项中选择其二，DM将告诉你在这两项上你是强于该生物，弱于该生物，或是与之相仿。 力量值 敏捷值 体质值 护甲等级 当前生命值 总职业等级（如果有） 战士职业等级（如果有） | R50: 凝神聚气 | S50: 从5级起，当你攻击检定未命中时，你可以花费1到3点气来使该次攻击检定获得加值，每点气的消耗能获得+2加值，这可能会使原本的未命中改为命中。 | T50: 额外攻击 | U50: 第5级起，你在自己回合内执行攻击动作时可以攻击两次而非一次。 | V50: 大地行者 | W50: 第8级起，你穿过非魔法的困难地形时不会消耗额外移动力。 你穿过非魔法的植物时不会消耗额外移动力，且这类植物的荆棘、毛刺或类似的危害物也无法对你造成伤害。 另外，在抵抗魔法制造或控制的植物造成的移动障碍效应时（例如纠缠术），你的豁免检定具有优势。 | X50: 极效潜行 | Y50: 第9级起，当回合内移动距离不超过自身速度一半时，你的敏捷（隐匿）检定将获得优势。 | Z50: 延效法术 | AA50: 施展一个持续时间不短于1分钟的法术时，你可以使用1术法点使法术的持续时间翻倍，但其最终结果不能超过24小时。 | AB50: 苦痛魔爆 | AC50: 施展魔能爆eldritch blast时，你可以将魅力调整值加到其每次命中所造成的伤害中。 先决条件：习得戏法 魔能爆 | AD50: 奥术守御 | AE50: 第2级起，你可以编织身边的魔法用作防护。 你施展一道1环或更高环阶的防护系法术时，可以用该法术的一丝魔力创造一个保护自己的魔法结界，该结界将持续至你完成一次长休。 结界的生命值等于你法师等级的两倍＋你的智力调整值。 每当你受伤害时，该结界都会替你承受伤害。 如果伤害使结界的生命值降至0，则你将承受剩余的伤害。 奥术守御的生命值降至0时不再吸收伤害，但其魔法仍然存在。 你每次施展1环或更高环阶防护系法术时，结界都能以此恢复两倍于该法术环阶数量的生命值。 创造奥术守御后，你必须完成一次长休才能再次创造新的奥术守御。 | AF50: 魔法物品熟稔 | AG50: 当你达到10级时，你对如何使用和制作魔法物品有了深刻的理解： 你一次最多可以调谐四个魔法物品。 如果你制作一件稀有度为普通或非普通的魔法物品，时间花费只需通常的四分之一，而且金钱花费只有通常的一半。 | AW50: =IFERROR(IF(AW49+1>BA26,IF(AW49+1>BA26,IF(AZ27+AZ49>BA27,"",AZ27+AZ49)),AW49+1),"") -> 21 | AX50: =IFERROR(INDEX(H31:AU181,AW50,AX26),"") | AY50: =IFERROR(INDEX(H31:AU181,AW50,AY26),"") | AZ50: =IFERROR(IF(AW49+1>BA26,AZ49+1,0),"") -> 0 | BB50: =IF(#REF!="","",#REF!) -> #REF! | BC50: =IFERROR(VLOOKUP(BB50,AX30:AY129,2,FALSE),"")
A51: 巨人道途 | B51: 1 | C51: 2 | D51: 57 | E51: 61 | G51: 21 | H51: 无我狂暴 | I51: 第6级起，你在狂暴中不会被魅惑或恐慌。 如果你开始狂暴时已经陷入魅惑或恐慌，则该效应在你狂暴期间被压制。 | J51: 魔法奥秘 | K51: 第10级起，你从旋律中了解了大量的魔法知识，使你可以从所有职业的法术列表里选择两个法术（包括诗人列表）加入已知法术中。你所选择的法术必须是你当前等级可以施展的环阶法术或戏法。 所选法术对你而言视为吟游诗人法术，且包含在“诗人职业表”上“已知法术”一栏所记录的数量之内。 第14和第18级时，你可以分别使用此特性再习得两个任选法术。 | L51: 知识祝福 | M51: 第1级起，你学会两门自选语言。你还从以下技能中选择两项加入你的熟练项中：奥秘、历史、自然、宗教。 你进行关于所选两项技能的属性检定时，可以加上双倍的熟练加值。 | N51: 自然恢复 | O51: 第2级起，你可以通过静坐冥想与自然建立交流，并以此恢复部分魔法能量。 完成一次短休后，你可以选择恢复部分已使用的法术位。 所恢复法术位环阶的总和等于你德鲁伊职业等级的一半（向下取整），且不能是6环或更高环阶。 你在完成一次长休后才能再次使用该特性。 例如，作为一名4级德鲁伊时，你可恢复环阶总数为二的法术位。 你可以选择恢复一枚2环法术位或者两枚1环法术位。 | P51: 精通卓越战技 | Q51: 第10级时，你的卓越骰变为d10。 第18级时，你的卓越骰变为d12。 | R51: 真气驻拳 | S51: 第6级起，攻击对非魔法攻击或伤害具有抗性或免疫的目标时，你的徒手打击视为魔法攻击。 | T51: 守护灵光 | U51: 第6级起，你与友方生物在你身边10尺内进行豁免检定时，可以将你的魅力调整值作为加值加在其豁免结果上（至少为 +1）。 提供该加值时你必须保持意识清醒。 第18级起，该灵光的作用范围扩展至30尺。 | V51: 遁术 | W51: 第10级起，你可以花1分钟来为自己制作伪裝。 你必须能取用新鲜的泥土、植物、煤烟等天然物料进行制作。 伪装完成后，你可以将自己贴上至少跟自己等高等阔的实体表面（如树干或墙壁）并尝试躲藏。 如果你留在原地不移动且不执行动作，则你的敏捷（隐匿）检定获得+10加值。一旦移动、执行动作或执行反应，你都必须重新伪装以重获该增益。 | X51: 使用魔法装置 | Y51: 第13级起，你学习的魔法知识足以让你使用并不是为你设计的魔法物品。 此后你在使用魔法物品时，可以忽略所有职业、种族和等级的限制条件。 | Z51: 升阶法术 | AA51: 施展一个迫使一个生物进行豁免以抵御其效应的法术时，你可以花费3术法点使该法术所有目标中的一个首次进行对抗该法术的豁免时具有劣势。 | AB51: 幽影护甲 | AC51: 你可以随意以自身为目标施展法师护甲mage armor，且无需消耗法术位和材料成分。 | AD51: 投射守御 | AE51: 第6级起，你周边30尺内一个你能看见的生物受到伤害时，你可以用你的反应，以你现有的奥术守御吸收这次伤害。 如果这次伤害将结界的生命值降至0，则被保护的目标将承受剩余的伤害值。 | AF51: 储法物品 | AG51: 当你达到第11级时，你将习得如何在一个物体中储存一个法术。当你完成一次长休，你能够触摸一件简易武器、军用武器或一个你可以将其作为法器使用的物品，从奇械师法术列表中选择一个施法时间为一个动作的1环或2环法术（你不需要准备这个法术）。 任何在手中持有该物品的生物能够使用你的施法关键属性来以一个动作通过该物品产生储存法术的效果。 如果该法术需要专注，则启动物品的生物必须进行专注。 该法术将留存在物品中，直到使用次数用完（最大使用次数等于你智力调整值的两倍（至少两次））或直到你再次使用该特性。 | AW51: =IFERROR(IF(AW50+1>BA26,IF(AW50+1>BA26,IF(AZ27+AZ50>BA27,"",AZ27+AZ50)),AW50+1),"") -> 22 | AX51: =IFERROR(INDEX(H31:AU181,AW51,AX26),"") | AY51: =IFERROR(INDEX(H31:AU181,AW51,AY26),"") | AZ51: =IFERROR(IF(AW50+1>BA26,AZ50+1,0),"") -> 0 | BB51: =IF(#REF!="","",#REF!) -> #REF! | BC51: =IFERROR(VLOOKUP(BB51,AX30:AY129,2,FALSE),"")
A52: 逸闻学院 | B52: 3 | C52: 4 | D52: 23 | E52: 26 | G52: 22 | H52: 威慑之姿 | I52: 第10级起，你可以用一个动作展示自己的可怖姿态来恐吓他人。指定30尺内一个你能看见的生物。如果该生物能看见你或听见你的声音，则其必须进行一次感知豁免（DC为8＋你的熟练加值＋你的魅力调整值），豁免失败者将因此而陷入恐慌，并持续至你的下回合结束。在接下来的回合里，你可以通过使用动作来延长此效应的持续时间，使之持续至你此后一回合结束。如果该生物在结束其回合时离开你的视线范围，或是离开你60尺外，则此效应提前终止。 如果此生物成功通过此豁免，则你在随后的24小时内无法对该生物使用此特性。 | J52: 先发激励 | K52: 第20级起，你骰先攻时若没有可用的诗人激励次数，则你获得一次使用次数。 | L52: 引导神力：岁月知识 | M52: 第2级起，你可以用引导神力特性接入神圣的知识之井。 作为一个动作，你可以选定一个技能或工具，并在接下来的10分钟内视为拥有其熟练项。 | N52: 结社法术 | O52: 你跟大地之间的神秘链接让你可以施展特别的法术。 在第3、第5、第7、第9级时，你根据成为德鲁伊时的所在地获得相应的结社法术。 选择一个地形：极地、海岸、荒漠、森林、草原、山地、沼泽，并依此获得相应的法术。 结社法术一旦获得，将会一直在你的已准备法术列表中，且不计入你的每日准备法术上限。 任何结社法术对你而言都是德鲁伊法术，而不论其是否在德鲁伊法术列表之上。 | P52: 坚韧 | Q52: 第15级起，你骰先攻时若没可用的卓越骰，则你获得1枚卓越骰。 | R52: 反射闪避 | S52: 第7级起，你敏锐的直觉让你可以躲过某些特定的区域效应，比如蓝龙的闪电吐息或是法术火球术。 你在成为某一范围效应影响对象时，若该效应允许你通过成功的敏捷豁免来使伤害减半，则你在该豁免成功时不受伤害，而豁免失败时只受一半伤害。 | T52: 勇气灵光 | U52: 第10级起，你与友方生物在你身边10尺内不会陷入恐慌。 提供该增益时你必须保持意识清醒。 第18级起，该灵光的作用范围扩展至30尺。 | V52: 自然面纱 | W52: 从10级起（替换遁术），你可以暂时地使用自然的力量将你的身形遮蔽。 以一个附赠动作，你可以魔法地使自己与正携带、着装的任何装备变得隐形，直到你的下个回合开始。 你可以使用该特性同等于你的熟练加值次，你在完成一次长休后恢复所有的使用次数。 | X52: 窃盗本能 | Y52: 第17级起，你变的更加擅长伏击和快速脱离险境。 战斗的第一轮里，你可以行动两个回合：即你先以自己正常的先攻执行一个回合行动，再以先攻数值减10的数值作为另一先攻额外执行一回合的行动。 你不能在遭受突袭时使用该特性。 | Z52: 瞬发法术 | AA52: 施展一个施法时间为1动作的法术时，你可以使用2术法点将其施法时间改为1附赠动作。 | AB52: 星移步法 | AC52: 你可以随意以自身为目标施展浮空术levitate，且无需消耗法术位和材料成分。 先决条件：第9级 | AD52: 精通防护 | AE52: 第10级起，你施展一个需要你在施法过程中进行属性检定的防护系法术时（比如反制法术和解除魔法），你可以在进行相应的属性检定时加上你的熟练加值。 | AF52: 魔法物品专家 | AG52: 当你达到14级时，你在魔法物品方面的技巧愈发精进： 你一次最多可以调谐五个魔法物品。 你无视调谐或使用魔法物品所需的任何职业、种族、法术和等级条件。 | AW52: =IFERROR(IF(AW51+1>BA26,IF(AW51+1>BA26,IF(AZ27+AZ51>BA27,"",AZ27+AZ51)),AW51+1),"") -> 23 | AX52: =IFERROR(INDEX(H31:AU181,AW52,AX26),"") | AY52: =IFERROR(INDEX(H31:AU181,AW52,AY26),"") | AZ52: =IFERROR(IF(AW51+1>BA26,AZ51+1,0),"") -> 0 | BB52: =IF(#REF!="","",#REF!) -> #REF! | BC52: =IFERROR(VLOOKUP(BB52,AX30:AY129,2,FALSE),"")
A53: 勇气学院 | B53: 3 | C53: 4 | D53: 27 | E53: 30 | G53: 23 | H53: 报偿 | I53: 第14级起，身边5尺内敌人对你造成伤害时，你可以用反应对该生物发动一次近战武器攻击。 | J53: 附赠熟练项 | K53: 第3级选择逸闻学院时，你获得三个自选技能的熟练项。 | L53: 引导神力：读心 | M53: 第6级起，你可以用引导神力特性阅读某生物的思想，以此接触其意识并对其下达命令。 作为一个动作，你指定身边60尺内一个你可以看见的生物。该生物必须进行一次感知豁免。豁免成功则你不能对其使用该特性，直至你完成一次长休。 如若豁免失败，且其仍身处你周边60尺内，则你可以阅读其表层的思想（最基础的意识，当前情绪的反映以及正活跃的思考内容）。该效应持续1分钟。 效应持续期间，你可以用你的动作终止该效应，并同时对其施展一个无需花费法术位的暗示术。而目标对该法术的豁免将直接判定为失败。 | N53: 大地行者 | O53: 第6级起，你穿过非魔法的困难地形时不会消耗额外移动力。 你穿过非魔法的植物时不会消耗额外的移动力，且这类植物的荆棘、毛刺或类似的危害物也无法对你造成伤害。 另外，在抵抗魔法制造或控制的植物造成的移动障碍效应时（例如纠缠术），你进行豁免检定时具有优势。 | P53: 战技 | Q53: 以下各战技按名称头字母顺序排列。 | R53: 心如止水 | S53: 第7级起，你可以用你的动作结束一个正影响你的魅惑或恐慌状态。 | T53: 精通至圣斩 | U53: 第11级起，你体内充盈的公正之力使你的近战武器打击中携带着神圣的力量。 当你使用近战武器命中一个生物时，该生物将额外受到1d8点光耀伤害。 | V53: 无踪步 | W53: 第14级起，你可以在自己回合以一个附赠动作的形式执行躲藏动作。 此时，你无法被非魔法手段追踪到，除非你主动留下踪迹。 | X53: 附赠熟练项 | Y53: 你在第3级选择此范型时，获得易容工具和制毒者工具的熟练项。 | Z53: 精妙法术 | AA53: 施展一个法术时，你可以使用1术法点无视该法术施法必须的语言成分或姿势成分。 | AB53: 野兽之语 | AC53: 你可以随意施展动物交谈speak with animals，且无需消耗法术位。 | AD53: 法术抗性 | AE53: 第14级起，你抵抗法术时进行的豁免检定具有优势。 此外，你对法术造成的伤害具有抗性。 | AF53: 魔法物品大师 | AG53: 18级起，你一次最多可以调谐六个魔法物品。 | AW53: =IFERROR(IF(AW52+1>BA26,IF(AW52+1>BA26,IF(AZ27+AZ52>BA27,"",AZ27+AZ52)),AW52+1),"") -> 24 | AX53: =IFERROR(INDEX(H31:AU181,AW53,AX26),"") | AY53: =IFERROR(INDEX(H31:AU181,AW53,AY26),"") | AZ53: =IFERROR(IF(AW52+1>BA26,AZ52+1,0),"") -> 0 | BB53: =IF(#REF!="","",#REF!) -> #REF! | BC53: =IFERROR(VLOOKUP(BB53,AX30:AY129,2,FALSE),"")
A54: 迷惑学院 | B54: 3 | C54: 4 | D54: 31 | E54: 34 | G54: 24 | H54: 精魄寻者 | I54: 你追求融入自然之道，与动物为友。在你选择此道途的第3级起，你获得施展法术野兽知觉beast sense与动物交谈speak with animals的能力，但你只能以仪式的方式施展它们。 | J54: 语出惊人 | K54: 第3级起，你学会运用你的妙语连珠来打断敌人，迷惑对方或影响他人的信心。当你身边60尺内一个你能看见的生物进行攻击检定，属性检定或伤害掷骰时，你可以用反应消耗一次诗人激励次数来掷一次激励骰。并在目标的掷骰结果中减去你的激励骰结果。你可以在目标掷出骰子后，DM宣布结果之前决定是否使用该特性。若目标无法听见你的话语或免疫魅惑状态，则目标同样也会免疫该特性。 | L54: 强力施法 | M54: 第8级起，你施展牧师戏法造成伤害时，可以再加上你的感知调整值。 | N54: 自然之护 | O54: 第10级起，你免疫元素生物或精类生物造成的魅惑或恐慌状态，并且免疫中毒和疾病。 | P54: 指挥官奇袭 | Q54: 你在自己回合内执行攻击动作时，可以放弃一次攻击并使用附赠动作指挥一名盟友发动奇袭。 使用此战技时，你消耗一粒卓越骰，并指定一名能看见你或能听到你声音的盟友。所选盟友可以立即使用反应发动一次武器攻击，并将消耗的卓越骰加在此次攻击的伤害掷骰中。 | R54: 百病不侵 | S54: 第10级起，你浑身的气流动使你免疫疾病和毒素。 | T54: 净化之触 | U54: 第14级起，你可以用动作触碰你自身或一个自愿生物，以中止该目标身上的一个法术效应。 该特性的可用次数等于你的魅力调整值（至少一次）。 而已消耗的特性使用次数则可以通过完成一次长休进行恢复。 | V54: 野性感官 | W54: 第18级时，你获得超自然的感官以帮助你对抗看不到的生物。 此后，你攻击一个看不到的生物时不会因此承受劣势。 另外，你还能感测30尺内所有隐形敌人的位置，前提是该生物并没有针对你进行躲藏，而你也没有陷入目盲或耳聋。 | X54: 暗杀 | Y54: 第3级起，你一旦获得先机就会变得更加致命。 你对战斗开始后还没开始过自己回合的生物发动攻击时，所进行的攻击检定具有优势。 此外，你攻击命中被突袭的生物时，必定则造成重击。 | Z54: 孪生法术 | AA54: 施展一个影响单一生物，且施法距离并非自身的法术时，你可以使用等于法术环阶的术法点（戏法消耗1点），并在法术施法距离内再指定另一个目标。 以高环阶施展的法术，其升环施法后如果目标变为复数则无法再使用该方式增加其目标。 例如，魔法飞弹和灼热射线可能无法使用该超魔法项，而冷冻射线和繁彩球则不会出现该问题。 适用该超魔的法术在其当前环阶时不能同时指定多个生物为目标。 比如，魔法飞弹和灼热射线不符合条件，而冷冻射线和繁彩球则符合条件。 | AB54: 诱导话术 | AC54: 你获得欺瞒和游说技能的熟练项。 | AD54: 咒法学者 | AE54: 从第2级你选择该学派起，你向法术书中抄写咒法系法术的时间和金钱花费减半。 | AF54: 奇械之魂 | AG54: 在20级时，你与你的魔法物品建立了一种神秘的联系，你可以利用它来保护自己。 你当前每有一件调谐中的魔法物品，你就在所有豁免检定中得到+1加值。 如果你的生命值降低到0，但没有立即死亡，你能以一个反应解除一个注法，使你的生命值降低到1而不是0。 | AW54: =IFERROR(IF(AW53+1>BA26,IF(AW53+1>BA26,IF(AZ27+AZ53>BA27,"",AZ27+AZ53)),AW53+1),"") -> 25 | AX54: =IFERROR(INDEX(H31:AU181,AW54,AX26),"") | AY54: =IFERROR(INDEX(H31:AU181,AW54,AY26),"") | AZ54: =IFERROR(IF(AW53+1>BA26,AZ53+1,0),"") -> 0 | BB54: =IF(#REF!="","",#REF!) -> #REF! | BC54: =IFERROR(VLOOKUP(BB54,AX30:AY129,2,FALSE),"")
A55: 剑舞学院 | B55: 3 | C55: 4 | D55: 35 | E55: 39 | G55: 25 | H55: 图腾精魄 | I55: 在你选择此道途的第3级时，选择一项图腾精魄并获得其能力。你必须制造或获取一个象征图腾兽其毛，羽，爪，牙或骨的图腾物件，可以是项链，也可以是其他类似的物件。如果你愿意，你的外貌也会发生些微改变，让人看到时不由得联想起你的图腾精魄。例如，如果选择熊的图腾精魄，你可能变得毛发旺盛，皮肤粗厚；如果选择雕的图腾精魄，你的眼睛可能变成明亮的黄色。 你可选择下表中的动物，或是其他更适合你故乡环境的类似动物。例如，你可以用鹰hawk或秃鹫vulture代替雕eagle。 • 熊：狂暴时，你获得对心灵伤害之外任何伤害类型的抗性。熊之精魄令你坚韧无匹，无惧于任何打击。 • 雕：狂暴时，如果你未着装重甲，则其他生物在对你进行借机攻击时进行的攻击检定具有劣势。另外，你在自己回合内可以用附赠动作执行疾行动作。雕之精魄让你成为在战场中自由穿梭的猎杀者。 • 狼：狂暴时，如果你周围５尺范围内有任何敌对生物，则你的盟友对这些生物发动近战攻击时的攻击检定具有优势。狼之精魄让你成为猎手中的领袖。 这些选项可以在你3级选择图腾动物时选择。 和《玩家手册》中的精魂一样，这里的选项需要一个与你图腾动物相关的物品，同时你也可能在相貌外形上与你的图腾精魂相似。例如如果你的图腾精魂是麋鹿，则你会有一个大鼻子；如果你的图腾精魂是老虎，则你的眼睛可能长的和猫类似。 此外，你的图腾精魂可能是一种更适合你生长的地方的动物，例如一匹马或者鹿来代替麋鹿，一只狮子或者豹或者其他大型猫科动物来代替老虎。 • 鹿Elk。狂暴期间，若你未着重甲，你的步行速度增加15尺。鹿之精魂的庇佑使你格外迅捷。 • 虎Tiger。狂暴期间，你增加10尺的跳跃距离和3尺的跳高距离。虎之精魂赋予你飞跃的能力。 | J55: 额外魔法奥秘 | K55: 第6级时，你从任意职业的法术列表里选择两个法术加入已知法术中。 你选择的法术必须是你当前等级可以施展的环阶或戏法。所选法术对你而言视为吟游诗人法术，但不包含在“诗人职业表”上“已知法术”一栏的所记录的数量之内。 | L55: 透视过去 | M55: 第17级起，你可以看到过去的情形。你花费至少1分钟冥想，然后将以梦幻阴暗的形式瞥见最近发生的事件。你在维持幻觉的时长分钟数等于你的感知值。而在这段时间里，你必须要如施法般维持专注。 你使用该特性后必须完成一次短休或长休才能再次启用。 • 物件解读：保持专注于某个物件时，你即可从幻觉中找到其之前的拥有者。1分钟冥想后，你将看到该拥有者如何获得以及如何丢失该物件。以及新近发生的涉及该物体与该拥有者的重大事件。如果对象在近期转交由另一个生物拥有（转交日距施法时的日数必须在等同于你感知值的日数之内），则每个生物你要花费额外1分钟进行冥想，以通过幻觉获得同类的信息。 • 区域解读：你在冥想时看到的景象是身处位置最近发生的事件（某处的房间、街道、地道、空地，或是与之类似的50尺立方空间），可回溯的日数等于你的感知值。每个重要事件的幻象都将额外花费你1分钟的时间。这些重大事件通常涉及强烈的情感，比如战争和背叛、结婚和谋杀、出生和葬礼等。而这其中也可能包含有一些当时看似平凡无奇，眼下却显得至关重要的事情。 | N55: 自然庇护所 | O55: 第14级起，自然界的生物感知到你跟自然的链接而不会主动攻击你。 当一个野兽或植物类的生物攻击你时，该生物必须先进行一次对抗你德鲁伊法术DC的感知豁免。 豁免失败时，该生物必须选择另一个目标，否则其攻击将判为未命中。 豁免成功时，该生物在随后的24小时内免疫此效应。 该生物会在攻击你之前就意识到你有此效应。 | P55: 缴械攻击 | Q55: 你以武器攻击命中敌人时，可消耗一粒卓越骰以尝试缴械目标，使其丢弃手中持握的一件物品。 使用此战技时，你将消耗的卓越骰加在此次攻击的伤害掷骰中，并迫使目标必须进行一次力量豁免。豁免失败则其丢弃手中持握的一件物品（由你选择）。被丢弃的物品将掉落在该生物脚下。 | R55: 天语通 | S55: 第13级起，你可以与其它生物进行心灵交流。 此后，你能够听懂所有语言，同时掌握至少一门语言的任何生物都能理解你讲的话语。 | T55: 奉献圣誓法术 | U55: 圣武士等级——法术 3rd——防护善恶，庇护术 5th——次级复原术，诚实之域 9th——希望信标，解除魔法 13th——行动自如，信仰守卫 17th——通神术，焰击术 | V55: 屠灭众敌 | W55: 第20级时，你成为了猎杀敌人的无双猎手。 你在自己的每个回合内，都有一次机会将你的感知调整值加到你对宿敌进行的攻击检定或伤害掷骰上。 你可以在掷骰之前或者之后决定使用该特性，但必须在该掷骰的相关效应被应用之前。 | X55: 专业渗透 | Y55: 第9级起，你可以不限次的为自己伪造身份。 你必须花费七天和25gp来为身份编造历史、工作和人际关系。 不过你不能伪造成已存在的角色。 例如，你获得相应的衣服、介绍信和官方证明，使得你自己看上去就是一个来自偏远城市贸易屋的成员，然后你就可以混入其他商人中间。 此后，如果你通过易容获取了这个身份，其他生物就相信你是那个人，直至其得到一个显而易见的理由可以否定这个身份。 | Z55: 追踪法术 | AA55: 当你因法术进行一次攻击检定并击失时，你可以使用2术法点重投之。 你必须使用重投的结果，追踪法术超魔可以与其他超魔法选项合用。 | AB55: 惑人低语 | AC55: 你可以消耗你的邪术师法术位施展一个强迫术compulsion。你必须完成一次长休才能再次施展该法术。 先决条件：第7级 | AD55: 次级咒术 | AE55: 从第2级你选择该学派起，你可以用你的动作召来一件无生命的物件。 该物件将出现在你手中，或者你周边10尺范围内一处那你能看见且未被占据的地面空间。 该物件每边长度不得大于3尺，重量不得大于10磅。 其形状必须是你曾经见过的一件非魔法物件的形状。 该物件看起来明显是由魔法构成且散发着出5尺范围的微光光照。 该物件将在1小时后消失不见。 当你再次使用该特性，或当其受到伤害或造成伤害时，物件也会提前消失。 | AF55: 奇械师注法 | AG55: 奇械师注法是一种非凡的、能将非魔法物品变成魔法物品的工序。每个注法的描述都会告诉你可以接受它的物品类型，以及所产生的魔法物品是否需要同调的要求。 有些注法规定了最低的奇械师等级。你必须达到那个等级或以上才能学习该注法。 除非注法的描述中写明，否则你无法重复学习同一个注法。 | AW55: =IFERROR(IF(AW54+1>BA26,IF(AW54+1>BA26,IF(AZ27+AZ54>BA27,"",AZ27+AZ54)),AW54+1),"") -> 26 | AX55: =IFERROR(INDEX(H31:AU181,AW55,AX26),"") | AY55: =IFERROR(INDEX(H31:AU181,AW55,AY26),"") | AZ55: =IFERROR(IF(AW54+1>BA26,AZ54+1,0),"") -> 0 | BB55: =IF(#REF!="","",#REF!) -> #REF! | BC55: =IFERROR(VLOOKUP(BB55,AX30:AY129,2,FALSE),"")
A56: 低语学院 | B56: 3 | C56: 4 | D56: 40 | E56: 43 | G56: 26 | H56: 兽之形 | I56: 第6级时，你根据所选的图腾兽获得一项魔法能力。 你可以选择和第3级时相同的图腾，也可以另做选择。 • 熊：你拥有熊之巨力。你的载重（包括最大负重和最大举重）翻倍，并且你在推、拉、举和破坏物件时进行的力量检定具有优势。 • 雕：你拥有雕之锐目。你可以轻易的看清1里之内的范围，细节之处与100尺距离内的影像一样清晰。此外，你在微光环境中进行感知（察觉）检定时不会具有劣势。 • 狼：你拥有狼之敏锐。你可以在用快速步调旅行的同时追踪其他生物，也可以在用正常步调旅行时保持隐匿（旅行步调见第8章）。 这些选项可以在你6级选择图腾动物时选择 。 • 鹿Elk。无论你是骑乘还是徒步，你的旅行速度变为双倍。只要你未失能，在你周围60尺内的最多十个同伴也能得到这个好处（参考《玩家手册》第八章得到更多有关旅行速度的信息）。鹿的精魂祝福你行得更远更快。 • 虎Tiger。你从下列技能中选择两个技能，你得到它们的熟练：运动、特技、潜行、求生。虎之精魂磨练了你的生存本能。 | J56: 超凡技艺 | K56: 第14级起，你进行属性检定时，可以花费一次诗人激励次数并掷一次激励骰，然后将结果加到你的属性检定上。 你可以在掷完属性检定后，DM宣布结果前决定是否使用此特性。 | L56: 生命领域法术 | M56: 牧师等级——法术 1st——祝福术，疗伤术 3rd——次级复原术，灵体武器 5th——希望信标，回生术 7th——防死结界，信仰守卫 9th——群体疗伤术，死者复活 | N56: 战斗荒野形态 | O56: 从你选择该结社的第2级起，你可以在自己回合内用一个附赠动作而不是动作来使用荒野形态特性。 此外，在你荒野形态变形期间，你可以用附赠动作消耗一个法术位来恢复相应法术位每环阶1d8点生命值。 | P56: 扰乱打击 | Q56: 你以武器攻击命中敌人时，可以消耗一粒卓越骰以扰乱该目标，让你的盟友有机可乘。 使用此战技时，你将消耗的卓越骰加在此次攻击的伤害掷骰中。此后直至你下一回合开始，下一次由除你之外的生物对目标发动的攻击检定具有优势。 | R56: 金刚魂 | S56: 第14级起，你对气的掌控令你所有的豁免检定都成了熟练项。 另外，当豁免失败时，你可以消耗1点气重掷豁免并使用重掷的结果。 | T56: 引导神力-奉献 | U56: 在第3级选择本誓言时，你获得以下两种引导神力选项。 神圣武器:作为一个动作，你可以用引导神力特性向你正持握的一把武器注入正能量。 随后1分钟内，你使用该武器进行攻击检定时可以加上你的魅力调整值（至少为+1）。 该武器同时提供20尺半径的明亮光照，该范围外再延伸出20尺微光光照。 如果该武器之前不是魔法武器，则在效应持续其间该武器将视为魔法武器。 你可以在自己回合内执行任何其他动作时终止该效应，而终止效应的行为视为该动作的一部分。 当你不再持握或携带这把武器，或者当你陷入昏迷时，该效应终止。 驱散不洁:作为一个动作，你可以用引导神力特性亮出圣徽高喊祷言，以逐退不死生物和邪魔。 你身边30尺范围内能够看见圣徽或能听到你祷言的不死生物或邪魔都必须进行一次感知豁免，豁免失败者将受到驱散，其效应持续1分钟或直至其受到任何伤害。 以该方式被驱散的生物必须花费其回合内的所有移动力尽量远离你，且无法主动靠近你30尺内。 被驱散的生物无法执行反应，只能使用既有的疾走动作或从任何妨碍其移动的效应中挣脱。 该生物无路可走时将执行回避动作。 | V56: 猎物 | W56: 第3级时，你选择获得以下特性之一。 巨像屠夫：你强而有力的攻击可以击倒最强壮的对手。 当你用武器攻击命中敌人时，如果该敌人当前生命值低于其上限，则其额外受到1d8点伤害。 你每回合只能造成一次这种额外伤害。 巨人杀手：一个距离你5尺内的大型或更大体型生物对你发动攻击时，无论该次攻击是否命中，只要你能看见它就可以在该攻击结束后用一个反应对该生物发动攻击。 灭族者：进行武器攻击时，你可以用该武器对位于目标5尺内，且在你武器射程内的另一生物发动一次攻击。 你在每个自己的回合里只能造成一次这种额外攻击。 | X56: 冒充者 | Y56: 第13级起，你获得准确模仿他人说话，写字和行为的能力。 你必须花费至少三小时来学习模仿目标的这三方面行为：听他说话，练习写字并观察其特殊习惯。 你伪装手段主要针对那些不细心观察的对象。 如果某个机警的生物觉得你有问题，则你此时为避免被识破而进行的所有魅力（欺瞒）检定都具有优势。 | Z56: 转化法术 | AA56: 当你施放一个能够造成以下列表中类型伤害的法术时，你可以使用1术法点将其改为列表中的另一种伤害类型：强酸、冷冻、火焰、闪电、毒素或雷鸣。 | AB56: 远古奥秘之书 | AC56: 现在你可以把魔法仪式抄录进你的“影之书”。你可以从任意职业法术列表中选择两个1环带仪式标签的法术（两法术可以属于不同法术列表）。所选法术将记录在“影之书”中，且不计入你的已知法术数量内。只要“影之书”在你的手中，你便可以施展所选的仪式法术。你不能通过仪式外的方式施展这些法术，除非你已经通过其他方式习得了这些法术。此外，你还可以把带有仪式描述的邪术师法术作为仪式法术进行施展。 冒险过程中，你还可以添加其他仪式法术到你的“影之书”中。当你发现一个这样的法术时，如果该法术的环阶等于或低于你邪术师等级的一半（向上取整），并且你能抽出时间抄录此法术，则你可以把此法术添加进“影之书”。抄录法术时其每环阶需要花费2小时时间和价值50 gp的珍稀墨水。 先决条件：书之魔契 | AD56: 王车易位 | AE56: 第6级起，你可以用你的动作传送至一处距离你30尺内，你能看见且未被占据的空间。 你也可以指定一处该距离内被一个小型或中型生物所占据的空间，如果该生物愿意，则你就可以与它交换位置。 你必须完成一次长休，或施展一个环阶不低于1环的咒法系法术才能再次使用该特性。 | AF56: 奥能动力甲 | AG56: 先决条件：14级奇械师 物品：一套盔甲（需同调） 穿戴者获得以下好处： 穿戴者的步行速度增加5尺。 每一只装甲附带的手套在没有持握任何物品时皆可被视为一件魔法近战武器。 穿戴者熟练于此手套，命中后会造成1d8力场伤害，此手套具有投掷属性，普通射程20尺，最大射程60尺。 投掷时，手套会脱离并飞向攻击目标，然后立即回到穿戴者身上并重新连接。 此盔甲除非你自愿，否则无法移除。 如果你有肢体缺失，装甲能够替换你所有缺失的肢体——手、臂、 脚、腿等，替换肢体的部分拥有和正常肢体一样的功能。 | AW56: =IFERROR(IF(AW55+1>BA26,IF(AW55+1>BA26,IF(AZ27+AZ55>BA27,"",AZ27+AZ55)),AW55+1),"") -> 27 | AX56: =IFERROR(INDEX(H31:AU181,AW56,AX26),"") | AY56: =IFERROR(INDEX(H31:AU181,AW56,AY26),"") | AZ56: =IFERROR(IF(AW55+1>BA26,AZ55+1,0),"") -> 0 | BB56: =IF(#REF!="","",#REF!) -> #REF! | BC56: =IFERROR(VLOOKUP(BB56,AX30:AY129,2,FALSE),"")
A57: 创造学院 | B57: 3 | C57: 4 | D57: 44 | E57: 47 | G57: 27 | H57: 精魄行者 | I57: 第10级起，你获得施展法术问道自然Commune with Nature的能力，但你只能以仪式的方式施展它。施展此法术时，你所选的图腾兽会以精魄形态现身并提供你想要得到的那些信息。 | J57: 附赠熟练项 | K57: 在第3级选择勇气学院时，你获得中甲、盾牌和军用武器的熟练项。 | L57: 附赠熟练项 | M57: 在第1级选择该领域时，你获得重甲的熟练项。 | N57: 结社形态 | O57: 结社的力量让你可以变成更危险的动物形态。 第2级起，你用荒野形态特性变身的野兽其挑战等级至高为1（无视表格“野兽形态”中的“最高CR栏”，但限制依然生效）。 第6级起，你所变身野兽的挑战等级最高等于你的德鲁伊等级除以3（向下取整）。 | P57: 灵巧步法 | Q57: 你在移动时，可以消耗一粒卓越骰，并将其加入你的AC中，直至你完成移动。 | R57: 不朽身 | S57: 第15级起，你的气充盈身体让你不受衰老的减益，并且无法被魔法变老。 尽管你依然会寿终正寝，但再不需要饮食。 | T57: 奉献灵光 | U57: 第7级起，你与友方生物在你身边10尺内不会被魅惑。 提供该增益时你必须保持意识清醒。 第18级起，灵光的作用范围扩展至30尺。 | V57: 防守战术 | W57: 第7级时，你选择获得以下特性之一。 冲出重围：以你为目标的借机攻击具有劣势。 多重防御：你被生物的攻击命中时，你在本回合内对抗该敌人所有后续攻击的AC获得+4加值。 钢铁意志：你对抗恐慌的豁免具有优势。 | X57: 致命一击 | Y57: 第17级起，你熟练掌握瞬杀的技巧。 你攻击命中一个被突袭的生物时，该生物必须进行一次体质豁免（DC8＋你的敏捷调整值＋你的熟练加值）。 豁免失败时，你将对其造成双倍伤害。 | Z57: 法力变换 | AA57: 从4级起，每当你通过提升术士等级获得属性值提升时，你可以进行以下一种行为，代表着你内在的法力流向了新的途径： 用另一个你能够选择的超魔法选项替换你当前的一个超魔法选项。 用另一个你能够从术士法术列表中选择的戏法替换你当前已知的一个术士戏法。 | AB57: 卡瑟利之链 | AC57: 你可以随意施展针对于天界生物、邪魔、或元素生物的怪物定身术hold monster，且无需消耗法术位和材料成分。你必须完成一次长休才能再次对同一生物使用此祈唤。 先决条件：第15级，链之魔契 | AD57: 咒法专注 | AE57: 第10级起，你在专注咒法系法术时，不会因承受伤害而打断专注。 | AF57: 魔法力量盔甲 | AG57: 物品：一套盔甲（需同调） 此盔甲拥有6发充能。穿戴者能以下列方式消耗充能： 进行力量检定或力量豁免检定时，你能消耗1发充能来获得等于你智力调整值的加值。 当穿着者将被击倒时，以一个反应消耗1发充能，就能避免被击倒。 此盔甲在每天的黎明时会恢复1d6发充能。 | AW57: =IFERROR(IF(AW56+1>BA26,IF(AW56+1>BA26,IF(AZ27+AZ56>BA27,"",AZ27+AZ56)),AW56+1),"") -> 28 | AX57: =IFERROR(INDEX(H31:AU181,AW57,AX26),"") | AY57: =IFERROR(INDEX(H31:AU181,AW57,AY26),"") | AZ57: =IFERROR(IF(AW56+1>BA26,AZ56+1,0),"") -> 0
A58: 雄辩学院 | B58: 3 | C58: 4 | D58: 48 | E58: 52 | G58: 28 | H58: 图腾同调 | I58: 第14级时，你根据所选的图腾兽获得一项魔法能力。 你可以选择和之前相同的图腾，也可以另做选择。 • 熊：狂暴时，如果身处你周边5尺内的任何敌对生物发动攻击，而其目标不是你或另一个具有此特性的生物，则该攻击的攻击检定具有劣势。无法看到你或听到你声音的生物，以及无法陷入恐慌的生物对该特性免疫。 • 雕：狂暴时，你获得等同于你移动速度的飞行速度。此特性只能用于短途冲刺。如果回合结束时你仍在空中且毫无凭依，则你将坠落。 • 狼：狂暴时，如果你在自己回合内以近战武器攻击命中一名大型或更小体型的生物，则你可以用一个附赠动作顺势将其打击至倒地。 这些选项可以在你14级选择图腾动物时选择 。 • 鹿Elk。狂暴期间，在你试图穿过一个被大体型或更小的生物占据的空间时，你可以使用你的附赠动作迫使那个生物进行一次力量豁免（DC 8 + 你的力量属性调整值 + 你的熟练值）。若失败，生物被击倒并且受到1d12+你的力量调整值的钝击伤害。 • 虎Tiger。狂暴期间，如果你向着一个大体型或者更小的目标直线接近至少20尺并且向它进行了一次近战武器攻击，你可以用附赠动作对它进行一次额外的近战武器攻击。 | J58: 战斗激励 | K58: 第3级起，你学会里如何激励他人作战。从你身上获得诗人激励的生物投掷武器伤害掷骰时，可以使用该激励骰并将其骰值加入本次伤害掷骰中。 另外，从你身上获得诗人激励的生物被攻击时，该生物可以用它的反应使用该激励骰，并将掷骰结果加入到它对抗该次攻击的AC中，该特性可以使用于攻击检定揭示后，但必须在命中与否宣布之前使用。 | L58: 生命门徒 | M58: 第1级起，你的治疗法术更加有效。 当你使用1环或更高环阶法术恢复生物生命值时，你的目标额外恢复2＋法术环阶数值的生命值。 | N58: 原初打击 | O58: 第6级起，你以野兽形态攻击时，如果目标对非魔法攻击或伤害具有免疫或抗性，则你的攻击此时视为魔法攻击。 | P58: 诡诈攻击 | Q58: 你可以在自己回合内消耗一粒卓越骰，以此指定你身边5尺范围内一个生物为目标，并使用附赠动作对其虚晃一招。 你在本回合内对该生物发动的下一次攻击检定具有优势。如果该攻击命中，则将消耗的卓越骰加在此次攻击的伤害掷骰中。 | R58: 空灵体 | S58: 第18级起，你可以消耗4点气并使用动作隐形1分钟。 此时，你对力场伤害之外的所有伤害都具有抗性。 另外，你可以消耗8点气施展法术星界投影，以该形式施展的法术不需要材料成分，且无法捎带其他生物与你同行。 | T58: 纯净之魂 | U58: 第15级起，你获得永远保持法术防护善恶效应的能力。 | V58: 多重攻击 | W58: 第11级时，你选择获得以下特性之一。 箭雨：你使用你的动作指定你的远程武器射程内你能看见的某点，并分别对该点周围10尺范围内任意数量的生物发动一次远程攻击。 发动该特性时，你必须有足够的弹药用以攻击敌人，且要为每个目标进行独立的攻击检定。 剑刃风暴：你使用你的动作指定你身边5尺内任意数量的生物，并分别对其发动一次近战攻击，每个受此攻击的目标必须进行独立的攻击检定。 | X58: 施法 | Y58: 第3级起，你获得施法能力。参考第10章的施法规则，以及第11章的法师法术列表。 | Z58: 属性值提升 | AA58: 当你达到第4，第8，第12，第16、第19级时，你可以选择一项属性值提升2点，或是选择两项属性各提升1点。 不过你不能通过该特性让属性值超过20。 | AB58: 魔鬼视界 | AC58: 你在黑暗中拥有120尺的可视距离，而无论其属于魔法黑暗还是非魔法黑暗。 | AD58: 强韧召唤 | AE58: 第14级起，你用咒法系法术所召唤或创造的生物获得30点临时生命值。 | AF58: 折返之靴 | AG58: 先决条件：6级奇械师 物品：一双靴子（需同调） 穿着这双靴子时，那个生物能以一个附赠动作传送到一个距离该生物15尺范围内的可以看到的未占据空间中。不过，该生物必须在本回合内的某个时间点里曾占据过这个空间。 | AW58: =IFERROR(IF(AW57+1>BA26,IF(AW57+1>BA26,IF(AZ27+AZ57>BA27,"",AZ27+AZ57)),AW57+1),"") -> 29 | AX58: =IFERROR(INDEX(H31:AU181,AW58,AX26),"") | AY58: =IFERROR(INDEX(H31:AU181,AW58,AY26),"") | AZ58: =IFERROR(IF(AW57+1>BA26,AZ57+1,0),"") -> 0
A59: 精魂学院 | B59: 3 | C59: 4 | D59: 53 | E59: 58 | G59: 29 | H59: 神性之怒 | I59: 从你在3级选择此道途开始，你可以引导神性怒火，将其注入你的武器打击中。 狂暴期间，你在每个自己回合中用武器攻击命中的第一个生物会受到等同于1d6+你野蛮人等级的一半的额外伤害。此伤害的类型为黯蚀或光耀；你在你得到此特性时选择它的类型。 | J59: 额外攻击 | K59: 第6级起，你在自己回合内执行攻击动作时可以攻击两次而非一次。 | L59: 引导神力：维持生命 | M59: 第2级起，你可以用引导神力特性来恢复严重的伤害。 你用一个动作展示圣徽，引导治疗能量来恢复等于你牧师等级五倍的生命值。你指定身边30尺内的任意生物作为该特性的目标，再为其分配从中获得的治疗能量。 该特性不能将目标恢复到其生命值上限的一半以上。而且你不能对不死生物或构装生物使用该特性。 | N59: 元素荒野形态 | O59: 第10级起，你可以花费两次荒野形态次数以变成气元素，土元素，火元素或者水元素。 | P59: 挑衅攻击 | Q59: 你以武器攻击命中敌人时，可以消耗一粒卓越骰以尝试挑衅该目标。 使用此战技时，你将所消耗的卓越骰加在此次攻击的伤害掷骰中，并迫使目标进行一次感知豁免。豁免失败者攻击除你之外的生物时，其进行的攻击检定具有劣势，直至你的下一回合结束。 | R59: 超凡入圣 | S59: 第20级起，若你骰先攻时身上未有储备的气，则你获得4点气。 | T59: 至圣光轮 | U59: 第20级时，你可以用一个动作生成一个散发阳光的灵光。 在随后的1分钟内，明亮光照从你身边往外辐射半径30尺的球状区域，并在该范围外额外辐射30尺范围的微光光照。 在该明亮光照范围内开始其回合的每个敌对生物都将受到10点光耀伤害。 此外，在该特性持续时间内，你对抗不死生物或邪魔的法术时进行的豁免检定具有优势。 你必须完成一次长休才能再次使用该特性。 | V59: 高效猎人防术 | W59: 第15级时，你选择获得以下特性之一。 反射闪避：你可以灵巧躲过某些特定的区域效应，比如红龙的火焰吐息或是法术闪电束。 你在成为某一范围效应影响对象时，若该效应允许你通过成功的敏捷豁免来使伤害减半，则你在该豁免成功时不受伤害，而豁免失败时只受一半伤害。 逆流而上：当敌人对你的近战攻击未命中时，你可以用反应迫使敌人向你所指定的生物（除攻击者外）重新发动攻击。 直觉闪避：当一个你能看见的敌人攻击命中你时，你可以用反应让此次攻击的伤害减半。 | X59: 戏法 | Y59: 你从法师法术列表中选择三个戏法作为已知法术（包括戏法法师之手和另外两个法师法术列表中的自选戏法）。 第10级时，你再获得额外一个法师戏法。 | Z59: 魔法指引 | AA59: 从5级起，你能够挖掘内在的魔力源泉，从失败中召唤成功。 当你进行一次属性检定并失败时，你可以使用1术法点重投之。 你必须使用重投的结果，此举可能使该检定改为成功。 | AB59: 恐惧箴言 | AC59: 你可以消耗你的邪术师法术位施展一个困惑术confusion。你必须完成一次长休才能再次施展该法术。 先决条件：第7级 | AD59: 预言学者 | AE59: 从第2级你选择该学派起，你向法术书中抄写预言系法术的时间和金钱花费减半。 | AF59: 增强奥术法器 | AG59: 物品：一根权杖、法杖或是魔杖（需同调） 当持用此物品时，持有者的法术攻击检定获得+1加值，同时在进行法术法术攻击时无视半身掩护。 当你拥有10个奇械师等级时，该加值变成+2。 | AW59: =IFERROR(IF(AW58+1>BA26,IF(AW58+1>BA26,IF(AZ27+AZ58>BA27,"",AZ27+AZ58)),AW58+1),"") -> 30 | AX59: =IFERROR(INDEX(H31:AU181,AW59,AX26),"") | AY59: =IFERROR(INDEX(H31:AU181,AW59,AY26),"") | AZ59: =IFERROR(IF(AW58+1>BA26,AZ58+1,0),"") -> 0
A60: 知识领域 | B60: 5 | C60: 6 | D60: 20 | E60: =D61-1 -> 25 | G60: 30 | H60: 神之勇者 | I60: 第3级起，你的灵魂被无尽的战斗所烙印。若一个法术只具有让你起死回生（而非令你变为不死生物）的效果，例如法术 死者复活raise dead ，则施法者在对你施展这一法术时不需要材料成分。 | J60: 战斗魔法 | K60: 第14级起，你可以自如地同时使用音乐魔法和武器。 每当用动作施展一个诗人法术时，你同时还可以用附赠动作发动一次武器攻击。 | L60: 神佑医者 | M60: 第6级起，你施展的治疗法术也会治疗你自身。 你对其他生物施展1环或更高环阶法术法术时，可对自身恢复2＋法术环阶数值的生命值。 | N60: 千面相 | O60: 第14级起，你学会了用魔法精确改变自身外形的方法。 你可以随意施展法术变身术。 | P60: 突刺攻击 | Q60: 你在自己回合内发动近战武器攻击时，可以消耗一粒卓越骰并令该攻击的触及范围增加５尺。如果该攻击命中，则将所消耗的卓越骰加在此次攻击的伤害掷骰中。 | R60: 散打技巧 | S60: 第3级选择散打宗后，你可以在击中敌人时操作其体内的气。 当你用疾风连击特性的攻击击中敌人时，你可以让该目标承受下列效应之一： 目标必须进行一次敏捷豁免，豁免失败则应击倒地。 目标必须进行一次力量豁免，豁免失败则被往远离你的方向推动至多15尺。 目标直到你的下一回合结束前，无法执行反应。 | T60: 古贤圣誓法术 | U60: 圣武士等级——法术 3rd——诱捕打击、动物交谈术 5th——月华之光、迷雾步 9th——植物滋长、防护能量伤害 13th——冰风暴、石肤术 17th——问道自然、树跃术 | V60: 游侠伴侣 | W60: 第3级时，你获得一个野兽伴侣陪你一起冒险，这名训练有素的伙伴能与你合作无间地战斗。 指定一个不大于中型体型，且挑战等级为1/4或更低的野兽（其属性数据以附录D中的猎鹰、獒犬和黑豹为例）。 将你的熟练加值加到该野兽的AC，攻击检定，伤害掷骰以及其所有具有熟练项的豁免和技能检定中。 其生命值上限选用其原上限，或你游侠等级的四倍两者中较高者。 跟其他别的生物一样，该野兽也可在短休时使用生命骰。 动物伴侣会尽可能执行你的命令。它会在轮到你的先攻时行动。 你在自己回合内可以用声音指令指示该野兽往何处移动（无需执行其他动作）。 你可以用你的动作以声音指令指示它执行攻击，疾走，撤离或协助动作。 若你无法发出指令，该野兽将自主执行回避动作。 如果你具有额外攻击特性，则你可以在命令该野兽执行攻击动作的同时自己发动一次武器攻击。 若你陷入失能或并不在场，该野兽将自主活动，并集中致力于保护你和它自己。 该野兽此时无需你下达指令即可使用期反应，比如以此发动一次借机攻击。 身处偏好地形时，如果只有该野兽与你一起，则你仍可以保持隐匿状态以正常步调旅行。 如果该野兽死亡，则你可以耗费8小时与另一个非敌对关系的野兽建立魔法联结成为伴侣，新的伴侣不一定要与之前的野兽类型相同。 该野兽可以跟其他生物一样在短休时使用其生命骰。当你陷入失能或不在身边时，该野兽也可以自主的保护你或者它自身。 它被借机攻击时，不需等待你的命令就可以执行其反应。 | X60: 法术位 | Y60: “诡术师施法能力”表中列出了你用以施展你法师法术的1环及更高环阶法术位数量。 施展这些法术时，你必须同时消耗一个不低于该法术环阶的法术位。 而已消耗的法术位可以通过完成以此长休进行恢复。 例如，若你已知1环法术魅惑人类，并且有一枚可用的1环法术位和一枚可用的2环法术位，则你可以用两者之一施展魅惑人类。 | Z60: 术法复苏 | AA60: 第20级时，你每完成一次短休，可以恢复4术法点。 | AB60: 魔能视界 | AC60: 你可以随意施展法术侦测魔法detect magic，且无需消耗法术位。 | AD60: 预兆 | AE60: 从第2级你选择该学派起，预知未来的片段会时常在你意识中闪过。 你在每次完成长休时投两次d20并记下两组骰值。 此后，你可以用这两组预知骰骰值中的任意一个，替代任何一次由你，或者由你能看见的某个生物所进行的攻击检定，豁免检定或属性检定。 你必须在相关检定开始前决定是否使用预知骰，且你每回合只能使用一次预知骰。 每个预知骰只能使用一次。 你完成一次长休后，将失去所有未使用的预知骰。 | AF60: 增强防御 | AG60: 物品：一套盔甲或一面盾牌 穿着该盔甲或挥舞该盾牌的生物在AC上获得+1加值。 当你拥有10个奇械师等级时，该加值变成+2。 | AW60: =IFERROR(IF(AW59+1>BA26,IF(AW59+1>BA26,IF(AZ27+AZ59>BA27,"",AZ27+AZ59)),AW59+1),"") -> 31 | AX60: =IFERROR(INDEX(H31:AU181,AW60,AX26),"") | AY60: =IFERROR(INDEX(H31:AU181,AW60,AY26),"") | AZ60: =IFERROR(IF(AW59+1>BA26,AZ59+1,0),"") -> 0
A61: 生命领域 | B61: 5 | C61: 6 | D61: 26 | E61: =D62-1 -> 32 | G61: 31 | H61: 专心炽志 | I61: 第6级起，驱使你愤怒的神力也能庇护你免遭干扰。 狂暴期间，若你豁免检定失败，你可以重新投掷该豁免检定，但你必须接受重骰后的结果。你每次狂暴中只能使用此能力一次。 | J61: 激励光环 | K61: 当你在3级加入迷惑学院起，你获得将妖精的魔法浸入歌曲的力量，为你的盟友们带来活力与速度。 以一个附赠动作，你可以消耗一次吟游激励的次数，让自己得到华美而出尘的外貌。此时，选择你周围60尺内的一定数量能看见你且你也能看见的生物，其数量至多等同于你的魅力调整值个（至少1个）。每个生物都会获得5点临时生命值。而当一个生物获得这些临时生命值时，它可以用其反应移动至多等同于其速度的距离，此次移动不会引发借机攻击。 在你达到此职业的特定等级后，你能给予它们更多的临时生命值，在5级后提高到8点，10级后11点，15级后14点。 | L61: 神圣打击 | M61: 第8级起，你可以使你的武器充满神圣能量。你在每个自己回合里有一次机会，可以在用武器攻击命中某生物时，使该攻击额外造成1d8的光耀伤害。14级时，该伤害提升到2d8。 | N61: 仲夏庭院的芬馥 | O61: 2级起，你将被灌注来自仲夏庭院的祝福，由此成为缓解旅者乏顿和伤者痛苦的圣洗池。 你得到等同于德鲁伊等级每d6作为代表的妖精能量池。 以一个附赠动作，你可以选择一名在你120尺内的可见盟友，并且花费最多等于你德鲁伊等级一半的d6骰。 投掷那些骰子并把结果加在一起。目标恢复等于那个总值的生命值。 目标同时也得到等同于花费骰子数目的临时生命值。 在你结束一次长休之后，你恢复所有花费掉的骰子。 | P61: 灵动攻击 | Q61: 你以武器攻击命中敌人时，可以消耗一粒卓越骰以让盟友移动到更有利的位置。 使用此战技时，你将所消耗的卓越骰加在此次攻击的伤害掷骰中，并指定一个能看见你或听到你声音的盟友。该盟友可以立即用其反应移动至多等于其速度一半的距离。本次移动不会引发本次所攻击目标的借机攻击。 | R61: 混元体 | S61: 第6级起，你获得自疗的能力。 你可以使用一个动作获得等同于三倍武僧职业等级的生命值。 你必须完成一次长休才能再次使用该特性。 | T61: 引导神力-古贤 | U61: 在第3级选择本誓言时，你获得以下两种引导神力选项。 自然之怒：你可以用引导神力特性唤起原初之力来诱捕敌人。 作为一个动作，你可以让特殊的藤蔓生长并缠绕一个距离你10尺内，你能看见的生物。 该生物必须进行一次力量或敏捷豁免（由其选择），豁免失败者将陷入束缚状态。 此后，每当该生物结束其回合时，都可以再进行一次该豁免。 一旦豁免成功，则该生物挣脱束缚，藤蔓也就此消失。 驱散无信者：你可以用引导神力特性发出远古的圣言，使听到圣言的精类生物和邪魔感到痛苦。 作为一个动作，你亮出圣徽，迫使身边30尺范围内能够听到你声音的所有精类生物或邪魔都进行一次感知豁免，豁免失败者将受到驱散，其效应持续1分钟或直至其受到任何伤害。 以该方式被驱散的生物必须花费其回合内的所有移动力尽量远离你，且无法主动靠近你30尺内。 被驱散的生物无法执行反应，只能使用既有的疾走动作或从任何妨碍其移动的效应中挣脱。 该生物无路可走时会执行回避动作。 如果被驱散生物的真实外形被幻术、变形、或其他效应掩盖，那么在被驱散后，它将显露出原形。 | V61: 原初伴侣 | W61: 3级驯兽师特性，替换游侠伴侣特性 你魔法性的召唤出一只原初野兽，其力量来自于与你与自然的联系。这只野兽对你和你的伙伴态度友善，并会听从你的命令。你从大地野兽，海洋野兽和天空野兽的数据中为它选择其一作为它的数据，它数据表中许多地方将会用到你的熟练加值（PB）。且你决定原初野兽是何种动物，选择适合其数据的外形。无论你选择什么样的动物，这只野兽都带有原始的印记，暗示着其神秘的起源。 在战斗中，原初野兽会在你的回合中行动。它能自主的移动或使用反应，但除非你在你的回合中以一个附赠动作命令它执行其他动作，它只会执行回避动作。命令的动作可以是其数据中列出的动作或是之外的其他动作。作为另一种命令方式，你也能在使用自己的攻击动作时，牺牲其中一次自己的攻击来命令野兽执行攻击动作。如果你陷入失能，野兽将会自主行动，而非仅使用回避动作。 如果野兽死亡不超过一小时，你能使用你的动作触碰它，并消耗一个一环或更高的法术位使他复活。它会在一分钟后死而复生并获得所有生命值。 当你结束一次长休后，你能够召唤一只不同的原初野兽。这只新的野兽出现在你5尺内未被占据的空间内，并由你选择其数据和外表。如果你已经通过此特性获得了一只原初野兽，它会在新的原初野兽出现时消失。原初野兽也会在你死亡时消失。 大地野兽Beast of the Land 中型野兽 -------------------------------------------------------------------------------- AC： 13+PB（天生护甲） HP：5+你游侠等级的五倍（野兽拥有与你游侠等级相同数量的生命骰[D8]） 速度：40尺，攀爬40尺 -------------------------------------------------------------------------------- 力量 敏捷 体质 智力 感知 魅力 14（+2） 14（+2） 15（+2） 8（-1） 14（+2） 11（+0） -------------------------------------------------------------------------------- 感官：黑暗视觉60尺，被动察觉12 语言：理解你说的语言 挑战等级：—— 熟练加值（PB）：等于你的熟练加值。 -------------------------------------------------------------------------------- 冲锋Charge。当大地野兽向一个目标直线移动了至少20尺，然后在同一回合以挥打攻击命中目标时。目标会额外受到1d6挥砍伤害。如果目标是生物，它必须成功通过对抗你法术豁免DC的力量豁免检定否则应击倒地。 原初联结Primal Bond。你能将你的熟练加值加到野兽进行的一切属性检定和豁免检定上。 -------------------------------------------------------------------------------- 动作Actions 挥打Maul。近战武器攻击：攻击加值等同于你的法术攻击加值，触及5尺，单个目标。命中：1d8+2+PB点挥砍伤害。 -------------------------------------------------------------------------------- 海洋野兽Beast of the Sea 中型野兽 -------------------------------------------------------------------------------- AC： 13+PB（天生护甲） HP：5+你游侠等级的五倍（野兽拥有与你游侠等级相同数量的生命骰[D8]） 速度：5尺，游泳60尺 -------------------------------------------------------------------------------- 力量 敏捷 体质 智力 感知 魅力 14（+2） 14（+2） 15（+2） 8（-1） 14（+2） 11（+0） -------------------------------------------------------------------------------- 感官：黑暗视觉60尺，被动察觉12 语言：理解你说的语言 挑战等级：—— 熟练加值（PB）：等于你的熟练加值。 -------------------------------------------------------------------------------- 水陆两栖Amphibious。野兽可以在空气和水中呼吸。 原初联结Primal Bond。你能将你的熟练加值加到野兽进行的一切属性检定和豁免检定上。 -------------------------------------------------------------------------------- 动作Actions 攫击Binding Srtike。近战武器攻击：攻击加值等同于你的法术攻击加值，触及5尺，单个目标。命中：1d6+2+PB点穿刺或1d6+2+PB点钝击伤害（由你选择），并且目标被擒抱（逃脱DC等于你的法术豁免DC）。 -------------------------------------------------------------------------------- 天空野兽Beast of the Sky 小型野兽 -------------------------------------------------------------------------------- AC： 13+PB（天生护甲） HP：4+你游侠等级的四倍（野兽拥有与你游侠等级相同数量的生命骰[D6]） 速度：10尺，飞行60尺 -------------------------------------------------------------------------------- 力量 敏捷 体质 智力 感知 魅力 6（-2） 16（+3） 13（+1） 8（-1） 14（+2） 11（+0） -------------------------------------------------------------------------------- 感官：黑暗视觉60尺，被动察觉12 语言：理解你说的语言 挑战等级：—— 熟练加值（PB）：等于你的熟练加值。 -------------------------------------------------------------------------------- 飞掠Flyby。野兽以飞行离开敌人的触及范围时不会引发对方的借机攻击。 原初联结Primal Bond。你能将你的熟练加值加到野兽进行的一切属性检定和豁免检定上。 -------------------------------------------------------------------------------- 动作Actions 撕咬Shred。近战武器攻击：攻击加值等同于你的法术攻击加值，触及5尺，单个目标。命中：1d4+3+PB点挥砍伤害。 -------------------------------------------------------------------------------- | X61: 已知法术 | Y61: 你习得三个自选的1环法师法术，其中两个必须从附魔系和幻术系中选择。 表格“诡术师施法能力”中“已知法术”一栏记录了你获得更多已知法术时的相应等级。 你只能选择附魔系或幻术系法术，且所获得法术的环阶不能好过你所拥有的最高法术位环阶。 例如，如果你在本职业打到第7级，则可以学习一个新的1环法术或2环法术。 你在第8，第14和第20级可学习来自任何学派的法术。 你每次提升本职业等级时，可以将一个已知法术替换为另一个法师法术。 这个新法术的环阶不能超过你所拥有的最高法术位打到环阶，且必须从附魔系或幻术系中选择（除非你替换的是第3，第8，第14或第20级习得的法术）。 | Z61: 巨龙先祖 | AA61: 第1级时，你选择一种巨龙作为你的先祖。 对应的伤害类型将在随后获得的特性中用到。 你可以说、读、写龙语。 此外，你与巨龙互动时进行的魅力检定可以使用熟练加值时，可以加上双倍的加值。 | AB61: 魔能长枪 | AC61: 施展魔能爆eldritch blast时，射程变为300尺。 先决条件：习得戏法 魔能爆 | AD61: 预言专家 | AE61: 第6级起，你对施展预言法术的技巧驾轻就熟，几乎不用使什么力气。 你用法术位施展一个环阶不低于2环的预言系法术时，可以恢复一个已耗用的法术位。 所恢复的法术位环阶必须比你正施展的预言系法术所用的法术位低，且不能高于5环。 | AF61: 增强武器 | AG61: 物品：一把简易或军用武器 该魔法武器在攻击和伤害检定中具有+1加值。 当你拥有10个奇械师等级时，该加值变成+2。 | AW61: =IFERROR(IF(AW60+1>BA26,IF(AW60+1>BA26,IF(AZ27+AZ60>BA27,"",AZ27+AZ60)),AW60+1),"") -> 32 | AX61: =IFERROR(INDEX(H31:AU181,AW61,AX26),"") | AY61: =IFERROR(INDEX(H31:AU181,AW61,AY26),"") | AZ61: =IFERROR(IF(AW60+1>BA26,AZ60+1,0),"") -> 0
A62: 光明领域 | B62: 5 | C62: 6 | D62: 33 | E62: =D63-1 -> 39 | G62: 32 | H62: 狂热威仪 | I62: 第10级起，你学会了引导神力，让其他人也被你的狂热所感染。以一个附赠动作，你愤怒的怒吼并释放出一道蕴含神圣能量的战吼。选择你周围60尺范围内至多10个能听到你吼叫声的其他生物，直到你的下个回合开始前，他们进行的攻击检定与豁免检定获得优势。 一旦你使用了此特性，直到你完成了一次长休为止你都不能再次使用它。 | J62: 醉人表演 | K62: 第3级起，你能将诱惑力和妖精的魔法充入你的表演。 若你进行了至少1分钟的表演，你就可以借由歌唱、吟诗、或舞蹈的方式来让你的观众们感受到奇妙的力量。在这次表演的结束时，选择你周围60尺范围内一定数量的、完整观看并聆听了你的表演的类人生物，可以选择的数量至多等同于你的魅力调整值个（至少1个）。每个目标必须通过一次对抗你的法术豁免DC的感知豁免，若豁免失败则其将被你魅惑。当被你以此法魅惑时，目标视你为偶像，他会热情的和任何和它交谈的人谈论你，反对任何对抗你的人，它会避免暴力，除非他已经站在你这边加入了战斗。每个目标身上的效应都将持续1小时。当受影响生物受到任何伤害、你攻击了它、或它目睹你对任何它的盟友进行攻击或造成伤害时会提前结束。 若一个目标对抗此效应的豁免成功，该目标不会察觉到你曾试图魅惑他的行为。 一旦你使用了此特性，直到你完成一次短休或长休前你都不能再次使用它。 | L62: 极效治疗 | M62: 第17级起，当你需要用一个法术来掷一粒或多粒骰子计算你所恢复的生命值时，所有骰子将取其最高值。例如，法术为某一生物恢复2d6生命值，则其结果直接取12。 | N62: 月光与阴影的炉心 | O62: 6级起，无论你在何处设立营灶，那都是的你家园。 在进行一次短休息或长休息时，你可以祈求薄暮庭院的幽影之力来保护你的营地不被外来者侵扰。 在休息开始时，你接触空间中的一点，以那一点为中心一个隐形的、半径30尺的球体魔法般地出现。 全掩护会阻断这个球体。 在这一领域内你和你的盟友在所有感知（观察）检定和敏捷（隐匿）检定中得到+5加值，并且由任何明火放射的光亮（营火，火把以及类似之物）从领域外是不可见的。 这些效果持续到休息结束或你离开这个领域。 | P62: 恐吓攻击 | Q62: 你以武器攻击命中敌人时，可消耗一粒卓越骰以尝试恐吓该目标。 使用此战技时，你将所消耗的卓越骰加在此次攻击的伤害掷骰中，并迫使目标进行一次感知豁免。豁免失败者将陷入对你恐慌的状态，直至你下一回合结束。 | R62: 宁神境 | S62: 第11级起，你可以进入一种特殊的冥想状态，使浑身环绕着和平的灵光。 完成长休后，你将获得法术庇护术的效应，其效应持续至你再次开始长休之前（该法术效应可以如常被提前终止）。 该法术效应的豁免DC等于8＋你的感知调整值＋你的熟练加值。 | T62: 守御灵光 | U62: 第7级起，强大的远古魔法眷顾着你，以至于在你身边形成了一道神秘的结界。 你和距离你10尺以内的友善生物获得对法术伤害的抗性。 第18级起，灵光的范围增加至30尺。 | V62: 特殊训练 | W62: 第7级起，如果你的野兽伴侣在你的回合内未曾发动攻击，则你可以在本回合用一个附赠动作命令该野兽在其回合内执行“疾走”“撤离”或“协助”动作。 此外，该野兽的攻击作用于非魔法攻击与伤害的免疫与抗性时视为魔法。 | X62: 施法关键属性 | Y62: 你通过研究和记忆学习魔法，因此智力是你施展法师法术的关键属性。 每当你的法术需要施法关键属性时均指向你的智力值。 而你的法师法术的豁免DC和攻击检定，则使用你的智力调整值 法术豁免DC＝8＋你的熟练加值＋你的智力调整值 法术攻击调整值＝你的熟练加值＋你的智力调整值 | Z62: 龙族体魄 | AA62: 魔法在你的体内流动，并使你显露出你巨龙先祖的部分身体特质。 第1级时，你的生命值上限提升1点，此后每提升一个术士等级，都将再次提升1点。 此外，你部分皮肤覆盖着龙鳞样式的柔鳞。 未着装护甲时，你的AC等于13＋你的敏捷调整值。 | AB62: 符文守护者之眼 | AC62: 你可以读懂任何文字。 | AD62: 天眼通 | AE62: 第10级起，你可以用你的动作增强你的感知能力。 使用此特性时，你选择一下增益其中之一。 其效应将持续至你陷入失能状态，或直至你开始一次短休或长休。 你必须完成一次休息才能再次使用该特性。 黑暗视觉：你获得60尺的黑暗视觉。 以太视界：你可以看到自身周边60尺范围内的以太位面。 高等理解力：你可以读懂任何语言。 识破隐形：你可以看到距离你10尺内，且处在你视线范围内的隐形生物或物件。 | AF62: 警觉之盔 | AG62: 先决条件：10级奇械师 物品：一件头盔（需同调） 穿戴此头盔时，那个生物在先攻检定上具有优势。此外，穿戴者只要未处于 失能incapacitated 状态，就无法被突袭。 | AW62: =IFERROR(IF(AW61+1>BA26,IF(AW61+1>BA26,IF(AZ27+AZ61>BA27,"",AZ27+AZ61)),AW61+1),"") -> 33 | AX62: =IFERROR(INDEX(H31:AU181,AW62,AX26),"") | AY62: =IFERROR(INDEX(H31:AU181,AW62,AY26),"") | AZ62: =IFERROR(IF(AW61+1>BA26,AZ61+1,0),"") -> 0
A63: 自然领域 | B63: 5 | C63: 6 | D63: 40 | E63: =D64-1 -> 46 | G63: 33 | H63: 怒不畏死 | I63: 从14级开始，驱使你狂暴的神力允许你忽视致命的打击。 狂暴期间，具有0点生命值并不会使你陷入 昏迷Unconscious 。不过你仍然需要进行死亡豁免，你在0生命值下受到伤害时依旧计算豁免失败次数。然而，若你因为未通过死亡豁免检定而即将死去时，只要你仍处于狂暴状态，你将拒绝死亡。而如果你的狂暴结束后你仍保持0点生命值，那么你将死亡。 | J63: 统御光环 | K63: 第6级起，你得到了用精类魔法覆盖自己的能力，令他人化为服从你指令的傀儡。以一个附赠动作，你施展法术 命令术command ，无需消耗法术位。且同时你获得无上的美貌，持续1分钟，如果你的专注结束（如同你专注于一个法术），它也会提前结束。在这段时间内，你在每个你的回合中都能再用一个附赠动作施展法术 命令术command ，且同样无需消耗法术位。 以此施展的 命令术Command 中，任何被你 魅惑Charmed 的生物将自动豁免失败。 一旦你使用了此特性，直到你完成一次长休前你都不能再次使用它。 | L63: 光明领域法术 | M63: 牧师等级——法术 1st——燃烧之手、妖火 3rd——炽焰法球、灼热射线 5th——昼明术、火球术 7th——信实守卫、火墙术 9th——焰击术、探知 | N63: 隐匿通途 | O63: 10级起，你可以使用那些被隐藏起来的、无法预测的魔法道路，像妖精一样在眨眼之间穿越空间。 在你的回合，你可以以一个附赠动作传送到60尺内一处未被占据的可见区域。 或者，你也可以用你的动作来接触一个自愿生物将它传送至30尺内一处未被占据的你可见的空间。 你可以使用这个能力的次数等同于你的感知调整值（至少1次），当你结束一次长休之后，你恢复所有使用次数。 | P63: 格挡 | Q63: 其他生物的近战攻击对你造成伤害时，你可以用反应消耗一粒卓越骰以减少伤害。减少的数值为卓越骰骰值＋你的敏捷调整值。 | R63: 渗透劲 | S63: 第17级起，你可以将暗劲击入他人体内。 你的徒手打击命中目标生物时，可以消耗3点气将一股致命的劲力送入敌人体内。 劲力的持续日数等于你的武僧等级，且在你用动作终止劲力之前它不产生任何减益。 若要终止劲力，你和目标必须在同一个位面。 而你使用动作终止劲力后，目标必须进行一次体质豁免，豁免失败则其生命值降为0，豁免成功则目标受到10d10的暗蚀伤害。 同一时间只能有一个生物受你渗透劲特性影响。 你也可以选择不造成任何伤害的终止渗透劲，且不需要使用动作。 | T63: 不灭哨卫 | U63: 第15级起，你生命值降至0点，但尚未被直接杀死时，可以选择让你的生命值降到1点而不是0点。 你必须完成一次长休后才能再次使用该能力。 此外，你不受任何衰老减益。 也不会因为魔法效应而衰老。 | V63: 兽性狂怒 | W63: 第11级起，当你命令野兽伴侣执行攻击动作时，它可以发动两次攻击。 或者，若其拥有“多重攻击”动作项，则它也可以执行该动作项。 | X63: 法师之手·诈 | Y63: 第3级起，你施展法师之手时可以制作一个隐形的幽灵手，且你可以用它来做下列特殊任务： 你可以传递一个幽灵手持握的物件到其他生物携带或着装的容器中。 你可以取回一个其他生物携带或着装容器内的物件。 你可以用盗贼工具在其施法范围内撬锁和解除陷阱。 你可以在目标生物不知情的前提下完成这些任务之一，前提是你必须进行一次敏捷（巧手）检定，并在与该生物的感知（察觉）检定对抗中胜出。 此外，你还可以用你的灵巧动作特性给予的附赠动作来控制法师之手。 | Z63: 元素亲和 | AA63: 第6级起，当你施展伤害类型与你巨龙先祖相对应的法术时，可以将你的魅力调整值附加到该法术其中一次伤害掷骰中。 此时你还可以用1术法点来获得持续1小时的相应伤害抗性。 | AB63: 邪魔活力 | AC63: 你可以随意施展1环法术虚假生命false life，且无需消耗法术位和材料成分。 | AD63: 高等预兆 | AE63: 第14级起，你梦中的景象更为清晰精确的在你意识中描绘出了将要发生的一切。 你的预兆特性获得三个预知骰，而不再是两个。 | AF63: 人工生命仆从 | AG63: 物品：一颗价值至少100gp的宝石或水晶 你习得了如何魔法性的创造一个为你服务的特殊人工生命。 你在注法中使用的物品将变成人工生命的心脏，而它的身体会立即围绕心脏成型。 你能够决定人工生命的外观。 有些奇械师喜欢看上去像机械的鸟，也有些喜欢长翅膀的小瓶或是拥有生命的小坩埚。 人工生命对你和你的同伴都十分友善，且服从你的命令。 人工生命的游戏数据见下，它的数据中某几项会适用你的熟练加值。 在战斗中，人工生命使用你的先攻，并且在你的回合后立即行动。 它能自由移动和执行反应，但除非你以一个附赠动作命令它进行数据中列出的动作或其他动作，否则它在回合中只能进行闪避动作。 如果你失能，人工生命可以进行任何动作，而不仅仅是闪避。 如果你对人工生命施放修复术，它将恢复2d6生命值。 如果你或人工生命死亡，它将消失，只有心脏会留在它之前占据的地方。 | AW63: =IFERROR(IF(AW62+1>BA26,IF(AW62+1>BA26,IF(AZ27+AZ62>BA27,"",AZ27+AZ62)),AW62+1),"") -> 34 | AX63: =IFERROR(INDEX(H31:AU181,AW63,AX26),"") | AY63: =IFERROR(INDEX(H31:AU181,AW63,AY26),"") | AZ63: =IFERROR(IF(AW62+1>BA26,AZ62+1,0),"") -> 0
A64: 风暴领域 | B64: 5 | C64: 6 | D64: 47 | E64: =D65-1 -> 53 | G64: 34 | H64: 先祖护卫 | I64: 从你在3级时选择此道途开始，你进入狂暴时一名精魂战士将出现在你身旁。狂暴期间，在每个你的回合中你攻击命中的第一个生物将成为这名精魂战士的目标，战士将阻挠目标对它人的攻击。直到你的下一个回合开始前，战士的目标对你以外的目标发动的攻击检定具有劣势，而若其在一次攻击中击中了除你以外的生物，该生物对那次攻击的伤害具有抗性。你的狂暴结束时，此效果也随之提前结束。 | J64: 绝对统御 | K64: 第14级起，你的外貌变得超凡脱俗，这让你看上去更加漂亮与骇人。 此外，以一个附赠动作，你展现出魔法性的完美仪度，持续1分钟，如果你陷入 失能Incapacitated，它也将提前结束。持续时间内，任何生物在每回合中首次试图对你进行攻击时都必须通过一次对抗你的法术豁免DC的魅力豁免。豁免失败时，该生物在这个回合内将无法攻击你，且必须要为本次攻击选定一个新的目标，或放弃攻击。豁免检定成功时，该生物能够正常攻击你，但它在下个你的回合中，对抗你的法术所做的任何豁免检定都将具有劣势。 一旦你使用了此特性，直到你完成一次短休或长休前你都不能再次使用它。 | L64: 附赠戏法 | M64: 在你第1级选择该领域时，获得戏法光亮术，如果你已经学会则不会重新获得。 | N64: 梦境行者 | O64: 14级起，妖精荒野的魔力让你能物理性或精神性地穿越梦境空间。 当你完成了一次短休息，你可以施展以下法术之一，无需消耗法术位也无需材料成分：托梦术（以你作为信使）、探知、或传送法阵。 以这种方法使用的传送法阵是特别的。 取代了打开入口通往永久性传送法阵的能力，它将打开入口通往你在现存位面上完成最后一次长休息的所在地。 如果你没有在现存位面上进行过长休息，这个法术会失败但不会浪费。 一旦你使用这个能力，直到你结束长休之前你不能再次使用。 | P64: 精准攻击 | Q64: 你进行武器攻击时，可以消耗一粒卓越骰以将其结果加在本次攻击的攻击检定中。你可以在进行攻击检定之前或之后使用此战技，不过必须在相应攻击效果生效之前作决定。 | R64: 暗影技艺 | S64: 第3级你选择本宗派起，你可复制某些特定法术的效应。 你可用一个动作消耗2点气以施放黑暗术，黑暗视觉，行动无踪或沉默术，且无需材料成分。 此外，若你仍未习得戏法次级幻影，则你将获得该戏法。 | T64: 上古斗士 | U64: 第20级起，你可以化作远古自然力量的化身，并获得一项你自己决定的外貌特征。 例如，你的皮肤可能变成绿色，或者长出树皮般的纹理。 你的头发也许会变得像树叶或青苔一般，又或者你长出了鹿角或者狮鬃。 你使用一个动作以经历该变化，并在接下来一分钟内获得以下增益： 你在每个自己的回合开始时，恢复10点生命值。 你施展施法时间为1动作的圣武士法术时，可以用一个附赠动作而不是一个动作来施展它。 距离你10尺以内的敌人对抗你圣武士法术和引导神力特性进行豁免检定时具有劣势。 你必须完成一次长休后才能再次使用该特性。 | V64: 法术共享 | W64: 第15级起，当你施展一个目标为自身的法术时，如果你的野兽伴侣处于你身边30尺范围内，则该法术效应同时也作用于你的野兽伴侣。 | X64: 诡术伏击 | Y64: 第9级起，如果你在针对某个生物躲藏的状态下对其施法，则该生物在本回合里对抗该法术所进行的豁免检定具有劣势。 | Z64: 龙翼 | AA64: 第14级时，你获得一对可以从背后张开的龙翼，并获得等于你当前速度的飞行速度。 你可以在自己回合内用一个附赠动作生成龙翼。 龙翼持续存在至你在自己回合内用一个附赠动作将其解散。 你不能在着装护甲时张开龙翼（除非该护甲经过特殊的设计）。 而当你显现龙翼时，未经过特殊设计的衣服可能会毁坏。 | AB64: 共视感官 | AC64: 你用动作触碰一个自愿的类人生物，并与其建立起感官的连接。连接状态持续到你下回合结束时终止。其间，只要你与该生物还处于同一位面中，就可以用动作继续维持连接，使其持续时间延长至你下回合结束时终止。 以所连接生物的感官进行观察时，你将拥有该生物所有的特殊感官收益，但你对于自身所处的环境则视为等同与处于目盲和耳聋状态。 | AD64: 附魔学者 | AE64: 从第2级你选择该学派起，你向法术书中抄写附魔系法术的时间和金钱花费减半。 | AF64: 思维砥石 | AG64: 物品：一套盔甲或法袍 这件注法物品能够向穿戴者发送震动，使其能够重新集中专注。此物品具有4发充能，当穿戴者在维持法术专注时所作的一次体质豁免中失败时，穿戴者能够以一个反应，消耗1发充能将结果改为成功。 此物品在每天的黎明时会恢复1d4发已被消耗的充能。 | AW64: =IFERROR(IF(AW63+1>BA26,IF(AW63+1>BA26,IF(AZ27+AZ63>BA27,"",AZ27+AZ63)),AW63+1),"") -> 35 | AX64: =IFERROR(INDEX(H31:AU181,AW64,AX26),"") | AY64: =IFERROR(INDEX(H31:AU181,AW64,AY26),"") | AZ64: =IFERROR(IF(AW63+1>BA26,AZ63+1,0),"") -> 0
A65: 诡术领域 | B65: 5 | C65: 6 | D65: 54 | E65: =D66-1 -> 59 | G65: 35 | H65: 精魂之盾 | I65: 从6级开始，卫士之魂会帮助你为你的盟友提供超自然保护。 狂暴期间，若一个处于你周围30尺内的、你能看到的其他生物受到伤害时，你可以用反应来为其降低2d6点的伤害。 当你此职业上达到特定等级后，你将可以减免更多的伤害：10级后3d6，14级后4d6。 | J65: 附赠熟练项 | K65: 当你在3级加入剑舞学院时，你得到中甲和弯刀的熟练项。 若你熟练于一把简易近战武器或者军用近战武器，你就可以将其作为你诗人法术的法器使用。 | L65: 守御闪光 | M65: 第1级起，你可以在自己与正发动攻击的敌人之间建起一道神圣之光。当你身边30尺内一个你能看见的生物向你发动攻击时，你可以用你的反应在攻击完成前对攻击者闪出一道光亮，以此迫使该攻击检定具有劣势。不受目盲状态影响的攻击者同样对该特性免疫。 你可以使用该特性的次数等于你的感知调整值（至少为一次）。而你将在完成一次长休后重新恢复所有的使用次数。 | N65: 林地之语 | O65: 2级时，你获得了和野兽以及许多精类进行交流的能力。 你学会对于木族语的说、读、和写的能力。 此外，野兽能理解你的语言，而你也能理解它们的声音和动作。 大多数野兽缺乏足够的智力去表述或理解复杂的概念，但友善的野兽可以复述它在最近听到或看到的事物。 此能力并不会让你和野兽形成特别的友谊，尽管你可以将此技能与讨好它们的礼物结合使用，就像是你能对其他NPC做的那样。 | P65: 推撞攻击 | Q65: 你以武器攻击命中敌人时，可以消耗一粒卓越骰以尝试将该目标推开。 使用此战技时，你将所消耗的卓越骰加在此次攻击的伤害掷骰中。如果该目标为大型或更小体型，则其必须进行一次力量豁免。豁免失败者将被往远离你的方向推动至多15尺。 | R65: 暗影步 | S65: 第6级起，你获得在阴影中漫步的能力。 你处于微光光照或黑暗环境时，可以用附赠动作传送至多60尺，到达一个你能看见且未被占据还必须同样处于微光光照或黑暗环境中的区域。 随后直至你本回合结束前，你下一次发动近战攻击时具有优势。 | T65: 复仇圣誓法术 | U65: 圣武士等级——法术 3rd——灾祸术、猎人印记 5th——人类定身术、迷踪步 9th——加速术、防护能量伤害 13th——放逐术、任意门 17th——怪物定身术、探知 | V65: 幽域追踪者法术 | W65: 3级起，你学会一个额外法术当你到达指定游侠等级时，如幽域追踪者法术列表所示。 这些法术对你视为游侠法术，它不计入你的已知法术总数中。 游侠等级——法术 3级——易容术 5级——魔绳术 9级——恐惧术 13级——高等隐身术 17级——伪装术 | X65: 万能诡术 | Y65: 第13级时，你获得用你的法师之手使目标分心的能力。 作为一个附赠动作，你可以在自己的回合内指定该法术之幽灵手周边5尺内的一个生物。 直至该回合结束之前，你对该生物发动的攻击检定具有优势。 | Z65: 真龙姿态 | AA65: 18级起，你可以导引你巨龙先祖的恐怖气息，使你周围的生物感到震撼或恐慌。 你可以用一个动作和5术法点引导这股力量，并张开一个60尺范围的震撼（或恐惧）灵光。 在1分钟内，只要你保持专注（等同于施法时进行专注），在灵光范围内开始其回合的每个敌对生物都必须进行一次感知豁免，豁免失败则被魅惑（震撼灵光）或陷入恐慌（恐惧灵光）直至灵光消失。 豁免成功者将在随后的24小时内免疫你的灵光效应。 | AB65: 饮命者 | AC65: 你使用契约武器命中某个生物时，额外造成相当于你魅力调整值的黯蚀伤害（最少为1）。 先决条件：第12级，刃之魔契 | AD65: 催眠凝视 | AE65: 从第2级你选择该学派起，你可以用轻柔的语言和魅惑的目光来施展魔法奴役其他生物。 作为一个动作，你指定身边5尺范围内一个你能看见的生物。 如果该生物能看见你或者能听到你的声音，则其必须进行一次对抗你法师法术豁免DC的感知豁免，豁免失败则受你魅惑，其状态持续至你下一回合结束。 该被魅惑生物的速度降至0，并陷入失能状态。 外表上看该生物会是一副头晕目眩的样子。 在接下来的回合中，你可以用另一个动作来延续该效应，以将其持续时间再延续至你的下一回合结束。 然而，如果你移动到目标生物5尺以外，或者该生物变得不能看见你也不能听到你的声音，又或者目标生物受到伤害时，该效应将提前终止。 如果该效应终止，或者该生物在最初的豁免中成功，则你将无法对这个生物再使用该特性，直至你完成一次长休。 | AF65: 光耀武器 | AG65: 先决条件：6级奇械师 物品：一把简易或军用武器（需同调） 在用此魔法武器发动的攻击检定和伤害掷骰获得+1加值。当持握该武器时，持用者能以一个附赠动作让它放出半径30尺的明亮照明以及该范围外30尺范围的昏暗照明。持有者也能以一个附赠动作熄灭武器的光芒。 此武器具有4发充能，当该武器的持有者被近战攻击命中之后，持用者能够立即以一个反应，消耗1发充能让攻击者对抗你的法术豁免DC进行一次体质豁免，若豁免失败，攻击者将陷入 目盲blinded 状态直到他的下个回合结束。此武器在每天的黎明时会恢复1d4发已被消耗的充能。 | AW65: =IFERROR(IF(AW64+1>BA26,IF(AW64+1>BA26,IF(AZ27+AZ64>BA27,"",AZ27+AZ64)),AW64+1),"") -> 36 | AX65: =IFERROR(INDEX(H31:AU181,AW65,AX26),"") | AY65: =IFERROR(INDEX(H31:AU181,AW65,AY26),"") | AZ65: =IFERROR(IF(AW64+1>BA26,AZ64+1,0),"") -> 0
A66: 战争领域 | B66: 5 | C66: 6 | D66: 60 | E66: =D67-1 -> 66 | G66: 36 | H66: 问道精魂 | I66: 第10级起，你获得了和你的先祖之魂进行交流的能力。当你想这么做时，你可以施展 卜筮术Augury 或 鹰眼术Clairvoyance ，且无需法术位与材料成分。这两个法术的施法属性为感知。以此施展的 鹰眼术Clairvoyance 中，作为法术描述中提及的球形探测器的代替，这个法术会在指定位置创造一个无形的先祖之魂。 一旦你使用这个特性施展了上述两者之一，直到你完成一次短休或长休为止你都不能再次使用这一特性。 | J66: 战斗风格 | K66: 第3级起，你可以选择一种战斗风格作为你的专精。选择下述战斗风格之一。即使你今后仍可有选择战斗风格的机会，你也不能多次选择同一种战斗风格。• 决斗：当你单手持一把近战武器，且不持用其他武器，你使用这把武器的武器伤害骰获得+2加值。 • 双武器战斗：当以双武器战斗时，你可以将你的属性调整值加到第二次攻击的伤害上。 | L66: 引导神力：黎明曙光 | M66: 第2级起，你可以用引导神力特性驱策阳光，以驱逐黑暗并对敌人造成光耀伤害。 作为一个动作，你可以展示你的圣徽，并驱散你身边30尺内所有源自魔法的黑暗。此外，你身边30尺内每个敌对生物都必须进行一次体质豁免。豁免失败者将受2d10＋你牧师等级的光耀伤害，豁免成功则伤害减半。相对你处于全身掩护的生物不受该效应影响。 | N66: 精魂图腾 | O66: 2级起，你获得了招现出自然精魂并借助它们影响你身边的世界的能力。 以一个附赠动作，你可以魔法般地召唤一个虚体的精魂，到处于你周围60英尺内、你能看到的一点处。 此精魂创造出一道环绕该点的、30英尺半径的光环。 精魂不算作是生物，也不算作是物体，尽管它有着符合对应生物的幽魂般的外表。 以一个附赠动作，你可以移动此精魂至多60英尺，到你能看到的一点处。 此精魂持续1分钟或直到你失能。 一旦你使用了此特性，你无法再次使用它，直到你完成一次短休息或长休息为止。 此精魂的光环效果基于你召唤的精魂的类别，如下面的选项所示。 熊精魂：熊精魂授予你和你的伙伴它的力量和坚韧。 在精魂出现时，每个处于此光环中、由你选择的生物，获得等于5+你的德鲁伊等级的临时生命值。 此外，你和你的盟友在处于光环内时，在力量检定和力量豁免检定中获得优势。 鹰精魂：鹰精魂是技艺精湛的猎手，用它敏锐的视力标记你的敌人。 当一个生物对一个处于此精魂光环内的目标进行一次攻击检定时，你可以使用你的反应让这次攻击检定获得优势。 此外，在光环内你和你的盟友得到感知（观察）检定的优势。 独角兽精魂：独角兽精魂为周围提供保护。 你和你的盟友在用于侦测在此精魂光环内的生物所进行的所有属性检定中获得优势。 此外，若你以一个法术位施展了一个为任何处于或不处于光环内的人恢复生命值的法术，每个处于光环内、由你选择的生物也恢复等于你德鲁伊等级的生命值。 | P66: 重整旗鼓 | Q66: 你在自己回合内可以使用一个附赠动作并消耗一粒卓越骰以鼓舞一名盟友的士气。 选择一名能看见你或听到你声音的盟友，并使其获得数量等于卓越骰结果＋你的魅力调整值的临时生命值。 | R66: 幽影斗篷 | S66: 第11级起，你学会如何化身为幽影。 当你处于微光光照或黑暗环境时，可以用动作变为隐形。 隐形状态将一直持续至你发动攻击、施展法术或进入明亮光照区域时结束。 | T66: 引导神力-复仇 | U66: 在第3级选择本誓言时，你获得以下两种引导神力选项。 破胆斥喝：作为一个动作，你亮出圣徽，高喊一句斥责敌人的祷言，并使用引导神力特性。 指定一个你能看见，且距离你60尺以内的生物。 目标生物必须进行一次感知豁免，除非其免疫恐慌。 邪魔和不死生物进行该豁免时具有劣势。 豁免失败者将在接下来的一分钟内陷入恐慌，直至其受到伤害。 在恐慌状态下，目标生物的速度降至0，且不能从任何增加移动速度的效应中上获益。 豁免成功，则目标生物的速度在接下来的1分钟内减半，直至其受到伤害。 仇敌誓言：作为一个附赠动作，你可以立下一个仇敌誓言，宣誓歼灭一个你可以看到，且距离你10尺以内的生物，同时使用你的引导神力。 在接下来的1分钟内，你对该生物发动攻击时进行的攻击检定具有优势，直至该生物的生命值降至0或者陷入昏迷状态。 | V66: 恐惧奇兵 | W66: 你精通于伏击的艺术。 你获得一个等同于你的感知调整值的加值在你的先攻投上。 在每一场战斗的你的第一个回合的开始，你的移动速度增加10尺，直到那个回合结束。 如果你在那个回合进行攻击动作，你可以做一次额外的武器攻击作为那一个动作的一部分。 如果那次攻击命中，目标受到额外1d8的武器伤害。 | X66: 法术窃贼 | Y66: 第17级起，你获得盗取其他施法者施法知识的能力。 当一个生物施展的一个法术以你为目标，或其法术效应范围包含你所在区域时，你可以立即用你的反应强迫该生物以其施法关键属性调整值进行一次豁免。 其DC等同于你的法术豁免DC。 若其豁免失败，则你取消该法术对你的效应。 如果该法术至少为1环且属于你可以施展的环阶（但不需要是法师法术），则你还可以盗取该法术的知识。 在接下来的8小时内，你视为习得该法术且能用你的法术位施展该法术。 而目标生物则无法施展该法术直至8小时过去。 你必须完成一次长休后才能再次使用该特性。 | Z66: 狂野魔法浪涌 | AA66: 在你第1级选择该起源开始，你施法时会释放出未经塑造的魔法浪涌。 你每次施展一个不低于1环的术士法术后，DM都可以要求你立刻骰一次d20。 如果你骰出1，则请根据表格“狂野魔法浪涌”骰出随机的魔法效应。 每回合一次，DM可以让你在施展一道1环或更高环阶术士法术后立即骰一次d20。 若你骰值为1，则按表格“狂野魔法浪涌”骰出一个魔法效应。 若该效果是一道法术，则其因过于狂野而无法受你的超魔法影响，而如果它正常情况下需要专注，则此时它无需专注。 该法术生效至其持续时间结束。 一个魔法浪涌每回合只能出现一次。 如果某个浪涌的效应是一个法术，则其狂野的本质让其无法受超魔法的影响。 如果其对应法术需要专注，则此时它并不需要专注。 以该方式生效的法术将维持至其持续时间结束。 | AB66: 千面之脸 | AC66: 你可以随意施展易容术disguise self，且无需消耗法术位。 | AD66: 直觉魅惑 | AE66: 第6级起，一个身处你周边30尺范围内你能看见的生物对你发动攻击检定时，你可以用你的反应来偏转本次攻击，前提是必须有另一生物在本次攻击的攻击范围内。 攻击者必须进行一次对抗你法师法术豁免DC的感知豁免。 豁免失败则攻击者必须转而攻击距离他最近的生物（不包括你或他自身）。 如果有多个目标离他的距离相等且都为最近，则攻击者可以从中自选一个攻击对象。 如果攻击者豁免成功，则你将无法对这个生物在使用该特性，直至你完成一次长休。 你必须在攻击确认命中与否前使用该特性。而免疫魅惑的生物也同样免疫该特性。 | AF66: 连射武器 | AG66: 物品：一把具有弹药特性的简单或军用武器（需同调） 在用此魔法武器发动的远程攻击检定和其伤害掷骰上获得+1加值，并且无视其装填特性（若有）。 如果此武器缺乏弹药，则在你持用它发起远程攻击时，它会自动创造一枚独属于它的魔法弹药。此武器创造的弹药在击中目标或失手后都会立即消失。 | AW66: =IFERROR(IF(AW65+1>BA26,IF(AW65+1>BA26,IF(AZ27+AZ65>BA27,"",AZ27+AZ65)),AW65+1),"") -> 37 | AX66: =IFERROR(INDEX(H31:AU181,AW66,AX26),"") | AY66: =IFERROR(INDEX(H31:AU181,AW66,AY26),"") | AZ66: =IFERROR(IF(AW65+1>BA26,AZ65+1,0),"") -> 0
A67: 锻造领域 | B67: 5 | C67: 6 | D67: 67 | E67: =D68-1 -> 73 | G67: 37 | H67: 先祖复仇 | I67: 第14级起，你的先祖之魂变得强大到足以打击伤害你所保护之人的敌人。当你使用 精魂之盾Spirit Shield 保护生物、降低一次攻击的伤害时，攻击者还将受到精魂之盾所降低伤害等量的力场伤害。 | J67: 剑舞 | K67: 第3级起，你学会使用你的战斗技巧和速度来进行一场令人赞叹的表演。 当你在自己回合执行攻击动作时，你的步行速度提升10尺直到该回合结束。当你在该攻击动作中发动的武器攻击命中生物时，你能选择并应用以下剑舞选项之一。每回合你只能使用一种剑舞选项。 • 守御剑舞 Defensive Flourish。 你可以消耗一次诗人激励的次数，并使该武器对你命中的目标造成额外的伤害。额外伤害等于你的激励骰掷骰结果。你的AC也会获得激励骰掷骰结果相等的加值，持续直至你的下回合开始。 • 乱击剑舞 Slashing Flourish。 你可以消耗一次诗人激励的次数，并使该武器对你命中的目标造成额外伤害，伤害等于你的激励骰投掷结果。你周围5尺范围内由你选择的其他可见生物也将受到这一额外伤害。 • 推击剑舞 Mobile Flourish。你可以消耗一次诗人激励的次数，并使该武器对你命中的目标造成额外的伤害，伤害等于你的激励骰投掷结果。你还能将目标向远离你的方向推动至多 5＋你的激励骰掷骰结果 尺。推动之后，你能立即使用你的反应移动至多等于你步行速度的距离，来到目标周围5尺范围内的一处未被占据的空间内。 | L67: 精通闪光 | M67: 第6级时，你能看见的生物在你周边30尺内攻击除你之外的某个生物时，你可以对该攻击者使用你的“守御闪光”。 | N67: 强力召唤 | O67: 6级起，你获得了召唤强力野兽和精类的能力。 任何你法术召唤或创造出的野兽或精类获得两种好处： 该生物出现时具有比正常情况下更多的生命值：它具有的每个HD会多出2点额外的生命值。 在克服对于非魔法攻击和伤害的免疫和抗力时，来自该生物天生武器的伤害被视为是魔法的。 | P67: 反击 | Q67: 当某生物对你发动近战攻击而未命中时，你可以使用反应并消耗一粒卓越骰对其发动一次近战武器攻击。如果该攻击命中，则将卓越骰加在此攻击的伤害掷骰中。 | R67: 灵机一斩 | S67: 第17级起，你可以抓住利用生物被攻击命中时的短暂停顿。 身处你身边5尺范围内的生物被除你之外的生物攻击命中时，你可以用反应对该被攻击生物发动一次近战攻击。 | T67: 坚韧复仇 | U67: 第7级起，你超自然的专注力使你可以拦截敌人撤退。 你以借机攻击中命中一个生物时，可以在该攻击后立刻移动至多相当于你速度一半的距离，本次移动是原反应的一部分。 且本次移动不引起借机攻击。 | V67: 阴影视野 | W67: 3级起，你获得60尺黑暗视觉。 如果你已经从种族特性中获得了黑暗视觉，它的范围增加30尺。 你还擅长回避依赖黑暗视觉的角色。 在黑暗中，你对于任何靠黑暗视觉观察你的角色是隐形的。 | X67: 听声辨谎 | Y67: 当你在3级选择此范型时，你的双耳变得锐利，能发现谎言。 当你进行一次感知（洞察）检定来察觉一个生物是否在说谎时，你可以将d20投中7或更低的结果都视为8。 | Z67: 混乱之潮 | AA67: 第1级起，你可以驾驭机运与混乱的力量，以使一次攻击检定，属性检定或豁免检定具有优势。 此后，你必须完成一次长休后才能再次使用该特性。 在你重获使用混乱之潮的能力前，你每次施展一个不低于1环的术士法术后，DM都可以要求你立刻骰一次狂野魔法浪涌效果。 此后，你重获使用该特性的能力。 | AB67: 万形之主 | AC67: 你可以随意施展变身术alter self，且无需消耗法术位。 先决条件：第15级 | AD67: 分裂附魔 | AE67: 第10级起，你施展一个以单一生物为目标的1环或更高环阶的附魔系法术时，可以为该法术指定第二个目标。 | AF67: 斥力之盾 | AG67: 先决条件；6级奇械师 物品：一个盾牌（需同调） 持用这面盾牌时，那个生物的AC获得+1加值 此盾牌有4发充能，当持用者被近战攻击命中后，持用者可以以一个反应消耗一发充能将攻击者击退至多15尺远。该盾牌在每日黎明时会恢复1d4发已被消耗的充能。 | AW67: =IFERROR(IF(AW66+1>BA26,IF(AW66+1>BA26,IF(AZ27+AZ66>BA27,"",AZ27+AZ66)),AW66+1),"") -> 38 | AX67: =IFERROR(INDEX(H31:AU181,AW67,AX26),"") | AY67: =IFERROR(INDEX(H31:AU181,AW67,AY26),"") | AZ67: =IFERROR(IF(AW66+1>BA26,AZ66+1,0),"") -> 0
A68: 坟墓领域 | B68: 5 | C68: 6 | D68: 74 | E68: =D69-1 -> 80 | G68: 38 | H68: 风暴灵光 | I68: 自3级起，在你狂暴期间，你会散发出一阵魔法性的灵光。它以你为中心向四周延展10尺，灵光无法穿透全掩护。 这一灵光在你进入狂暴时会激活一种效应，而你在后续的每个自己的回合中也可以用一个附赠动作再次来激活该效应。从以下三种环境中选择其一，你选择的环境类型将决定你灵光激活时会产生的效应。每当你此职业的等级获得提升时，你可以更换你选择的环境。 如果你灵光的效应需要生物进行豁免，其豁免DC等同于 8+你的熟练加值+你的体质调整值。 • 荒漠Desert。此效应激活时，你的灵光中所有其他生物都会受到2点火焰伤害。当你在这个职业达到特定等级后，这一灵光的伤害将增加：在5级后变为3点，10级后4点，15级后5点，20级后6点。 • 海洋Sea。当这个效果被激活时，你可以选择一个处于灵光中且你能看到的其他生物。目标必须通过一次敏捷豁免，豁免失败受到1d6闪电伤害，豁免成功则只受半数伤害。当你在这个职业达到特定等级后，这一灵光的伤害将增加：10级后变为2d6，15级后3d6，20级后4d6。 • 冻原Tundra。当这个效果被激活时，寒冰精魂加护于灵光中每个你选择的生物，令他们得以忍受伤害。它们获得2点临时生命值。当你在这个职业达到特定等级后，这一灵光给予的临时生命值将增加：在5级后变为3点，10级后变为4点，15级后变为5点，20级后变为6点。 | J68: 额外攻击 | K68: 第6级起，你在自己回合内执行攻击动作时可以攻击两次而非一次。 | L68: 强力施法 | M68: 第8级起，你施展牧师戏法造成伤害时，可以再加上你的感知调整值。 | N68: 精魂守卫 | O68: 10级起，你的精魂图腾会守护那些你用你的魔法呼唤出的野兽和精类。 当一个你以一道法术召唤或创造的野兽或精类在你的精魂图腾光环内结束其回合时，该生物恢复等于你德鲁伊等级一半的生命值。 | P68: 横扫攻击 | Q68: 你以近战武器攻击命中敌人时，可以消耗一粒卓越骰以尝试连带伤害附近的另一个生物。 使用此战技时，指定你触及范围内一个距离初始目标不超过5尺的生物。如果你原本的攻击检定足以命中第二个目标，则它将受到等同于你卓越骰结果的伤害。此伤害与你原本攻击的伤害类型相同。 | R68: 四象门徒 | S68: 第3级选择本宗派起，你开始学习操控元素的法门。每种法门在使用时都需要消耗气。 你会先习得元素同调法门和另一个自选法门，所有法门具体见下。你将在第6、第11、第17级时，将各习得一个新法门。 你每次习得新的法门时，还可以将一个你已知的法门替换为另一个符合选择条件的法门。 施放元素法术：某些法门让你可施展法术。通过法门施法也适用正常的施法时间和其它规则，只是你不需要提供材料成分。 第5级起，你可以通过消耗额外的气来提升以法门施展法术的环阶，使得法术更具威力。每额外消耗1点气，法术环阶就提升1级。例如，作为一名5级武僧，你通过飞炎击法门来施展法术燃烧之手。则此时你可以消耗3点气来施展2环的燃烧之手（该法门的基本消耗2加上额外消耗1）。 你以该方式施展法术可消耗气的数量上限如上表（该消耗上限包括法门的基本消耗加上额外消耗），其具体情况与你的武僧等级相关联。 气与法术 武僧等级——施法最高气消耗量 5th~8th——3 9th~12th——4 13th~16th——5 17th~20th——6 | T68: 复仇之魂 | U68: 第15级起，你立下仇敌誓言时所宣誓之存在赐予你更大的力量以击倒敌人。 一个受你仇敌誓言影响的生物发动攻击时，如果其身处你的近战武器攻击范围内，则你就可以用你的反应对其发动一次近战武器攻击。 | V68: 钢铁意志 | W68: 7级时，你已经磨炼出用来抵御来自于你的猎物的精神影响能量的能力。 你获得感知豁免熟练。 如果你已经有这项熟练，你可以获得智力或者魅力豁免熟练（取决于你）来代替。 | X68: 细致入微 | Y68: 3级起，你可以使用附赠动作来进行一次感知（观察）检定来侦测到一个隐藏的生物或物体，或者是进行一次智力（调查）检定来揭示和破译线索。 | Z68: 扭曲幸运 | AA68: 第6级起，你获得用你的狂野魔法扭曲命运的能力。 当一个你能看见的生物进行攻击检定、属性检定或豁免检定时，你可以用一个反应并消耗2术法点骰一次1d4，再将结果用作加值或减值（由你决定）加到目标生物的检定结果中。 你可以在看到检定结果后使用该特性，但必须在这次检定生效前声明。 | AB68: 混沌手下 | AC68: 你可以消耗你的邪术师法术位施展一个元素咒唤术conjure elemental。你必须完成一次长休才能再次施展该法术。 先决条件：第9级 | AD68: 编演记忆 | AE68: 第14级起，你获得让生物无法认识到你对其魔法影响的能力。 你施展一个可以魅惑一个或更多生物的附魔系法术时，可以改变某一个生物的认识，以令其无法察觉自己已经被魅惑。 此外，在法术持续时间结束前，你有一次机会可以用你的动作尝试修改被指定生物的记忆，让他忘记被魅惑期间的一些记忆。 该生物必须进行一次对抗你法师法术豁免DC的智力豁免，豁免失败则其失去一定小时的记忆，其数值为1＋你的魅力调整值（至少为1）。 你可以选择让目标忘记更短时间内的记忆，而所忘记记忆的长度不能超过该附魔法术的持续时间。 | AF68: 抗性盔甲 | AG68: 先决条件：6级奇械师 物品：一套盔甲（需同调） 穿戴该盔甲的生物对以下伤害类型中的一种具有抗性（在你为这个物品注法时选择）：强酸、冷冻、火焰、力场、闪电、黯蚀、毒素、心灵、光耀、雷鸣。 | AW68: =IFERROR(IF(AW67+1>BA26,IF(AW67+1>BA26,IF(AZ27+AZ67>BA27,"",AZ27+AZ67)),AW67+1),"") -> 39 | AX68: =IFERROR(INDEX(H31:AU181,AW68,AX26),"") | AY68: =IFERROR(INDEX(H31:AU181,AW68,AY26),"") | AZ68: =IFERROR(IF(AW67+1>BA26,AZ67+1,0),"") -> 0
A69: 奥秘领域 | B69: 5 | C69: 6 | D69: 81 | E69: =D70-1 -> 86 | G69: 39 | H69: 风暴之魂 | I69: 第6级起，不论你是否散发着灵光，风暴都能为你带来增益。这一增益效果基于你在 风暴灵光Storm Aura 特性中所选择的环境类型。 • 荒漠Desert。你获得火焰伤害的抗性，且不会受到 炎热Extreme Heat 的效应影响（其记载于《城主手册》中）。此外，你可以以一个动作，触碰一个未被他人穿戴或携带的易燃物体来点燃它。 • 海洋Sea。你获得闪电伤害的抗性，与在水下呼吸的能力。你还将获得30尺的游泳速度。 • 冻原Tundra。你获得冷冻伤害的抗性，且不会受到 严寒Extreme Cold 的效应影响（其记载于《城主手册》中）。此外，你可以以一个动作，触碰水体并将5尺立方的水冻结成冰，这种冰将会在1分钟后融化。如果该立方空间中有任何生物，这一动作将会失败。 | J69: 剑舞大师 | K69: 第14级起，当你使用剑舞选项时，你可以不消耗诗人激励次数，并投掷d6以代替选项中诗人激励骰使用。 | L69: 光冕 | M69: 第17级起，你可以用你的动作启动日光的灵光，其效应持续1分钟或直至你用另一个动作将其解散。你将释放出半径60尺的亮光光照，以及其外延伸30尺的微光光照。身处该亮光光照中的敌人，为抵抗任何火焰或光耀伤害的法术而进行豁免检定时具有劣势。 | N69: 忠诚召唤 | O69: 从14级开始，你通联的自然精魂会在你最为无助的时候保护你。 若你的生命值降到0，或非自愿地变得失能，你可以立即获得召唤野兽法术的好处，如同它是以一个9级法术位施展的那样。 它召唤出四只由你选择的、挑战等级2或更低的野兽。 被召唤的野兽出现在你周围20英尺内。 如它们没有从你那里获得命令，它们会保护你免受伤害并攻击你的敌人。 此法术持续1小时，无需专注，或直到你解消它（无需动作）。 一旦你使用了此特性，你无法再次使用它，直到你完成了一次长休息为止。 | P69: 摔绊攻击 | Q69: 你以武器攻击命中敌人时，可以消耗一粒卓越骰以尝试击倒该目标。 使用此战技时，你将所消耗的卓越骰加在此次攻击的伤害骰中。如果该目标为大型或更小体型，则其必须进行一次力量豁免。豁免失败则其应击倒地。 | R69: 寒冬之息 | S69: 你可以消耗6点气施展法术寒冰锥。（需17级） | T69: 复仇天使 | U69: 第20级起，你可以化身为复仇的天使。 你可以使用动作实行这种转变，并在接下来的1小时内获得以下增益： 你背生双翼，获得60尺飞行速度。 你散发出一个30尺半径范围的威胁灵光。 在一次战斗中，任何敌对生物第一次进入灵光范围，或者在灵光范围内开始其回合时，都必须进行一次感知豁免。 豁免失败者将在接下来的1分钟陷入对你的恐慌状态，直至受到伤害。 对因此陷入恐慌的生物所进行的任何攻击检定都具有优势。 你必须完成一次长休后才能再次使用该特性。 | V69: 追猎如风 | W69: 11级时，你学会以出人意料的速度来发动攻击以至于你能够将一次失手转化为另一次攻击。 你的每个回合一次，当你的一次武器攻击未命中时，你可以做出另一次武器攻击作为同一动作的一部分。 | X69: 战斗洞察 | Y69: 3级时，你得到了解到一个敌人的战术并加以反制的能力。 以一个附赠动作，你对于一个你能看见的，并非失能的生物进行一次感知（洞察）检定，对抗目标的魅力（欺瞒）检定。 若你成功，你可以在你并未对该生物具有优势时对他发动偷袭攻击，但在你的攻击骰有劣势时不行。 这个效果持续1分钟或直到你成功的对另一个目标使用了战斗洞察为止。 | Z69: 操控混沌 | AA69: 第14级起，你获得了对狂野魔法涌动的些微掌控。你每次骰狂野魔法浪涌效果时，可以骰两次检定再自选其一生效。 | AB69: 心灵泥沼 | AC69: 你可以消耗你的邪术师法术位施展一个缓慢术slow。你必须完成一次长休才能再次施展该法术。 先决条件：第5级 | AD69: 塑能学者 | AE69: 从第2级你选择该学派起，你向法术书中抄写塑能系法术的时间和金钱花费减半。 | AF69: 回力武器 | AG69: 物品：一把带有投掷属性的简易或军用武器 在用此魔法武器发动的攻击检定和伤害掷骰获得+1加值，并在使用它发动远程攻击后，它会立即回到持用者的手中。 | AW69: =IFERROR(IF(AW68+1>BA26,IF(AW68+1>BA26,IF(AZ27+AZ68>BA27,"",AZ27+AZ68)),AW68+1),"") -> 40 | AX69: =IFERROR(INDEX(H31:AU181,AW69,AX26),"") | AY69: =IFERROR(INDEX(H31:AU181,AW69,AY26),"") | AZ69: =IFERROR(IF(AW68+1>BA26,AZ68+1,0),"") -> 0
A70: 秩序领域 | B70: 5 | C70: 6 | D70: 87 | E70: =D71-1 -> 93 | G70: 40 | H70: 风暴之盾 | I70: 第10级起，你学会了运用你对风暴的掌控力来保护你的盟友。处于你灵光内的、由你选择的生物也将同样受益于你 风暴之魂 Storm Soul 特性所带来的伤害抗性。 | J70: 心灵之刃 | K70: 你在3级加入低语学院起，你得到了让你的武器攻击毒害生物精神的魔法能力。 当你以一次武器攻击命中一个生物时，你可以消耗一次吟游激励的次数并对目标造成额外的2d6点心灵伤害。你每轮在你的回合中只能这么做一次。 在你达到此职业的特定等级后，额外心灵伤害的值将提高，在5级后提高到3d6，10级后5d6，15级后8d6。 | L70: 自然领域法术 | M70: 牧师等级——法术 1st——化兽为友、动物交谈 3rd——树肤术、荆棘丛生 5th——植物滋长、风墙术 7th——支配野兽、擒抱藤 9th——疫病虫群、树跃术 | N70: 孢子结社法术 | O70: 你和真菌间形成了共生连接，而你踏入生死循环的能力为你带来了特定的法术。 在2级时，你学会戏法寒冷之触。 在3级，5级，7级，和9级你获得下表：孢子之环法术中对应等级列出的法术。 一旦你获得了这些法术之一，你总是准备了该法术，而其不计入你每天可准备的法术的限额中。 若你获得了一个没有出现在德鲁伊法术列表中的法术，该法术对你而言是一个德鲁伊法术。 德鲁伊等级 法术 3级 遗体防腐，目盲/耳聋术 5级 操纵死尸，气化形体 7级 枯萎术，困惑术 9级 死云术，疫病术 | P70: 伏击 | Q70: 当你进行一次敏捷（隐匿）检定或先攻检定时，你可以消耗一枚卓越骰，并将消耗的卓越骰加入本次检定中。 | R70: 北风之握 | S70: 你可以消耗3点气施展法术人类定身术。（需6级） | T70: 征服圣誓法术 | U70: 圣武士等级——法术 3——艾嘉西斯之铠，命令术 5——人类定身术，灵体武器 9——降咒，恐惧术 13——支配野兽，石肤术 17——死云术，支配人类 | V70: 暗影闪避 | W70: 15级起，伴随着一缕围绕在你身边的神奇暗影，你能以某种让人始料未及的方式躲闪。 无论何时一名角色对你做出一次攻击投掷且那次投掷没有优势，你都能用反应对其施加劣势。 你必须在知道攻击投掷的结果之前使用该特性。 | X70: 镇定之眼 | Y70: 9级时，你可以在进行任何感知（观察）检定或智力（调查）检定中得到优势，只要你在同一回合中移动不超过一半的速度。 | Z70: 法术轰击 | AA70: 第18级起，你法术中的伤害性能量极度扩张。 你在为法术进行伤害掷骰时，如果其中的任何一粒骰子掷出最大值，则选择这些骰子之一再骰一次，并将其结果加在伤害数值上。 你每回合只能使用一次该特性。 | AB70: 迷雾幻影 | AC70: 你可以随意施展无声幻影silent image，且无需消耗法术位和材料成分。 | AD70: 法术塑形 | AE70: 第2级起，你的塑能系法术作用范围里可以保留一小部分相对安全的区域。 你施展某个塑能系法术时，如果该法术的效应影响你能看见的其他生物，则你可以从中指定一定数量的生物作特殊处理。 被指定生物的数量等于1＋该法术的环阶，而被指定生物进行该法术豁免时将直接判为成功，且豁免成功伤害减半的法术此时也不对该生物造成任何伤害。 | AF70: 法力恢复戒指 | AG70: 先决条件：6级奇械师 物品：一枚戒指（需同调） 在佩戴此戒指期间，那个生物能够以一个动作恢复一个已被消耗掉的法术位。被恢复的法术位环阶必须是3环或更低环阶的法术位。一旦使用，此戒指在次日黎明前将无法再次使用。 | AW70: =IFERROR(IF(AW69+1>BA26,IF(AW69+1>BA26,IF(AZ27+AZ69>BA27,"",AZ27+AZ69)),AW69+1),"") -> 41 | AX70: =IFERROR(INDEX(H31:AU181,AW70,AX26),"") | AY70: =IFERROR(INDEX(H31:AU181,AW70,AY26),"") | AZ70: =IFERROR(IF(AW69+1>BA26,AZ69+1,0),"") -> 0
A71: 和平领域 | B71: 5 | C71: 6 | D71: 94 | E71: =D72-1 -> 100 | G71: 41 | H71: 狂怒风暴 | I71: 第14级起，你能引导的风暴之力变得更加强大，足以打击你的敌人。你获得基于你在 风暴灵光Storm Aura 特性中所选择的环境类型的增益： • 荒漠Desert。当处于你灵光中的生物在一次攻击命中你后，你可以立刻用你的反应迫使该生物进行一次敏捷豁免。豁免失败则受到等同于你野蛮人等级半数点火焰伤害。 • 海洋Sea。任何处于你灵光中的生物若被你以一次攻击击中，你可以用你的反应迫使该生物进行一次力量豁免。豁免失败时，它将如同被波浪拍打般应击 倒地Prone。 • 冻原Tundra。每当你激活你的 风暴灵光Storm Aura 时，你可以选择一个处于灵光里的你可见的生物。该生物必须通过一次力量豁免。豁免失败时，魔法的冰霜将它覆盖，使其速度降为0，持续直至你的下一个回合开始。 | J71: 惊骇之语 | K71: 第3级起，你学会了将险恶的魔法混入看似无害的语言中。一个听到你说话的生物可能会因此陷入恐惧或妄想。 若你单独的对一个类人生物交谈了至少1分钟，你可以尝试在其心灵中埋下多疑与恐惧的种子。在这次谈话的结束时，该目标必须通过一次对抗你的法术豁免DC的感知豁免，豁免失败将陷入对你或者你指定的某一生物的 恐慌Frightened ，持续1小时。如果它被攻击或伤害、它目击其盟友被攻击或伤害，这一效应将提前终止。 若一个目标对抗此效应的豁免成功，该目标不会察觉到你曾试图惊吓他的行为。 一旦你使用了此特性，直到你完成一次短休或长休前你都不能再次使用它。 | L71: 自然侍僧 | M71: 第1级时，你习得一个自选的德鲁伊戏法。你还可以获得以下技能之一的熟练项：驯兽、自然、生存。这个戏法不计入你的已知戏法数量中。 | N71: 孢子光晕 | O71: 从2级起，你被无形的坏死的孢子包围着，直到你把他们释放到附近的生物上。 当一个生物进入你的10英尺内时，或在其中开始其回合时，你可以使用反应来激发孢子光晕特性。 造成1d4点暗蚀伤害，除非其通过一个等同于你法术DC的体质豁免。 此伤害在6级时提高到1d6，在10级时提高到1d8，在14级时提高到1d10。 | P71: 换位诈术 | Q71: 在你自己的回合中，若你身旁有某个盟友处于你周围5尺范围内，你就能够消耗一枚卓越骰并消耗至少5尺的移动力，来与那个盟友互换位置，这次移动不会引发借机攻击。 投掷那枚被消耗的卓越骰。直到你的下个回合开始前，你或被互换位置的另一生物（由你选择）的AC获得等于卓越骰结果的加值。 | R71: 元素同调 | S71: 你可以用动作短暂操控身边30尺内的元素之力，并产生下列效应之一： • 用土、水、气、火创造一次无害的瞬间视听效应，比如火花闪现、清风吹拂、青雾飘散、岩石轰隆。 • 瞬间点燃或吹熄蜡烛，火炬或小型营火。 • 加热或降温至多1磅无生命的物质，至多持续1小时。 • 将土，水，雾或火按照你的心意塑形成至多1尺立方的粗糙形状，至多持续1分钟。 | T71: 引导神力-征服 | U71: 在3级选择本誓言时，你获得以下两种引导神力选项。 引导神力如何运作，参见神圣誓约职业特性。 征服威压：你可以使用你的引导神力来发出一阵可怕的威压。 以一个动作，你强迫每个处于你周围30英尺内、你能看见的、由你选择的生物各进行一次感知豁免检定。 若豁免失败，目标变得恐慌于你，持续1分钟。变得恐慌的生物可以在其每个回合的结束时重复此豁免检定，成功则结束其身上的此效果。 神助打击：你可以使用你的引导神力来以超自然的精确性进行打击。 当你进行一次攻击检定时，你可以使用你的引导神力以在此检定中得到+10加值。 你在你看到掷骰后进行决定，但需要在DM宣布此攻击命中与否前声明。 | V71: 边界行者魔法 | W71: 3级起，你学会一个额外法术当你到达指定游侠等级时，如边界行者法术列表所示。 这些法术对你视为游侠法术，它不计入你的已知法术总数中。 游侠等级——法术 3级——防护善恶 5级——迷踪步 9级——加速术 13级——放逐术 17级 ——传送法阵 | X71: 精准之眼 | Y71: 13级时，你得到侦测魔法欺瞒的能力。 以一个动作，你感知到你周围30英尺内的幻术存在，不在天生形态下的变形生物，和其他意在欺瞒感官的魔法，前提是你没有目盲或耳聋。 你能了解到了有一个效果正在试图欺骗你，不过你并没有得到对其后所掩盖的真相和对他真实本质的特殊洞察力。 你可以使用这个功能的次数等于你的感知调整值（至少一次），当你完成一次长休，你重新获得所有次数。 | Z71: 神圣魔法 | AA71: 你对于神力的联系允许你学习通常与牧师职业相关的法术。 当你的施法特性让你学会一个术士戏法或一个1级或更高级的术士法术时，在术士法术列表之外，你可以从牧师法术列表中选择新法术。 除此之外，你必须满足选择该法术的所有限制，而它对你而言成为一个术士法术。 此外，选择一种对你神力来源的亲和力：善、恶、守序、混乱或中立。 你可以根据这个关联，学习一个额外的法术，如下所示。 这对你来说是一个术士法术，但它不与你术士法术的数量有关。 如果你以后替换了这个法术，你必须用牧师的法术列表来替换它。 亲和力——法术 善良：治疗伤口 邪恶：造成伤口 秩序：祝福术 混乱：灾祸术 中立：防护善恶 | AB71: 融身入影 | AC71: 身处微光或黑暗环境时，你可以使用动作进入隐形，其效应持续至你进行移动、执行动作或执行反应时终止。 先决条件：第5级 | AD71: 强力戏法 | AE71: 第6级起，你造成伤害的戏法可以影响本可免受戏法效应影响的生物。 生物对抗你戏法的豁免成功时，它仍将受到一半伤害（若有），但仍不会受该戏法的其他效应影响。 | AF71: 复制魔法物品 | AG71: 先决条件：见下 使用此注法，你能够复制一个特定的魔法物品。 你能够多次学习此注法；每次这样做时，你需要从下面的可复制魔法物品表中选择一个不同的魔法物品。 如果表格的标题中有一个等级，那么你必须到达该等级才能在这个表格中选择一个魔法物品。 另外，你也可以选择一个游戏中存在且并非卷轴或药水的普通级魔法物品。 在表格中，物品的条目会告诉你该项目是否需要调谐。 有关该物品的更多信息，包括制作该物品所需的物品类型，请参阅《地下城主指南》中的物品描述。 复制魔法物品（2级奇械师）——调谐 炼金壶——否 次元袋——否 水下呼吸帽——否 夜视镜——否 攀爬绳——否 传讯石——否 侦测魔法魔杖——否 探秘魔杖——否 复制魔法物品（6级奇械师）——调谐 精灵靴——否 精灵斗篷——是 蝠鲼斗篷——否 魅惑镜片——是 窃贼手套——否 显像提灯——否 颤栗乐笙——否 水行戒指——否 复制魔法物品（10级奇械师）——调谐 跳跑靴——是 雪地之靴——是 射手护腕——是 护盾胸针——是 防护斗篷——是 鹰眼镜片——是 食人魔力量手套——是 辟矢夺箭手套——是 运动健将手套——是 易容帽——是 智力头带——是 心灵感应头盔——是 读心勋章——是 适应项链——是 愈合护符——是 唤鼠乐笙——是 艾罗娜的箭袋——否 跳跃戒指——是 心灵护盾戒指——是 蛛行鞋——是 飞翼靴——是 复制魔法物品（14级奇械师）——调谐 健康护符——是 山丘巨人之力腰带——是 浮空靴——是 速度之靴——是 防御护腕——是 蝙蝠斗篷——是 次元镣铐——否 真视宝石——是 音爆号角——否 自由行动戒指——是 防御戒指——是 公羊戒指——是 | AW71: =IFERROR(IF(AW70+1>BA26,IF(AW70+1>BA26,IF(AZ27+AZ70>BA27,"",AZ27+AZ70)),AW70+1),"") -> 42 | AX71: =IFERROR(INDEX(H31:AU181,AW71,AX26),"") | AY71: =IFERROR(INDEX(H31:AU181,AW71,AY26),"") | AZ71: =IFERROR(IF(AW70+1>BA26,AZ70+1,0),"") -> 0
A72: 暮光领域 | B72: 5 | C72: 6 | D72: 101 | E72: 108 | G72: 42 | H72: 战狂道途 | I72: 只有矮人才可以选择战狂道途。在矮人的社会和文化中战狂占据了一个特殊的位置。 你的DM可以调整这一规则使之更符合战役。 | J72: 低语光环 | K72: 第6级时，你得到了吸取类人生物的人格的能力。当一个类人生物在你周围30尺内死去时，你可以使用你的反应，魔法性的捕获其影。直到你完成了一次长休或你使用掉它为止你能一直抓住这道影子。 你可以以一个动作使用这道影子。当你这么做时，影子将消散，并化作一具完美的伪装覆盖在你的身上。现在，你看起来就像是那个死去的人物生前健康活着的状态一样。伪装效应将持续1小时。你可以以一个附赠动作提前结束此效应。 当你处于伪装中，你会获得所有该生物会与他人分享的信息。这包括了其背景和人生的一般细节，但不包括秘密。这些信息足够你借用它的记忆来伪装成该生物。 其他生物可以通过进行一次感知（洞悉）检定对抗你的魅力（欺瞒）检定，以此来看穿此伪装。不过你在你的这一检定中具有+5加值。 一旦你使用此特性捕获了一道影子，直到你完成一次短休或长休前你都不能再捕获另一道影子。 | L72: 附赠熟练项 | M72: 第1级起，你获得重甲的熟练项。 | N72: 一体共生 | O72: 在2级时，你获得了向体内的孢子引导魔法的能力。 当你使用你的荒野形态特性时，你可以唤醒这些孢子，而非进行变形。 当你这样做的时候，你每在此职业上具有一个等级便获得4点临时生命值。 当你这样做时，你获得下列好处： 当你的孢子光晕特性造成伤害时，额外骰一个伤害骰加在原有的伤害骰上。 并且你的近战武器攻击对任何被击中的目标造成额外的1d6点暗蚀伤害。 这些好处持续10分钟，或直到你失去所有临时生命值或再次使用了你的荒野形态。 | P72: 警戒 | Q72: 当一个生物移动进你的触及范围而你手握武器时，你能以一个反应消耗一枚卓越骰对该生物进行一次武器攻击。如果攻击命中，将消耗的卓越骰加入此次攻击的伤害掷骰中。 | R72: 苍山庇佑 | S72: 你可以消耗5点气对自身施展石肤术。（需17级） | T72: 征服光环 | U72: 从7级起，只要你并未失能，你便弥漫出一阵威吓的灵光。 光环包括你的格子，从你向各个方向延伸10英尺，它会被全掩蔽所阻挡。 若一个生物恐慌于你，当其处于此光环内，其速度降为0，若其在光环内开始其回合，则受到等于你圣武士等级一半的心灵伤害。 在18级，此光环的距离增加到30英尺。 | V72: 侦测传送门 | W72: 在3级时，你获得侦测传送门的魔法灵光的能力。 以一个动作，在离你1英里的范围内，你侦测到离你最近的传送门的距离和方向。 你使用这一特性后，你无法再次使用直到你进行完一次短休或长休。 | X72: 识破弱点 | Y72: 17级时，你学会通过认真的研究一个生物的战术和移动来找到他的弱点的能力。 当你的战斗洞察对一个生物使用时，你对该生物的偷袭伤害提高3d6。 | Z72: 众神眷恩 | AA72: 从1级起，神圣力量指引着你的命运。 若你未通过一次豁免检定或在一次攻击检定中失手，你可以投2d4，并将它加到总值上，这可能会改变结果。 一旦你使用了此特性，你无法在完成一次短休息或长休息前再次使用它。 | AB72: 超凡跳跃 | AC72: 你可以随意以自身为目标施展跳跃术jump，且无需消耗法术位和材料成分。 先决条件：第9级 | AD72: 强效塑能 | AE72: 第10级起，你施展任何塑能系法师法术时，可以将你的智力调整值加到该法术的其中一次伤害掷骰中。 | AF72: 工具精通 | AG72: 当你在第三级选择此专业时，你获得炼金工具的熟练。 如果你已经拥有此熟练，作为代替，你能获得另一种工匠工具的熟练。 | AW72: =IFERROR(IF(AW71+1>BA26,IF(AW71+1>BA26,IF(AZ27+AZ71>BA27,"",AZ27+AZ71)),AW71+1),"") -> 43 | AX72: =IFERROR(INDEX(H31:AU181,AW72,AX26),"") | AY72: =IFERROR(INDEX(H31:AU181,AW72,AY26),"") | AZ72: =IFERROR(IF(AW71+1>BA26,AZ71+1,0),"") -> 0
A73: 大地结社 | B73: 7 | C73: 8 | D73: 20 | E73: =D74-1 -> 25 | G73: 43 | H73: 战狂装甲 | I73: 从3级起，你得到将钉刺甲作为武器使用的能力。 当你穿着钉刺甲并在狂暴中，你可以使用你的附赠动作用钉刺甲对5尺内的目标进行一次近战武器攻击。若攻击命中，钉刺将造成1d4的穿刺伤害。把你的力量调整加在武器的攻击和伤害骰上。 另外，当你使用攻击动作去擒抱一个生物，你在擒抱检定成功时对他造成3点穿刺伤害。 钉刺甲是一种罕见的中甲，它们出自矮人工匠之手，造型看上去像是覆盖了金属尖刺的皮革外套和护腿。 价格：75gp AC：14+敏捷调整值（最大+2） 潜行：劣势 重量：45磅 | J73: 阴暗学识 | K73: 第14级起，你学会了在言语中织入黑暗魔法激发一个生物内心最深处的恐惧。 以一个动作，你对一个30尺内，能听见你的声音的生物发出一段魔法低语。目标必须进行一次对抗你的法术豁免DC的感知豁免。若它与你没有共通的语言、或是它不能听见你的声音，它的豁免将自动成功。豁免成功时，你的低语声听起来就像是一段不知所云的呢喃，且没有任何效果。 豁免失败时，他将被你 魅惑Charmed ，持续8小时。如果你或你的盟友攻击了它、伤害了它、或是迫使它进行一次豁免检定这一状态也将提前结束。他认为这段低语描述了他最为困窘的秘密。尽管你并不会因此了解到这个秘密是什么，但是目标会坚信你已经知道了。 当被以此法魅惑时，该生物因为畏惧你会公开他的秘密而遵循你的命令。不过它不会为了你而进行危及自身性命的事，也不会为你战斗（除非他已经倾向于这么做了）。它会视你为挚友，并会像密友那样提供关爱和恩惠。 当此效应结束时，该生物将无法明白为何他会对你如此恐惧。 一旦你使用了此特性，直到你完成一次长休前你都不能再次使用它。 | L73: 引导神力：魅惑动植物 | M73: 第2级起，你可以用引导神力特性魅惑动物和植物。 作为一个动作，你可以展示你的圣徽同时呼唤守护神之名。身处你身边30尺内每个你能看见的野兽或植物生物都必须进行一次感知豁免。豁免失败者将受你魅惑，该魅惑状态将持续1分钟或直至其受到伤害。受你魅惑时，该生物对你及你指定的生物均保持友善。 | N73: 真菌感染 | O73: 在6级时，你的孢子获得了感染并活化遗体的能力。 如果一个小型或中型的野兽或类人生物在你十尺内死亡，你可以以一个反应动作活化它，令它站起并具有1点生命值。 该生物使用MM中僵尸的属性，它将持续活化状态1小时，之后会倒下死去。 在战斗中，它的回合紧接着你的。 它遵从你的精神指令，而它只能进行攻击动作，进行一次近战攻击。 该特性的可用次数等于你的感知调整值（至少一次）。 而已消耗的特性使用次数则可以通过完成一次长休进行恢复。 | P73: 领导风范 | Q73: 当你进行一次魅力（威吓）、魅力（表演）或魅力（说服）检定时，你能够消耗一枚卓越骰，将消耗的卓越骰加入此次属性检定中。 | R73: 火蛇利牙 | S73: 你在自己回合内执行攻击动作时，可以消耗1点气使得火焰触须从四肢喷涌而出。在本回合余下时间里，你进行徒手打击时的触及范围增加10尺。 而这些攻击造成的伤害变为火焰伤害，而非钝击伤害。若在攻击命中时再消耗1点气，则该次攻击还可额外造成1d10的火焰伤害。 | T73: 轻蔑呵斥 | U73: 从15级起，那些胆敢击中你的人，将在心灵上因为无礼而受到惩罚。 当一个生物以一次攻击击中你时，若你并未失能，该生物受到等于你魅力调整值（最小为1）的心灵伤害。 | V73: 位面战士 | W73: 3级起，你学会通过吸取多元宇宙的能量来强化你的攻击。 以一个附赠动作，选择一名在你30尺范围内对你可见的角色，这回合你对其的下一次武器攻击造成的伤害变成力场伤害，且目标额外受到来自于该攻击的1d8力场伤害，当你的游侠等级到达11级时，额外伤害变成2d8。 | X73: 阴谋大师 | Y73: 从3级起，你可以得到易容工具、文书伪造工具和一种自选赌博工具的熟练。 你同时可以学会两种自选语言。 此外，如果你听到一个生物讲话长于1分钟，你可以确切无误地模仿他的语气和口音。 这允许你模仿来自某个特殊地区的特别口音，只要你知晓这种语言。 | Z73: 强效治疗 | AA73: 6级起，你可以通过神圣之力增幅治疗法术。 当你或你的盟友在你周围5英尺内掷骰子来决定法术恢复hp点数的时候，只要你没有失能，你便可以花费1个术法点，重扔其中任意数量的骰子。 每轮只能使用一次该能力。 | AB73: 斥力魔爆 | AC73: 施展魔能爆eldritch blast时，你可以将被命中的生物沿直线往远离你的方向推动至多10尺。 先决条件：习得戏法 魔能爆 | AD73: 超限导能 | AE73: 第14级起，你可以为你的简单法术增强力量。 施展一个造成伤害的1~5环法师法术时，你可以让法术的伤害直接取其最大值。 该特性不能作用于戏法。 首次发动该特性时，你并不会承受任何减益。 如果你在完成一次长休前再次使用此特性，则你将在施法完成后立刻受到等于该法术每环阶2d12点黯蚀伤害。 你在完成一次长休前，每再使用一次该特性，每环阶的黯蚀伤害就增加1d12。这种反噬伤害将无视任何的抗性和免疫。 | AF73: 炼金师法术 | AG73: 第3级起，只要你达到相应的职业等级，炼金师法术表格中的法术总是被视为已准备。 这些法术对你来说是奇械师法术，且不会计入你可以准备法术的总数。 奇械师等级 法术 3级 治愈真言，致病射线 5级 炽焰法球，马友夫强酸箭 9级 气化形体，群体治愈真言 13级 枯萎术，防死结界 17级 死云术，死者复活 | AW73: =IFERROR(IF(AW72+1>BA26,IF(AW72+1>BA26,IF(AZ27+AZ72>BA27,"",AZ27+AZ72)),AW72+1),"") -> 44 | AX73: =IFERROR(INDEX(H31:AU181,AW73,AX26),"") | AY73: =IFERROR(INDEX(H31:AU181,AW73,AY26),"") | AZ73: =IFERROR(IF(AW72+1>BA26,AZ72+1,0),"") -> 0
A74: 月亮结社 | B74: 7 | C74: 8 | D74: 26 | E74: =D75-1 -> 30 | G74: 44 | H74: 凶蛮无羁 | I74: 从6级起，当你在狂暴期间使用 鲁莽攻击Reckless Attack 时，你还可以得到等同于你的 体质调整值（最少1点） 点的临时生命。这一临时生命值在你狂暴结束后还剩余一部分时，剩余部分会消失。 | J74: 潜能微尘 | K74: 第3级起，每当你给予一个生物诗人激励骰时，你可以唱出造物之歌的一个音符，创造一团微小的潜能微尘，在那个生物五尺以内的轨道上环绕。这个微尘是无形且不可被摧毁的，它将在这个诗人激励骰被消耗掉前一直存在。这团微尘看起来像一个音符，或是一颗星星，一朵花，抑或其他任何一种艺术或者生命的符号，这将由你来决定。 当这个生物使用那个诗人激励骰时，这团微尘将会根据这个诗人激励骰被使用的方式即用于属性检定、攻击检定还是豁免检定产生不同的额外效果。具体细节如下所示： • 属性检定：当该生物将诗人激励骰用于增益属性检定时，他可以重新掷一次诗人激励骰并且选择使用其中一个掷骰结果，这团微尘会炸开，发射出多彩而无害的闪光。 • 攻击检定：当该生物将诗人激励骰用于增益攻击检定时，掷出诗人激励骰后，这团微尘会立刻如雷霆般破碎，该生物这次攻击的目标以及其5尺距离内你能看到的由你决定的所有生物必须进行一次体质豁免，其DC为你的施法DC，如果豁免失败，将会承受等同于该诗人激励骰子所掷结果的雷鸣伤害。 • 豁免检定：当该生物将诗人激励骰用于增益豁免检定时，掷出诗人激励骰后，这团微尘会立刻伴随着一段舒缓的音乐消失不见，给予这个生物等同于该诗人激励骰子所掷结果加上你的魅力调整值的临时生命值（最低为1）。 | L74: 抑制元素 | M74: 第6级起，身处你或身处你身边30尺内的一个生物受到强酸，冷冻，火焰，闪电或雷鸣伤害时，你可以用你的反应使该生物在本次伤害过程中对该伤害类型具有抗性。 | N74: 扩散孢子 | O74: 在10级时，你获得了在一片区域内散布致命的孢子的能力。 当你的一体共生特性处于开启状态下，你可以用一个附赠动作，将真菌孢子抛向至多30英尺外，它们将漂浮在那里10英尺见方的空间中，持续1分钟。 若你再次使用此特性，或使用一个附赠动作取消掉，或你的一体共生特性不再起作用，这片孢子将提前消失。 任何在此空间内开始其回合的生物受到你的孢子光晕伤害，除非其通过一个等同于你法术DC的体质豁免，一个生物每轮只能受到一次该伤害。 只要这片孢子存在，你就不能使用你孢子光晕的反应动作。 | P74: 擒拿击 | Q74: 当你在一次近战武器攻击命中一个生物时，你能够立即消耗一枚卓越骰，以一个附赠动作对目标进行一次擒抱（见玩家手册的擒抱规则）。将消耗的卓越骰加入你的力量（运动）检定中。 | R74: 四雷拳 | S74: 你可以消耗2点气施展雷鸣波。 | T74: 不移胜者 | U74: 在20级时，你得到驾驭特异武艺的能力。 以一个动作，你可以魔法性的变成征服的化身，获得下述的好处，持续1分钟： 你对于所有伤害得到抗力。 当你在你的回合进行攻击动作时，你可以进行一次额外的攻击，作为该动作的一部分。 你的近战武器攻击在掷出19或20时即可造成重击。 一旦你使用了此特性，直到你完成了一次长休息后不能再使用它。 | V74: 灵界漫步 | W74: 在7级时，你学会如何进入灵界位面。 以一个附赠动作，你能够以这个特性不消耗法术位施放同游灵界，但是这个法术在当前回合结束时结束，你使用该特性后，你无法再次使用直到你进行完一次短休或长休。 | X74: 战术大师 | Y74: 从第3级开始，你可以把协助动作作为附赠动作使用。 此外，当你使用协助动作帮助一个盟友攻击一个生物时，如果目标可以看到你或者听到你的话，攻击的目标可以在30尺以内，而不是你的5尺之内。 | Z74: 神圣之翼 | AA74: 14级起，你可以使用一个附赠动作，在你的背部展现一对光翼。 当光翼展现时，你具有30ft的飞行速度。 它们会一直展现着，直到你失能、死亡、或者你以一个附赠动作遣散。 你为你神圣魔法的特性所选择的亲和力，决定了光翼的外观：鹰翼属于善良或守序，蝠翼属于邪恶或混乱，中立则是蜻蜓的翅膀。 | AB74: 重塑血肉 | AC74: 你可以消耗你的邪术师法术位施展一个变形术polyorph。你必须完成一次长休才能再次施展该法术。 先决条件：第7级 | AD74: 幻术学者 | AE74: 从第2级你选择该学派起，你向法术书中抄写幻术系法术的时间和金钱花费减半。 | AF74: 实验性灵药 | AG74: 第3级起，每当你完成一次长休，你能在一个你接触的空的 扁瓶flask 中魔法性的制造出一瓶实验性灵药通过实验性灵药表来掷骰决定这瓶灵药在被某人饮用时的效果。 生物能以一个动作饮用这瓶灵药、或是将灵药灌给一个失能生物饮用。 你能通过消耗一枚1环或更高环的法术位来制造额外的实验性灵药。 此时，你以一个动作接触一个空的 扁瓶flask ，在其中充入灵药，然后从实验性灵药表中选择这瓶灵药的效果。 你必须要拥有炼金工具才能制造实验性灵药，你通过此特性创造的任何灵药会一直存在，直到被饮用、或是你的下一次长休结束时。 当你在本职业达到某些特定等级时，你将能够在长休结束时制造更多灵药：6级时2瓶，15级时3瓶。 每一瓶灵药都需要掷骰决定效果，且都需要用独立的 扁瓶flask 盛放。 实验性灵药 d6 效果 1 治疗。饮用者恢复等同于 2d4+你智力调整值 的生命值。 2 疾速。饮用者的速度增加10尺，持续1小时。 3 韧性。饮用者的AC获得+1加值，持续10分钟。 4 气魄。饮用者在接下来的一分钟内，能够在每个攻击检定与豁免检定中投掷一枚d4并将结果加入到检定中。 5 飞行。饮用者获得10尺飞行速度，持续10分钟。 6 变形。饮用者的身体产生如同受到法术变身术Alter Self一样的变化。法术的变化具体怎样由饮用者决定，该效果会持续10分钟。 | AW74: =IFERROR(IF(AW73+1>BA26,IF(AW73+1>BA26,IF(AZ27+AZ73>BA27,"",AZ27+AZ73)),AW73+1),"") -> 45 | AX74: =IFERROR(INDEX(H31:AU181,AW74,AX26),"") | AY74: =IFERROR(INDEX(H31:AU181,AW74,AY26),"") | AZ74: =IFERROR(IF(AW73+1>BA26,AZ73+1,0),"") -> 0
A75: 梦境结社 | B75: 7 | C75: 8 | D75: 31 | E75: =D76-1 -> 34 | G75: 45 | H75: 战狂冲锋 | I75: 从10级起，你在狂暴期间可以以附赠动作执行疾走动作。 | J75: 造物表演 | K75: 第3级起，以一个动作，你可以引导造物之歌的魔力来创造一个你选择的非魔法物品，它会在你选择的距离你10尺内的一处未被占据的空间里生成。它必须要生成在液体中或是表面上的一个可以支撑它的地方。这件物品的价值不能超过你吟游诗人等级的二十倍gp，而且必须是中型或者更小的物品。这件物品会闪烁着柔和的微光。当一个生物触碰它的时候，会听到轻微的音乐。在被创造出等同于你的熟练加值数的小时之后，这件物品会消失。你可以通过此方法创造的各种物品，玩家手册中的装备章节里的物品大多数物品就是很好的例子。 每当你用这一特性创造出一件物品后，直到下一次长休结束前你都不能再次使用这个能力。你也可以消耗一个2环或者更高级的法术位去再次使用这个能力。你同时只能保持一件以此法被创造出的物品。如果在你使用这个能力创造物品时已经有一件被创造出来的物品了，那么那个旧的物品会立刻消失不见。 你创造的物品都大小限制会随着你的吟游诗人等级提高而增长。6级时你可以创造出大型物品，14级时你可以创造去巨型物品。 | L75: 神圣打击 | M75: 第8级起，你可以使你的武器充满神圣能量。你在每个自己回合里有一次机会，可以在用武器攻击命中某生物时，使该攻击额外造成1d8点冷冻，火焰或闪电伤害（由你选择）。14级时，该伤害提升到2d8。 | N75: 真菌之躯 | O75: 在14级，你体内的真菌改变了你：你不再会被目盲，耳聋，恐慌，或中毒；若一次攻击对你造成重击，它不会对你造成额外伤害除非你处于失能状态。 | P75: 快手投掷 | Q75: 以一个附赠动作，你能消耗一枚卓越骰以一件具有投掷属性的武器进行一次远程攻击。在进行此攻击时，你能拔出一把投掷武器作为攻击的一部分。如果此次攻击命中，你能将消耗的卓越骰加入此次攻击的伤害掷骰中。 | R75: 凝气刚拳 | S75: 你可以将大气凝聚成拳进行打击。作为一个动作，你可以消耗2点气并指定一个在你身边30尺内的生物。 该生物必须进行一次力量豁免，豁免失败者将受到3d10点钝击伤害，此外你每额外消耗1点气则再增加1d10点钝击伤害，并且可以将目标从远离你的方向推开至多20尺再使其倒地。豁免成功则伤害减半，且不会被推离和击倒。 | T75: 救赎圣誓法术 | U75: 圣武士等级——法术 3——庇护术，睡眠术 5——安定心神，人类定身术 9——法术反制，催眠图纹 13——欧提路克弹力法球，石肤术 17——怪物定身术，力墙术 | V75: 闪现打击 | W75: 在11级时，你能够在眨眼之间穿梭于两个位置。 当你进行攻击动作时，你能够在每一次攻击前传送10尺到一片对你可见的空地上。 如果你用一个动作攻击了至少两名不同的角色，你可以额外攻击一次第三名角色。 | X75: 洞察力 | Y75: 从第9级开始，如果你至少花1分钟观察或与战斗之外的其他生物进行交互，你可以了解到跟你自己的能力相比较的某些信息。 DM告诉你，在你选择的下列两个特征中，是否你的相等、优越或低等： 智力值 感知值 魅力值 职业等级（如果有的话） 如果你的DM允许，你也有可能知道这个生物的一段经历或者它的一个性格特征，如果它有的话。 | Z75: 神秘复原 | AA75: 18级起，你具备了克服重伤的能力。 当你的hp不足一半时，以一个附赠动作，你可以获得等同于你一半生命值的生命。 一旦你使用了这个特性，你就不能再使用它，直到你完成一次长休息。 | AB75: 凶兆符记 | AC75: 你可以消耗你的邪术师法术位施展一个降咒bestow curse。你必须完成一次长休才能再次施展该法术。 先决条件：第5级 | AD75: 精通次级幻影 | AE75: 从第2级你选择该学派起，你习得戏法次级幻影。 如果你已学会此戏法，则你可以学习另一个自选的法师戏法。 该戏法不计入你的已知戏法数目限制。 你施展戏法次级幻影时，可以在一次施法中同时创造出声音和影像。 | AF75: 炼金术掌握 | AG75: 第5级起，你对魔法化学物质的掌握变得非常熟练，这使得你通过炼金物质造成的治疗和伤害更加有效。 当你使用炼金工具作为法器施展任何法术时，你在法术的一次掷骰中获得等同于你的智力调整值（最低+1）的加值。该掷骰必须是恢复的生命值量，或是造成强酸、火焰、黯蚀、或毒素伤害。 | AW75: =IFERROR(IF(AW74+1>BA26,IF(AW74+1>BA26,IF(AZ27+AZ74>BA27,"",AZ27+AZ74)),AW74+1),"") -> 46 | AX75: =IFERROR(INDEX(H31:AU181,AW75,AX26),"") | AY75: =IFERROR(INDEX(H31:AU181,AW75,AY26),"") | AZ75: =IFERROR(IF(AW74+1>BA26,AZ74+1,0),"") -> 0
A76: 牧人结社 | B76: 7 | C76: 8 | D76: 35 | E76: =D77-1 -> 39 | G76: 46 | H76: 钉刺反冲 | I76: 从14级起，狂暴期间，若你未处于失能状态、且穿着钉刺甲，当你周围5尺范围内有生物用近战攻击命中你时，攻击者将受到3点穿刺伤害。 | J76: 活化表演 | K76: 第6级起，以一个动作，你可以选择你30尺内一个你可以看见大型或者更小的非魔法物品，赋予其生命。 这件活化的物品将会使用如下舞空物品的属性，并且使用你的熟练加值。 这件物品将会对你以及你的伙伴保持友好，而且会听从你的命令。 它将持续保持活性一个小时，如果期间其生命值降低为0，或者你死亡，则该物品失去活性。 在战斗中，该物品将会与你共用先攻，它会紧随在你的回合后行动。 它可以自行移动并执行自己的反应，不过在它的回合它只会进行回避动作。 除非使用附赠动作对它发出命令，他可以做其动作列表中的动作，当然你也可以命令它做其他事情。 如果你的角色失能昏迷了，那么这件活化物品会做其他动作，不仅仅是回避动作。 当你使用附赠动作发出诗人激励时，作为发出诗人激励的附赠动作的一部分，你同时也可以对这个活化物品发出指令。 每当你用这一特性活化一件物品后，直到下一次长休结束前你都不能再次使用这个能力。 你可以消耗一个3环或者更高级的法术位去重制这个能力的使用次数。 你同时只能保持一件以此法被活化的物品，如果在你使用这个能力活化物品时已经有一件被活化的物品了，那么那个旧的物品会立刻停止不动，变回死物。 | L76: 自然大师 | M76: 第17级起，你获得命令动物和植物生物的能力。 当生物受你的魅惑动植物特性魅惑时，你可以在自己回合内执行一个附赠动作并发出一个口头指令，而所有这些受魅惑生物都将在其下一回合执行该指令。 | N76: 星图 | O76: 第2级起，作为你天文学研究的一部分，你创造了一张星图。它是一个微型物体，可以用作你施展德鲁伊法术时的法器。你通过在星图列表上掷骰或选择一个来确定它的形态。 当你持握这件星图时，你获得这些好处： • 你习得戏法 神导术guidance • 你时刻准备着 光导箭guiding bolt这个法术，它对你来说视为一个德鲁伊法术，且不计入你的每日准备法术上限。 • 你可以施展数次 光导箭guiding bolt 无而无需消耗法术位。其次数等同于你的熟练加值次，在你完成一次长休后你会重获全部已消耗使用次数。 如果你丢失了星图，你可以举行一场为时一小时的仪式来使用魔法创造一个替代品。这一仪式可以在一场短休或长休时举行，并会摧毁先前的星图。 星图形态 D6——星图样式 1：一幅布满星座图列的卷轴。 2：一块钻有细孔的石板 3：一张斑点枭熊皮，标有凸痕记号 4：一套黑檀木封皮地图集 5：一块遇光会投射出星辰轨迹的水晶 6：描绘星座排列的玻璃圆盘 | P76: 战术预估 | Q76: 当你进行一次智力（调查）、智力（历史）或感知（洞悉）检定时，你能够消耗一枚卓越骰，将消耗的卓越骰加入此次属性检定中。 | R76: 凤凰烈焰 | S76: 你可以消耗4点气施展火球术。（需11级） | T76: 引导神力-救赎 | U76: 在3级选择本誓言时，你获得以下两种引导神力选项。 引导神力如何运作，参见神圣誓约职业特性。 和平使节：你可以使用你的引导神力来以神圣力量增强自己的存在。 以一个附赠动作，你为自己在接下来的10分钟内进行的下次魅力（说服）检定中提供+5加值。 斥喝暴力：你可以使用你的引导神力来斥喝那些使用暴力的人。 当一个处于你周围30英尺内的敌人以一次攻击对一个你之外的生物造成伤害时，以一个反应，你强迫攻击者进行一次感知豁免检定。 检定失败则攻击者受到等同于其刚刚造成的伤害的光耀伤害。 成功则受到一半伤害。 | V76: 虚体防御 | W76: 15级时，你的空间传送能力能让你在战斗中流转于空间边缘以减少伤害。当你受到一次攻击伤害时，你可以用你的反应来给予你对那次攻击全部伤害的抗性在这一回合。 | X76: 误导 | Y76: 从13级起，你的急才有时候能让另一个生物代替你承受攻击。 每当你成为一次攻击的目标，并且在你的5尺距离内有生物为你对抗这次攻击提供了掩蔽，你可以使用你的反应将这次攻击的目标转移给这个生物。 | Z76: 幽暗之瞳 | AA76: 1级起你获得120尺黑暗视觉。 当你在该职业3级时，你掌握了黑暗术，这不会占用你术士已知法术数量。 你可以用2点术法点或1个法术位来释放。 当你用法术点施法时，你能够看穿该法术所制造的黑暗。 | AB76: 命运窃贼 | AC76: 你可以消耗你的邪术师法术位施展一个灾祸术bane。你必须完成一次长休才能再施展该法术。 | AD76: 易变幻象 | AE76: 第6级起，你施展持续时间不少于1分钟的幻术系法术时，可以用你的动作改变幻象的外形（仍需遵守相应法术的描述），前提是你必须可以看见该幻象。 | AF76: 复原药剂 | AG76: 第9级起，你可以在你的一些作品中加入复原药剂： • 每当一个生物饮用一瓶你制造的实验性灵药时，生物都将获得 2d6+你智力调整值 的临时生命值（至少1点临时生命点）。 • 只要你使用炼金工具作为你的法器，你就可以在不花费法术位、无需准备的情况下施展 次级复原术Lesser Restoration 。你能够这么做的次数等于你的智力调整值（最少1次），当你完成一次长休后，你恢复所有已被消耗的次数。 | AW76: =IFERROR(IF(AW75+1>BA26,IF(AW75+1>BA26,IF(AZ27+AZ75>BA27,"",AZ27+AZ75)),AW75+1),"") -> 47 | AX76: =IFERROR(INDEX(H31:AU181,AW76,AX26),"") | AY76: =IFERROR(INDEX(H31:AU181,AW76,AY26),"") | AZ76: =IFERROR(IF(AW75+1>BA26,AZ75+1,0),"") -> 0
A77: 孢子结社 | B77: 7 | C77: 8 | D77: 40 | E77: =D78-1 -> 45 | G77: 47 | H77: 魔法察觉 | I77: 第3级起，以一个动作，你让你的感官对聚集的魔力的存在保持警觉。直到你的下一个回合结束前，你可以知晓60尺内任何对你来说不处于完全掩护的任何法术或者魔法物品的位置。当你察觉到一个法术的存在时，你还能知晓这个法术属于哪一个学派。 你可以使用该能力的次数等于你的熟练加值。每完成一次长休之后你恢复所有已消耗的使用次数。 | J77: 渐强创音 | K77: 第14级起，当你使用造物表演特性创造物品时，你可以一次性创造多件物品，其数量等于你的魅力调整值（最低为两件物品）。如果你创造新的物品后，物品的总数超过了这个上限，那么你可以选择你先前创造的物品中的哪几件将会消失不见。你所创造的物品中只有一件可以达到你创造物品的大小峰值，其他的必须是小型或者微型。 你的创造表演特性不再会有创造物品的价值限制。 | L77: 风暴领域法术 | M77: 牧师等级——法术 1st——云雾术、雷鸣波 3rd——造风术、粉碎音波 5th——召雷术、雪雨暴 7th——操控水体、冰风暴 9th——湮灭波、疫病虫群 | N77: 星耀形态 | O77: 第2级起，以一个附赠动作，你可以消耗一次荒野形态特性使用次数以呈现一个星耀形态，而非变化为野兽形态。 当处于星耀形态时，你保留你的游戏数据，但你的身体变得明亮；你的关节星光熠熠并有如星图一般由亮线连接。这一形态散发出10尺半径的明亮光照以及其外10尺的昏暗光照。这一形态持续10分钟。如果你解除它（无需动作）、失能、死亡、或再次使用此特性，它就会提前结束。 每当你化身星耀形态时，你选择以下在你身上闪耀的星座旨意；你的选择将为你在形态中提供特定的增益： • 射手座Archer。 一个弓箭射手的星座于你身上浮现。当你激活这个形态时，你可以进行一次远程法术攻击，对你60尺内的一个生物射出一发光箭。命中时，此攻击将造成等同于1d8+你的感知调整值点的光耀伤害。你也可以在它结束前的后续回合中以一个附赠动作再次进行这一攻击。 • 圣杯座Chalice。一个予命圣杯的星座于你身上浮现。当你消耗法术位施展法术时，你或你周围30尺内的另一生物可以恢复等同于 1d8+你的感知调整值 点的生命值。那个法术必须是能为生物恢复生命值的法术。 • 巨龙座Dragon。 一个智慧巨龙的星座于你身上浮现。当你进行一次智力或感知检定，或是进行一次体质豁免来维持法术专注时，你可以将d20 中9或以下的骰值视为10。 | P77: 施法 | Q77: 第3级时，你学会以武斗技术施展法术的能力。 参考第10章的施法规则，以及第11章的法师法术列表。 | R77: 狮吼功 | S77: 你可以消耗3点气施展粉碎音波。（需6级） | T77: 护卫光环 | U77: 从7级起，你可以以自己的健康为代价保护盟友免受伤害。 当一个处于你10尺内的生物受到伤害时，你可以用一个反应动作，魔法性地使你代替该生物承受此伤害。 此特性不会传递任何该伤害可能附带的效果，该伤害也无法被任何方式减少。 在18级，此光环的距离增加到30英尺。 | V77: 怪物杀手魔法 | W77: 3级起，你学会一个额外法术当你到达指定游侠等级时，如怪物杀手法术列表所示。 这些法术对你视为游侠法术，它不计入你的已知法术总数中。 游侠等级——法术 3级——防护善恶 5级——诚实之域 9级——防护法阵 13级——放逐术 17级——怪物定身术 | X77: 心灵欺骗 | Y77: 从17级起，除非你允许，否则你的思想不能被心灵感应或者其他能力阅读。 如果你使用魅力（欺瞒）检定并在与思想阅读者的感知（洞悉）检定的对抗之中胜出，你还可以伪造思想使对方信以为真。 此外，不管你说什么，你总是可以选择让魔法判定你在说真话并显现出相应的迹象。 你也不会因为魔法效应的影响而被强迫说出真话。 | Z77: 终焉之力 | AA77: 1级起，存在于生和死的朦胧状态中使得你难以被击败。 当生命值被降至0点时，你可以通过一个DC=该次所受伤害+5的魅力豁免。 若豁免成功，作为代替你的生命值被降至1点。 若该次伤害为光耀或重击时你不可使用此能力。 当你通过豁免后直到下一次长休前不能再使用此能力。 | AB77: 饥渴魔刃 | AC77: 当你自身回合内使用契约武器执行攻击动作时，你可以发动两次攻击而非一次。 先决条件：第5级，刃之魔契 | AD77: 幻影化形 | AE77: 第10级起，你可以如同本能反应般，瞬间创造出一个自身的幻象分身以应对危险。 当一个生物对你发动攻击检定时，你可以用你的反应，在攻击者和你之间插入你自身的幻象分身。 攻击者对你的攻击将直接判为未命中，幻象分身也随即消失。 你必须完成一次长休或短休后才能再次使用该特性。 | AF77: 化学专家 | AG77: 第15级起，你已经接触了太多的化学物质，并解开了它们的秘密，它们对你的危害很小，你可以使用它们来迅速治愈某些疾病： • 你获得了对强酸伤害和毒素伤害的抗性，并且你免疫于中毒状态。 • 只要你使用炼金工具作为你的法器，就能够在不消费法术位、不需要准备、不需要材料成分的情况下施展 高级复原术Greater Restoration 与 医疗术heal。一旦你通过此特性施展这些法术中的一个，你就不能再以这种方式施展那个法术，直到你完成一次长休。 | AW77: =IFERROR(IF(AW76+1>BA26,IF(AW76+1>BA26,IF(AZ27+AZ76>BA27,"",AZ27+AZ76)),AW76+1),"") -> 48 | AX77: =IFERROR(INDEX(H31:AU181,AW77,AX26),"") | AY77: =IFERROR(INDEX(H31:AU181,AW77,AY26),"") | AZ77: =IFERROR(IF(AW76+1>BA26,AZ76+1,0),"") -> 0
A78: 星辰结社 | B78: 7 | C78: 8 | D78: 46 | E78: =D79-1 -> 50 | G78: 48 | H78: 狂野浪潮 | I78: 第3级起，你体内那翻滚不息的魔法能量有时会从你身上爆发出来。当你进入狂暴时，投掷下方的狂野魔法列表中决定它所产生的魔法效应。 如果这个狂野魔法需要进行豁免检定，则其DC等于8+你的熟练加值+你的体质调整值。 狂野魔法 D8 魔法效果 1 阴暗的卷须在你身边疯狂挥舞。在你能看到的30尺内由你选择的生物都必须进行一次体质豁免，如果失败，则将受到1d12的暗蚀伤害。此外。你还会立刻获得1d12点临时生命值。 2 你可以传送至多30尺到一个未被占据的、你可以看见的空间。直至你的狂暴结束为止，你的每个回合都可以再用一个附赠动作，再次发动这个效果。 3 一个看起来像呋噜或者皮克精（由你决定）的不定形精魂，出现在一个你30尺内可以看到的生物的5尺以内。并且在当前回合结束时，这个精魂会爆炸，所有它周围5尺范围内的生物都必须通过一次敏捷豁免，若失败将承受1d6的力场伤害。直至你的狂暴结束为止，你的每个回合都可以再用一个附赠动作，再次发动这个效果。 4 魔力与你正持握着的一件武器（由你选择）紧紧相融在一起。直至你的狂暴结束为止，这把武器的伤害类型转变为力场伤害，并且获得 轻型 和 投掷 的属性，其投掷射程为常规20尺与最大60尺。如果这把武器脱离了你的手，它将会在脱离的同一回合结束时重新出现在你的手中。 5 直至你的狂暴结束为止，每当一个生物以攻击检定击中了你，你身上的魔力将抽打反击它，对其造成1d6的力场伤害。 6 直至你的狂暴结束为止，你将被彩色的防护光芒环绕，使你的AC获得+1加值。在你10尺内的盟友也可以享受到相同的AC加值。 7 你身边将不断临时生长出花朵与藤蔓。直至你的狂暴结束为止，你周围15尺的地面对你的敌人来说变为困难地形。 8 一束光从你胸膛射出。你所选择的30尺内的你可以看到的另一个生物必须进行一次体质豁免，如果失败，将会受到1d6的光耀伤害，并陷入 目盲blinded ，直到你的下一个回合开始前。直至你的狂暴结束为止，你的每个回合都可以再用一个附赠动作，再次发动这个效果。 | J78: 巧舌如簧 | K78: 第3级起，你是语言的大师，懂得在合适的时刻说出正确的话语。当你在进行一次魅力（游说/说服）检定或魅力（欺瞒）检定时，如果你可以将9或更低的骰值全部视为10。 | L78: 附赠熟练项 | M78: 第1级起，你获得军用武器和重甲的熟练项。 | N78: 宇宙预兆 | O78: 第6级起，每当你完成一次长休，你可以参照你的星图来寻找预兆。此时，掷一枚骰子。直到你完成下一次长休为止，你获得一个基于此掷骰结果奇偶性的特殊反应能力。 • 吉兆Weal（奇数）。 当你周围30尺内的一个可见生物进行一次攻击检定、豁免检定、或属性检定，你可以使用你的反应来骰一个d6，并将结果加入到检定结果中。 • 凶兆Woe（偶数）。 当你周围30尺内的一个可见生物进行一次攻击检定、豁免检定、或属性检定，你可以使用你的反应来骰一个d6，并将结果从检定结果中减去。 你可以使用这一反应能力的次数等同于你的熟练加值次，在你完成一次长休后，你会重获全部已消耗的使用次数。 | P78: 戏法 | Q78: 你从法师法术列表中选择两个戏法作为已知法术。 第10级时，你再获得一个额外的法师戏法。 | R78: 云雾势 | S78: 你可以消耗4点气对自身施展气化形体。（需11级） | T78: 守护之魂 | U78: 从15级起，神圣的实体在战斗中为你治疗伤口。 若你在战斗中结束你的回合时，剩余的生命值少于一半，且你未处于失能状态，则你恢复等于1d6+你圣武士等级一半的生命值。 | V78: 猎人感知 | W78: 3级起，你获得了观察生物并魔法性地分析出最佳狩猎方式的能力。 以一个动作，选择一名60尺范围内对你可见的角色。你立刻知晓该角色的伤害免疫，抗性和易伤。 如果该角色被预言系魔法覆盖，你感觉它没有任何伤害免疫，抗性和易伤。 你能使用该特性的次数等同于你的感知调整值（至少为1）。 你重新获得所有使用过的次数当你完成一次长休时。 | X78: 散兵战术 | Y78: 从3级起，你在战斗中变得难以被压制。 当一个敌人在你周围5英尺内结束其回合时，你可以以一个反应移动至多你速度的一半。 此移动不会导致借机攻击。 | Z78: 凶兆猎犬 | AA78: 6级时，你获得一种能力，你能够驱使嚎叫的幽暗生物来折磨你的敌人的。 你可以以一个附赠动作消耗3点术法点选择一个120尺内你可见的生物作为目标，用魔法召唤一头凶兆猎犬的猎犬去猎杀它。 凶兆猎犬用恐狼的模板但有以下变化： 猎犬的体型由大体型变为中等体型，猎犬视作怪兽而不是野兽。 当猎犬被召唤时获得等同于你术士等级一半的临时生命值。 猎犬可以像穿越困难地形一样穿过其他生物或物体。 如果当猎犬的回合结束时处于某个物体内则会受到5点的力场伤害。 当猎犬的回合开始时，自动知晓猎物的所在。 如果目标处于躲藏状态，它对猎犬来说不再处于该状态。 猎犬被召唤时出现在目标30尺内一个由你选择的空间。 为猎犬投掷先攻。 当猎犬行动时，它只能以最短路径冲向目标猎物，以及只能在攻击目标猎物时执行动作。 猎犬可以使用借机攻击，但对象只能是目标猎物。 此外，当凶兆猎犬在目标猎物5尺内时，目标对你所释放的任何法术的豁免上都承受劣势。 凶兆猎犬会在它自己降为0血、猎物降为0血或5分钟后消失。 | AB78: 穹宇尽视 | AC78: 你可以随意施展秘法眼arcane eye，且无需消耗法术位。 先决条件：第15级 | AD78: 亦真亦幻 | AE78: 第14级起，你学会将暗影魔法编入幻术中的秘法，并以此使你的幻术获得半真实的效果。 你施展一个1环或更高环阶的幻术系法术时，可以选择幻象中一个非活化的非魔法物件，并让该物件化作真实。 你可以在自己回合中，相应法术持续时间内以一个附赠动作完成此事。 被指定的物件将在接下来1分钟内保持真实。 例如，你可以用幻术创造出一座桥梁横跨峡谷，而后将之化作真实以让你的队友在持续时间内穿行于桥面。 被化作真实的物件无法造成伤害，也无法以任何其他方式直接伤害任何事物。 | AF78: 工具精通 | AG78: 当你在第三级选择此专业时，你获得木匠工具的熟练。 如果你已经拥有此熟练，作为代替，你能获得另一种工匠工具的熟练。 | AW78: =IFERROR(IF(AW77+1>BA26,IF(AW77+1>BA26,IF(AZ27+AZ77>BA27,"",AZ27+AZ77)),AW77+1),"") -> 49 | AX78: =IFERROR(INDEX(H31:AU181,AW78,AX26),"") | AY78: =IFERROR(INDEX(H31:AU181,AW78,AY26),"") | AZ78: =IFERROR(IF(AW77+1>BA26,AZ77+1,0),"") -> 0
A79: 野火结社 | B79: 7 | C79: 8 | D79: 51 | E79: 55 | G79: 49 | H79: 振奋魔法 | I79: 第6级起，你可以控制你的狂野魔法并用于振奋自己或者一个同伴。以一个动作，你触碰一个生物（可以是你自己）并且为该生物提供以下增益中你所选择的一种： • 10分钟内，该生物在投掷攻击检定或者属性检定时可以额外掷一枚d3，将其加到所扔的d20中。 • 掷一枚d3。这个生物将恢复一个环数小于等于所掷出骰子的结果的法术位（由这个生物决定具体的环阶）。当一个生物享受了这一增益后，直到下一次长休结束前那个生物都不能再次从此特性中获益。 你可以使用此能力的次数等同于你的熟练加值次，完成一次长休后，你重获全部已消耗的使用次数。 | J79: 扰神之词 | K79: 第3级起，你可以编造一些带有魔力的话语，扰乱一个生物的心神，使其自我怀疑。消耗一个附赠动作，你可以消耗一个诗人激励骰，选择一个你可见的距你60尺以内的生物。掷出诗人激励骰，在你的下一个回合开始前，该生物的下一次豁免检定将会减去这个激励骰所投出的值。 | L79: 风暴狂怒 | M79: 第1级起，你可以用雷霆驱逐攻击者。 身处你周边5尺范围内一个你能看见的生物攻击命中你时，你可以用你的反应迫使该生物进行一次敏捷豁免。豁免失败者将受到2d8点闪电或雷鸣伤害（由你选择），豁免成功则伤害减半。 你可以使用该特性的次数等于你的感知调整值（至少为一次）。而你将在完成一次长休后重新恢复所有的使用次数。 | N79: 闪耀星座 | O79: 第10级起，你的星耀形态星座增强了。射手座和圣杯座中的1d8都变成了2d8，而在巨龙座激活期间，你将获得20尺的飞行速度，并且可以悬浮。 不止如此，每个你的回合开始时，若此时你处于在星耀形态下，你可以更改当前身上闪耀的星座。 | P79: 法术位 | Q79: “奥法骑士施法能力”表中列出了你用以施展你的法师法术的1环及更高环阶法术位数量。 施展这些法术时，你必须同时消耗一个不低于该法术环阶的法术位。 而已消耗的法术位可以通过完成一次长休进行恢复。 例如，若你已知1环法术护盾术，并且拥有一枚可用的1环法术位和一枚可用的2环法术位，则你可以用两者之一施展护盾术。 | R79: 攀云步 | S79: 你可以消耗4点气对自身施展飞行术。（需11级） | T79: 救赎使节 | U79: 在20级时，你成为了和平的化身，使你获得下述好处： 你对于其他生物造成的所有伤害具有抗力（它们的攻击、法术、和其他效果）。 当一个生物以一次攻击对你造成伤害时，它受到等同于其对你造成的一半伤害的光耀伤害。 当你对一个生物攻击、施法或以此特性以外的方式造成伤害，那么在完成一次长休息之前此特性对该生物无效。 | V79: 狩猎开始 | W79: 3级起，你能够专注于你的一名敌人，来增加你对它的伤害。 以一个附赠动作，你选择一名60尺范围内对你可见角色作为该特性的目标。 每回合你以一次武器攻击第一次击中该目标，它额外受到1d6的武器伤害。 该收益持续到你完成一次短休或者长休。 如果你选择一名不同的目标，它会提前结束。 | X79: 生存专家 | Y79: 当你在3级时选择此范型时，你得到对于自然和生存技能的熟练。 当使用上述熟练进行的任何属性检定中，你的熟练加值加倍。 | Z79: 幽影漫步 | AA79: 14级时，你获得在暗影间穿梭的能力。 当你处于微光或黑暗中时，以一个附赠动作你可以魔法地将自己传送至120尺内另一处未被占据并自己可见的微光或黑暗中。 | AB79: 缚主之音 | AC79: 只要你与你的魔宠处于同一位面，你就可以用心灵感应与其进行交流，以及使用其感官感知世界。此外，当你通过魔宠的感官感知时，你可以通过魔宠用你自己的声音说话，而不论你的魔宠是否能够说话。 先决条件：链之魔契 | AD79: 死灵学者 | AE79: 从第2级你选择该学派起，你向法术书中抄写死灵系法术的时间和金钱花费减半。 | AF79: 魔炮师法术 | AG79: 第3级起，只要你达到相应的职业等级，魔炮师法术表格中的法术总是被视为已准备。 这些法术对你来说是奇械师法术，且不会计入你可以准备法术的总数。 奇械师等级 法术 3级 护盾术，雷鸣波 5级 灼热射线，粉碎音波 9级 火球术，风墙术 13级 冰风暴，火墙术 17级 寒冰锥，力墙术 | AW79: =IFERROR(IF(AW78+1>BA26,IF(AW78+1>BA26,IF(AZ27+AZ78>BA27,"",AZ27+AZ78)),AW78+1),"") -> 50 | AX79: =IFERROR(INDEX(H31:AU181,AW79,AX26),"") | AY79: =IFERROR(INDEX(H31:AU181,AW79,AY26),"") | AZ79: =IFERROR(IF(AW78+1>BA26,AZ78+1,0),"") -> 0
A80: 勇士 | B80: 9 | C80: 10 | D80: 13 | E80: =D81-1 -> 17 | G80: 50 | H80: 无常反冲 | I80: 第10级起，在你狂暴期间，如果你受到危险，你体内的魔法会猛烈爆发。 每当你在狂暴时受到伤害或者没能通过豁免检定后，你都可以立刻用反应再次重骰你的狂野魔法表，并立刻产生一次骰出的新的魔法效应。这个魔法效应将会替代你当前有的狂野魔法效应。 | J80: 不竭鼓舞 | K80: 第6级起，你的激励言语是如此的具有感染力，以至于被鼓舞的人感受到他们必须行，不行也得行的做到成功。当一个生物使用了你的诗人激励骰子，将结果加入到攻击检定、属性检定、或豁免检定中，但仍然失败了，他可以保留这个诗人激励骰而不消耗。 | L80: 引导神力：毁灭狂怒 | M80: 第2级起，你可以用引导神力特性为自己装备无拘束的凶猛风暴之力。 当你造成闪电或雷鸣伤害时，可以使用引导神力使该伤害的伤害掷骰直接取最高值而无需掷骰。 | N80: 灿若繁星 | O80: 第14级起，当你处于星耀形态时，你的身体部分无实质化，使你获得钝击、穿刺、与挥砍伤害的抗性。 | P80: 已知法术 | Q80: 你习得三个自选的1环法师法术，其中两个必须从防护系和塑能系中选择。 表格“奥法骑士施法能力”中“已知法术”一栏记录了你获得更多已知法术时的相应等级。 你只能选择防护系或塑能系法术，且所获得法术的环阶不能超过你所拥有的最高法术位环阶。 例如，如果你在本职业达到第7级，则可以学习一个新的1环法术或2环法术。 在第8、14和20级时，你可以学习任何学派的法术。 你每次提升本职业等级时，可以将一个已知法术替换为另一个法师法术。 这个新法术的环阶不能超过你所拥有的最高法术位的环阶，且必须从防护系或塑能系中选择（除非你替换的是第3、第8、第14和第20级时习得的任何学派法术）。 | R80: 噬焰流 | S80: 你可以消耗5点气施展火墙术。（需17级） | T80: 王冠圣誓法术 | U80: 3rd 命令术，强制决斗。 5th 守护之链，诚实之域 9th 活力灵光，灵体卫士 13th 放逐术，信仰守卫 17th 威力法阵，指使术 | V80: 卓越防守 | W80: 7级时，对于你的猎物对你的身体和精神的攻击，你拥有额外韧性。 无论何时你的狩猎开始特性目标使你做出一个豁免投和你做一次技能检定来脱离目标的擒抱，加1d6到你的那次投掷上。 | X80: 优异灵活 | Y80: 在9级时，你的行走速度增加10英尺。 若你具有攀爬或游泳速度，这个能力也会增加在这些速度上。 | Z80: 幽暗形态 | AA80: 18级时，你可以耗费6点术法点以一个附赠动作魔法地将自己转变为暗影形态。 在此形态中，你对除力场和光耀之外的所有伤害形势都具有抗性。 并且你可以像穿越困难地形一般地穿过其他生物或物体。 若回合结束时你处于某个物体内则会受到5点的力场伤害。 你能维持这种状态1分钟。 当你以一个附赠动作来解除暗影形态、处于失能或死亡时会提前结束状态效果。 | AB80: 坟墓低语 | AC80: 你可以随意施展法术死者交谈speak with dead，且无需消耗法术位。 先决条件：第9级 | AD80: 惧怖收割 | AE80: 第2级时，你可以在用法术杀死敌人时汲取其生命能量。 你每回合有一次机会，在以一个环阶不低于1环的法术杀死一个或多个生物时，可以恢复等于该法术环阶两倍的生命值。 如果你使用的是死灵系法术，则其恢复的生命值为法术环阶的三倍。 你以此杀死不死生物或构装生物时，无法从该特性获得任何益处。 | AF80: 魔能炮台 | AG80: 第3级起，你习得了如何制造一个魔法炮台。 使用你的木匠工具或铁匠工具，你能用一个动作在距离你5尺且没被占据的水平空间内魔法性地召唤出一架小型或微型炮台。小型魔能炮台会占据它所在的方格，而微型炮台能用一只手持用。 当你创造炮台后，直到你完成一次长休前你都不能再创造它，或者你也可以通过消耗一个法术位来创造它。 你只能同时拥有一个炮台，在上一个炮台还在的情况下你不能创造第二个炮台。 炮台是一个魔法物件。不论尺寸，它的AC都是18，而其生命值是你奇械师等级的5倍。 它免疫于毒素伤害和心灵伤害。如果它被迫进行属性检定或豁免检定，则将其所有属性都视为10(+0)。如果一个法术 修复术mending 被施展到它身上，它将恢复2d6生命值。炮台在生命值降低到0或1小时后消失。你也可以以一个动作来提早让它消失。 当你制造炮台时，你决定它的外观，以及是否有腿。你还需要决定它的类型——从下方的魔能炮台列表中选择一项。 在你的每个回合中，只要你离炮台不到60尺，你就能以一个附赠动作来使炮台激活。作为该附赠动作的一部分，你还可以引导有腿的炮台步行或攀爬到15尺内的一处未被占据的空间中。 魔能炮台 炮台：描述 投火机：炮台在你指定的一个15尺锥形范围内发射火焰。该区域内的每个生物必须对你的法术豁免DC做一次敏捷豁免检定，如果豁免失败则受到2d8火焰伤害，成功的豁免检定将使伤害减半。火焰会点燃该地区内任何未被穿戴或携带的易燃物品。 力场弩炮：对一个距离炮台120尺以内的生物或物体进行远程法术攻击。击中时，目标受到2d8力场伤害，如果目标是一个生物，它将向远离炮台的方向推开5尺。 防御者：炮台释放出一股正能量，给予它自己和10尺距离内每个你选择的生物1d8+你智力调整值的临时生命值（最低+1）。 | AW80: =IFERROR(IF(AW79+1>BA26,IF(AW79+1>BA26,IF(AZ27+AZ79>BA27,"",AZ27+AZ79)),AW79+1),"") -> 51 | AX80: =IFERROR(INDEX(H31:AU181,AW80,AX26),"") | AY80: =IFERROR(INDEX(H31:AU181,AW80,AY26),"") | AZ80: =IFERROR(IF(AW79+1>BA26,AZ79+1,0),"") -> 0
A81: 战斗大师 | B81: 9 | C81: 10 | D81: 18 | E81: =D82-1 -> 46 | G81: 51 | H81: 掌控浪潮 | I81: 第14级起，每当你投掷狂野魔法表时，你可以掷两次骰子并且选择其中之一作为生效的狂野魔法效应。 如果你掷出的两个骰子数值相同，那么你可以无视这个数字，任选表中的一个效应生效。 | J81: 统一言说 | K81: 第6级起，你掌握了一种一让你的话语被任何有智慧的生物理解的方法。以一个动作，你可以选择至多为你魅力调整数量的生物（至少为一个），他们必须在你六十尺内。在接下来的一个小时内，被选中的生物可以魔法性的理解你，不论你所说的话是用何种语言说的。 每当你用这一能力，直到下一次长休结束前你都不能再次使用这个能力。你也可以消耗任意一个的法术位去再次使用这个能力。 | L81: 雷鸣打击 | M81: 第6级起，当你对一个大型或更小体型的生物造成闪电伤害时，你还可以同时将其往远离你的方向推动至多10尺。 | N81: 野火法术 | O81: 从2级起，你与野火精魂——一位兼具创生和毁灭的原初存在——之间的神秘连接业已形成。 当你在此职业到达特定等级时，你与精魂的连接使你获取了一些特定法术的使用权，就如野火结社法术列表所示。 一旦你获得了其中某个法术的使用权，你就会一直准备着它，且不计入你的每日准备法术上限。 如果你学会一个不在德鲁伊法术列表中的法术，该法术对你来说视作德鲁伊法术。 等级 - 扩展法术 Lv.2 - 燃烧之手，疗伤术 Lv.3 - 炽焰法球，灼热射线 Lv.5 - 植物滋长，回生术 Lv.7 - 生命灵光，火焰护盾 Lv.9 - 焰击术，群体疗伤术 | P81: 施法关键属性 | Q81: 你通过研究和记忆学习魔法，因此智力是你施展法师法术的关键属性。 每当你的法术需要施法关键属性时均指向你的智力值。 而你法师法术的豁免DC和攻击检定，则使用你的智力调整值。 法术豁免DC＝8＋你的熟练加值＋你的智力调整值 法术攻击调整值＝你的熟练加值＋你的智力调整值 | R81: 风灵突进 | S81: 你可以消耗2点气施展造风术。 | T81: 引导神力-王冠 | U81: 从3级起，若选取此誓言，你获得以下引导神力选项。 捍卫挑战：以一个附赠动作，你发出挑战逼迫其他生物与你战斗。 你可以选择30尺内任意数量你可以看见的生物，他们每一个都必须要通过一次感知豁免。 如果豁免失败，那个生物将不能自愿从你周围30尺范围离开。 如果你死亡，或者你失能，或者生物与你距离超过30尺，则此效果终结。 扭转局势：以一个附赠动作，你可以引导神力支撑受伤的生物继续战斗。 你可以选择你周围30尺内任意数量可以听见你说话的生物，如果他们生命值在一半以下，他们将立即恢复1d6+你的魅力调整值（最小为1点）的生命值。 | V81: 魔法克星 | W81: 11级时，你获得打断其他人的魔法的能力。 60尺内，当你看到一名角色使用法术或者传送，你可以用你的反应魔法性地来尝试打断它。 角色必须成功通过一个难度等同于你的施法DC的感知豁免，否则它的法术和传送失败并浪费。 你使用该特性后，不能再次使用它直到你完成一次短休或者长休。 | X81: 突袭大师 | Y81: 从13级起，你精通于引领突袭，在战斗中首先行动。 你在先攻检定时具有优势。 此外，在第一轮战斗中你所命中的第一个生物对你和其他人而言会变得更容易打击；直到你下一回合开始之前，所有对它进行的攻击检定具有优势。 | Z81: 风语者 | AA81: 从1级起，你操纵的奥术魔法浸染着风元素之力。 你可以听、说、读、写原初语。 （了解这种语言允许你了解这些说这种语言的种族，同时你说的话也被他们理解：水族语,气族语,火族语,土族语）。 | AB81: 巫术视界 | AC81: 变形生物以及由幻术和变化系魔法变形的生物在你身边30尺视线范围内时，你将直接看出其真实形态。 先决条件：第15级 | AD81: 不死奴仆 | AE81: 第6级起，如果你法术书中未有法术操纵死尸，则将之加入法术书。 施展操纵死尸 时，你可以指定额外的一具尸体或一堆骸骨以创造一个额外的僵尸或骷髅，并按法术详述进行设定。 此外，每当你用死灵系法术创造不死生物时，这些生物还可以获得以下增益： 其生命值上限增加，数值等于你的法师等级。 其武器的伤害掷骰可以加上你的熟练加值。 | AF81: 奥法火器 | AG81: 第5级起，你知道如何把魔杖、法杖或权杖变成一件奥法火器，一个传送你的毁灭性法术的管道。 当你完成一次长休后，你可以用木匠工具在一根魔杖、法杖或权杖上刻印一个特殊印记，从而把它变成你的奥法火器。 印记会一直存在，除非你之后在另一件物品上刻上这种印记，这样的话，之前物体上印记就会消失。 你可以将你的奥法火器作为你奇械师法术的法器。 当你通过奥法火器施放一个奇械师法术时，掷一个d8，你在法术的一次伤害检定中获得与掷骰结果相同的加值。 | AW81: =IFERROR(IF(AW80+1>BA26,IF(AW80+1>BA26,IF(AZ27+AZ80>BA27,"",AZ27+AZ80)),AW80+1),"") -> 52 | AX81: =IFERROR(INDEX(H31:AU181,AW81,AX26),"") | AY81: =IFERROR(INDEX(H31:AU181,AW81,AY26),"") | AZ81: =IFERROR(IF(AW80+1>BA26,AZ80+1,0),"") -> 0
A82: 奥法骑士 | B82: 9 | C82: 10 | D82: 47 | E82: =D83-1 -> 56 | G82: 52 | H82: 野兽起源 | I82: 踏上野兽道途的野蛮人点燃其灵魂深处熊熊燃烧的兽性火花以激活狂暴。其内心的野兽在嗥叫中被释放，在狂怒中爆发，并改变野蛮人的形态。这些野蛮人可能体内住着一只原初精魂，又或是某个化兽者的后人。请你为自己的野性之力选择一种起源，或在下方的“野兽起源表”随机选择。 D4野兽起源 1 你的生父或生母是一个兽化人，你也遗传了这方面的一些诅咒。 2 你是一位大德鲁伊的后人，并且继承了变形部分躯体的能力。 3 一只精类的精魂赐予你变换不同野兽形态的能力。 4 一只上古野兽的精魂住在你的体内，为你打开走上此道途的大门。 | J82: 传播鼓舞 | K82: 第14级起，当你成功激励了他人之后，你那雄辩言辞的力量会散播开去。当一个距离你60尺内的生物使用了你的诗人激励骰增益了一次攻击检定、属性检定、或豁免检定并且成功之后，你可以用你的反应去借此鼓励另一个能够听见你的生物（除了你）。那个生物会获得一个诗人激励骰，而你并不会因此消耗你的诗人激励次数。 你可以使用这个能力的次数等于你的魅力调整值（最低为一次）次，完成一次长休后你重获该能力所有被消耗的使用次数。 | L82: 神圣打击 | M82: 第8级起，你可以使你的武器充满神圣能量。你在每个自己回合里有一次机会，可以在用武器攻击命中某生物时使该攻击额外造成1d8点雷鸣伤害。14级时，该伤害提升到2d8。 | N82: 召唤野火精魂 | O82: 从2级起，你能召唤出与你灵魂连接的原初精魂。 以一个动作，你可以消耗一次荒野形态使用次数召唤你的野火精魂，而不是变化为野兽形态。 精魂出现在你所选择的距离你30尺内未被占据的可见空间内。 每个精魂10尺内的生物（除你之外）在它出现时都必须成功一次对抗你法术豁免DC的敏捷豁免否则受到2d6火焰伤害。 野火精魂对你与你的同伴保持友善并遵从你的命令。 在野火精魂资料表中可以看到这只生物的游戏数据，其中几处采用了你的熟练加值（PB）。 由你来决定精魂的外形。 一些精魂是熊熊燃烧的枝条虬结而成的人形，而另一些则像是被火焰包裹的野兽。 在战斗中，野火精魂与你使用同一先攻，但在你的回合之后紧接着行动。 它仅能使用回避动作，除非你使用一个附赠动作命令它采取其他动作。 那个动作可以是其资料表上的一个，也可以是其他动作。 如果你陷入失能，精魂可以采取任何它选择的动作，不只是回避。 野火精魂持续存在1小时，直到其生命值降低至0，或直到你再次使用此特性召唤此精魂，或直到你死亡。 | P82: 武器联结 | Q82: 第3级时，你习得一种让你和你的武器建立魔法联结的仪式。 仪式耗时1小时，且可在短休时进行。 仪式过程中武器必须在你的触及范围内，直至仪式结束前，你都要碰触该武器以完成联结。 联结建立后，只要你不处于失能状态，使用联结武器时就不会被缴械。 如果联结武器与你处于同一位面，则你可以用一个附赠动作召唤其回到你手中。 你至多可以拥有两把建立联结的武器，但一个附赠动作只能召唤一把武器。 如果你试图和第三把武器建立联结，则必须与已经联结的一把武器取消联结。 | R82: 身化长流 | S82: 作为一个动作，你可以消耗1点气并指定你周边120尺内一块不大于30尺的冰或水的区域。你可以将该区域内的水凝为冰，反之亦可，并且还可以将区域内的冰塑造成任意的形状。你可以提高或降低冰的高度，创造或填平沟壑，竖起或放倒冰墙，或是塑造一根冰柱。这些造型的最大尺寸不能超过该区域最大边长的一半。 例如，假设你影响一块30尺的方状区域，你可以竖起的冰柱高度至多为15尺，提升或降低区域内总体高度至多15尺，创造的沟壑最深15尺，等等。你不能通过塑形冰来困住或伤害区域内的生物。 | T82: 神圣誓忠 | U82: 从7级起，如果一个在你周围5尺内的生物受到伤害，你可以使用你的反应魔法地代替目标生物承受这一次伤害，使目标不再受伤。 你不能用任何方式减少或者阻止这个伤害。 | V82: 杀手反制 | W82: 15级时，当你的猎物企图干扰你时你能够反击。 如果你的狩猎开始特性目标使你做出一个豁免投，你能够使用你的反应来对其做出一次武器攻击。 你在进行豁免检定前立刻做出该攻击。 如果你击中，你的豁免自动成功，否则只造成普通攻击效果。 | X82: 突袭打击 | Y82: 从17级起，你可以以致命的速度进行打击。 若你在你的回合进行攻击动作，你可以以一个附赠动作进行一次额外的攻击。 此攻击可以从你的偷袭中收益，即使你已经在此回合中使用了它，但是你不能在一回合中对同一目标偷袭一次以上。 | Z82: 暴风魔法 | AA82: 从1级起，你与风元素魔法紧密联系起来。 每当你在你自己的行动轮内施展一个并非戏法的法术时，你可以用附赠动作导致旋转的风元素飙风围绕着你。 此时你可以飞行10尺，而不引起借机攻击。 | AB82: 月之仪态 | AC82: 你不再需要睡眠，同样不能以任何方式强行陷入睡眠。为了获得长休的益处，你可以在8小时内执行一些轻度活动，像是阅读你的 影之书Book of Shadows 或是放哨之类的。 先决条件：书之魔契 | AD82: 不死适应 | AE82: 第10级起，你对黯蚀伤害具有抗性，且你的生命值上限不会被降低。 你已经花了相当长的时间研究不死生物和驱役其力量，所以你已经可以适应其一些负面效应。 | AF82: 高爆炮台 | AG82: 第9级起，你制造的每一门奥法炮台都将拥有更大的破坏力： • 所有炮台的伤害增加1d8。 • 如果你距离炮台不到60尺，你能以一个动作命令你的炮台自爆。这么做会摧毁炮台，并迫使每一个离它20尺以内的生物对你的法术豁免dc进行一次敏捷豁免检定，若豁免失败，将受到3d8力场伤害，成功的豁免检定将使伤害减半。 | AW82: =IFERROR(IF(AW81+1>BA26,IF(AW81+1>BA26,IF(AZ27+AZ81>BA27,"",AZ27+AZ81)),AW81+1),"") -> 53 | AX82: =IFERROR(INDEX(H31:AU181,AW82,AX26),"") | AY82: =IFERROR(INDEX(H31:AU181,AW82,AY26),"") | AZ82: =IFERROR(IF(AW81+1>BA26,AZ81+1,0),"") -> 0
A83: 魔射手 | B83: 9 | C83: 10 | D83: 57 | E83: =D84-1 -> 69 | G83: 53 | H83: 野兽之形 | I83: 第3级起，你能在进入狂暴时变形，展现潜在的野兽之力。你将长出一种天生武器，直至狂暴结束。它对你来说被视为一件简易近战武器，并正常使用你的力量调整值进行攻击检定与伤害掷骰。天生武器将一直存在，直到你狂暴结束为止。 你在每次进入狂暴时，可以选择如下的天生武器之一： • 啃咬Bite。 你的嘴变成一张野兽的血盆大口或双颚长得巨大（由你选择）。它在击中时造成1d8穿刺伤害。每个你的回合一次，当你用这一啃咬攻击命中一个生物， 并且你的生命值数值小于一半时，你能恢复等于你的熟练加值点的生命值。 • 爪击Claws。 你的双手变成利爪，它们在你手空闲时可以作为武器使用。它在击中时造成1d6挥砍伤害。此外，当你在自己的回合使用攻击动作进行了爪击，你可以追加执行一次爪击作为该攻击动作的一部分（一回合一次）。 • 尾击Tail。你长出一条如长鞭般带刺的尾巴，其造成1d8穿刺伤害，具有 触及Reach 属性。如果一个你可见的、距离你10尺以内的生物发动的攻击击中了你，你可以用反应挥起你的尾巴，骰一个d8并将骰值加在你的AC上，可能导致这次攻击打失。 | J83: 呢喃指引 | K83: 第3级起，你可以通过与精魂沟通来引导你和其他人。你习得戏法神导术guidance，且不计入你已习得的吟游诗人戏法数量。对你来说，当你施展神导术guidance时，其施法距离为60尺。 | L83: 风暴降生 | M83: 第17级起，当你不在地底或室内时，你得到等同于你步行速度的飞行速度。 | N83: 强化链接 | O83: 在6级时，你与野火精魂的连接增强了你的破坏与恢复法术。 当你在野火精魂处于召唤状态下施展一个造成火焰伤害或回复生命值的法术时，骰一个 d8，你在该法术的一次掷骰时获得等同于骰出数值的加值。 此外，当你施展一个射程非自身的法术时，该法术可以源自你或你的野火精魂。 | P83: 战争魔法 | Q83: 第7级起，当你使用动作施展戏法时，可以用附赠动作发动一次武器攻击。 | R83: 飞炎击 | S83: 你可以消耗2点气施展燃烧之手。 | T83: 顽强精神 | U83: 从15级起，你在避免陷入震慑或者麻痹状态的豁免骰中得到优势。 | V83: 蜂聚集群 | W83: 从3级起，无形自然精魂形成的集群与你形影不离并会在战斗中对你施以援手。 直到你死亡，集群会存在于你的空间中，在你身上爬行或在你周身的空间里飞舞或窜动。 你决定集群的外观，或者你通过按照集群外观表格掷骰生成其外表。 群聚的昆虫、微小的枯枝怪、飞舞的群鸟、好动的皮克精 在你的回合中每回合一次，当你以一次攻击命中一个生物之后，你能让集群以以下一种方式助你一臂之力。 这次攻击的目标因集群受到1d6穿刺伤害。 这次攻击的目标必须成功通过对抗你法术DC的力量豁免检定否则被集群朝你选择的方向水平移动最多15尺。 你被集群朝着你所选择的方向水平移动5尺。 | X83: 梦幻舞步 | Y83: 从3级起，你冲刺，攻击，摆脱这些战斗中的动作就像一串模糊的身影。 在你的回合，如果你对一个生物进行一次近身攻击，那个生物在你回合剩下的时间内无法对你进行借机攻击。 | Z83: 风暴之心 | AA83: 从6级起，你对闪电和雷鸣伤害获得抗力。 每当你施展一个1环或以上且造成闪电或雷鸣伤害的法术时，猛烈的魔法从你身体内爆发而出。 这次爆发导致所有10尺内你选择的可见生物（每次使用此能力都指定），都承受等于你术士等级一半的闪电或雷鸣伤害。 | AB83: 飞蝇斗篷 | AC83: 以一个附赠动作，你周身环绕起外观如同纷飞蚊蝇般的魔法灵光。灵光以你为中心向四周散发5尺距离，其无法穿透全掩护。灵光会一直持续到你陷入 失能Incapacitated 、或以一个附赠动作主动解消它为止。 这一灵光会使你在魅力（威吓）检定具有优势，但你进行的其他任何魅力检定都将具有劣势。任何在灵光内开始其回合的生物，会受到等同于你魅力调整值点的毒素伤害（最低0点伤害）。 使用本祈唤后，直到你完成一次短休或长休前，你都无法再次使用它。 先决条件：第5级 | AD83: 命令亡灵 | AE83: 第14级起，你可以用魔法夺取不死生物的控制权，甚至可以夺取其他法师所创造的不死生物。 作为一个动作，你可以指定一个在距你60尺内你能看见的不死生物。 该生物必须进行一次对抗你法师法术豁免DC的魅力豁免。 若豁免成功，则你将不能对该生物再次使用此特性。 若豁免失败，则该生物变为对你友善，并服从你的命令，直至你再次使用此特性。 以该方式操纵智慧不死生物要更难一些。 如果目标的智力值不低于8，则它在进行该豁免时具有优势。 而智力不低于12的不死生物，即使其豁免失败也可以每小时重掷豁免，直至其豁免成功并挣脱你的控制。 | AF83: 坚固要塞 | AG83: 第15级起，你成为了用魔能炮台构筑阵地的大师。 • 由于你用魔能炮台特性创造的炮台所发出的闪光魔法保护场，你和你的盟友在距离炮台不到10尺的地方有半身掩护。 • 你现在同时拥有二个炮台，你能以一个动作同时制造两台炮台（但使用法术位制造时，每个炮台都要一个法术位），此外，你能够以一个附赠动作来同时激活两个炮台。这二个炮台可以是不同的类型。你在拥有两个炮台时，不能制造第三个炮台。 | AW83: =IFERROR(IF(AW82+1>BA26,IF(AW82+1>BA26,IF(AZ27+AZ82>BA27,"",AZ27+AZ82)),AW82+1),"") -> 54 | AX83: =IFERROR(INDEX(H31:AU181,AW83,AX26),"") | AY83: =IFERROR(INDEX(H31:AU181,AW83,AY26),"") | AZ83: =IFERROR(IF(AW82+1>BA26,AZ82+1,0),"") -> 0
